Workbook

Sheet ABA
A1: Abacus | B1: Actuals 2025 | O1: 2026 Actual / Forecast | AC1: 2027 Forecast | AK1: YoY | AL1: YoY
B2: Jan | C2: Feb | D2: Mar | E2: Apr | F2: May | G2: Jun | H2: Jul | I2: Aug | J2: Sep | K2: Oct | L2: Nov | M2: Dec | N2: FY2025 Total | O2: Jan | P2: Feb | Q2: Mar | R2: Apr | S2: May | T2: Jun | U2: Jul | V2: Aug | W2: Sep | X2: Oct | Y2: Nov | Z2: Dec | AA2: YTD | AB2: FY2026 Outlook | AC2: Jan | AD2: Feb | AE2: Mar | AF2: Apr | AG2: May | AH2: Jun | AI2: Jul-Dec Proj. | AJ2: FY2027 | AK2: 25→26 % | AL2: 26→27 %
A3: INCOME
A4: Fee Income Regular | B4: 45121.08 | C4: 48317.09 | D4: 59604 | E4: 58999.57 | F4: 54973.4 | G4: 54200.75 | H4: 68470.83 | I4: 57893.73 | J4: 46302.96 | K4: 47210.81 | L4: 44551.63 | M4: 58823.32 | N4: =SUM(B4:M4) | O4: 51261.86 | P4: 47040 | Q4: 62383.2 | R4: 65608.49 | S4: 54732.77 | T4: 63533.84 | U4: 77254.32 | AA4: =SUM(O4:U4) | AB4: =SUM(O4:Z4) | AC4: 105589.88 | AD4: 122011.99 | AE4: 95286.97 | AF4: 109311.06 | AG4: 116010.76 | AH4: 110257.62 | AI4: =SUM(AC4:AH4) | AJ4: =SUM(AC4:AH4)+AI4 | AK4: =IF(N4<>0,(AB4-N4)/ABS(N4),0) | AL4: =IF(AB4<>0,(AJ4-AB4)/ABS(AB4),0)
A5: EEEF Embedded | B5: 11395.45 | C5: 30240.26 | D5: 33852.92 | E5: 11973.37 | F5: 11973.37 | G5: 44731.22 | H5: 40794.17 | I5: 0 | J5: 12746.69 | K5: 34548.74 | L5: 34548.75 | M5: 37093.27 | N5: =SUM(B5:M5) | O5: 16246.68 | P5: 45919.86 | Q5: 45919.86 | R5: 36357.78 | S5: 36357.78 | T5: 37136.04 | U5: 39324.86 | AA5: =SUM(O5:U5) | AB5: =SUM(O5:Z5) | AC5: 0 | AD5: 0 | AE5: 0 | AF5: 0 | AG5: 0 | AH5: 0 | AI5: =SUM(AC5:AH5) | AJ5: =SUM(AC5:AH5)+AI5 | AK5: =IF(N5<>0,(AB5-N5)/ABS(N5),0) | AL5: =IF(AB5<>0,(AJ5-AB5)/ABS(AB5),0)
A6: Other Income | B6: 1000 | C6: 0 | D6: 0 | E6: 240 | F6: 150 | G6: 150 | H6: 150 | I6: 150 | J6: 150 | K6: 150 | L6: 150 | M6: 150 | N6: =SUM(B6:M6) | O6: 650 | P6: 150 | Q6: 150 | R6: 150 | S6: 150 | T6: 150 | U6: 150 | AA6: =SUM(O6:U6) | AB6: =SUM(O6:Z6) | AC6: 0 | AD6: 0 | AE6: 0 | AF6: 0 | AG6: 0 | AH6: 0 | AI6: =SUM(AC6:AH6) | AJ6: =SUM(AC6:AH6)+AI6 | AK6: =IF(N6<>0,(AB6-N6)/ABS(N6),0) | AL6: =IF(AB6<>0,(AJ6-AB6)/ABS(AB6),0)
A7: Total Income | B7: =B4+B5+B6 | C7: =C4+C5+C6 | D7: =D4+D5+D6 | E7: =E4+E5+E6 | F7: =F4+F5+F6 | G7: =G4+G5+G6 | H7: =H4+H5+H6 | I7: =I4+I5+I6 | ... AJ7: =AJ4+AJ5+AJ6 | AK7: =IF(N7<>0,(AB7-N7)/ABS(N7),0) | AL7: =IF(AB7<>0,(AJ7-AB7)/ABS(AB7),0)
A9: DIRECT COSTS
A10: Personnel
A11: Nursery Salaries | B11: 31316.14 | C11: 32272.71 | D11: 33507.52 | E11: 35857.02 | F11: 36300.07 | G11: 37005.6 | H11: 38811.34 | I11: 36024.66 | J11: 35973.55 | K11: 34210.75 | L11: 33941.4 | M11: 34611.41 | N11: =SUM(B11:M11) | O11: 33098.55 | P11: 37530.83 | Q11: 38072.4 | R11: 42905.75 | S11: 44862.47 | T11: 42474.52 | U11: 44079.43 | AA11: =SUM(O11:U11) | AB11: =SUM(O11:Z11) | AC11: 44079.43 | AD11: 44079.43 | AE11: 44079.43 | AF11: 44079.43 | AG11: 44079.43 | AH11: 44079.43 | AI11: =SUM(AC11:AH11) | AJ11: =SUM(AC11:AH11)+AI11 | AK11: =IF(N11<>0,(AB11-N11)/ABS(N11),0) | AL11: =IF(AB11<>0,(AJ11-AB11)/ABS(AB11),0)
A12: Nursery NI | B12: 2200.8 | C12: 2181.6 | D12: 2265.66 | E12: 3434.81 | F12: 3452.56 | G12: 3639.83 | H12: 4034.6 | I12: 3525.03 | J12: 3409.27 | K12: 3148 | L12: 3079.55 | M12: 3438.39 | N12: =SUM(B12:M12) | O12: 3146.95 | P12: 3574.88 | Q12: 3481.84 | R12: 3882.54 | S12: 4221.13 | T12: 4123.59 | U12: 4289.92 | AA12: =SUM(O12:U12) | AB12: =SUM(O12:Z12) | AC12: 4289.92 | AD12: 4289.92 | AE12: 4289.92 | AF12: 4289.92 | AG12: 4289.92 | AH12: 4289.92 | AI12: =SUM(AC12:AH12) | AJ12: =SUM(AC12:AH12)+AI12 | AK12: =IF(N12<>0,(AB12-N12)/ABS(N12),0) | AL12: =IF(AB12<>0,(AJ12-AB12)/ABS(AB12),0)
A13: Nursery Pension | B13: 609.12 | C13: 604.7 | D13: 593.33 | E13: 633.2 | F13: 631.9 | G13: 716.47 | H13: 746.36 | I13: 648.61 | J13: 678.39 | K13: 624.58 | L13: 612.97 | M13: 624.69 | N13: =SUM(B13:M13) | O13: 571.62 | P13: 534.23 | Q13: 534.37 | R13: 564.58 | S13: 653.95 | T13: 674.11 | U13: 706.29 | AA13: =SUM(O13:U13) | AB13: =SUM(O13:Z13) | AC13: 706.29 | AD13: 706.29 | AE13: 706.29 | AF13: 706.29 | AG13: 706.29 | AH13: 706.29 | AI13: =SUM(AC13:AH13) | AJ13: =SUM(AC13:AH13)+AI13 | AK13: =IF(N13<>0,(AB13-N13)/ABS(N13),0) | AL13: =IF(AB13<>0,(AJ13-AB13)/ABS(AB13),0)
A14: Uniform | B14: 86.04 | C14: 0 | D14: 181.94 | E14: 0 | F14: 251.04 | G14: 85.92 | H14: 0 | I14: 0 | J14: 105.66 | K14: 0 | L14: 0 | M14: 0 | N14: =SUM(B14:M14) | O14: 371.7 | P14: 98.82 | Q14: 0 | R14: 203.82 | S14: 98.82 | T14: 263.64 | U14: 100.81 | AA14: =SUM(O14:U14) | AB14: =SUM(O14:Z14) | AC14: 173 | AD14: 173 | AE14: 173 | AF14: 173 | AG14: 173 | AH14: 173 | AI14: =SUM(AC14:AH14) | AJ14: =SUM(AC14:AH14)+AI14 | AK14: =IF(N14<>0,(AB14-N14)/ABS(N14),0) | AL14: =IF(AB14<>0,(AJ14-AB14)/ABS(AB14),0)
A15: Training | B15: 270 | C15: 66 | D15: 145 | E15: 29.43 | F15: 291.7 | G15: 0 | H15: 298.2 | I15: 0 | J15: 0 | K15: 123.5 | L15: 247.5 | M15: 176.67 | N15: =SUM(B15:M15) | O15: 295.67 | P15: 29.94 | Q15: 177.97 | R15: 857.74 | S15: 106 | T15: 468.5 | U15: 579.1 | AA15: =SUM(O15:U15) | AB15: =SUM(O15:Z15) | AC15: 323 | AD15: 323 | AE15: 323 | AF15: 323 | AG15: 323 | AH15: 323 | AI15: =SUM(AC15:AH15) | AJ15: =SUM(AC15:AH15)+AI15 | AK15: =IF(N15<>0,(AB15-N15)/ABS(N15),0) | AL15: =IF(AB15<>0,(AJ15-AB15)/ABS(AB15),0)
A16: Staff Welfare | B16: 92.7 | C16: 249.13 | D16: 279.46 | E16: 346.01 | F16: 289.41 | G16: 78.07 | H16: 604.42 | I16: 209.95 | J16: 136.72 | K16: 248.7 | L16: 246.42 | M16: 79.21 | N16: =SUM(B16:M16) | O16: 150.67 | P16: 252.42 | Q16: 238.57 | R16: 211.38 | S16: 213.69 | T16: 198.14 | U16: 358.37 | AA16: =SUM(O16:U16) | AB16: =SUM(O16:Z16) | AC16: 211 | AD16: 211 | AE16: 211 | AF16: 211 | AG16: 211 | AH16: 211 | AI16: =SUM(AC16:AH16) | AJ16: =SUM(AC16:AH16)+AI16 | AK16: =IF(N16<>0,(AB16-N16)/ABS(N16),0) | AL16: =IF(AB16<>0,(AJ16-AB16)/ABS(AB16),0)
A17: Recruitment | B17: 0 | C17: 0 | D17: 0 | E17: 0 | F17: 0 | G17: 0 | H17: 0 | I17: 0 | J17: 0 | K17: 0 | L17: 0 | M17: 0 | N17: =SUM(B17:M17) | O17: 0 | P17: 0 | Q17: 0 | R17: 0 | S17: 0 | T17: 0 | U17: 0 | V17: 0 | W17: 0 | X17: 0 | Y17: 0 | Z17: 0 | AA17: =SUM(O17:U17) | AB17: =SUM(O17:Z17) | AC17: 0 | AD17: 0 | AE17: 0 | AF17: 0 | AG17: 0 | AH17: 0 | AI17: =SUM(AC17:AH17) | AJ17: =SUM(AC17:AH17)+AI17 | AK17: =IF(N17<>0,(AB17-N17)/ABS(N17),0) | AL17: =IF(AB17<>0,(AJ17-AB17)/ABS(AB17),0)
A18: Rewards & Recognition | B18: 0 | C18: 0 | D18: 0 | E18: 0 | F18: 0 | G18: 0 | H18: 330 | I18: 25 | J18: 0 | K18: 48.95 | L18: 21.64 | M18: 218.89 | N18: =SUM(B18:M18) | O18: 106.69 | P18: 67.96 | Q18: 139.8 | R18: 111.47 | S18: 216.45 | T18: 83.25 | U18: 113.9 | AA18: =SUM(O18:U18) | AB18: =SUM(O18:Z18) | AC18: 121 | AD18: 121 | AE18: 121 | AF18: 121 | AG18: 121 | AH18: 121 | AI18: =SUM(AC18:AH18) | AJ18: =SUM(AC18:AH18)+AI18 | AK18: =IF(N18<>0,(AB18-N18)/ABS(N18),0) | AL18: =IF(AB18<>0,(AJ18-AB18)/ABS(AB18),0)
A19: Temps | B19: 0 | C19: 0 | D19: 0 | E19: 0 | F19: 0 | G19: 0 | H19: 0 | I19: 0 | J19: 0 | K19: 0 | L19: 0 | M19: 0 | N19: =SUM(B19:M19) | O19: 0 | P19: 0 | Q19: 0 | R19: 0 | S19: 0 | T19: 0 | U19: 0 | V19: 0 | W19: 0 | X19: 0 | Y19: 0 | Z19: 0 | AA19: =SUM(O19:U19) | AB19: =SUM(O19:Z19) | AC19: 0 | AD19: 0 | AE19: 0 | AF19: 0 | AG19: 0 | AH19: 0 | AI19: =SUM(AC19:AH19) | AJ19: =SUM(AC19:AH19)+AI19 | AK19: =IF(N19<>0,(AB19-N19)/ABS(N19),0) | AL19: =IF(AB19<>0,(AJ19-AB19)/ABS(AB19),0)
A20: Total Personnel | B20: =B11+B12+B13+B14+B15+B16+B17+B18+B19 | C20: =C11+C12+C13+C14+C15+C16+C17+C18+C19 | D20: =D11+D12+D13+D14+D15+D16+D17+D18+D19 | E20: =E11+E12+E13+E14+E15+E16+E17+E18+E19 | F20: =F11+F12+F13+F14+F15+F16+F17+F18+F19 | G20: =G11+G12+G13+G14+G15+G16+G17+G18+G19 | H20: =H11+H12+H13+H14+H15+H16+H17+H18+H19 | I20: =I11+I12+I13+I14+I15+I16+I17+I18+I19 | ... AJ20: =AJ11+AJ12+AJ13+AJ14+AJ15+AJ16+AJ17+AJ18+AJ19 | AK20: =IF(N20<>0,(AB20-N20)/ABS(N20),0) | AL20: =IF(AB20<>0,(AJ20-AB20)/ABS(AB20),0)
A21: Sal:Rev | B21: =IF(B7>0,B20/B7,0) | C21: =IF(C7>0,C20/C7,0) | D21: =IF(D7>0,D20/D7,0) | E21: =IF(E7>0,E20/E7,0) | F21: =IF(F7>0,F20/F7,0) | G21: =IF(G7>0,G20/G7,0) | H21: =IF(H7>0,H20/H7,0) | I21: =IF(I7>0,I20/I7,0) | ... AJ21: =IF(AJ7>0,AJ20/AJ7,0)
A23: Childcare
A24: Catering Costs | N24: =SUM(B24:M24) | O24: 1508.1 | P24: 1785.93 | Q24: 1663.75 | R24: 1925.35 | S24: 1813.7 | T24: 2243.37 | U24: 1983.4 | V24: 2224.935 | W24: 3005.0682 | X24: 3228.8766 | Y24: 3386.9226 | Z24: 3287.8974 | AA24: =SUM(O24:U24) | AB24: =SUM(O24:Z24) | AC24: 3357.7582 | AD24: 3879.9813 | AE24: 3030.1256 | AF24: 3476.0917 | AG24: 3689.1422 | AH24: 3506.1923 | AI24: =SUM(AC24:AH24) | AJ24: =SUM(AC24:AH24)+AI24 | AK24: =IF(N24<>0,(AB24-N24)/ABS(N24),0) | AL24: =IF(AB24<>0,(AJ24-AB24)/ABS(AB24),0)
A25: Toys and Games | B25: 91.51 | C25: 452.3 | D25: 327.22 | E25: 103.6 | F25: 851.51 | G25: 37.37 | H25: 2634.18 | I25: 1272.86 | J25: -132.59 | K25: 313.94 | L25: 334.54 | M25: 543.53 | N25: =SUM(B25:M25) | O25: 100.23 | P25: 133.83 | Q25: 501.26 | R25: 235.26 | S25: 513.58 | T25: 239.97 | U25: 555.67 | AA25: =SUM(O25:U25) | AB25: =SUM(O25:Z25) | AC25: 100 | AD25: 100 | AE25: 100 | AF25: 100 | AG25: 100 | AH25: 100 | AI25: =SUM(AC25:AH25) | AJ25: =SUM(AC25:AH25)+AI25 | AK25: =IF(N25<>0,(AB25-N25)/ABS(N25),0) | AL25: =IF(AB25<>0,(AJ25-AB25)/ABS(AB25),0)
A26: Art Materials | N26: =SUM(B26:M26) | O26: 303.04 | P26: 223.68 | Q26: 252.26 | R26: 79.11 | S26: 149.63 | T26: 291.66 | U26: 81 | V26: 296.658 | W26: 400.67576 | X26: 430.51688 | Y26: 451.58968 | Z26: 438.38632 | AA26: =SUM(O26:U26) | AB26: =SUM(O26:Z26) | AC26: 447.70109 | AD26: 517.33084 | AE26: 404.01675 | AF26: 463.47889 | AG26: 491.88562 | AH26: 467.49231 | AI26: =SUM(AC26:AH26) | AJ26: =SUM(AC26:AH26)+AI26 | AK26: =IF(N26<>0,(AB26-N26)/ABS(N26),0) | AL26: =IF(AB26<>0,(AJ26-AB26)/ABS(AB26),0)
A27: Nursery Stationery | B27: 94.15 | C27: 42.29 | D27: 57.79 | E27: 75.59 | F27: 44.53 | G27: 83.45 | H27: 34.42 | I27: 28.37 | J27: 31.5 | K27: 12.34 | L27: 338.1 | M27: 33.94 | N27: =SUM(B27:M27) | O27: 168.45 | P27: 260.32 | Q27: 107.71 | R27: 152.41 | S27: 36.04 | T27: 155.55 | U27: 55.27 | AA27: =SUM(O27:U27) | AB27: =SUM(O27:Z27) | AC27: 100 | AD27: 100 | AE27: 100 | AF27: 100 | AG27: 100 | AH27: 100 | AI27: =SUM(AC27:AH27) | AJ27: =SUM(AC27:AH27)+AI27 | AK27: =IF(N27<>0,(AB27-N27)/ABS(N27),0) | AL27: =IF(AB27<>0,(AJ27-AB27)/ABS(AB27),0)
A28: Nursery Equipment | B28: 189.9 | C28: 131.91 | D28: 63.11 | E28: 17.99 | F28: 140.72 | G28: 671.26 | H28: 453.3 | I28: 32.21 | J28: 25.47 | K28: 59.66 | L28: 94.7 | M28: 57.97 | N28: =SUM(B28:M28) | O28: 275.4 | P28: 107.01 | Q28: 152.55 | R28: 51.51 | S28: 816.79 | T28: 427.2 | U28: 120.7 | AA28: =SUM(O28:U28) | AB28: =SUM(O28:Z28) | AC28: 100 | AD28: 100 | AE28: 100 | AF28: 100 | AG28: 100 | AH28: 100 | AI28: =SUM(AC28:AH28) | AJ28: =SUM(AC28:AH28)+AI28 | AK28: =IF(N28<>0,(AB28-N28)/ABS(N28),0) | AL28: =IF(AB28<>0,(AJ28-AB28)/ABS(AB28),0)
A29: Nursery Consumables | N29: =SUM(B29:M29) | O29: 382.52 | P29: 459.73 | Q29: 663.45 | R29: 360.23 | S29: 640.16 | T29: 717.62 | U29: 558.66 | V29: 436.59102 | W29: 589.67376 | X29: 633.59088 | Y29: 664.60368 | Z29: 645.17232 | AA29: =SUM(O29:U29) | AB29: =SUM(O29:Z29) | AC29: 658.88085 | AD29: 761.35482 | AE29: 594.59069 | AF29: 682.10101 | AG29: 723.90714 | AH29: 688.00755 | AI29: =SUM(AC29:AH29) | AJ29: =SUM(AC29:AH29)+AI29 | AK29: =IF(N29<>0,(AB29-N29)/ABS(N29),0) | AL29: =IF(AB29<>0,(AJ29-AB29)/ABS(AB29),0)
A30: Total Childcare Costs | B30: =B24+B25+B26+B27+B28+B29 | C30: =C24+C25+C26+C27+C28+C29 | D30: =D24+D25+D26+D27+D28+D29 | E30: =E24+E25+E26+E27+E28+E29 | F30: =F24+F25+F26+F27+F28+F29 | G30: =G24+G25+G26+G27+G28+G29 | H30: =H24+H25+H26+H27+H28+H29 | I30: =I24+I25+I26+I27+I28+I29 | ... AJ30: =AJ24+AJ25+AJ26+AJ27+AJ28+AJ29 | AK30: =IF(N30<>0,(AB30-N30)/ABS(N30),0) | AL30: =IF(AB30<>0,(AJ30-AB30)/ABS(AB30),0)
A32: Premises & Admin
A33: Rent | B33: 0 | C33: 0 | D33: 0 | E33: 0 | F33: 0 | G33: 0 | H33: 0 | I33: 0 | J33: 0 | K33: 0 | L33: 0 | M33: 0 | N33: =SUM(B33:M33) | O33: 0 | P33: 0 | Q33: 0 | R33: 0 | S33: 0 | T33: 0 | U33: 0 | V33: 0 | W33: 0 | X33: 0 | Y33: 0 | Z33: 0 | AA33: =SUM(O33:U33) | AB33: =SUM(O33:Z33) | AC33: 0 | AD33: 0 | AE33: 0 | AF33: 0 | AG33: 0 | AH33: 0 | AI33: =SUM(AC33:AH33) | AJ33: =SUM(AC33:AH33)+AI33 | AK33: =IF(N33<>0,(AB33-N33)/ABS(N33),0) | AL33: =IF(AB33<>0,(AJ33-AB33)/ABS(AB33),0)
A34: Business Rates | B34: 1704.92 | C34: 1704.92 | D34: 1704.92 | E34: 1704.92 | F34: 1704.92 | G34: 1704.92 | H34: 1704.92 | I34: 1704.92 | J34: 1704.92 | K34: 1704.92 | L34: 1704.92 | M34: 1704.92 | N34: =SUM(B34:M34) | O34: 1704.91 | P34: 1704.91 | Q34: 1704.9 | R34: 1823.25 | S34: 1823.25 | T34: 1823.25 | U34: 1823.25 | AA34: =SUM(O34:U34) | AB34: =SUM(O34:Z34) | AC34: 1823.25 | AD34: 1823.25 | AE34: 1823.25 | AF34: 1823.25 | AG34: 1823.25 | AH34: 1823.25 | AI34: =SUM(AC34:AH34) | AJ34: =SUM(AC34:AH34)+AI34 | AK34: =IF(N34<>0,(AB34-N34)/ABS(N34),0) | AL34: =IF(AB34<>0,(AJ34-AB34)/ABS(AB34),0)
A35: Utilities | B35: 895.97 | C35: 27.47 | D35: 1315.56 | E35: 712.07 | F35: 4544.52 | G35: 684.57 | H35: 627.64 | I35: 514.2 | J35: -607.48 | K35: 4237.07 | L35: 769.03 | M35: 2369.66 | N35: =SUM(B35:M35) | O35: 899.42 | P35: 3128.63 | Q35: 1798.29 | R35: 1482.2 | S35: 906.43 | T35: 319.81 | U35: 724.03 | AA35: =SUM(O35:U35) | AB35: =SUM(O35:Z35) | AC35: 1429 | AD35: 1429 | AE35: 1429 | AF35: 1429 | AG35: 1429 | AH35: 1429 | AI35: =SUM(AC35:AH35) | AJ35: =SUM(AC35:AH35)+AI35 | AK35: =IF(N35<>0,(AB35-N35)/ABS(N35),0) | AL35: =IF(AB35<>0,(AJ35-AB35)/ABS(AB35),0)
A36: Repairs & Maintenance | B36: 46.95 | C36: 4832.91 | D36: 603.49 | E36: 179.64 | F36: 504.08 | G36: 1430 | H36: 0 | I36: 5.99 | J36: 14 | K36: 0 | L36: 55.29 | M36: 225.21 | N36: =SUM(B36:M36) | O36: 0 | P36: 57.06 | Q36: 9.14 | R36: 10.19 | S36: 141.97 | T36: 150.64 | U36: 415.34 | AA36: =SUM(O36:U36) | AB36: =SUM(O36:Z36) | AC36: 0 | AD36: 0 | AE36: 0 | AF36: 0 | AG36: 0 | AH36: 0 | AI36: =SUM(AC36:AH36) | AJ36: =SUM(AC36:AH36)+AI36 | AK36: =IF(N36<>0,(AB36-N36)/ABS(N36),0) | AL36: =IF(AB36<>0,(AJ36-AB36)/ABS(AB36),0)
A37: Cleaning | B37: 1610.41 | C37: 1341.28 | D37: 618.85 | E37: 1357.49 | F37: 1371.67 | G37: 703.42 | H37: 477.23 | I37: 1549.67 | J37: 1414.78 | K37: 1644.37 | L37: 1432.79 | M37: 1367.21 | N37: =SUM(B37:M37) | O37: 1432.83 | P37: 1526.79 | Q37: 1392.29 | R37: 1387.82 | S37: 235.62 | T37: 321.07 | U37: 332.24 | AA37: =SUM(O37:U37) | AB37: =SUM(O37:Z37) | AC37: 400 | AD37: 400 | AE37: 400 | AF37: 400 | AG37: 400 | AH37: 400 | AI37: =SUM(AC37:AH37) | AJ37: =SUM(AC37:AH37)+AI37 | AK37: =IF(N37<>0,(AB37-N37)/ABS(N37),0) | AL37: =IF(AB37<>0,(AJ37-AB37)/ABS(AB37),0)
A38: Waste Disposal | B38: 384.51 | C38: 339.51 | D38: 605.71 | E38: 354.44 | F38: 460.69 | G38: 328.31 | H38: 432.13 | I38: 328.31 | J38: 474.42 | K38: 328.32 | L38: 445.29 | M38: 381.72 | N38: =SUM(B38:M38) | O38: 335.82 | P38: 454.31 | Q38: 484.3 | R38: 586.95 | S38: 531.72 | T38: 247.26 | U38: 599.65 | AA38: =SUM(O38:U38) | AB38: =SUM(O38:Z38) | AC38: 400 | AD38: 400 | AE38: 400 | AF38: 400 | AG38: 400 | AH38: 400 | AI38: =SUM(AC38:AH38) | AJ38: =SUM(AC38:AH38)+AI38 | AK38: =IF(N38<>0,(AB38-N38)/ABS(N38),0) | AL38: =IF(AB38<>0,(AJ38-AB38)/ABS(AB38),0)
A39: Postage/Printing/Stationery | B39: 137.34 | C39: 73.97 | D39: 80.18 | E39: 84.23 | F39: 71.16 | G39: 66.28 | H39: 105.45 | I39: 71.08 | J39: 92.42 | K39: 81.83 | L39: 67.49 | M39: 78.18 | N39: =SUM(B39:M39) | O39: 56.7 | P39: 92.7 | Q39: 63.53 | R39: 87.16 | S39: 87.41 | T39: 180.51 | U39: 100.82 | AA39: =SUM(O39:U39) | AB39: =SUM(O39:Z39) | AC39: 106 | AD39: 106 | AE39: 106 | AF39: 106 | AG39: 106 | AH39: 106 | AI39: =SUM(AC39:AH39) | AJ39: =SUM(AC39:AH39)+AI39 | AK39: =IF(N39<>0,(AB39-N39)/ABS(N39),0) | AL39: =IF(AB39<>0,(AJ39-AB39)/ABS(AB39),0)
A40: Telephone | B40: 0 | C40: 0 | D40: 0 | E40: 0 | F40: 0 | G40: 0 | H40: 0 | I40: 0 | J40: 0 | K40: 0 | L40: 0 | M40: 0 | N40: =SUM(B40:M40) | O40: 0 | P40: 0 | Q40: 390 | R40: 0 | S40: 0 | T40: 0 | U40: 0 | AA40: =SUM(O40:U40) | AB40: =SUM(O40:Z40) | AC40: 0 | AD40: 0 | AE40: 0 | AF40: 0 | AG40: 0 | AH40: 0 | AI40: =SUM(AC40:AH40) | AJ40: =SUM(AC40:AH40)+AI40 | AK40: =IF(N40<>0,(AB40-N40)/ABS(N40),0) | AL40: =IF(AB40<>0,(AJ40-AB40)/ABS(AB40),0)
A41: Marketing | B41: 0 | C41: 0 | D41: 588.81 | E41: 0 | F41: 0 | G41: 45 | H41: 0 | I41: 45 | J41: 0 | K41: 0 | L41: 0 | M41: 0 | N41: =SUM(B41:M41) | O41: 135 | P41: 0 | Q41: 0 | R41: 147 | S41: 6.99 | T41: 220 | U41: 0 | AA41: =SUM(O41:U41) | AB41: =SUM(O41:Z41) | AC41: 106 | AD41: 106 | AE41: 106 | AF41: 106 | AG41: 106 | AH41: 106 | AI41: =SUM(AC41:AH41) | AJ41: =SUM(AC41:AH41)+AI41 | AK41: =IF(N41<>0,(AB41-N41)/ABS(N41),0) | AL41: =IF(AB41<>0,(AJ41-AB41)/ABS(AB41),0)
A42: Total Premises & Admin | B42: =B33+B34+B35+B36+B37+B38+B39+B40+B41 | C42: =C33+C34+C35+C36+C37+C38+C39+C40+C41 | D42: =D33+D34+D35+D36+D37+D38+D39+D40+D41 | E42: =E33+E34+E35+E36+E37+E38+E39+E40+E41 | F42: =F33+F34+F35+F36+F37+F38+F39+F40+F41 | G42: =G33+G34+G35+G36+G37+G38+G39+G40+G41 | H42: =H33+H34+H35+H36+H37+H38+H39+H40+H41 | I42: =I33+I34+I35+I36+I37+I38+I39+I40+I41 | ... AJ42: =AJ33+AJ34+AJ35+AJ36+AJ37+AJ38+AJ39+AJ40+AJ41 | AK42: =IF(N42<>0,(AB42-N42)/ABS(N42),0) | AL42: =IF(AB42<>0,(AJ42-AB42)/ABS(AB42),0)
A44: Total Direct Costs | AK44: =IF(N44<>0,(AB44-N44)/ABS(N44),0) | AL44: =IF(AB44<>0,(AJ44-AB44)/ABS(AB44),0)
A46: CONTRIBUTION | B46: =B7-B44 | C46: =C7-C44 | D46: =D7-D44 | E46: =E7-E44 | F46: =F7-F44 | G46: =G7-G44 | H46: =H7-H44 | I46: =I7-I44 | ... AJ46: =AJ7-AJ44 | AK46: =IF(N46<>0,(AB46-N46)/ABS(N46),0) | AL46: =IF(AB46<>0,(AJ46-AB46)/ABS(AB46),0)

Sheet BK
A1: Bees Knees | B1: Actuals 2025 | O1: 2026 Actual / Forecast | AC1: 2027 Forecast | AK1: YoY | AL1: YoY
B2: Jan | C2: Feb | D2: Mar | E2: Apr | F2: May | G2: Jun | H2: Jul | I2: Aug | J2: Sep | K2: Oct | L2: Nov | M2: Dec | N2: FY2025 Total | O2: Jan | P2: Feb | Q2: Mar | R2: Apr | S2: May | T2: Jun | U2: Jul | V2: Aug | W2: Sep | X2: Oct | Y2: Nov | Z2: Dec | AA2: YTD | AB2: FY2026 Outlook | AC2: Jan | AD2: Feb | AE2: Mar | AF2: Apr | AG2: May | AH2: Jun | AI2: Jul-Dec Proj. | AJ2: FY2027 | AK2: 25→26 % | AL2: 26→27 %
A3: INCOME
A4: Fee Income Regular | B4: 28822.91 | C4: 27527.48 | D4: 31969.83 | E4: 35157.71 | F4: 28423.99 | G4: 26822.46 | H4: 35071.73 | I4: 29292.16 | J4: 20414.75 | K4: 19819.13 | L4: 18348.67 | M4: 27249.99 | N4: =SUM(B4:M4) | O4: 23326.9 | P4: 20657.48 | Q4: 21148.33 | R4: 24565.23 | S4: 21826.64 | T4: 23094.61 | U4: 27100.72 | AA4: =SUM(O4:U4) | AB4: =SUM(O4:Z4) | AC4: 33849.27 | AD4: 40863.29 | AE4: 33168.87 | AF4: 37302.1 | AG4: 39624.94 | AH4: 49227.72 | AI4: =SUM(AC4:AH4) | AJ4: =SUM(AC4:AH4)+AI4 | AK4: =IF(N4<>0,(AB4-N4)/ABS(N4),0) | AL4: =IF(AB4<>0,(AJ4-AB4)/ABS(AB4),0)
A5: EEEF Embedded | B5: 8562.4 | C5: 8562.4 | D5: 33256.45 | E5: 10591.2 | F5: 10591.2 | G5: 21480.3 | H5: 21480.3 | I5: 0 | J5: 15872.22 | K5: 15872.22 | L5: 18615.75 | M5: 19798.35 | N5: =SUM(B5:M5) | O5: 18772.32 | P5: 23544.12 | Q5: 23544.12 | R5: 16732.05 | S5: 16732.05 | T5: 18043.28 | U5: 18043.28 | AA5: =SUM(O5:U5) | AB5: =SUM(O5:Z5) | AC5: 0 | AD5: 0 | AE5: 0 | AF5: 0 | AG5: 0 | AH5: 0 | AI5: =SUM(AC5:AH5) | AJ5: =SUM(AC5:AH5)+AI5 | AK5: =IF(N5<>0,(AB5-N5)/ABS(N5),0) | AL5: =IF(AB5<>0,(AJ5-AB5)/ABS(AB5),0)
A6: Other Income | B6: 100 | C6: 0 | D6: 100 | E6: 300 | F6: 0 | G6: 300 | H6: 0 | I6: 2568.76 | J6: 450 | K6: 150 | L6: 300 | M6: 300 | N6: =SUM(B6:M6) | O6: 650 | P6: 150 | Q6: 300 | R6: 150 | S6: 150 | T6: 0 | U6: 300 | AA6: =SUM(O6:U6) | AB6: =SUM(O6:Z6) | AC6: 0 | AD6: 0 | AE6: 0 | AF6: 0 | AG6: 0 | AH6: 0 | AI6: =SUM(AC6:AH6) | AJ6: =SUM(AC6:AH6)+AI6 | AK6: =IF(N6<>0,(AB6-N6)/ABS(N6),0) | AL6: =IF(AB6<>0,(AJ6-AB6)/ABS(AB6),0)
A7: Total Income | B7: =B4+B5+B6 | C7: =C4+C5+C6 | D7: =D4+D5+D6 | E7: =E4+E5+E6 | F7: =F4+F5+F6 | G7: =G4+G5+G6 | H7: =H4+H5+H6 | I7: =I4+I5+I6 | ... AJ7: =AJ4+AJ5+AJ6 | AK7: =IF(N7<>0,(AB7-N7)/ABS(N7),0) | AL7: =IF(AB7<>0,(AJ7-AB7)/ABS(AB7),0)
A9: DIRECT COSTS
A10: Personnel
A11: Nursery Salaries | B11: 17812.5 | C11: 17339.68 | D11: 20177.72 | E11: 22232.54 | F11: 22270.94 | G11: 23588.71 | H11: 23343.5 | I11: 23511.85 | J11: 20681.56 | K11: 22301.58 | L11: 19748.45 | M11: 21714.13 | N11: =SUM(B11:M11) | O11: 22032.4 | P11: 23448.09 | Q11: 21766.47 | R11: 24395.78 | S11: 23187.74 | T11: 23614.63 | U11: 23226.6 | AA11: =SUM(O11:U11) | AB11: =SUM(O11:Z11) | AC11: 23226.6 | AD11: 23226.6 | AE11: 23226.6 | AF11: 23226.6 | AG11: 23226.6 | AH11: 23226.6 | AI11: =SUM(AC11:AH11) | AJ11: =SUM(AC11:AH11)+AI11 | AK11: =IF(N11<>0,(AB11-N11)/ABS(N11),0) | AL11: =IF(AB11<>0,(AJ11-AB11)/ABS(AB11),0)
A12: Nursery NI | B12: 1475.26 | C12: 1417.07 | D12: 1686.46 | E12: 2563.92 | F12: 2567.89 | G12: 2767.34 | H12: 2749.77 | I12: 2755.82 | J12: 2340.87 | K12: 2518.95 | L12: 2309.57 | M12: 2480.48 | N12: =SUM(B12:M12) | O12: 2577.7 | P12: 2679.93 | Q12: 2363.36 | R12: 2662.5 | S12: 2390.53 | T12: 2246.22 | U12: 2177.1 | AA12: =SUM(O12:U12) | AB12: =SUM(O12:Z12) | AC12: 2177.1 | AD12: 2177.1 | AE12: 2177.1 | AF12: 2177.1 | AG12: 2177.1 | AH12: 2177.1 | AI12: =SUM(AC12:AH12) | AJ12: =SUM(AC12:AH12)+AI12 | AK12: =IF(N12<>0,(AB12-N12)/ABS(N12),0) | AL12: =IF(AB12<>0,(AJ12-AB12)/ABS(AB12),0)
A13: Nursery Pension | B13: 347.13 | C13: 330.13 | D13: 333.41 | E13: 342.51 | F13: 397.67 | G13: 473.08 | H13: 489.34 | I13: 523.31 | J13: 440.32 | K13: 418.9 | L13: 382.73 | M13: 421.57 | N13: =SUM(B13:M13) | O13: 404.05 | P13: 451.49 | Q13: 394.61 | R13: 507.74 | S13: 453.36 | T13: 427.58 | U13: 413.76 | AA13: =SUM(O13:U13) | AB13: =SUM(O13:Z13) | AC13: 413.76 | AD13: 413.76 | AE13: 413.76 | AF13: 413.76 | AG13: 413.76 | AH13: 413.76 | AI13: =SUM(AC13:AH13) | AJ13: =SUM(AC13:AH13)+AI13 | AK13: =IF(N13<>0,(AB13-N13)/ABS(N13),0) | AL13: =IF(AB13<>0,(AJ13-AB13)/ABS(AB13),0)
A14: Uniform | B14: 0 | C14: 59.28 | D14: 0 | E14: 105.18 | F14: 155.4 | G14: 104.69 | H14: 11.99 | I14: 0 | J14: 0 | K14: 0 | L14: 0 | M14: 401.76 | N14: =SUM(B14:M14) | O14: 0 | P14: 38.12 | Q14: 85.02 | R14: 51.5 | S14: 0 | T14: 0 | U14: 110.94 | AA14: =SUM(O14:U14) | AB14: =SUM(O14:Z14) | AC14: 50 | AD14: 50 | AE14: 50 | AF14: 50 | AG14: 50 | AH14: 50 | AI14: =SUM(AC14:AH14) | AJ14: =SUM(AC14:AH14)+AI14 | AK14: =IF(N14<>0,(AB14-N14)/ABS(N14),0) | AL14: =IF(AB14<>0,(AJ14-AB14)/ABS(AB14),0)
A15: Training | B15: 57 | C15: 0 | D15: 0 | E15: 0 | F15: 0 | G15: 24 | H15: 0 | I15: 33 | J15: 0 | K15: 684 | L15: 172.6 | M15: 384 | N15: =SUM(B15:M15) | O15: 0 | P15: 114 | Q15: 480 | R15: 0 | S15: 0 | T15: 0 | U15: 83.88 | AA15: =SUM(O15:U15) | AB15: =SUM(O15:Z15) | AC15: 0 | AD15: 0 | AE15: 0 | AF15: 0 | AG15: 0 | AH15: 0 | AI15: =SUM(AC15:AH15) | AJ15: =SUM(AC15:AH15)+AI15 | AK15: =IF(N15<>0,(AB15-N15)/ABS(N15),0) | AL15: =IF(AB15<>0,(AJ15-AB15)/ABS(AB15),0)
A16: Staff Welfare | B16: 53.68 | C16: 350.21 | D16: 17.06 | E16: 46.05 | F16: 300.11 | G16: 272.05 | H16: 224.64 | I16: 246.79 | J16: 129.2 | K16: 88.43 | L16: 342.9 | M16: 243.13 | N16: =SUM(B16:M16) | O16: 727.69 | P16: 91.99 | Q16: 354.17 | R16: 348.94 | S16: 77.08 | T16: 154.95 | U16: 550.89 | AA16: =SUM(O16:U16) | AB16: =SUM(O16:Z16) | AC16: 80 | AD16: 80 | AE16: 80 | AF16: 80 | AG16: 80 | AH16: 80 | AI16: =SUM(AC16:AH16) | AJ16: =SUM(AC16:AH16)+AI16 | AK16: =IF(N16<>0,(AB16-N16)/ABS(N16),0) | AL16: =IF(AB16<>0,(AJ16-AB16)/ABS(AB16),0)
A17: Recruitment | B17: 0 | C17: 0 | D17: 0 | E17: 0 | F17: 0 | G17: 0 | H17: 0 | I17: 0 | J17: 3861 | K17: 0 | L17: 0 | M17: 0 | N17: =SUM(B17:M17) | O17: 0 | P17: 0 | Q17: 0 | R17: 0 | S17: 0 | T17: 0 | U17: 0 | V17: 0 | W17: 0 | X17: 0 | Y17: 0 | Z17: 0 | AA17: =SUM(O17:U17) | AB17: =SUM(O17:Z17) | AC17: 0 | AD17: 0 | AE17: 0 | AF17: 0 | AG17: 0 | AH17: 0 | AI17: =SUM(AC17:AH17) | AJ17: =SUM(AC17:AH17)+AI17 | AK17: =IF(N17<>0,(AB17-N17)/ABS(N17),0) | AL17: =IF(AB17<>0,(AJ17-AB17)/ABS(AB17),0)
A18: Rewards & Recognition | B18: 0 | C18: 0 | D18: 0 | E18: 0 | F18: 0 | G18: 0 | H18: 12.8 | I18: 0 | J18: 22.88 | K18: 0 | L18: 50.97 | M18: 88.44 | N18: =SUM(B18:M18) | O18: 0 | P18: 0 | Q18: 0 | R18: 55.97 | S18: 47.98 | T18: 7.99 | U18: 38.98 | AA18: =SUM(O18:U18) | AB18: =SUM(O18:Z18) | AC18: 33 | AD18: 33 | AE18: 33 | AF18: 33 | AG18: 33 | AH18: 33 | AI18: =SUM(AC18:AH18) | AJ18: =SUM(AC18:AH18)+AI18 | AK18: =IF(N18<>0,(AB18-N18)/ABS(N18),0) | AL18: =IF(AB18<>0,(AJ18-AB18)/ABS(AB18),0)
A19: Temps | B19: 0 | C19: 0 | D19: 0 | E19: 0 | F19: 0 | G19: 0 | H19: 0 | I19: 0 | J19: 0 | K19: 475.44 | L19: 0 | M19: 0 | N19: =SUM(B19:M19) | O19: 0 | P19: 0 | Q19: 0 | R19: 0 | S19: 0 | T19: 0 | U19: 0 | V19: 0 | W19: 0 | X19: 0 | Y19: 0 | Z19: 0 | AA19: =SUM(O19:U19) | AB19: =SUM(O19:Z19) | AC19: 0 | AD19: 0 | AE19: 0 | AF19: 0 | AG19: 0 | AH19: 0 | AI19: =SUM(AC19:AH19) | AJ19: =SUM(AC19:AH19)+AI19 | AK19: =IF(N19<>0,(AB19-N19)/ABS(N19),0) | AL19: =IF(AB19<>0,(AJ19-AB19)/ABS(AB19),0)
A20: Total Personnel | B20: =B11+B12+B13+B14+B15+B16+B17+B18+B19 | C20: =C11+C12+C13+C14+C15+C16+C17+C18+C19 | D20: =D11+D12+D13+D14+D15+D16+D17+D18+D19 | E20: =E11+E12+E13+E14+E15+E16+E17+E18+E19 | F20: =F11+F12+F13+F14+F15+F16+F17+F18+F19 | G20: =G11+G12+G13+G14+G15+G16+G17+G18+G19 | H20: =H11+H12+H13+H14+H15+H16+H17+H18+H19 | I20: =I11+I12+I13+I14+I15+I16+I17+I18+I19 | ... AJ20: =AJ11+AJ12+AJ13+AJ14+AJ15+AJ16+AJ17+AJ18+AJ19 | AK20: =IF(N20<>0,(AB20-N20)/ABS(N20),0) | AL20: =IF(AB20<>0,(AJ20-AB20)/ABS(AB20),0)
A21: Sal:Rev | B21: =IF(B7>0,B20/B7,0) | C21: =IF(C7>0,C20/C7,0) | D21: =IF(D7>0,D20/D7,0) | E21: =IF(E7>0,E20/E7,0) | F21: =IF(F7>0,F20/F7,0) | G21: =IF(G7>0,G20/G7,0) | H21: =IF(H7>0,H20/H7,0) | I21: =IF(I7>0,I20/I7,0) | ... AJ21: =IF(AJ7>0,AJ20/AJ7,0)
A23: Childcare
A24: Catering Costs | N24: =SUM(B24:M24) | O24: 930.57 | P24: 1165.35 | Q24: 1341.06 | R24: 1180.59 | S24: 1129.19 | T24: 1238.46 | U24: 1343.35 | V24: 710.6112 | W24: 1009.2582 | X24: 1029.8808 | Y24: 989.6952 | Z24: 926.5464 | AA24: =SUM(O24:U24) | AB24: =SUM(O24:Z24) | AC24: 1056.0972 | AD24: 1274.9346 | AE24: 1034.8687 | AF24: 1163.8255 | AG24: 1236.2981 | AH24: 1535.9049 | AI24: =SUM(AC24:AH24) | AJ24: =SUM(AC24:AH24)+AI24 | AK24: =IF(N24<>0,(AB24-N24)/ABS(N24),0) | AL24: =IF(AB24<>0,(AJ24-AB24)/ABS(AB24),0)
A25: Toys and Games | B25: 85.72 | C25: 41.49 | D25: 55.22 | E25: 133.77 | F25: 115.2 | G25: 40.97 | H25: 119.18 | I25: 0 | J25: 937.39 | K25: 75.82 | L25: 34 | M25: 44.21 | N25: =SUM(B25:M25) | O25: 158.33 | P25: 73.69 | Q25: 139.02 | R25: 64.23 | S25: 65.86 | T25: 40.92 | U25: 61.05 | AA25: =SUM(O25:U25) | AB25: =SUM(O25:Z25) | AC25: 50 | AD25: 50 | AE25: 50 | AF25: 50 | AG25: 50 | AH25: 50 | AI25: =SUM(AC25:AH25) | AJ25: =SUM(AC25:AH25)+AI25 | AK25: =IF(N25<>0,(AB25-N25)/ABS(N25),0) | AL25: =IF(AB25<>0,(AJ25-AB25)/ABS(AB25),0)
A26: Art Materials | N26: =SUM(B26:M26) | O26: 36.95 | P26: 132.23 | Q26: 184.1 | R26: 15.97 | S26: 0 | T26: 39.16 | U26: 29.81 | V26: 94.74816 | W26: 134.56776 | X26: 137.31744 | Y26: 131.95936 | Z26: 123.53952 | AA26: =SUM(O26:U26) | AB26: =SUM(O26:Z26) | AC26: 140.81296 | AD26: 169.99129 | AE26: 137.9825 | AF26: 155.17674 | AG26: 164.83975 | AH26: 204.78732 | AI26: =SUM(AC26:AH26) | AJ26: =SUM(AC26:AH26)+AI26 | AK26: =IF(N26<>0,(AB26-N26)/ABS(N26),0) | AL26: =IF(AB26<>0,(AJ26-AB26)/ABS(AB26),0)
A27: Nursery Stationery | B27: 7.64 | C27: 23.2 | D27: 31.14 | E27: 14.94 | F27: 11.95 | G27: 23.88 | H27: 107.69 | I27: 201.64 | J27: 13.58 | K27: 61.35 | L27: 13.78 | M27: 158.03 | N27: =SUM(B27:M27) | O27: 72.57 | P27: 85.8 | Q27: 0 | R27: 49.71 | S27: 47.25 | T27: 25.12 | U27: 15.98 | AA27: =SUM(O27:U27) | AB27: =SUM(O27:Z27) | AC27: 50 | AD27: 50 | AE27: 50 | AF27: 50 | AG27: 50 | AH27: 50 | AI27: =SUM(AC27:AH27) | AJ27: =SUM(AC27:AH27)+AI27 | AK27: =IF(N27<>0,(AB27-N27)/ABS(N27),0) | AL27: =IF(AB27<>0,(AJ27-AB27)/ABS(AB27),0)
A28: Nursery Equipment | B28: 7.99 | C28: 25.96 | D28: 0 | E28: 57.87 | F28: 0 | G28: 152.18 | H28: 18.98 | I28: 40.86 | J28: 0 | K28: 337.45 | L28: 777.25 | M28: 160.58 | N28: =SUM(B28:M28) | O28: 42.68 | P28: 26.97 | Q28: 40.95 | R28: 46.3 | S28: 49.99 | T28: 44.99 | U28: 0 | AA28: =SUM(O28:U28) | AB28: =SUM(O28:Z28) | AC28: 50 | AD28: 50 | AE28: 50 | AF28: 50 | AG28: 50 | AH28: 50 | AI28: =SUM(AC28:AH28) | AJ28: =SUM(AC28:AH28)+AI28 | AK28: =IF(N28<>0,(AB28-N28)/ABS(N28),0) | AL28: =IF(AB28<>0,(AJ28-AB28)/ABS(AB28),0)
A29: Nursery Consumables | N29: =SUM(B29:M29) | O29: 175.68 | P29: 336.46 | Q29: 254.99 | R29: 144.3 | S29: 200.22 | T29: 395.74 | U29: 20.35 | V29: 94.74816 | W29: 134.56776 | X29: 137.31744 | Y29: 131.95936 | Z29: 123.53952 | AA29: =SUM(O29:U29) | AB29: =SUM(O29:Z29) | AC29: 140.81296 | AD29: 169.99129 | AE29: 137.9825 | AF29: 155.17674 | AG29: 164.83975 | AH29: 204.78732 | AI29: =SUM(AC29:AH29) | AJ29: =SUM(AC29:AH29)+AI29 | AK29: =IF(N29<>0,(AB29-N29)/ABS(N29),0) | AL29: =IF(AB29<>0,(AJ29-AB29)/ABS(AB29),0)
A30: Total Childcare Costs | B30: =B24+B25+B26+B27+B28+B29 | C30: =C24+C25+C26+C27+C28+C29 | D30: =D24+D25+D26+D27+D28+D29 | E30: =E24+E25+E26+E27+E28+E29 | F30: =F24+F25+F26+F27+F28+F29 | G30: =G24+G25+G26+G27+G28+G29 | H30: =H24+H25+H26+H27+H28+H29 | I30: =I24+I25+I26+I27+I28+I29 | ... AJ30: =AJ24+AJ25+AJ26+AJ27+AJ28+AJ29 | AK30: =IF(N30<>0,(AB30-N30)/ABS(N30),0) | AL30: =IF(AB30<>0,(AJ30-AB30)/ABS(AB30),0)
A32: Premises & Admin
A33: Rent | B33: 0 | C33: 0 | D33: 0 | E33: 0 | F33: 0 | G33: 0 | H33: 0 | I33: 0 | J33: 0 | K33: 0 | L33: 0 | M33: 0 | N33: =SUM(B33:M33) | O33: 0 | P33: 0 | Q33: 0 | R33: 0 | S33: 0 | T33: 0 | U33: 0 | V33: 0 | W33: 0 | X33: 0 | Y33: 0 | Z33: 0 | AA33: =SUM(O33:U33) | AB33: =SUM(O33:Z33) | AC33: 0 | AD33: 0 | AE33: 0 | AF33: 0 | AG33: 0 | AH33: 0 | AI33: =SUM(AC33:AH33) | AJ33: =SUM(AC33:AH33)+AI33 | AK33: =IF(N33<>0,(AB33-N33)/ABS(N33),0) | AL33: =IF(AB33<>0,(AJ33-AB33)/ABS(AB33),0)
A34: Business Rates | B34: 1060.38 | C34: 1060.38 | D34: 1060.38 | E34: 1060.38 | F34: 1060.38 | G34: 1060.38 | H34: 1060.38 | I34: 1060.38 | J34: 1060.38 | K34: 1060.38 | L34: 1060.38 | M34: 1060.38 | N34: =SUM(B34:M34) | O34: 1060.36 | P34: 1060.36 | Q34: 1060.36 | R34: 1178.67 | S34: 1178.67 | T34: 1178.67 | U34: 1178.67 | AA34: =SUM(O34:U34) | AB34: =SUM(O34:Z34) | AC34: 1178.6667 | AD34: 1178.6667 | AE34: 1178.6667 | AF34: 1178.6667 | AG34: 1178.6667 | AH34: 1178.6667 | AI34: =SUM(AC34:AH34) | AJ34: =SUM(AC34:AH34)+AI34 | AK34: =IF(N34<>0,(AB34-N34)/ABS(N34),0) | AL34: =IF(AB34<>0,(AJ34-AB34)/ABS(AB34),0)
A35: Utilities | B35: 1084.35 | C35: 1856.09 | D35: 680.11 | E35: 1041.36 | F35: 1404.7 | G35: 49.78 | H35: 566.46 | I35: 748.44 | J35: 123.63 | K35: 557.7 | L35: 914.73 | M35: 843.45 | N35: =SUM(B35:M35) | O35: 976.88 | P35: 1232.13 | Q35: 699.24 | R35: 870 | S35: 652.42 | T35: 416.51 | U35: 537.13 | AA35: =SUM(O35:U35) | AB35: =SUM(O35:Z35) | AC35: 808 | AD35: 808 | AE35: 808 | AF35: 808 | AG35: 808 | AH35: 808 | AI35: =SUM(AC35:AH35) | AJ35: =SUM(AC35:AH35)+AI35 | AK35: =IF(N35<>0,(AB35-N35)/ABS(N35),0) | AL35: =IF(AB35<>0,(AJ35-AB35)/ABS(AB35),0)
A36: Repairs & Maintenance | B36: 1970.4 | C36: 4574.36 | D36: 3343.43 | E36: 2248.52 | F36: 1000.26 | G36: 36.5 | H36: 1663.64 | I36: 470.86 | J36: 14.64 | K36: 856.82 | L36: 36 | M36: 171.36 | N36: =SUM(B36:M36) | O36: 0 | P36: 0 | Q36: 9.98 | R36: 0 | S36: 29.27 | T36: 121.79 | U36: 108 | AA36: =SUM(O36:U36) | AB36: =SUM(O36:Z36) | AC36: 0 | AD36: 0 | AE36: 0 | AF36: 0 | AG36: 0 | AH36: 0 | AI36: =SUM(AC36:AH36) | AJ36: =SUM(AC36:AH36)+AI36 | AK36: =IF(N36<>0,(AB36-N36)/ABS(N36),0) | AL36: =IF(AB36<>0,(AJ36-AB36)/ABS(AB36),0)
A37: Cleaning | B37: 188.6 | C37: 249.73 | D37: 292.16 | E37: 49.57 | F37: 542.98 | G37: 335.03 | H37: 284.16 | I37: 299.86 | J37: 559.89 | K37: 291.24 | L37: 101.59 | M37: 113.21 | N37: =SUM(B37:M37) | O37: 203.38 | P37: 611.38 | Q37: 303.73 | R37: 143.24 | S37: 217.05 | T37: 365.89 | U37: 206.52 | AA37: =SUM(O37:U37) | AB37: =SUM(O37:Z37) | AC37: 310 | AD37: 310 | AE37: 310 | AF37: 310 | AG37: 310 | AH37: 310 | AI37: =SUM(AC37:AH37) | AJ37: =SUM(AC37:AH37)+AI37 | AK37: =IF(N37<>0,(AB37-N37)/ABS(N37),0) | AL37: =IF(AB37<>0,(AJ37-AB37)/ABS(AB37),0)
A38: Waste Disposal | B38: 332.71 | C38: 364.75 | D38: 380.11 | E38: 561.51 | F38: 426.52 | G38: 400.96 | H38: 339.75 | I38: 354.05 | J38: 630.66 | K38: 354.05 | L38: 404.45 | M38: 415.26 | N38: =SUM(B38:M38) | O38: 354.05 | P38: 363.36 | Q38: 474.96 | R38: 471.4 | S38: 390.36 | T38: 255.3 | U38: 494.27 | AA38: =SUM(O38:U38) | AB38: =SUM(O38:Z38) | AC38: 385 | AD38: 385 | AE38: 385 | AF38: 385 | AG38: 385 | AH38: 385 | AI38: =SUM(AC38:AH38) | AJ38: =SUM(AC38:AH38)+AI38 | AK38: =IF(N38<>0,(AB38-N38)/ABS(N38),0) | AL38: =IF(AB38<>0,(AJ38-AB38)/ABS(AB38),0)
A39: Postage/Printing/Stationery | B39: 52.03 | C39: 23.34 | D39: 21.74 | E39: 61.92 | F39: 81.43 | G39: 32.69 | H39: 84.15 | I39: 53.12 | J39: 75.13 | K39: 81.79 | L39: 68.57 | M39: 86.96 | N39: =SUM(B39:M39) | O39: 87.21 | P39: 82.62 | Q39: 91.56 | R39: 93.77 | S39: 73.19 | T39: 98.51 | U39: 78.42 | AA39: =SUM(O39:U39) | AB39: =SUM(O39:Z39) | AC39: 0 | AD39: 0 | AE39: 0 | AF39: 0 | AG39: 0 | AH39: 0 | AI39: =SUM(AC39:AH39) | AJ39: =SUM(AC39:AH39)+AI39 | AK39: =IF(N39<>0,(AB39-N39)/ABS(N39),0) | AL39: =IF(AB39<>0,(AJ39-AB39)/ABS(AB39),0)
A40: Telephone | B40: 0 | C40: 0 | D40: 0 | E40: 0 | F40: 0 | G40: 0 | H40: 0 | I40: 0 | J40: 0 | K40: 0 | L40: 0 | M40: 0 | N40: =SUM(B40:M40) | O40: 0 | P40: 0 | Q40: 0 | R40: 0 | S40: 0 | T40: 22 | U40: 0 | AA40: =SUM(O40:U40) | AB40: =SUM(O40:Z40) | AC40: 0 | AD40: 0 | AE40: 0 | AF40: 0 | AG40: 0 | AH40: 0 | AI40: =SUM(AC40:AH40) | AJ40: =SUM(AC40:AH40)+AI40 | AK40: =IF(N40<>0,(AB40-N40)/ABS(N40),0) | AL40: =IF(AB40<>0,(AJ40-AB40)/ABS(AB40),0)
A41: Marketing | B41: 14.58 | C41: 14.58 | D41: 149.79 | E41: 234.58 | F41: 1.59 | G41: 46.59 | H41: -1.3 | I41: 45 | J41: 0 | K41: 0 | L41: 0 | M41: 0 | N41: =SUM(B41:M41) | O41: 66 | P41: 0 | Q41: 0 | R41: 72 | S41: 0 | T41: 0 | U41: 4.99 | AA41: =SUM(O41:U41) | AB41: =SUM(O41:Z41) | AC41: 100 | AD41: 100 | AE41: 100 | AF41: 100 | AG41: 100 | AH41: 100 | AI41: =SUM(AC41:AH41) | AJ41: =SUM(AC41:AH41)+AI41 | AK41: =IF(N41<>0,(AB41-N41)/ABS(N41),0) | AL41: =IF(AB41<>0,(AJ41-AB41)/ABS(AB41),0)
A42: Total Premises & Admin | B42: =B33+B34+B35+B36+B37+B38+B39+B40+B41 | C42: =C33+C34+C35+C36+C37+C38+C39+C40+C41 | D42: =D33+D34+D35+D36+D37+D38+D39+D40+D41 | E42: =E33+E34+E35+E36+E37+E38+E39+E40+E41 | F42: =F33+F34+F35+F36+F37+F38+F39+F40+F41 | G42: =G33+G34+G35+G36+G37+G38+G39+G40+G41 | H42: =H33+H34+H35+H36+H37+H38+H39+H40+H41 | I42: =I33+I34+I35+I36+I37+I38+I39+I40+I41 | ... AJ42: =AJ33+AJ34+AJ35+AJ36+AJ37+AJ38+AJ39+AJ40+AJ41 | AK42: =IF(N42<>0,(AB42-N42)/ABS(N42),0) | AL42: =IF(AB42<>0,(AJ42-AB42)/ABS(AB42),0)
A44: Total Direct Costs | AK44: =IF(N44<>0,(AB44-N44)/ABS(N44),0) | AL44: =IF(AB44<>0,(AJ44-AB44)/ABS(AB44),0)
A46: CONTRIBUTION | B46: =B7-B44 | C46: =C7-C44 | D46: =D7-D44 | E46: =E7-E44 | F46: =F7-F44 | G46: =G7-G44 | H46: =H7-H44 | I46: =I7-I44 | ... AJ46: =AJ7-AJ44 | AK46: =IF(N46<>0,(AB46-N46)/ABS(N46),0) | AL46: =IF(AB46<>0,(AJ46-AB46)/ABS(AB46),0)

Sheet BW
A1: Bramley Wood | B1: Actuals 2025 | O1: 2026 Actual / Forecast | AC1: 2027 Forecast | AK1: YoY | AL1: YoY
B2: Jan | C2: Feb | D2: Mar | E2: Apr | F2: May | G2: Jun | H2: Jul | I2: Aug | J2: Sep | K2: Oct | L2: Nov | M2: Dec | N2: FY2025 Total | O2: Jan | P2: Feb | Q2: Mar | R2: Apr | S2: May | T2: Jun | U2: Jul | V2: Aug | W2: Sep | X2: Oct | Y2: Nov | Z2: Dec | AA2: YTD | AB2: FY2026 Outlook | AC2: Jan | AD2: Feb | AE2: Mar | AF2: Apr | AG2: May | AH2: Jun | AI2: Jul-Dec Proj. | AJ2: FY2027 | AK2: 25→26 % | AL2: 26→27 %
A3: INCOME
A4: Fee Income Regular | B4: 122156.52 | C4: 106947.36 | D4: 128166.24 | E4: 139357.58 | F4: 114644.73 | G4: 108480.27 | H4: 145137.16 | I4: 119462.05 | J4: 97287.09 | K4: 96101.48 | L4: 84850.06 | M4: 119634.28 | N4: =SUM(B4:M4) | O4: 92712.5 | P4: 82084.3 | Q4: 99688.3 | R4: 113186 | S4: 93282.1 | T4: 104024 | U4: 127224 | AA4: =SUM(O4:U4) | AB4: =SUM(O4:Z4) | AC4: 144535.68 | AD4: 132031.1 | AE4: 158165.89 | AF4: 141527.16 | AG4: 148240.86 | AH4: 153396.96 | AI4: =SUM(AC4:AH4) | AJ4: =SUM(AC4:AH4)+AI4 | AK4: =IF(N4<>0,(AB4-N4)/ABS(N4),0) | AL4: =IF(AB4<>0,(AJ4-AB4)/ABS(AB4),0)
A5: EEEF Embedded | B5: 33585.45 | C5: 66581.12 | D5: 66581.12 | E5: 28706.8 | F5: 28706.8 | G5: 67317.07 | H5: 67317.05 | I5: 0 | J5: 35210.21 | K5: 33827.21 | L5: 97735.45 | M5: 101444.41 | N5: =SUM(B5:M5) | O5: 44989.2 | P5: 94001.8 | Q5: 103241 | R5: 48659.8 | S5: 48659.8 | T5: 112571 | U5: 69963.4 | AA5: =SUM(O5:U5) | AB5: =SUM(O5:Z5) | AC5: 0 | AD5: 0 | AE5: 0 | AF5: 0 | AG5: 0 | AH5: 0 | AI5: =SUM(AC5:AH5) | AJ5: =SUM(AC5:AH5)+AI5 | AK5: =IF(N5<>0,(AB5-N5)/ABS(N5),0) | AL5: =IF(AB5<>0,(AJ5-AB5)/ABS(AB5),0)
A6: Other Income | B6: 200 | C6: 200 | D6: 250 | E6: 150 | F6: 150 | G6: 150 | H6: 150 | I6: 12901.66 | J6: 150 | K6: 150 | L6: 150 | M6: 150 | N6: =SUM(B6:M6) | O6: 150 | P6: 150 | Q6: 150 | R6: 150 | S6: 150 | T6: 450 | U6: 150 | AA6: =SUM(O6:U6) | AB6: =SUM(O6:Z6) | AC6: 0 | AD6: 0 | AE6: 0 | AF6: 0 | AG6: 0 | AH6: 0 | AI6: =SUM(AC6:AH6) | AJ6: =SUM(AC6:AH6)+AI6 | AK6: =IF(N6<>0,(AB6-N6)/ABS(N6),0) | AL6: =IF(AB6<>0,(AJ6-AB6)/ABS(AB6),0)
A7: Total Income | B7: =B4+B5+B6 | C7: =C4+C5+C6 | D7: =D4+D5+D6 | E7: =E4+E5+E6 | F7: =F4+F5+F6 | G7: =G4+G5+G6 | H7: =H4+H5+H6 | I7: =I4+I5+I6 | ... AJ7: =AJ4+AJ5+AJ6 | AK7: =IF(N7<>0,(AB7-N7)/ABS(N7),0) | AL7: =IF(AB7<>0,(AJ7-AB7)/ABS(AB7),0)
A9: DIRECT COSTS
A10: Personnel
A11: Nursery Salaries | B11: 68586.24 | C11: 60676.75 | D11: 61011.57 | E11: 67443.19 | F11: 72917.98 | G11: 67825.41 | H11: 75334.7 | I11: 72777.63 | J11: 80807.62 | K11: 70161.91 | L11: 67160.5 | M11: 64917.87 | N11: =SUM(B11:M11) | O11: 67397.79 | P11: 65169.32 | Q11: 57920.38 | R11: 61937.98 | S11: 66920.32 | T11: 67131.93 | U11: 67043.3 | AA11: =SUM(O11:U11) | AB11: =SUM(O11:Z11) | AC11: 67043.3 | AD11: 67043.3 | AE11: 67043.3 | AF11: 67043.3 | AG11: 67043.3 | AH11: 67043.3 | AI11: =SUM(AC11:AH11) | AJ11: =SUM(AC11:AH11)+AI11 | AK11: =IF(N11<>0,(AB11-N11)/ABS(N11),0) | AL11: =IF(AB11<>0,(AJ11-AB11)/ABS(AB11),0)
A12: Nursery NI | B12: 5300.22 | C12: 4463.01 | D12: 4517.4 | E12: 6985.94 | F12: 7294.24 | G12: 6627.99 | H12: 7346.36 | I12: 7134.49 | J12: 9821.09 | K12: 6696.34 | L12: 6289.94 | M12: 6024.82 | N12: =SUM(B12:M12) | O12: 6420.59 | P12: 5749.78 | Q12: 5741.09 | R12: 6217.05 | S12: 6359.57 | T12: 6618.61 | U12: 6517.08 | AA12: =SUM(O12:U12) | AB12: =SUM(O12:Z12) | AC12: 6517.08 | AD12: 6517.08 | AE12: 6517.08 | AF12: 6517.08 | AG12: 6517.08 | AH12: 6517.08 | AI12: =SUM(AC12:AH12) | AJ12: =SUM(AC12:AH12)+AI12 | AK12: =IF(N12<>0,(AB12-N12)/ABS(N12),0) | AL12: =IF(AB12<>0,(AJ12-AB12)/ABS(AB12),0)
A13: Nursery Pension | B13: 1186.64 | C13: 1102.67 | D13: 1084.37 | E13: 1172.06 | F13: 1236.3 | G13: 1145.18 | H13: 1293.63 | I13: 1252.61 | J13: 1273.7 | K13: 1200.38 | L13: 1188.64 | M13: 1124.16 | N13: =SUM(B13:M13) | O13: 1190.11 | P13: 1065.61 | Q13: 997.11 | R13: 1098.81 | S13: 1034.65 | T13: 1054.41 | U13: 1087.65 | AA13: =SUM(O13:U13) | AB13: =SUM(O13:Z13) | AC13: 1087.65 | AD13: 1087.65 | AE13: 1087.65 | AF13: 1087.65 | AG13: 1087.65 | AH13: 1087.65 | AI13: =SUM(AC13:AH13) | AJ13: =SUM(AC13:AH13)+AI13 | AK13: =IF(N13<>0,(AB13-N13)/ABS(N13),0) | AL13: =IF(AB13<>0,(AJ13-AB13)/ABS(AB13),0)
A14: Uniform | B14: 149.22 | C14: 0 | D14: 79.08 | E14: 0 | F14: 0 | G14: 350.58 | H14: 0 | I14: 0 | J14: 0 | K14: 0 | L14: 77.22 | M14: 1091.59 | N14: =SUM(B14:M14) | O14: 145.8 | P14: 0 | Q14: 0 | R14: 114.42 | S14: 0 | T14: 0 | U14: 0 | AA14: =SUM(O14:U14) | AB14: =SUM(O14:Z14) | AC14: 176 | AD14: 176 | AE14: 176 | AF14: 176 | AG14: 176 | AH14: 176 | AI14: =SUM(AC14:AH14) | AJ14: =SUM(AC14:AH14)+AI14 | AK14: =IF(N14<>0,(AB14-N14)/ABS(N14),0) | AL14: =IF(AB14<>0,(AJ14-AB14)/ABS(AB14),0)
A15: Training | B15: 0 | C15: 30 | D15: 480 | E15: 0 | F15: 18 | G15: 540 | H15: 189.28 | I15: 0 | J15: 0 | K15: 384 | L15: 50 | M15: -156 | N15: =SUM(B15:M15) | O15: 1254 | P15: 100 | Q15: 0 | R15: 335 | S15: -7.87 | T15: 55.86 | U15: 0 | AA15: =SUM(O15:U15) | AB15: =SUM(O15:Z15) | AC15: 500 | AD15: 500 | AE15: 500 | AF15: 500 | AG15: 500 | AH15: 500 | AI15: =SUM(AC15:AH15) | AJ15: =SUM(AC15:AH15)+AI15 | AK15: =IF(N15<>0,(AB15-N15)/ABS(N15),0) | AL15: =IF(AB15<>0,(AJ15-AB15)/ABS(AB15),0)
A16: Staff Welfare | B16: 292.56 | C16: 327.49 | D16: 190 | E16: 238.69 | F16: 147.43 | G16: 436.17 | H16: 265.44 | I16: 187.74 | J16: 173.74 | K16: 173.74 | L16: 327.78 | M16: 302.37 | N16: =SUM(B16:M16) | O16: 0 | P16: 212.72 | Q16: 232.51 | R16: 452.35 | S16: 231.54 | T16: 29.19 | U16: 139.62 | AA16: =SUM(O16:U16) | AB16: =SUM(O16:Z16) | AC16: 360 | AD16: 360 | AE16: 360 | AF16: 360 | AG16: 360 | AH16: 360 | AI16: =SUM(AC16:AH16) | AJ16: =SUM(AC16:AH16)+AI16 | AK16: =IF(N16<>0,(AB16-N16)/ABS(N16),0) | AL16: =IF(AB16<>0,(AJ16-AB16)/ABS(AB16),0)
A17: Recruitment | B17: 0 | C17: 64.8 | D17: 0 | E17: 0 | F17: 0 | G17: 0 | H17: 0 | I17: 0 | J17: 0 | K17: 0 | L17: 0 | M17: 0 | N17: =SUM(B17:M17) | O17: 0 | P17: 0 | Q17: 0 | R17: 0 | S17: 0 | T17: 0 | U17: 0 | V17: 0 | W17: 0 | X17: 0 | Y17: 0 | Z17: 0 | AA17: =SUM(O17:U17) | AB17: =SUM(O17:Z17) | AC17: 0 | AD17: 0 | AE17: 0 | AF17: 0 | AG17: 0 | AH17: 0 | AI17: =SUM(AC17:AH17) | AJ17: =SUM(AC17:AH17)+AI17 | AK17: =IF(N17<>0,(AB17-N17)/ABS(N17),0) | AL17: =IF(AB17<>0,(AJ17-AB17)/ABS(AB17),0)
A18: Rewards & Recognition | B18: 0 | C18: 0 | D18: 0 | E18: 0 | F18: 0 | G18: 0 | H18: 0 | I18: 0 | J18: 0 | K18: 47.96 | L18: 101.16 | M18: 0 | N18: =SUM(B18:M18) | O18: 0 | P18: 0 | Q18: 0 | R18: 0 | S18: 0 | T18: 0 | U18: 0 | V18: 0 | W18: 0 | X18: 0 | Y18: 0 | Z18: 0 | AA18: =SUM(O18:U18) | AB18: =SUM(O18:Z18) | AC18: 150 | AD18: 150 | AE18: 150 | AF18: 150 | AG18: 150 | AH18: 150 | AI18: =SUM(AC18:AH18) | AJ18: =SUM(AC18:AH18)+AI18 | AK18: =IF(N18<>0,(AB18-N18)/ABS(N18),0) | AL18: =IF(AB18<>0,(AJ18-AB18)/ABS(AB18),0)
A19: Temps | B19: 0 | C19: 0 | D19: 0 | E19: 0 | F19: 0 | G19: 0 | H19: 0 | I19: 0 | J19: 0 | K19: 0 | L19: 0 | M19: 0 | N19: =SUM(B19:M19) | O19: 0 | P19: 0 | Q19: 0 | R19: 0 | S19: 0 | T19: 0 | U19: 0 | V19: 0 | W19: 0 | X19: 0 | Y19: 0 | Z19: 0 | AA19: =SUM(O19:U19) | AB19: =SUM(O19:Z19) | AC19: 0 | AD19: 0 | AE19: 0 | AF19: 0 | AG19: 0 | AH19: 0 | AI19: =SUM(AC19:AH19) | AJ19: =SUM(AC19:AH19)+AI19 | AK19: =IF(N19<>0,(AB19-N19)/ABS(N19),0) | AL19: =IF(AB19<>0,(AJ19-AB19)/ABS(AB19),0)
A20: Total Personnel | B20: =B11+B12+B13+B14+B15+B16+B17+B18+B19 | C20: =C11+C12+C13+C14+C15+C16+C17+C18+C19 | D20: =D11+D12+D13+D14+D15+D16+D17+D18+D19 | E20: =E11+E12+E13+E14+E15+E16+E17+E18+E19 | F20: =F11+F12+F13+F14+F15+F16+F17+F18+F19 | G20: =G11+G12+G13+G14+G15+G16+G17+G18+G19 | H20: =H11+H12+H13+H14+H15+H16+H17+H18+H19 | I20: =I11+I12+I13+I14+I15+I16+I17+I18+I19 | ... AJ20: =AJ11+AJ12+AJ13+AJ14+AJ15+AJ16+AJ17+AJ18+AJ19 | AK20: =IF(N20<>0,(AB20-N20)/ABS(N20),0) | AL20: =IF(AB20<>0,(AJ20-AB20)/ABS(AB20),0)
A21: Sal:Rev | B21: =IF(B7>0,B20/B7,0) | C21: =IF(C7>0,C20/C7,0) | D21: =IF(D7>0,D20/D7,0) | E21: =IF(E7>0,E20/E7,0) | F21: =IF(F7>0,F20/F7,0) | G21: =IF(G7>0,G20/G7,0) | H21: =IF(H7>0,H20/H7,0) | I21: =IF(I7>0,I20/I7,0) | ... AJ21: =IF(AJ7>0,AJ20/AJ7,0)
A23: Childcare
A24: Catering Costs | N24: =SUM(B24:M24) | O24: 4148.71 | P24: 4930.31 | Q24: 5124.93 | R24: 4010.78 | S24: 5788.22 | T24: 5150.48 | U24: 4936.23 | V24: 3546.5876 | W24: 4510.5528 | X24: 4607.5224 | Y24: 4439.916 | Z24: 4176.4632 | AA24: =SUM(O24:U24) | AB24: =SUM(O24:Z24) | AC24: 4509.5132 | AD24: 4119.3703 | AE24: 4934.7758 | AF24: 4415.6474 | AG24: 4625.1148 | AH24: 4785.9852 | AI24: =SUM(AC24:AH24) | AJ24: =SUM(AC24:AH24)+AI24 | AK24: =IF(N24<>0,(AB24-N24)/ABS(N24),0) | AL24: =IF(AB24<>0,(AJ24-AB24)/ABS(AB24),0)
A25: Toys and Games | B25: 330.13 | C25: 1111.29 | D25: 135.72 | E25: 172.74 | F25: 1014.7 | G25: 1919.79 | H25: 265.47 | I25: 171.34 | J25: 0 | K25: 183.06 | L25: 257.43 | M25: 59.92 | N25: =SUM(B25:M25) | O25: 91.2 | P25: 89.62 | Q25: 249.67 | R25: 456.76 | S25: 98.94 | T25: 1175.49 | U25: 39.09 | AA25: =SUM(O25:U25) | AB25: =SUM(O25:Z25) | AC25: 100 | AD25: 100 | AE25: 100 | AF25: 100 | AG25: 100 | AH25: 100 | AI25: =SUM(AC25:AH25) | AJ25: =SUM(AC25:AH25)+AI25 | AK25: =IF(N25<>0,(AB25-N25)/ABS(N25),0) | AL25: =IF(AB25<>0,(AJ25-AB25)/ABS(AB25),0)
A26: Art Materials | N26: =SUM(B26:M26) | O26: 0 | P26: 160.57 | Q26: 230.91 | R26: 143.14 | S26: 88.79 | T26: 256.61 | U26: 223.33 | V26: 236.43917 | W26: 300.70352 | X26: 307.16816 | Y26: 295.9944 | Z26: 278.43088 | AA26: =SUM(O26:U26) | AB26: =SUM(O26:Z26) | AC26: 300.63421 | AD26: 274.62469 | AE26: 328.98505 | AF26: 294.37649 | AG26: 308.34099 | AH26: 319.06568 | AI26: =SUM(AC26:AH26) | AJ26: =SUM(AC26:AH26)+AI26 | AK26: =IF(N26<>0,(AB26-N26)/ABS(N26),0) | AL26: =IF(AB26<>0,(AJ26-AB26)/ABS(AB26),0)
A27: Nursery Stationery | B27: 15 | C27: 63.01 | D27: 61.27 | E27: 3.06 | F27: 1.38 | G27: 44.8 | H27: 112.74 | I27: 0 | J27: 104.18 | K27: 88.44 | L27: 41.01 | M27: 38.29 | N27: =SUM(B27:M27) | O27: 6.39 | P27: 72.61 | Q27: 43.57 | R27: 35.07 | S27: 16.02 | T27: 69.76 | U27: 48.33 | AA27: =SUM(O27:U27) | AB27: =SUM(O27:Z27) | AC27: 278 | AD27: 278 | AE27: 278 | AF27: 278 | AG27: 278 | AH27: 278 | AI27: =SUM(AC27:AH27) | AJ27: =SUM(AC27:AH27)+AI27 | AK27: =IF(N27<>0,(AB27-N27)/ABS(N27),0) | AL27: =IF(AB27<>0,(AJ27-AB27)/ABS(AB27),0)
A28: Nursery Equipment | B28: 134.83 | C28: 92.94 | D28: 339.69 | E28: 63.56 | F28: 390.09 | G28: 775.99 | H28: 63.76 | I28: 35.62 | J28: 45.98 | K28: 380.46 | L28: 86.04 | M28: 54.77 | N28: =SUM(B28:M28) | O28: 55.86 | P28: 123.78 | Q28: 0 | R28: 22.45 | S28: 59.08 | T28: 466.76 | U28: 206.96 | AA28: =SUM(O28:U28) | AB28: =SUM(O28:Z28) | AC28: 100 | AD28: 100 | AE28: 100 | AF28: 100 | AG28: 100 | AH28: 100 | AI28: =SUM(AC28:AH28) | AJ28: =SUM(AC28:AH28)+AI28 | AK28: =IF(N28<>0,(AB28-N28)/ABS(N28),0) | AL28: =IF(AB28<>0,(AJ28-AB28)/ABS(AB28),0)
A29: Nursery Consumables | N29: =SUM(B29:M29) | O29: 1014.79 | P29: 667.24 | Q29: 625.97 | R29: 1223.46 | S29: 1072.87 | T29: 248.7 | U29: 985.75 | V29: 472.87835 | W29: 601.40704 | X29: 614.33632 | Y29: 591.9888 | Z29: 556.86176 | AA29: =SUM(O29:U29) | AB29: =SUM(O29:Z29) | AC29: 601.26843 | AD29: 549.24938 | AE29: 657.9701 | AF29: 588.75299 | AG29: 616.68198 | AH29: 638.13135 | AI29: =SUM(AC29:AH29) | AJ29: =SUM(AC29:AH29)+AI29 | AK29: =IF(N29<>0,(AB29-N29)/ABS(N29),0) | AL29: =IF(AB29<>0,(AJ29-AB29)/ABS(AB29),0)
A30: Total Childcare Costs | B30: =B24+B25+B26+B27+B28+B29 | C30: =C24+C25+C26+C27+C28+C29 | D30: =D24+D25+D26+D27+D28+D29 | E30: =E24+E25+E26+E27+E28+E29 | F30: =F24+F25+F26+F27+F28+F29 | G30: =G24+G25+G26+G27+G28+G29 | H30: =H24+H25+H26+H27+H28+H29 | I30: =I24+I25+I26+I27+I28+I29 | ... AJ30: =AJ24+AJ25+AJ26+AJ27+AJ28+AJ29 | AK30: =IF(N30<>0,(AB30-N30)/ABS(N30),0) | AL30: =IF(AB30<>0,(AJ30-AB30)/ABS(AB30),0)
A32: Premises & Admin
A33: Rent | B33: 0 | C33: 0 | D33: 0 | E33: 0 | F33: 0 | G33: 0 | H33: 0 | I33: 0 | J33: 0 | K33: 0 | L33: 0 | M33: 0 | N33: =SUM(B33:M33) | O33: 0 | P33: 0 | Q33: 0 | R33: 0 | S33: 0 | T33: 0 | U33: 0 | V33: 0 | W33: 0 | X33: 0 | Y33: 0 | Z33: 0 | AA33: =SUM(O33:U33) | AB33: =SUM(O33:Z33) | AC33: 0 | AD33: 0 | AE33: 0 | AF33: 0 | AG33: 0 | AH33: 0 | AI33: =SUM(AC33:AH33) | AJ33: =SUM(AC33:AH33)+AI33 | AK33: =IF(N33<>0,(AB33-N33)/ABS(N33),0) | AL33: =IF(AB33<>0,(AJ33-AB33)/ABS(AB33),0)
A34: Business Rates | B34: 3025.75 | C34: 3025.75 | D34: 3025.75 | E34: 3075.63 | F34: 3075.63 | G34: 3075.63 | H34: 3075.63 | I34: 3075.63 | J34: 3075.63 | K34: 3075.63 | L34: 3075.63 | M34: 3075.63 | N34: =SUM(B34:M34) | O34: 3075.61 | P34: 3075.61 | Q34: 3075.61 | R34: 3123.75 | S34: 3123.75 | T34: 3123.75 | U34: 3123.75 | AA34: =SUM(O34:U34) | AB34: =SUM(O34:Z34) | AC34: 3123.75 | AD34: 3123.75 | AE34: 3123.75 | AF34: 3123.75 | AG34: 3123.75 | AH34: 3123.75 | AI34: =SUM(AC34:AH34) | AJ34: =SUM(AC34:AH34)+AI34 | AK34: =IF(N34<>0,(AB34-N34)/ABS(N34),0) | AL34: =IF(AB34<>0,(AJ34-AB34)/ABS(AB34),0)
A35: Utilities | B35: 2790.8 | C35: 2628.84 | D35: 4292.94 | E35: 5529.95 | F35: 1656.64 | G35: 2428.37 | H35: 1773.3 | I35: 1422.35 | J35: 2223.76 | K35: 3805.35 | L35: 3193.73 | M35: 3368.92 | N35: =SUM(B35:M35) | O35: 4087.64 | P35: 4314.61 | Q35: 2945.05 | R35: 2778.49 | S35: 2142.48 | T35: 2285.87 | U35: 1722.41 | AA35: =SUM(O35:U35) | AB35: =SUM(O35:Z35) | AC35: 3138 | AD35: 3138 | AE35: 3138 | AF35: 3138 | AG35: 3138 | AH35: 3138 | AI35: =SUM(AC35:AH35) | AJ35: =SUM(AC35:AH35)+AI35 | AK35: =IF(N35<>0,(AB35-N35)/ABS(N35),0) | AL35: =IF(AB35<>0,(AJ35-AB35)/ABS(AB35),0)
A36: Repairs & Maintenance | B36: 924.68 | C36: 752.58 | D36: 409.33 | E36: 1010.79 | F36: 213.72 | G36: 535.98 | H36: 2248.4 | I36: 2709.69 | J36: 912.31 | K36: 1226.69 | L36: 65.19 | M36: 192.39 | N36: =SUM(B36:M36) | O36: 482.98 | P36: 65.19 | Q36: 81.48 | R36: 217.62 | S36: 546.64 | T36: 445.08 | U36: 1103.45 | AA36: =SUM(O36:U36) | AB36: =SUM(O36:Z36) | AC36: 0 | AD36: 0 | AE36: 0 | AF36: 0 | AG36: 0 | AH36: 0 | AI36: =SUM(AC36:AH36) | AJ36: =SUM(AC36:AH36)+AI36 | AK36: =IF(N36<>0,(AB36-N36)/ABS(N36),0) | AL36: =IF(AB36<>0,(AJ36-AB36)/ABS(AB36),0)
A37: Cleaning | B37: 3992.33 | C37: 3985.5 | D37: 3876.24 | E37: 4757.82 | F37: 3752.54 | G37: 3993.33 | H37: 4752.64 | I37: 8059.97 | J37: 4609.84 | K37: 755.69 | L37: 4164.74 | M37: 4041.48 | N37: =SUM(B37:M37) | O37: 3097.61 | P37: 7311.5 | Q37: 416.9 | R37: 4015.5 | S37: 4246.18 | T37: 4420.44 | U37: 4546.02 | AA37: =SUM(O37:U37) | AB37: =SUM(O37:Z37) | AC37: 4300 | AD37: 4300 | AE37: 4300 | AF37: 4300 | AG37: 4300 | AH37: 4300 | AI37: =SUM(AC37:AH37) | AJ37: =SUM(AC37:AH37)+AI37 | AK37: =IF(N37<>0,(AB37-N37)/ABS(N37),0) | AL37: =IF(AB37<>0,(AJ37-AB37)/ABS(AB37),0)
A38: Waste Disposal | B38: 623.08 | C38: 831.76 | D38: 836.49 | E38: 747.74 | F38: 481.62 | G38: 810.65 | H38: 662.91 | I38: 701.49 | J38: 1035.73 | K38: 720.8 | L38: 715.36 | M38: 834.2 | N38: =SUM(B38:M38) | O38: 715.36 | P38: 715.36 | Q38: 843.86 | R38: 1039.5 | S38: 796.4 | T38: 429.02 | U38: 1016.67 | AA38: =SUM(O38:U38) | AB38: =SUM(O38:Z38) | AC38: 746 | AD38: 746 | AE38: 746 | AF38: 746 | AG38: 746 | AH38: 746 | AI38: =SUM(AC38:AH38) | AJ38: =SUM(AC38:AH38)+AI38 | AK38: =IF(N38<>0,(AB38-N38)/ABS(N38),0) | AL38: =IF(AB38<>0,(AJ38-AB38)/ABS(AB38),0)
A39: Postage/Printing/Stationery | B39: 72.16 | C39: 108.21 | D39: 93.42 | E39: 86.88 | F39: 91.48 | G39: 133.56 | H39: 135.07 | I39: 63.11 | J39: 156.44 | K39: 93.01 | L39: 12.84 | M39: 72.92 | N39: =SUM(B39:M39) | O39: 75.37 | P39: 96.28 | Q39: 268.58 | R39: 106.13 | S39: 149.21 | T39: 172.86 | U39: 64.6 | AA39: =SUM(O39:U39) | AB39: =SUM(O39:Z39) | AC39: 150 | AD39: 150 | AE39: 150 | AF39: 150 | AG39: 150 | AH39: 150 | AI39: =SUM(AC39:AH39) | AJ39: =SUM(AC39:AH39)+AI39 | AK39: =IF(N39<>0,(AB39-N39)/ABS(N39),0) | AL39: =IF(AB39<>0,(AJ39-AB39)/ABS(AB39),0)
A40: Telephone | B40: 0 | C40: 0 | D40: 0 | E40: 0 | F40: 0 | G40: 0 | H40: 0 | I40: 0 | J40: 0 | K40: 0 | L40: 0 | M40: 0 | N40: =SUM(B40:M40) | O40: 0 | P40: 0 | Q40: 0 | R40: 0 | S40: 0 | T40: 0 | U40: 0 | V40: 0 | W40: 0 | X40: 0 | Y40: 0 | Z40: 0 | AA40: =SUM(O40:U40) | AB40: =SUM(O40:Z40) | AC40: 0 | AD40: 0 | AE40: 0 | AF40: 0 | AG40: 0 | AH40: 0 | AI40: =SUM(AC40:AH40) | AJ40: =SUM(AC40:AH40)+AI40 | AK40: =IF(N40<>0,(AB40-N40)/ABS(N40),0) | AL40: =IF(AB40<>0,(AJ40-AB40)/ABS(AB40),0)
A41: Marketing | B41: 0 | C41: 64.8 | D41: 345.62 | E41: 0 | F41: 129.6 | G41: 45 | H41: 0 | I41: 90 | J41: 0 | K41: 0 | L41: 220 | M41: 0 | N41: =SUM(B41:M41) | O41: 264 | P41: 0 | Q41: 0 | R41: 282 | S41: 0 | T41: 0 | U41: 3.75 | AA41: =SUM(O41:U41) | AB41: =SUM(O41:Z41) | AC41: 100 | AD41: 100 | AE41: 100 | AF41: 100 | AG41: 100 | AH41: 100 | AI41: =SUM(AC41:AH41) | AJ41: =SUM(AC41:AH41)+AI41 | AK41: =IF(N41<>0,(AB41-N41)/ABS(N41),0) | AL41: =IF(AB41<>0,(AJ41-AB41)/ABS(AB41),0)
A42: Total Premises & Admin | B42: =B33+B34+B35+B36+B37+B38+B39+B40+B41 | C42: =C33+C34+C35+C36+C37+C38+C39+C40+C41 | D42: =D33+D34+D35+D36+D37+D38+D39+D40+D41 | E42: =E33+E34+E35+E36+E37+E38+E39+E40+E41 | F42: =F33+F34+F35+F36+F37+F38+F39+F40+F41 | G42: =G33+G34+G35+G36+G37+G38+G39+G40+G41 | H42: =H33+H34+H35+H36+H37+H38+H39+H40+H41 | I42: =I33+I34+I35+I36+I37+I38+I39+I40+I41 | ... AJ42: =AJ33+AJ34+AJ35+AJ36+AJ37+AJ38+AJ39+AJ40+AJ41 | AK42: =IF(N42<>0,(AB42-N42)/ABS(N42),0) | AL42: =IF(AB42<>0,(AJ42-AB42)/ABS(AB42),0)
A44: Total Direct Costs | AK44: =IF(N44<>0,(AB44-N44)/ABS(N44),0) | AL44: =IF(AB44<>0,(AJ44-AB44)/ABS(AB44),0)
A46: CONTRIBUTION | B46: =B7-B44 | C46: =C7-C44 | D46: =D7-D44 | E46: =E7-E44 | F46: =F7-F44 | G46: =G7-G44 | H46: =H7-H44 | I46: =I7-I44 | ... AJ46: =AJ7-AJ44 | AK46: =IF(N46<>0,(AB46-N46)/ABS(N46),0) | AL46: =IF(AB46<>0,(AJ46-AB46)/ABS(AB46),0)

Sheet CED
A1: Cedars | B1: Actuals 2025 | O1: 2026 Actual / Forecast | AC1: 2027 Forecast | AK1: YoY | AL1: YoY
B2: Jan | C2: Feb | D2: Mar | E2: Apr | F2: May | G2: Jun | H2: Jul | I2: Aug | J2: Sep | K2: Oct | L2: Nov | M2: Dec | N2: FY2025 Total | O2: Jan | P2: Feb | Q2: Mar | R2: Apr | S2: May | T2: Jun | U2: Jul | V2: Aug | W2: Sep | X2: Oct | Y2: Nov | Z2: Dec | AA2: YTD | AB2: FY2026 Outlook | AC2: Jan | AD2: Feb | AE2: Mar | AF2: Apr | AG2: May | AH2: Jun | AI2: Jul-Dec Proj. | AJ2: FY2027 | AK2: 25→26 % | AL2: 26→27 %
A3: INCOME
A4: Fee Income Regular | B4: 23814.44 | C4: 20657.57 | D4: 26472.4 | E4: 28682.3 | F4: 21069.85 | G4: 21588.68 | H4: 29637.32 | I4: 22500.55 | J4: 19945.64 | K4: 19659.5 | L4: 18229.14 | M4: 23118.77 | N4: =SUM(B4:M4) | O4: 22240.66 | P4: 18321.22 | Q4: 22883.28 | R4: 22685.93 | S4: 18910.69 | T4: 20776.58 | U4: 25818.48 | AA4: =SUM(O4:U4) | AB4: =SUM(O4:Z4) | AC4: 28315.98 | AD4: 26840.28 | AE4: 31507.8 | AF4: 30543.59 | AG4: 30885.6 | AH4: 33002.04 | AI4: =SUM(AC4:AH4) | AJ4: =SUM(AC4:AH4)+AI4 | AK4: =IF(N4<>0,(AB4-N4)/ABS(N4),0) | AL4: =IF(AB4<>0,(AJ4-AB4)/ABS(AB4),0)
A5: EEEF Embedded | B5: 5791.72 | C5: 14479.3 | D5: 15684.58 | E5: 5185.26 | F5: 5185.26 | G5: 15608.08 | H5: 13375.26 | I5: 0 | J5: 5986.21 | K5: 12205.6 | L5: 12205.6 | M5: 16957.76 | N5: =SUM(B5:M5) | O5: 6629.51 | P5: 17491.45 | Q5: 17491.45 | R5: 12006.04 | S5: 12006.05 | T5: 12927.15 | U5: 12313.08 | AA5: =SUM(O5:U5) | AB5: =SUM(O5:Z5) | AC5: 0 | AD5: 0 | AE5: 0 | AF5: 0 | AG5: 0 | AH5: 0 | AI5: =SUM(AC5:AH5) | AJ5: =SUM(AC5:AH5)+AI5 | AK5: =IF(N5<>0,(AB5-N5)/ABS(N5),0) | AL5: =IF(AB5<>0,(AJ5-AB5)/ABS(AB5),0)
A6: Other Income | B6: 200 | C6: 200 | D6: 300 | E6: 0 | F6: 300 | G6: 300 | H6: 150 | I6: 0 | J6: 0 | K6: 150 | L6: 150 | M6: 150 | N6: =SUM(B6:M6) | O6: 650 | P6: 150 | Q6: 150 | R6: 150 | S6: 150 | T6: 150 | U6: 150 | AA6: =SUM(O6:U6) | AB6: =SUM(O6:Z6) | AC6: 0 | AD6: 0 | AE6: 0 | AF6: 0 | AG6: 0 | AH6: 0 | AI6: =SUM(AC6:AH6) | AJ6: =SUM(AC6:AH6)+AI6 | AK6: =IF(N6<>0,(AB6-N6)/ABS(N6),0) | AL6: =IF(AB6<>0,(AJ6-AB6)/ABS(AB6),0)
A7: Total Income | B7: =B4+B5+B6 | C7: =C4+C5+C6 | D7: =D4+D5+D6 | E7: =E4+E5+E6 | F7: =F4+F5+F6 | G7: =G4+G5+G6 | H7: =H4+H5+H6 | I7: =I4+I5+I6 | ... AJ7: =AJ4+AJ5+AJ6 | AK7: =IF(N7<>0,(AB7-N7)/ABS(N7),0) | AL7: =IF(AB7<>0,(AJ7-AB7)/ABS(AB7),0)
A9: DIRECT COSTS
A10: Personnel
A11: Nursery Salaries | B11: 15964.89 | C11: 15432.95 | D11: 16980.77 | E11: 19492.28 | F11: 19492.07 | G11: 16093.17 | H11: 19196.5 | I11: 14959.37 | J11: 19873.92 | K11: 18038.34 | L11: 18266.77 | M11: 21533.17 | N11: =SUM(B11:M11) | O11: 19941.96 | P11: 18433.95 | Q11: 16301.53 | R11: 22374.13 | S11: 22592.61 | T11: 21699.26 | U11: 22510.48 | AA11: =SUM(O11:U11) | AB11: =SUM(O11:Z11) | AC11: 22510.48 | AD11: 22510.48 | AE11: 22510.48 | AF11: 22510.48 | AG11: 22510.48 | AH11: 22510.48 | AI11: =SUM(AC11:AH11) | AJ11: =SUM(AC11:AH11)+AI11 | AK11: =IF(N11<>0,(AB11-N11)/ABS(N11),0) | AL11: =IF(AB11<>0,(AJ11-AB11)/ABS(AB11),0)
A12: Nursery NI | B12: 1212.08 | C12: 1115.32 | D12: 1300.33 | E12: 2055.72 | F12: 1957.17 | G12: 1471.56 | H12: 1976.99 | I12: 1386.1 | J12: 2097.99 | K12: 1993.75 | L12: 1962.85 | M12: 2264.02 | N12: =SUM(B12:M12) | O12: 2075.7 | P12: 2156.24 | Q12: 2109.88 | R12: 2614.86 | S12: 2663.12 | T12: 2437.78 | U12: 2763.77 | AA12: =SUM(O12:U12) | AB12: =SUM(O12:Z12) | AC12: 2763.77 | AD12: 2763.77 | AE12: 2763.77 | AF12: 2763.77 | AG12: 2763.77 | AH12: 2763.77 | AI12: =SUM(AC12:AH12) | AJ12: =SUM(AC12:AH12)+AI12 | AK12: =IF(N12<>0,(AB12-N12)/ABS(N12),0) | AL12: =IF(AB12<>0,(AJ12-AB12)/ABS(AB12),0)
A13: Nursery Pension | B13: 216.18 | C13: 203.88 | D13: 196.57 | E13: 233.26 | F13: 228.75 | G13: 190.93 | H13: 276.28 | I13: 243.1 | J13: 298.73 | K13: 272.53 | L13: 352.17 | M13: 373.97 | N13: =SUM(B13:M13) | O13: 390.39 | P13: 333.89 | Q13: 284.46 | R13: 420.57 | S13: 427.46 | T13: 446.28 | U13: 478.22 | AA13: =SUM(O13:U13) | AB13: =SUM(O13:Z13) | AC13: 478.22 | AD13: 478.22 | AE13: 478.22 | AF13: 478.22 | AG13: 478.22 | AH13: 478.22 | AI13: =SUM(AC13:AH13) | AJ13: =SUM(AC13:AH13)+AI13 | AK13: =IF(N13<>0,(AB13-N13)/ABS(N13),0) | AL13: =IF(AB13<>0,(AJ13-AB13)/ABS(AB13),0)
A14: Uniform | B14: 0 | C14: 524.28 | D14: 0 | E14: 0 | F14: 100.14 | G14: 100.14 | H14: 0 | I14: 0 | J14: 262.56 | K14: 0 | L14: 0 | M14: 100.14 | N14: =SUM(B14:M14) | O14: 6.99 | P14: 0 | Q14: 0 | R14: 133.87 | S14: 0 | T14: 0 | U14: 0 | AA14: =SUM(O14:U14) | AB14: =SUM(O14:Z14) | AC14: 6.99 | AD14: 6.99 | AE14: 6.99 | AF14: 6.99 | AG14: 6.99 | AH14: 6.99 | AI14: =SUM(AC14:AH14) | AJ14: =SUM(AC14:AH14)+AI14 | AK14: =IF(N14<>0,(AB14-N14)/ABS(N14),0) | AL14: =IF(AB14<>0,(AJ14-AB14)/ABS(AB14),0)
A15: Training | B15: 48 | C15: 78 | D15: 0 | E15: 0 | F15: 0 | G15: 72 | H15: 0 | I15: 0 | J15: 216 | K15: 916 | L15: 10 | M15: 686.49 | N15: =SUM(B15:M15) | O15: 388.79 | P15: 0 | Q15: 24 | R15: 0 | S15: 0 | T15: 0 | U15: 0 | AA15: =SUM(O15:U15) | AB15: =SUM(O15:Z15) | AC15: 100 | AD15: 100 | AE15: 100 | AF15: 100 | AG15: 100 | AH15: 100 | AI15: =SUM(AC15:AH15) | AJ15: =SUM(AC15:AH15)+AI15 | AK15: =IF(N15<>0,(AB15-N15)/ABS(N15),0) | AL15: =IF(AB15<>0,(AJ15-AB15)/ABS(AB15),0)
A16: Staff Welfare | B16: 10 | C16: 108.63 | D16: 61.08 | E16: 109.86 | F16: 137.21 | G16: 52.06 | H16: 92.57 | I16: 92.28 | J16: 92.52 | K16: 68.13 | L16: 161.98 | M16: 194.07 | N16: =SUM(B16:M16) | O16: 125.23 | P16: 203.51 | Q16: 281.37 | R16: 239.69 | S16: 156.06 | T16: 149.88 | U16: 224.47 | AA16: =SUM(O16:U16) | AB16: =SUM(O16:Z16) | AC16: 150 | AD16: 150 | AE16: 150 | AF16: 150 | AG16: 150 | AH16: 150 | AI16: =SUM(AC16:AH16) | AJ16: =SUM(AC16:AH16)+AI16 | AK16: =IF(N16<>0,(AB16-N16)/ABS(N16),0) | AL16: =IF(AB16<>0,(AJ16-AB16)/ABS(AB16),0)
A17: Recruitment | B17: 0 | C17: 5040 | D17: 0 | E17: 0 | F17: 0 | G17: 0 | H17: 0 | I17: 0 | J17: 0 | K17: 0 | L17: 0 | M17: 3650.4 | N17: =SUM(B17:M17) | O17: 0 | P17: 0 | Q17: 0 | R17: 0 | S17: 0 | T17: 0 | U17: 0 | V17: 0 | W17: 0 | X17: 0 | Y17: 0 | Z17: 0 | AA17: =SUM(O17:U17) | AB17: =SUM(O17:Z17) | AC17: 0 | AD17: 0 | AE17: 0 | AF17: 0 | AG17: 0 | AH17: 0 | AI17: =SUM(AC17:AH17) | AJ17: =SUM(AC17:AH17)+AI17 | AK17: =IF(N17<>0,(AB17-N17)/ABS(N17),0) | AL17: =IF(AB17<>0,(AJ17-AB17)/ABS(AB17),0)
A18: Rewards & Recognition | B18: 0 | C18: 0 | D18: 0 | E18: 0 | F18: 0 | G18: 0 | H18: 10 | I18: 10 | J18: 0 | K18: 0 | L18: 0 | M18: 12.99 | N18: =SUM(B18:M18) | O18: 0 | P18: 0 | Q18: 0 | R18: 0 | S18: 0 | T18: 35.95 | U18: 66.9 | AA18: =SUM(O18:U18) | AB18: =SUM(O18:Z18) | AC18: 42 | AD18: 42 | AE18: 42 | AF18: 42 | AG18: 42 | AH18: 42 | AI18: =SUM(AC18:AH18) | AJ18: =SUM(AC18:AH18)+AI18 | AK18: =IF(N18<>0,(AB18-N18)/ABS(N18),0) | AL18: =IF(AB18<>0,(AJ18-AB18)/ABS(AB18),0)
A19: Temps | B19: 0 | C19: 0 | D19: 0 | E19: 0 | F19: 0 | G19: 0 | H19: 0 | I19: 0 | J19: 0 | K19: 0 | L19: 0 | M19: 0 | N19: =SUM(B19:M19) | O19: 0 | P19: 0 | Q19: 0 | R19: 0 | S19: 0 | T19: 0 | U19: 0 | V19: 0 | W19: 0 | X19: 0 | Y19: 0 | Z19: 0 | AA19: =SUM(O19:U19) | AB19: =SUM(O19:Z19) | AC19: 0 | AD19: 0 | AE19: 0 | AF19: 0 | AG19: 0 | AH19: 0 | AI19: =SUM(AC19:AH19) | AJ19: =SUM(AC19:AH19)+AI19 | AK19: =IF(N19<>0,(AB19-N19)/ABS(N19),0) | AL19: =IF(AB19<>0,(AJ19-AB19)/ABS(AB19),0)
A20: Total Personnel | B20: =B11+B12+B13+B14+B15+B16+B17+B18+B19 | C20: =C11+C12+C13+C14+C15+C16+C17+C18+C19 | D20: =D11+D12+D13+D14+D15+D16+D17+D18+D19 | E20: =E11+E12+E13+E14+E15+E16+E17+E18+E19 | F20: =F11+F12+F13+F14+F15+F16+F17+F18+F19 | G20: =G11+G12+G13+G14+G15+G16+G17+G18+G19 | H20: =H11+H12+H13+H14+H15+H16+H17+H18+H19 | I20: =I11+I12+I13+I14+I15+I16+I17+I18+I19 | ... AJ20: =AJ11+AJ12+AJ13+AJ14+AJ15+AJ16+AJ17+AJ18+AJ19 | AK20: =IF(N20<>0,(AB20-N20)/ABS(N20),0) | AL20: =IF(AB20<>0,(AJ20-AB20)/ABS(AB20),0)
A21: Sal:Rev | B21: =IF(B7>0,B20/B7,0) | C21: =IF(C7>0,C20/C7,0) | D21: =IF(D7>0,D20/D7,0) | E21: =IF(E7>0,E20/E7,0) | F21: =IF(F7>0,F20/F7,0) | G21: =IF(G7>0,G20/G7,0) | H21: =IF(H7>0,H20/H7,0) | I21: =IF(I7>0,I20/I7,0) | ... AJ21: =IF(AJ7>0,AJ20/AJ7,0)
A23: Childcare
A24: Catering Costs | N24: =SUM(B24:M24) | O24: 1124.3 | P24: 897.62 | Q24: 1008.18 | R24: 1170.82 | S24: 811.64 | T24: 968.12 | U24: 1225.01 | V24: 559.62 | W24: 610.02 | X24: 657.09 | Y24: 744.51 | Z24: 812.28 | AA24: =SUM(O24:U24) | AB24: =SUM(O24:Z24) | AC24: 849.4794 | AD24: 805.2084 | AE24: 945.234 | AF24: 916.3077 | AG24: 926.568 | AH24: 990.0612 | AI24: =SUM(AC24:AH24) | AJ24: =SUM(AC24:AH24)+AI24 | AK24: =IF(N24<>0,(AB24-N24)/ABS(N24),0) | AL24: =IF(AB24<>0,(AJ24-AB24)/ABS(AB24),0)
A25: Toys and Games | B25: 183.52 | C25: 90.93 | D25: 151.06 | E25: 177.29 | F25: 242.78 | G25: 1990.96 | H25: 406.66 | I25: 353.82 | J25: 175.28 | K25: 16.3 | L25: 60.14 | M25: 19.96 | N25: =SUM(B25:M25) | O25: 22.2 | P25: 40.4 | Q25: 106.77 | R25: 36.99 | S25: 110.33 | T25: 12 | U25: 1314.02 | AA25: =SUM(O25:U25) | AB25: =SUM(O25:Z25) | AC25: 100 | AD25: 100 | AE25: 100 | AF25: 100 | AG25: 100 | AH25: 100 | AI25: =SUM(AC25:AH25) | AJ25: =SUM(AC25:AH25)+AI25 | AK25: =IF(N25<>0,(AB25-N25)/ABS(N25),0) | AL25: =IF(AB25<>0,(AJ25-AB25)/ABS(AB25),0)
A26: Art Materials | N26: =SUM(B26:M26) | O26: 16.11 | P26: 7.99 | Q26: 68.7 | R26: 75.15 | S26: 0 | T26: 295.2 | U26: 93.08 | V26: 55.962 | W26: 61.002 | X26: 65.709 | Y26: 74.451 | Z26: 81.228 | AA26: =SUM(O26:U26) | AB26: =SUM(O26:Z26) | AC26: 84.94794 | AD26: 80.52084 | AE26: 94.5234 | AF26: 91.63077 | AG26: 92.6568 | AH26: 99.00612 | AI26: =SUM(AC26:AH26) | AJ26: =SUM(AC26:AH26)+AI26 | AK26: =IF(N26<>0,(AB26-N26)/ABS(N26),0) | AL26: =IF(AB26<>0,(AJ26-AB26)/ABS(AB26),0)
A27: Nursery Stationery | B27: 92.49 | C27: 10.97 | D27: 0 | E27: 10.29 | F27: 45.52 | G27: 52.51 | H27: 31.85 | I27: 57.34 | J27: 65.91 | K27: 51.77 | L27: 20.32 | M27: 86.42 | N27: =SUM(B27:M27) | O27: 17.54 | P27: 65.64 | Q27: 10.58 | R27: 0 | S27: 30.62 | T27: 0 | U27: 6.98 | AA27: =SUM(O27:U27) | AB27: =SUM(O27:Z27) | AC27: 100 | AD27: 100 | AE27: 100 | AF27: 100 | AG27: 100 | AH27: 100 | AI27: =SUM(AC27:AH27) | AJ27: =SUM(AC27:AH27)+AI27 | AK27: =IF(N27<>0,(AB27-N27)/ABS(N27),0) | AL27: =IF(AB27<>0,(AJ27-AB27)/ABS(AB27),0)
A28: Nursery Equipment | B28: 243.75 | C28: 56.46 | D28: 68.98 | E28: 0 | F28: 446.65 | G28: 238.6 | H28: 206.36 | I28: 17.01 | J28: 146.95 | K28: 217.2 | L28: 103.41 | M28: 87.68 | N28: =SUM(B28:M28) | O28: 25.98 | P28: 64.59 | Q28: 42.76 | R28: 0 | S28: 159.29 | T28: 0 | U28: 116.23 | AA28: =SUM(O28:U28) | AB28: =SUM(O28:Z28) | AC28: 100 | AD28: 100 | AE28: 100 | AF28: 100 | AG28: 100 | AH28: 100 | AI28: =SUM(AC28:AH28) | AJ28: =SUM(AC28:AH28)+AI28 | AK28: =IF(N28<>0,(AB28-N28)/ABS(N28),0) | AL28: =IF(AB28<>0,(AJ28-AB28)/ABS(AB28),0)
A29: Nursery Consumables | N29: =SUM(B29:M29) | O29: 179.58 | P29: 223.95 | Q29: 176.34 | R29: 285.91 | S29: 131 | T29: 172.44 | U29: 163.98 | V29: 93.27 | W29: 101.67 | X29: 109.515 | Y29: 124.085 | Z29: 135.38 | AA29: =SUM(O29:U29) | AB29: =SUM(O29:Z29) | AC29: 141.5799 | AD29: 134.2014 | AE29: 157.539 | AF29: 152.71795 | AG29: 154.428 | AH29: 165.0102 | AI29: =SUM(AC29:AH29) | AJ29: =SUM(AC29:AH29)+AI29 | AK29: =IF(N29<>0,(AB29-N29)/ABS(N29),0) | AL29: =IF(AB29<>0,(AJ29-AB29)/ABS(AB29),0)
A30: Total Childcare Costs | B30: =B24+B25+B26+B27+B28+B29 | C30: =C24+C25+C26+C27+C28+C29 | D30: =D24+D25+D26+D27+D28+D29 | E30: =E24+E25+E26+E27+E28+E29 | F30: =F24+F25+F26+F27+F28+F29 | G30: =G24+G25+G26+G27+G28+G29 | H30: =H24+H25+H26+H27+H28+H29 | I30: =I24+I25+I26+I27+I28+I29 | ... AJ30: =AJ24+AJ25+AJ26+AJ27+AJ28+AJ29 | AK30: =IF(N30<>0,(AB30-N30)/ABS(N30),0) | AL30: =IF(AB30<>0,(AJ30-AB30)/ABS(AB30),0)
A32: Premises & Admin
A33: Rent | B33: 0 | C33: 0 | D33: 0 | E33: 0 | F33: 0 | G33: 0 | H33: 0 | I33: 0 | J33: 0 | K33: 0 | L33: 0 | M33: 0 | N33: =SUM(B33:M33) | O33: 0 | P33: 0 | Q33: 0 | R33: 0 | S33: 0 | T33: 0 | U33: 0 | V33: 0 | W33: 0 | X33: 0 | Y33: 0 | Z33: 0 | AA33: =SUM(O33:U33) | AB33: =SUM(O33:Z33) | AC33: 0 | AD33: 0 | AE33: 0 | AF33: 0 | AG33: 0 | AH33: 0 | AI33: =SUM(AC33:AH33) | AJ33: =SUM(AC33:AH33)+AI33 | AK33: =IF(N33<>0,(AB33-N33)/ABS(N33),0) | AL33: =IF(AB33<>0,(AJ33-AB33)/ABS(AB33),0)
A34: Business Rates | B34: 769.29 | C34: 769.29 | D34: 769.29 | E34: 769.29 | F34: 769.29 | G34: 769.29 | H34: 769.29 | I34: 769.29 | J34: 769.29 | K34: 769.29 | L34: 769.29 | M34: 769.29 | N34: =SUM(B34:M34) | O34: 769.3 | P34: 769.3 | Q34: 769.29 | R34: 736.67 | S34: 736.67 | T34: 736.67 | U34: 736.67 | AA34: =SUM(O34:U34) | AB34: =SUM(O34:Z34) | AC34: 736.67 | AD34: 736.67 | AE34: 736.67 | AF34: 736.67 | AG34: 736.67 | AH34: 736.67 | AI34: =SUM(AC34:AH34) | AJ34: =SUM(AC34:AH34)+AI34 | AK34: =IF(N34<>0,(AB34-N34)/ABS(N34),0) | AL34: =IF(AB34<>0,(AJ34-AB34)/ABS(AB34),0)
A35: Utilities | B35: 876.66 | C35: 427.76 | D35: 1456.67 | E35: -952.99 | F35: 898.87 | G35: 314.48 | H35: 283.44 | I35: 288.93 | J35: 180.99 | K35: 399.17 | L35: 339.71 | M35: 38.67 | N35: =SUM(B35:M35) | O35: 1216.68 | P35: 1004.18 | Q35: 1025.61 | R35: 261.16 | S35: 176.45 | T35: 336.16 | U35: 332.86 | AA35: =SUM(O35:U35) | AB35: =SUM(O35:Z35) | AC35: 448 | AD35: 448 | AE35: 448 | AF35: 448 | AG35: 448 | AH35: 448 | AI35: =SUM(AC35:AH35) | AJ35: =SUM(AC35:AH35)+AI35 | AK35: =IF(N35<>0,(AB35-N35)/ABS(N35),0) | AL35: =IF(AB35<>0,(AJ35-AB35)/ABS(AB35),0)
A36: Repairs & Maintenance | B36: 622.57 | C36: 29.99 | D36: 0 | E36: 0 | F36: 39.52 | G36: 38.49 | H36: 11.88 | I36: 4.99 | J36: 198.21 | K36: 11 | L36: 495.96 | M36: 747.47 | N36: =SUM(B36:M36) | O36: 0 | P36: 0 | Q36: 246 | R36: 0 | S36: 0 | T36: 46.82 | U36: 135.38 | AA36: =SUM(O36:U36) | AB36: =SUM(O36:Z36) | AC36: 0 | AD36: 0 | AE36: 0 | AF36: 0 | AG36: 0 | AH36: 0 | AI36: =SUM(AC36:AH36) | AJ36: =SUM(AC36:AH36)+AI36 | AK36: =IF(N36<>0,(AB36-N36)/ABS(N36),0) | AL36: =IF(AB36<>0,(AJ36-AB36)/ABS(AB36),0)
A37: Cleaning | B37: 277.47 | C37: 312.04 | D37: 97.82 | E37: 304.23 | F37: 397.89 | G37: 132.94 | H37: 215.21 | I37: 111.14 | J37: 34.12 | K37: 237.1 | L37: 312.9 | M37: 226.92 | N37: =SUM(B37:M37) | O37: 30.74 | P37: 116.71 | Q37: 102.81 | R37: 50 | S37: 107.99 | T37: 96.7 | U37: 56.69 | AA37: =SUM(O37:U37) | AB37: =SUM(O37:Z37) | AC37: 210 | AD37: 210 | AE37: 210 | AF37: 210 | AG37: 210 | AH37: 210 | AI37: =SUM(AC37:AH37) | AJ37: =SUM(AC37:AH37)+AI37 | AK37: =IF(N37<>0,(AB37-N37)/ABS(N37),0) | AL37: =IF(AB37<>0,(AJ37-AB37)/ABS(AB37),0)
A38: Waste Disposal | B38: 204 | C38: 377.46 | D38: 255 | E38: 398.32 | F38: 282.34 | G38: 296.99 | H38: 243.58 | I38: 243.58 | J38: 404.69 | K38: 243.58 | L38: 338.48 | M38: 391.89 | N38: =SUM(B38:M38) | O38: 489.68 | P38: 346.63 | Q38: 500.33 | R38: 416.6 | S38: 335.56 | T38: 250.9 | U38: 392.52 | AA38: =SUM(O38:U38) | AB38: =SUM(O38:Z38) | AC38: 300 | AD38: 300 | AE38: 300 | AF38: 300 | AG38: 300 | AH38: 300 | AI38: =SUM(AC38:AH38) | AJ38: =SUM(AC38:AH38)+AI38 | AK38: =IF(N38<>0,(AB38-N38)/ABS(N38),0) | AL38: =IF(AB38<>0,(AJ38-AB38)/ABS(AB38),0)
A39: Postage/Printing/Stationery | B39: 52.02 | C39: 41.97 | D39: 46.18 | E39: 47.3 | F39: 35.68 | G39: 66.4 | H39: 372.16 | I39: 41.5 | J39: 78.95 | K39: 83.34 | L39: 36.06 | M39: 79.35 | N39: =SUM(B39:M39) | O39: 31.59 | P39: 82.27 | Q39: 119.08 | R39: 163.25 | S39: 25.98 | T39: 122.27 | U39: 48.27 | AA39: =SUM(O39:U39) | AB39: =SUM(O39:Z39) | AC39: 0 | AD39: 0 | AE39: 0 | AF39: 0 | AG39: 0 | AH39: 0 | AI39: =SUM(AC39:AH39) | AJ39: =SUM(AC39:AH39)+AI39 | AK39: =IF(N39<>0,(AB39-N39)/ABS(N39),0) | AL39: =IF(AB39<>0,(AJ39-AB39)/ABS(AB39),0)
A40: Telephone | B40: 0 | C40: 0 | D40: 0 | E40: 0 | F40: 0 | G40: 0 | H40: 0 | I40: 0 | J40: 0 | K40: 0 | L40: 0 | M40: 0 | N40: =SUM(B40:M40) | O40: 0 | P40: 0 | Q40: 0 | R40: 0 | S40: 0 | T40: 0 | U40: 0 | V40: 0 | W40: 0 | X40: 0 | Y40: 0 | Z40: 0 | AA40: =SUM(O40:U40) | AB40: =SUM(O40:Z40) | AC40: 0 | AD40: 0 | AE40: 0 | AF40: 0 | AG40: 0 | AH40: 0 | AI40: =SUM(AC40:AH40) | AJ40: =SUM(AC40:AH40)+AI40 | AK40: =IF(N40<>0,(AB40-N40)/ABS(N40),0) | AL40: =IF(AB40<>0,(AJ40-AB40)/ABS(AB40),0)
A41: Marketing | B41: 0 | C41: 220 | D41: 0 | E41: 0 | F41: 0 | G41: 3.98 | H41: 3.75 | I41: 90 | J41: 0 | K41: 0 | L41: 0 | M41: 0 | N41: =SUM(B41:M41) | O41: 54 | P41: 0 | Q41: 220 | R41: 57 | S41: 0 | T41: 0 | U41: 0 | AA41: =SUM(O41:U41) | AB41: =SUM(O41:Z41) | AC41: 100 | AD41: 100 | AE41: 100 | AF41: 100 | AG41: 100 | AH41: 100 | AI41: =SUM(AC41:AH41) | AJ41: =SUM(AC41:AH41)+AI41 | AK41: =IF(N41<>0,(AB41-N41)/ABS(N41),0) | AL41: =IF(AB41<>0,(AJ41-AB41)/ABS(AB41),0)
A42: Total Premises & Admin | B42: =B33+B34+B35+B36+B37+B38+B39+B40+B41 | C42: =C33+C34+C35+C36+C37+C38+C39+C40+C41 | D42: =D33+D34+D35+D36+D37+D38+D39+D40+D41 | E42: =E33+E34+E35+E36+E37+E38+E39+E40+E41 | F42: =F33+F34+F35+F36+F37+F38+F39+F40+F41 | G42: =G33+G34+G35+G36+G37+G38+G39+G40+G41 | H42: =H33+H34+H35+H36+H37+H38+H39+H40+H41 | I42: =I33+I34+I35+I36+I37+I38+I39+I40+I41 | ... AJ42: =AJ33+AJ34+AJ35+AJ36+AJ37+AJ38+AJ39+AJ40+AJ41 | AK42: =IF(N42<>0,(AB42-N42)/ABS(N42),0) | AL42: =IF(AB42<>0,(AJ42-AB42)/ABS(AB42),0)
A44: Total Direct Costs | AK44: =IF(N44<>0,(AB44-N44)/ABS(N44),0) | AL44: =IF(AB44<>0,(AJ44-AB44)/ABS(AB44),0)
A46: CONTRIBUTION | B46: =B7-B44 | C46: =C7-C44 | D46: =D7-D44 | E46: =E7-E44 | F46: =F7-F44 | G46: =G7-G44 | H46: =H7-H44 | I46: =I7-I44 | ... AJ46: =AJ7-AJ44 | AK46: =IF(N46<>0,(AB46-N46)/ABS(N46),0) | AL46: =IF(AB46<>0,(AJ46-AB46)/ABS(AB46),0)

Sheet HAB
A1: Boot Farm | B1: Actuals 2025 | O1: 2026 Actual / Forecast | AC1: 2027 Forecast | AK1: YoY | AL1: YoY
B2: Jan | C2: Feb | D2: Mar | E2: Apr | F2: May | G2: Jun | H2: Jul | I2: Aug | J2: Sep | K2: Oct | L2: Nov | M2: Dec | N2: FY2025 Total | O2: Jan | P2: Feb | Q2: Mar | R2: Apr | S2: May | T2: Jun | U2: Jul | V2: Aug | W2: Sep | X2: Oct | Y2: Nov | Z2: Dec | AA2: YTD | AB2: FY2026 Outlook | AC2: Jan | AD2: Feb | AE2: Mar | AF2: Apr | AG2: May | AH2: Jun | AI2: Jul-Dec Proj. | AJ2: FY2027 | AK2: 25→26 % | AL2: 26→27 %
A3: INCOME
A4: Fee Income Regular | B4: 22608.68 | C4: 22243.72 | D4: 27570.94 | E4: 32753.01 | F4: 29946.42 | G4: 32181.69 | H4: 44859.07 | I4: 41767.17 | J4: 32212.18 | K4: 31485.29 | L4: 27574.28 | M4: 37778.25 | N4: =SUM(B4:M4) | O4: 33113.54 | P4: 31541.7 | Q4: 35742.73 | R4: 40112.94 | S4: 32985.6 | T4: 34775.34 | U4: 43764.87 | AA4: =SUM(O4:U4) | AB4: =SUM(O4:Z4) | AC4: 38106.5 | AD4: 35852.39 | AE4: 43430.94 | AF4: 32359.2 | AG4: 31981.84 | AH4: 34163.18 | AI4: =SUM(AC4:AH4) | AJ4: =SUM(AC4:AH4)+AI4 | AK4: =IF(N4<>0,(AB4-N4)/ABS(N4),0) | AL4: =IF(AB4<>0,(AJ4-AB4)/ABS(AB4),0)
A5: EEEF Embedded | B5: 5242.38 | C5: 14026.65 | D5: 14026.65 | E5: 5098.36 | F5: 5098.36 | G5: 21148.51 | H5: 21148.51 | I5: 0 | J5: 7047.23 | K5: 18081.4 | L5: 18081.4 | M5: 22099.92 | N5: =SUM(B5:M5) | O5: 8524.28 | P5: 23183.36 | Q5: 27880.5 | R5: 19300.66 | S5: 19300.66 | T5: 19088.16 | U5: 21005.55 | AA5: =SUM(O5:U5) | AB5: =SUM(O5:Z5) | AC5: 0 | AD5: 0 | AE5: 0 | AF5: 0 | AG5: 0 | AH5: 0 | AI5: =SUM(AC5:AH5) | AJ5: =SUM(AC5:AH5)+AI5 | AK5: =IF(N5<>0,(AB5-N5)/ABS(N5),0) | AL5: =IF(AB5<>0,(AJ5-AB5)/ABS(AB5),0)
A6: Other Income | B6: 0 | C6: 0 | D6: 0 | E6: 300 | F6: 150 | G6: 2213.27 | H6: 300 | I6: 300 | J6: 150 | K6: 230 | L6: 150 | M6: 150 | N6: =SUM(B6:M6) | O6: 150 | P6: 150 | Q6: 150 | R6: 159.23 | S6: 150 | T6: 150 | U6: 0 | AA6: =SUM(O6:U6) | AB6: =SUM(O6:Z6) | AC6: 0 | AD6: 0 | AE6: 0 | AF6: 0 | AG6: 0 | AH6: 0 | AI6: =SUM(AC6:AH6) | AJ6: =SUM(AC6:AH6)+AI6 | AK6: =IF(N6<>0,(AB6-N6)/ABS(N6),0) | AL6: =IF(AB6<>0,(AJ6-AB6)/ABS(AB6),0)
A7: Total Income | B7: =B4+B5+B6 | C7: =C4+C5+C6 | D7: =D4+D5+D6 | E7: =E4+E5+E6 | F7: =F4+F5+F6 | G7: =G4+G5+G6 | H7: =H4+H5+H6 | I7: =I4+I5+I6 | ... AJ7: =AJ4+AJ5+AJ6 | AK7: =IF(N7<>0,(AB7-N7)/ABS(N7),0) | AL7: =IF(AB7<>0,(AJ7-AB7)/ABS(AB7),0)
A9: DIRECT COSTS
A10: Personnel
A11: Nursery Salaries | B11: 14028.96 | C11: 16418.51 | D11: 17522.64 | E11: 18482.09 | F11: 20020.2 | G11: 19124.39 | H11: 19993.06 | I11: 18672.65 | J11: 22682.26 | K11: 23747.06 | L11: 22885.49 | M11: 23532.82 | N11: =SUM(B11:M11) | O11: 21737.98 | P11: 23681.85 | Q11: 23572.62 | R11: 22709.62 | S11: 24378.86 | T11: 25046.45 | U11: 26811.22 | AA11: =SUM(O11:U11) | AB11: =SUM(O11:Z11) | AC11: 24045 | AD11: 24045 | AE11: 24045 | AF11: 24045 | AG11: 24045 | AH11: 24045 | AI11: =SUM(AC11:AH11) | AJ11: =SUM(AC11:AH11)+AI11 | AK11: =IF(N11<>0,(AB11-N11)/ABS(N11),0) | AL11: =IF(AB11<>0,(AJ11-AB11)/ABS(AB11),0)
A12: Nursery NI | B12: 1203.75 | C12: 1428.91 | D12: 1476.68 | E12: 2209.36 | F12: 2440.06 | G12: 2305.71 | H12: 2435.99 | I12: 2237.92 | J12: 2496.6 | K12: 2529.67 | L12: 2509.06 | M12: 2620.8 | N12: =SUM(B12:M12) | O12: 2278.05 | P12: 2565.96 | Q12: 2663.88 | R12: 2675.84 | S12: 2716.1 | T12: 2746.05 | U12: 2955.86 | AA12: =SUM(O12:U12) | AB12: =SUM(O12:Z12) | AC12: 2713 | AD12: 2713 | AE12: 2713 | AF12: 2713 | AG12: 2713 | AH12: 2713 | AI12: =SUM(AC12:AH12) | AJ12: =SUM(AC12:AH12)+AI12 | AK12: =IF(N12<>0,(AB12-N12)/ABS(N12),0) | AL12: =IF(AB12<>0,(AJ12-AB12)/ABS(AB12),0)
A13: Nursery Pension | B13: 311.63 | C13: 367.72 | D13: 365.22 | E13: 382.57 | F13: 424.4 | G13: 305.58 | H13: 307.23 | I13: 283.62 | J13: 355.96 | K13: 382.65 | L13: 386.03 | M13: 392.32 | N13: =SUM(B13:M13) | O13: 315.27 | P13: 466.06 | Q13: 442.88 | R13: 419.77 | S13: 440.94 | T13: 498.05 | U13: 494.63 | AA13: =SUM(O13:U13) | AB13: =SUM(O13:Z13) | AC13: 453 | AD13: 453 | AE13: 453 | AF13: 453 | AG13: 453 | AH13: 453 | AI13: =SUM(AC13:AH13) | AJ13: =SUM(AC13:AH13)+AI13 | AK13: =IF(N13<>0,(AB13-N13)/ABS(N13),0) | AL13: =IF(AB13<>0,(AJ13-AB13)/ABS(AB13),0)
A14: Uniform | B14: 0 | C14: 0 | D14: 166.92 | E14: 0 | F14: 0 | G14: 155.16 | H14: 0 | I14: 0 | J14: 274.38 | K14: 0 | L14: 0 | M14: 0 | N14: =SUM(B14:M14) | O14: 97.74 | P14: 0 | Q14: 0 | R14: 0 | S14: 55.43 | T14: 178.56 | U14: 79.68 | AA14: =SUM(O14:U14) | AB14: =SUM(O14:Z14) | AC14: 49 | AD14: 49 | AE14: 49 | AF14: 49 | AG14: 49 | AH14: 49 | AI14: =SUM(AC14:AH14) | AJ14: =SUM(AC14:AH14)+AI14 | AK14: =IF(N14<>0,(AB14-N14)/ABS(N14),0) | AL14: =IF(AB14<>0,(AJ14-AB14)/ABS(AB14),0)
A15: Training | B15: 97.9 | C15: 24.95 | D15: 53.94 | E15: 109.2 | F15: 36 | G15: 29.94 | H15: 0 | I15: 74.4 | J15: 387.94 | K15: 115.2 | L15: 45 | M15: 636.5 | N15: =SUM(B15:M15) | O15: 666.67 | P15: 78 | Q15: 0 | R15: 10 | S15: 78 | T15: 0 | U15: 0 | AA15: =SUM(O15:U15) | AB15: =SUM(O15:Z15) | AC15: 100 | AD15: 100 | AE15: 100 | AF15: 100 | AG15: 100 | AH15: 100 | AI15: =SUM(AC15:AH15) | AJ15: =SUM(AC15:AH15)+AI15 | AK15: =IF(N15<>0,(AB15-N15)/ABS(N15),0) | AL15: =IF(AB15<>0,(AJ15-AB15)/ABS(AB15),0)
A16: Staff Welfare | B16: 6 | C16: 169.43 | D16: 78.2 | E16: 155.13 | F16: 174.31 | G16: 86.18 | H16: 68.6 | I16: 55.43 | J16: 96.39 | K16: 12.05 | L16: 77.67 | M16: 88.14 | N16: =SUM(B16:M16) | O16: 73.11 | P16: 37.21 | Q16: 47.72 | R16: 77.6 | S16: 66.87 | T16: 100.93 | U16: 26.72 | AA16: =SUM(O16:U16) | AB16: =SUM(O16:Z16) | AC16: 100 | AD16: 100 | AE16: 100 | AF16: 100 | AG16: 100 | AH16: 100 | AI16: =SUM(AC16:AH16) | AJ16: =SUM(AC16:AH16)+AI16 | AK16: =IF(N16<>0,(AB16-N16)/ABS(N16),0) | AL16: =IF(AB16<>0,(AJ16-AB16)/ABS(AB16),0)
A17: Recruitment | B17: 0 | C17: 0 | D17: 0 | E17: 0 | F17: 0 | G17: 0 | H17: 0 | I17: 0 | J17: 0 | K17: 0 | L17: 0 | M17: 0 | N17: =SUM(B17:M17) | O17: 0 | P17: 0 | Q17: 0 | R17: 0 | S17: 0 | T17: 0 | U17: 0 | V17: 0 | W17: 0 | X17: 0 | Y17: 0 | Z17: 0 | AA17: =SUM(O17:U17) | AB17: =SUM(O17:Z17) | AC17: 0 | AD17: 0 | AE17: 0 | AF17: 0 | AG17: 0 | AH17: 0 | AI17: =SUM(AC17:AH17) | AJ17: =SUM(AC17:AH17)+AI17 | AK17: =IF(N17<>0,(AB17-N17)/ABS(N17),0) | AL17: =IF(AB17<>0,(AJ17-AB17)/ABS(AB17),0)
A18: Rewards & Recognition | B18: 0 | C18: 0 | D18: 0 | E18: 0 | F18: 0 | G18: 0 | H18: 45 | I18: 0 | J18: 62.98 | K18: 32.48 | L18: 14.88 | M18: 130.64 | N18: =SUM(B18:M18) | O18: 18.95 | P18: 58.3 | Q18: 0 | R18: 0 | S18: 0 | T18: 0 | U18: 74.22 | AA18: =SUM(O18:U18) | AB18: =SUM(O18:Z18) | AC18: 42 | AD18: 42 | AE18: 42 | AF18: 42 | AG18: 42 | AH18: 42 | AI18: =SUM(AC18:AH18) | AJ18: =SUM(AC18:AH18)+AI18 | AK18: =IF(N18<>0,(AB18-N18)/ABS(N18),0) | AL18: =IF(AB18<>0,(AJ18-AB18)/ABS(AB18),0)
A19: Temps | B19: 0 | C19: 0 | D19: 0 | E19: 0 | F19: 0 | G19: 0 | H19: 0 | I19: 0 | J19: 0 | K19: 0 | L19: 0 | M19: 0 | N19: =SUM(B19:M19) | O19: 0 | P19: 0 | Q19: 0 | R19: 0 | S19: 0 | T19: 0 | U19: 0 | V19: 0 | W19: 0 | X19: 0 | Y19: 0 | Z19: 0 | AA19: =SUM(O19:U19) | AB19: =SUM(O19:Z19) | AC19: 0 | AD19: 0 | AE19: 0 | AF19: 0 | AG19: 0 | AH19: 0 | AI19: =SUM(AC19:AH19) | AJ19: =SUM(AC19:AH19)+AI19 | AK19: =IF(N19<>0,(AB19-N19)/ABS(N19),0) | AL19: =IF(AB19<>0,(AJ19-AB19)/ABS(AB19),0)
A20: Total Personnel | B20: =B11+B12+B13+B14+B15+B16+B17+B18+B19 | C20: =C11+C12+C13+C14+C15+C16+C17+C18+C19 | D20: =D11+D12+D13+D14+D15+D16+D17+D18+D19 | E20: =E11+E12+E13+E14+E15+E16+E17+E18+E19 | F20: =F11+F12+F13+F14+F15+F16+F17+F18+F19 | G20: =G11+G12+G13+G14+G15+G16+G17+G18+G19 | H20: =H11+H12+H13+H14+H15+H16+H17+H18+H19 | I20: =I11+I12+I13+I14+I15+I16+I17+I18+I19 | ... AJ20: =AJ11+AJ12+AJ13+AJ14+AJ15+AJ16+AJ17+AJ18+AJ19 | AK20: =IF(N20<>0,(AB20-N20)/ABS(N20),0) | AL20: =IF(AB20<>0,(AJ20-AB20)/ABS(AB20),0)
A21: Sal:Rev | B21: =IF(B7>0,B20/B7,0) | C21: =IF(C7>0,C20/C7,0) | D21: =IF(D7>0,D20/D7,0) | E21: =IF(E7>0,E20/E7,0) | F21: =IF(F7>0,F20/F7,0) | G21: =IF(G7>0,G20/G7,0) | H21: =IF(H7>0,H20/H7,0) | I21: =IF(I7>0,I20/I7,0) | ... AJ21: =IF(AJ7>0,AJ20/AJ7,0)
A23: Childcare
A24: Catering Costs | N24: =SUM(B24:M24) | O24: 968.69 | P24: 1153.13 | Q24: 1045.2 | R24: 1430.46 | S24: 861.84 | T24: 1051.83 | U24: 1395.99 | V24: 1046.925 | W24: 1108.9416 | X24: 1213.1808 | Y24: 1195.116 | Z24: 1179.7344 | AA24: =SUM(O24:U24) | AB24: =SUM(O24:Z24) | AC24: 1188.9228 | AD24: 1118.5946 | AE24: 1355.0453 | AF24: 1009.607 | AG24: 997.83341 | AH24: 1065.8912 | AI24: =SUM(AC24:AH24) | AJ24: =SUM(AC24:AH24)+AI24 | AK24: =IF(N24<>0,(AB24-N24)/ABS(N24),0) | AL24: =IF(AB24<>0,(AJ24-AB24)/ABS(AB24),0)
A25: Toys and Games | B25: 683.49 | C25: 332.85 | D25: 213.47 | E25: 84.29 | F25: 1142.04 | G25: 347.81 | H25: 169.15 | I25: 231.52 | J25: 132.85 | K25: 444.81 | L25: 168.92 | M25: 104.22 | N25: =SUM(B25:M25) | O25: 167.5 | P25: 207.32 | Q25: 354.51 | R25: 49.2 | S25: 165.54 | T25: 97.45 | U25: 79.11 | AA25: =SUM(O25:U25) | AB25: =SUM(O25:Z25) | AC25: 58 | AD25: 58 | AE25: 58 | AF25: 58 | AG25: 58 | AH25: 58 | AI25: =SUM(AC25:AH25) | AJ25: =SUM(AC25:AH25)+AI25 | AK25: =IF(N25<>0,(AB25-N25)/ABS(N25),0) | AL25: =IF(AB25<>0,(AJ25-AB25)/ABS(AB25),0)
A26: Art Materials | N26: =SUM(B26:M26) | O26: 84.06 | P26: 39.52 | Q26: 99.69 | R26: 40.39 | S26: 49.93 | T26: 94.53 | U26: 89.75 | V26: 104.6925 | W26: 110.89416 | X26: 121.31808 | Y26: 119.5116 | Z26: 117.97344 | AA26: =SUM(O26:U26) | AB26: =SUM(O26:Z26) | AC26: 118.89228 | AD26: 111.85946 | AE26: 135.50453 | AF26: 100.9607 | AG26: 99.783341 | AH26: 106.58912 | AI26: =SUM(AC26:AH26) | AJ26: =SUM(AC26:AH26)+AI26 | AK26: =IF(N26<>0,(AB26-N26)/ABS(N26),0) | AL26: =IF(AB26<>0,(AJ26-AB26)/ABS(AB26),0)
A27: Nursery Stationery | B27: 69.2 | C27: 20.73 | D27: 82.73 | E27: 16.99 | F27: 110.64 | G27: 52.16 | H27: 63.11 | I27: 0 | J27: 167.04 | K27: 39.54 | L27: 92.5 | M27: 7.71 | N27: =SUM(B27:M27) | O27: 107.66 | P27: 12.79 | Q27: 19.05 | R27: 34.21 | S27: 42.26 | T27: 62.46 | U27: 43.83 | AA27: =SUM(O27:U27) | AB27: =SUM(O27:Z27) | AC27: 100 | AD27: 100 | AE27: 100 | AF27: 100 | AG27: 100 | AH27: 100 | AI27: =SUM(AC27:AH27) | AJ27: =SUM(AC27:AH27)+AI27 | AK27: =IF(N27<>0,(AB27-N27)/ABS(N27),0) | AL27: =IF(AB27<>0,(AJ27-AB27)/ABS(AB27),0)
A28: Nursery Equipment | B28: 158.02 | C28: 184.27 | D28: 189.68 | E28: 63.74 | F28: 202.4 | G28: 267.82 | H28: 261.62 | I28: 42.89 | J28: 215.43 | K28: 821.35 | L28: 88.28 | M28: 254.5 | N28: =SUM(B28:M28) | O28: 26.67 | P28: 16.99 | Q28: 99.65 | R28: 30.76 | S28: 48.77 | T28: 139.95 | U28: 191.54 | AA28: =SUM(O28:U28) | AB28: =SUM(O28:Z28) | AC28: 50 | AD28: 50 | AE28: 50 | AF28: 50 | AG28: 50 | AH28: 50 | AI28: =SUM(AC28:AH28) | AJ28: =SUM(AC28:AH28)+AI28 | AK28: =IF(N28<>0,(AB28-N28)/ABS(N28),0) | AL28: =IF(AB28<>0,(AJ28-AB28)/ABS(AB28),0)
A29: Nursery Consumables | N29: =SUM(B29:M29) | O29: 37.28 | P29: 173.28 | Q29: 69.61 | R29: 163.95 | S29: 223.29 | T29: 304.13 | U29: 104.9 | V29: 174.48751 | W29: 184.8236 | X29: 202.1968 | Y29: 199.186 | Z29: 196.6224 | AA29: =SUM(O29:U29) | AB29: =SUM(O29:Z29) | AC29: 198.1538 | AD29: 186.43243 | AE29: 225.84089 | AF29: 168.26784 | AG29: 166.30557 | AH29: 177.64854 | AI29: =SUM(AC29:AH29) | AJ29: =SUM(AC29:AH29)+AI29 | AK29: =IF(N29<>0,(AB29-N29)/ABS(N29),0) | AL29: =IF(AB29<>0,(AJ29-AB29)/ABS(AB29),0)
A30: Total Childcare Costs | B30: =B24+B25+B26+B27+B28+B29 | C30: =C24+C25+C26+C27+C28+C29 | D30: =D24+D25+D26+D27+D28+D29 | E30: =E24+E25+E26+E27+E28+E29 | F30: =F24+F25+F26+F27+F28+F29 | G30: =G24+G25+G26+G27+G28+G29 | H30: =H24+H25+H26+H27+H28+H29 | I30: =I24+I25+I26+I27+I28+I29 | ... AJ30: =AJ24+AJ25+AJ26+AJ27+AJ28+AJ29 | AK30: =IF(N30<>0,(AB30-N30)/ABS(N30),0) | AL30: =IF(AB30<>0,(AJ30-AB30)/ABS(AB30),0)
A32: Premises & Admin
A33: Rent | B33: 4000 | C33: 4000 | D33: 4000 | E33: 4000 | F33: 4000 | G33: 4000 | H33: 4000 | I33: 4000 | J33: 4000 | K33: 4000 | L33: 4000 | M33: 4000 | N33: =SUM(B33:M33) | O33: 0 | P33: 0 | Q33: 0 | R33: 0 | S33: 0 | T33: 0 | U33: 0 | AA33: =SUM(O33:U33) | AB33: =SUM(O33:Z33) | AC33: 0 | AD33: 0 | AE33: 0 | AF33: 0 | AG33: 0 | AH33: 0 | AI33: =SUM(AC33:AH33) | AJ33: =SUM(AC33:AH33)+AI33 | AK33: =IF(N33<>0,(AB33-N33)/ABS(N33),0) | AL33: =IF(AB33<>0,(AJ33-AB33)/ABS(AB33),0)
A34: Business Rates | B34: 288.13 | C34: 288.13 | D34: 288.13 | E34: 332.67 | F34: 332.66 | G34: 332.67 | H34: 332.67 | I34: 332.67 | J34: 332.67 | K34: 332.67 | L34: 332.67 | M34: 332.67 | N34: =SUM(B34:M34) | O34: 332.66 | P34: 332.66 | Q34: 332.66 | R34: 349.3 | S34: 349.3 | T34: 1234.3 | U34: 349.3 | AA34: =SUM(O34:U34) | AB34: =SUM(O34:Z34) | AC34: 567 | AD34: 567 | AE34: 567 | AF34: 567 | AG34: 567 | AH34: 567 | AI34: =SUM(AC34:AH34) | AJ34: =SUM(AC34:AH34)+AI34 | AK34: =IF(N34<>0,(AB34-N34)/ABS(N34),0) | AL34: =IF(AB34<>0,(AJ34-AB34)/ABS(AB34),0)
A35: Utilities | B35: 303.39 | C35: 600.05 | D35: 339.82 | E35: 1107.55 | F35: 191.41 | G35: 433.34 | H35: 13.48 | I35: 270.72 | J35: 252.23 | K35: 193.9 | L35: 265.24 | M35: 276.9 | N35: =SUM(B35:M35) | O35: 1223.6 | P35: 629.46 | Q35: 822.72 | R35: 0 | S35: 235.27 | T35: 533.9 | U35: 592.62 | AA35: =SUM(O35:U35) | AB35: =SUM(O35:Z35) | AC35: 370 | AD35: 370 | AE35: 370 | AF35: 370 | AG35: 370 | AH35: 370 | AI35: =SUM(AC35:AH35) | AJ35: =SUM(AC35:AH35)+AI35 | AK35: =IF(N35<>0,(AB35-N35)/ABS(N35),0) | AL35: =IF(AB35<>0,(AJ35-AB35)/ABS(AB35),0)
A36: Repairs & Maintenance | B36: 14.75 | C36: 860.16 | D36: 301.16 | E36: 135.95 | F36: 458.86 | G36: 143.28 | H36: 52.85 | I36: 0 | J36: 837.03 | K36: 0 | L36: 0 | M36: 0 | N36: =SUM(B36:M36) | O36: 0 | P36: 150 | Q36: 407.76 | R36: 21.45 | S36: 0 | T36: 0 | U36: 132.22 | AA36: =SUM(O36:U36) | AB36: =SUM(O36:Z36) | AC36: 0 | AD36: 0 | AE36: 0 | AF36: 0 | AG36: 0 | AH36: 0 | AI36: =SUM(AC36:AH36) | AJ36: =SUM(AC36:AH36)+AI36 | AK36: =IF(N36<>0,(AB36-N36)/ABS(N36),0) | AL36: =IF(AB36<>0,(AJ36-AB36)/ABS(AB36),0)
A37: Cleaning | B37: 241.17 | C37: 155.6 | D37: 234.59 | E37: 34.56 | F37: 327.88 | G37: 324.71 | H37: 295.57 | I37: 176.07 | J37: 356.19 | K37: 263.93 | L37: 133.32 | M37: 172.64 | N37: =SUM(B37:M37) | O37: 283.56 | P37: 93.11 | Q37: 375.91 | R37: 96.76 | S37: 261.6 | T37: 118.25 | U37: 366.06 | AA37: =SUM(O37:U37) | AB37: =SUM(O37:Z37) | AC37: 240 | AD37: 240 | AE37: 240 | AF37: 240 | AG37: 240 | AH37: 240 | AI37: =SUM(AC37:AH37) | AJ37: =SUM(AC37:AH37)+AI37 | AK37: =IF(N37<>0,(AB37-N37)/ABS(N37),0) | AL37: =IF(AB37<>0,(AJ37-AB37)/ABS(AB37),0)
A38: Waste Disposal | B38: 174 | C38: 430.4 | D38: 327.59 | E38: 331.37 | F38: 431.6 | G38: 420.67 | H38: 375.23 | I38: 402.05 | J38: 655.86 | K38: 402.05 | L38: 307.15 | M38: 360.56 | N38: =SUM(B38:M38) | O38: 307.15 | P38: 307.15 | Q38: 345.56 | R38: 415.2 | S38: 343.44 | T38: 208.38 | U38: 434.15 | AA38: =SUM(O38:U38) | AB38: =SUM(O38:Z38) | AC38: 395 | AD38: 395 | AE38: 395 | AF38: 395 | AG38: 395 | AH38: 395 | AI38: =SUM(AC38:AH38) | AJ38: =SUM(AC38:AH38)+AI38 | AK38: =IF(N38<>0,(AB38-N38)/ABS(N38),0) | AL38: =IF(AB38<>0,(AJ38-AB38)/ABS(AB38),0)
A39: Postage/Printing/Stationery | B39: 57.7 | C39: 32.5 | D39: 46.08 | E39: 27.84 | F39: 46.06 | G39: 31.21 | H39: 278.14 | I39: 30.06 | J39: 26.83 | K39: 100.92 | L39: 34.91 | M39: 59.33 | N39: =SUM(B39:M39) | O39: 256.04 | P39: 296.51 | Q39: 534 | R39: 639.81 | S39: 234.32 | T39: 166.74 | U39: 337.08 | AA39: =SUM(O39:U39) | AB39: =SUM(O39:Z39) | AC39: 0 | AD39: 0 | AE39: 0 | AF39: 0 | AG39: 0 | AH39: 0 | AI39: =SUM(AC39:AH39) | AJ39: =SUM(AC39:AH39)+AI39 | AK39: =IF(N39<>0,(AB39-N39)/ABS(N39),0) | AL39: =IF(AB39<>0,(AJ39-AB39)/ABS(AB39),0)
A40: Telephone | B40: 99.91 | C40: 98.52 | D40: 98.52 | E40: 99.91 | F40: 99.91 | G40: 99.91 | H40: 99.91 | I40: 99.91 | J40: 110.53 | K40: 7.5 | L40: 0 | M40: 7.5 | N40: =SUM(B40:M40) | O40: 72 | P40: 30 | Q40: 0 | R40: 110 | S40: 192 | T40: 335 | U40: 75 | AA40: =SUM(O40:U40) | AB40: =SUM(O40:Z40) | AC40: 0 | AD40: 0 | AE40: 0 | AF40: 0 | AG40: 0 | AH40: 0 | AI40: =SUM(AC40:AH40) | AJ40: =SUM(AC40:AH40)+AI40 | AK40: =IF(N40<>0,(AB40-N40)/ABS(N40),0) | AL40: =IF(AB40<>0,(AJ40-AB40)/ABS(AB40),0)
A41: Marketing | B41: 0 | C41: 0 | D41: 0 | E41: 0 | F41: 0 | G41: 0 | H41: 0 | I41: 0 | J41: 0 | K41: 0 | L41: 0 | M41: 0 | N41: =SUM(B41:M41) | O41: 0 | P41: 0 | Q41: 0 | R41: 0 | S41: 0 | T41: 0 | U41: 0 | V41: 0 | W41: 0 | X41: 0 | Y41: 0 | Z41: 0 | AA41: =SUM(O41:U41) | AB41: =SUM(O41:Z41) | AC41: 100 | AD41: 100 | AE41: 100 | AF41: 100 | AG41: 100 | AH41: 100 | AI41: =SUM(AC41:AH41) | AJ41: =SUM(AC41:AH41)+AI41 | AK41: =IF(N41<>0,(AB41-N41)/ABS(N41),0) | AL41: =IF(AB41<>0,(AJ41-AB41)/ABS(AB41),0)
A42: Total Premises & Admin | B42: =B33+B34+B35+B36+B37+B38+B39+B40+B41 | C42: =C33+C34+C35+C36+C37+C38+C39+C40+C41 | D42: =D33+D34+D35+D36+D37+D38+D39+D40+D41 | E42: =E33+E34+E35+E36+E37+E38+E39+E40+E41 | F42: =F33+F34+F35+F36+F37+F38+F39+F40+F41 | G42: =G33+G34+G35+G36+G37+G38+G39+G40+G41 | H42: =H33+H34+H35+H36+H37+H38+H39+H40+H41 | I42: =I33+I34+I35+I36+I37+I38+I39+I40+I41 | ... AJ42: =AJ33+AJ34+AJ35+AJ36+AJ37+AJ38+AJ39+AJ40+AJ41 | AK42: =IF(N42<>0,(AB42-N42)/ABS(N42),0) | AL42: =IF(AB42<>0,(AJ42-AB42)/ABS(AB42),0)
A44: Total Direct Costs | AK44: =IF(N44<>0,(AB44-N44)/ABS(N44),0) | AL44: =IF(AB44<>0,(AJ44-AB44)/ABS(AB44),0)
A46: CONTRIBUTION | B46: =B7-B44 | C46: =C7-C44 | D46: =D7-D44 | E46: =E7-E44 | F46: =F7-F44 | G46: =G7-G44 | H46: =H7-H44 | I46: =I7-I44 | ... AJ46: =AJ7-AJ44 | AK46: =IF(N46<>0,(AB46-N46)/ABS(N46),0) | AL46: =IF(AB46<>0,(AJ46-AB46)/ABS(AB46),0)

Sheet HB
A1: Hazebrouck | B1: Actuals 2025 | O1: 2026 Actual / Forecast | AC1: 2027 Forecast | AK1: YoY | AL1: YoY
B2: Jan | C2: Feb | D2: Mar | E2: Apr | F2: May | G2: Jun | H2: Jul | I2: Aug | J2: Sep | K2: Oct | L2: Nov | M2: Dec | N2: FY2025 Total | O2: Jan | P2: Feb | Q2: Mar | R2: Apr | S2: May | T2: Jun | U2: Jul | V2: Aug | W2: Sep | X2: Oct | Y2: Nov | Z2: Dec | AA2: YTD | AB2: FY2026 Outlook | AC2: Jan | AD2: Feb | AE2: Mar | AF2: Apr | AG2: May | AH2: Jun | AI2: Jul-Dec Proj. | AJ2: FY2027 | AK2: 25→26 % | AL2: 26→27 %
A3: INCOME
A4: Fee Income Regular | B4: 44526.36 | C4: 42668.15 | D4: 49356.27 | E4: 55745.42 | F4: 50381.74 | G4: 50496.26 | H4: 61970.37 | I4: 50217.38 | J4: 36754.18 | K4: 35941.95 | L4: 31455.98 | M4: 43997.17 | N4: =SUM(B4:M4) | O4: 40552.59 | P4: 36292.39 | Q4: 41164.9 | R4: 42853.83 | S4: 34239.51 | T4: 35527.34 | U4: 44114.18 | AA4: =SUM(O4:U4) | AB4: =SUM(O4:Z4) | AC4: 59616.39 | AD4: 56865.4 | AE4: 68454.33 | AF4: 58114.53 | AG4: 45217.21 | AH4: 47158.84 | AI4: =SUM(AC4:AH4) | AJ4: =SUM(AC4:AH4)+AI4 | AK4: =IF(N4<>0,(AB4-N4)/ABS(N4),0) | AL4: =IF(AB4<>0,(AJ4-AB4)/ABS(AB4),0)
A5: EEEF Embedded | B5: 16877.61 | C5: 16877.61 | D5: 17395.39 | E5: 12211.58 | F5: 12211.58 | G5: 12211.58 | H5: 35264.02 | I5: 0 | J5: 14082.29 | K5: 14082.29 | L5: 33950.17 | M5: 34388.31 | N5: =SUM(B5:M5) | O5: 24341.41 | P5: 24341.41 | Q5: 31208.03 | R5: 23609.06 | S5: 23609.06 | T5: 26879.66 | U5: 24032.53 | AA5: =SUM(O5:U5) | AB5: =SUM(O5:Z5) | AC5: 0 | AD5: 0 | AE5: 0 | AF5: 0 | AG5: 0 | AH5: 0 | AI5: =SUM(AC5:AH5) | AJ5: =SUM(AC5:AH5)+AI5 | AK5: =IF(N5<>0,(AB5-N5)/ABS(N5),0) | AL5: =IF(AB5<>0,(AJ5-AB5)/ABS(AB5),0)
A6: Other Income | B6: 100 | C6: 100 | D6: 150 | E6: 150 | F6: 150 | G6: 150 | H6: 150 | I6: 3333.04 | J6: 150 | K6: 150 | L6: 150 | M6: 150 | N6: =SUM(B6:M6) | O6: 150 | P6: 150 | Q6: 150 | R6: 150 | S6: 150 | T6: 150 | U6: 150 | AA6: =SUM(O6:U6) | AB6: =SUM(O6:Z6) | AC6: 0 | AD6: 0 | AE6: 0 | AF6: 0 | AG6: 0 | AH6: 0 | AI6: =SUM(AC6:AH6) | AJ6: =SUM(AC6:AH6)+AI6 | AK6: =IF(N6<>0,(AB6-N6)/ABS(N6),0) | AL6: =IF(AB6<>0,(AJ6-AB6)/ABS(AB6),0)
A7: Total Income | B7: =B4+B5+B6 | C7: =C4+C5+C6 | D7: =D4+D5+D6 | E7: =E4+E5+E6 | F7: =F4+F5+F6 | G7: =G4+G5+G6 | H7: =H4+H5+H6 | I7: =I4+I5+I6 | ... AJ7: =AJ4+AJ5+AJ6 | AK7: =IF(N7<>0,(AB7-N7)/ABS(N7),0) | AL7: =IF(AB7<>0,(AJ7-AB7)/ABS(AB7),0)
A9: DIRECT COSTS
A10: Personnel
A11: Nursery Salaries | B11: 24899.66 | C11: 26577.82 | D11: 26925.91 | E11: 29092.65 | F11: 30703.98 | G11: 32699.41 | H11: 32041.49 | I11: 30033.99 | J11: 30047.01 | K11: 23930.87 | L11: 23821.02 | M11: 27265.52 | N11: =SUM(B11:M11) | O11: 28276.3 | P11: 26802.27 | Q11: 25382.96 | R11: 25595.28 | S11: 24639.07 | T11: 24164.19 | U11: 25386.13 | AA11: =SUM(O11:U11) | AB11: =SUM(O11:Z11) | AC11: 25386.13 | AD11: 25386.13 | AE11: 25386.13 | AF11: 25386.13 | AG11: 25386.13 | AH11: 25386.13 | AI11: =SUM(AC11:AH11) | AJ11: =SUM(AC11:AH11)+AI11 | AK11: =IF(N11<>0,(AB11-N11)/ABS(N11),0) | AL11: =IF(AB11<>0,(AJ11-AB11)/ABS(AB11),0)
A12: Nursery NI | B12: 2002.62 | C12: 2207.05 | D12: 2189.18 | E12: 3403.25 | F12: 3660.67 | G12: 3726.55 | H12: 3675.17 | I12: 3450.1 | J12: 3516.17 | K12: 2723.85 | L12: 2722.83 | M12: 2951.52 | N12: =SUM(B12:M12) | O12: 3122.38 | P12: 2859.56 | Q12: 2641.72 | R12: 2695.94 | S12: 2587.54 | T12: 2503.45 | U12: 2708.66 | AA12: =SUM(O12:U12) | AB12: =SUM(O12:Z12) | AC12: 2708.66 | AD12: 2708.66 | AE12: 2708.66 | AF12: 2708.66 | AG12: 2708.66 | AH12: 2708.66 | AI12: =SUM(AC12:AH12) | AJ12: =SUM(AC12:AH12)+AI12 | AK12: =IF(N12<>0,(AB12-N12)/ABS(N12),0) | AL12: =IF(AB12<>0,(AJ12-AB12)/ABS(AB12),0)
A13: Nursery Pension | B13: 498.73 | C13: 506.68 | D13: 526.7 | E13: 643.53 | F13: 694.99 | G13: 708.16 | H13: 700.99 | I13: 652.88 | J13: 662.3 | K13: 516.93 | L13: 516.73 | M13: 527.27 | N13: =SUM(B13:M13) | O13: 546.7 | P13: 540.97 | Q13: 497.41 | R13: 511.34 | S13: 489.65 | T13: 472.83 | U13: 513.88 | AA13: =SUM(O13:U13) | AB13: =SUM(O13:Z13) | AC13: 513.88 | AD13: 513.88 | AE13: 513.88 | AF13: 513.88 | AG13: 513.88 | AH13: 513.88 | AI13: =SUM(AC13:AH13) | AJ13: =SUM(AC13:AH13)+AI13 | AK13: =IF(N13<>0,(AB13-N13)/ABS(N13),0) | AL13: =IF(AB13<>0,(AJ13-AB13)/ABS(AB13),0)
A14: Uniform | B14: 70.56 | C14: 56.16 | D14: 171.23 | E14: 0 | F14: 119.96 | G14: 78.48 | H14: 0 | I14: 0 | J14: 0 | K14: 136.44 | L14: 0 | M14: 0 | N14: =SUM(B14:M14) | O14: 135.3 | P14: 0 | Q14: 0 | R14: 0 | S14: 0 | T14: 59.28 | U14: 29.94 | AA14: =SUM(O14:U14) | AB14: =SUM(O14:Z14) | AC14: 50 | AD14: 50 | AE14: 50 | AF14: 50 | AG14: 50 | AH14: 50 | AI14: =SUM(AC14:AH14) | AJ14: =SUM(AC14:AH14)+AI14 | AK14: =IF(N14<>0,(AB14-N14)/ABS(N14),0) | AL14: =IF(AB14<>0,(AJ14-AB14)/ABS(AB14),0)
A15: Training | B15: 96 | C15: 0 | D15: 48 | E15: 156 | F15: 98.4 | G15: 0 | H15: 270 | I15: 0 | J15: 0 | K15: 193.2 | L15: 594 | M15: 37.2 | N15: =SUM(B15:M15) | O15: 0 | P15: 58 | Q15: 0 | R15: 24 | S15: 0 | T15: -500 | U15: 331.63 | AA15: =SUM(O15:U15) | AB15: =SUM(O15:Z15) | AC15: 0 | AD15: 0 | AE15: 0 | AF15: 0 | AG15: 0 | AH15: 0 | AI15: =SUM(AC15:AH15) | AJ15: =SUM(AC15:AH15)+AI15 | AK15: =IF(N15<>0,(AB15-N15)/ABS(N15),0) | AL15: =IF(AB15<>0,(AJ15-AB15)/ABS(AB15),0)
A16: Staff Welfare | B16: 133.75 | C16: 119.98 | D16: 168.98 | E16: 151.14 | F16: 162.64 | G16: 156.4 | H16: 78.24 | I16: 238.74 | J16: 0 | K16: 154.24 | L16: 73.01 | M16: 375.95 | N16: =SUM(B16:M16) | O16: 132.69 | P16: 153.97 | Q16: 157.6 | R16: 163.93 | S16: 163.71 | T16: 48.41 | U16: 199.54 | AA16: =SUM(O16:U16) | AB16: =SUM(O16:Z16) | AC16: 132.69 | AD16: 132.69 | AE16: 132.69 | AF16: 132.69 | AG16: 132.69 | AH16: 132.69 | AI16: =SUM(AC16:AH16) | AJ16: =SUM(AC16:AH16)+AI16 | AK16: =IF(N16<>0,(AB16-N16)/ABS(N16),0) | AL16: =IF(AB16<>0,(AJ16-AB16)/ABS(AB16),0)
A17: Recruitment | B17: 0 | C17: 0 | D17: 0 | E17: 0 | F17: 0 | G17: 0 | H17: 0 | I17: 0 | J17: 0 | K17: 0 | L17: 0 | M17: 0 | N17: =SUM(B17:M17) | O17: 0 | P17: 0 | Q17: 0 | R17: 0 | S17: 0 | T17: 0 | U17: 0 | V17: 0 | W17: 0 | X17: 0 | Y17: 0 | Z17: 0 | AA17: =SUM(O17:U17) | AB17: =SUM(O17:Z17) | AC17: 0 | AD17: 0 | AE17: 0 | AF17: 0 | AG17: 0 | AH17: 0 | AI17: =SUM(AC17:AH17) | AJ17: =SUM(AC17:AH17)+AI17 | AK17: =IF(N17<>0,(AB17-N17)/ABS(N17),0) | AL17: =IF(AB17<>0,(AJ17-AB17)/ABS(AB17),0)
A18: Rewards & Recognition | B18: 0 | C18: 0 | D18: 0 | E18: 0 | F18: 0 | G18: 0 | H18: 30 | I18: 9.49 | J18: 21 | K18: 26.97 | L18: 0 | M18: 10.05 | N18: =SUM(B18:M18) | O18: 30 | P18: 50.75 | Q18: 27.55 | R18: 0 | S18: 0 | T18: 0 | U18: 0 | AA18: =SUM(O18:U18) | AB18: =SUM(O18:Z18) | AC18: 42 | AD18: 42 | AE18: 42 | AF18: 42 | AG18: 42 | AH18: 42 | AI18: =SUM(AC18:AH18) | AJ18: =SUM(AC18:AH18)+AI18 | AK18: =IF(N18<>0,(AB18-N18)/ABS(N18),0) | AL18: =IF(AB18<>0,(AJ18-AB18)/ABS(AB18),0)
A19: Temps | B19: 0 | C19: 0 | D19: 0 | E19: 0 | F19: 0 | G19: 0 | H19: 0 | I19: 0 | J19: 0 | K19: 0 | L19: 0 | M19: 0 | N19: =SUM(B19:M19) | O19: 0 | P19: 0 | Q19: 0 | R19: 0 | S19: 0 | T19: 0 | U19: 0 | V19: 0 | W19: 0 | X19: 0 | Y19: 0 | Z19: 0 | AA19: =SUM(O19:U19) | AB19: =SUM(O19:Z19) | AC19: 0 | AD19: 0 | AE19: 0 | AF19: 0 | AG19: 0 | AH19: 0 | AI19: =SUM(AC19:AH19) | AJ19: =SUM(AC19:AH19)+AI19 | AK19: =IF(N19<>0,(AB19-N19)/ABS(N19),0) | AL19: =IF(AB19<>0,(AJ19-AB19)/ABS(AB19),0)
A20: Total Personnel | B20: =B11+B12+B13+B14+B15+B16+B17+B18+B19 | C20: =C11+C12+C13+C14+C15+C16+C17+C18+C19 | D20: =D11+D12+D13+D14+D15+D16+D17+D18+D19 | E20: =E11+E12+E13+E14+E15+E16+E17+E18+E19 | F20: =F11+F12+F13+F14+F15+F16+F17+F18+F19 | G20: =G11+G12+G13+G14+G15+G16+G17+G18+G19 | H20: =H11+H12+H13+H14+H15+H16+H17+H18+H19 | I20: =I11+I12+I13+I14+I15+I16+I17+I18+I19 | ... AJ20: =AJ11+AJ12+AJ13+AJ14+AJ15+AJ16+AJ17+AJ18+AJ19 | AK20: =IF(N20<>0,(AB20-N20)/ABS(N20),0) | AL20: =IF(AB20<>0,(AJ20-AB20)/ABS(AB20),0)
A21: Sal:Rev | B21: =IF(B7>0,B20/B7,0) | C21: =IF(C7>0,C20/C7,0) | D21: =IF(D7>0,D20/D7,0) | E21: =IF(E7>0,E20/E7,0) | F21: =IF(F7>0,F20/F7,0) | G21: =IF(G7>0,G20/G7,0) | H21: =IF(H7>0,H20/H7,0) | I21: =IF(I7>0,I20/I7,0) | ... AJ21: =IF(AJ7>0,AJ20/AJ7,0)
A23: Childcare
A24: Catering Costs | N24: =SUM(B24:M24) | O24: 1913.69 | P24: 2339.36 | Q24: 2227.04 | R24: 1978.58 | S24: 1723.72 | T24: 2074.85 | U24: 2481.22 | V24: 1146.27 | W24: 1532.3724 | X24: 1791.27 | Y24: 1764.99 | Z24: 1495.74 | AA24: =SUM(O24:U24) | AB24: =SUM(O24:Z24) | AC24: 1788.4917 | AD24: 1705.962 | AE24: 2053.6299 | AF24: 1743.4359 | AG24: 1356.5163 | AH24: 1414.7652 | AI24: =SUM(AC24:AH24) | AJ24: =SUM(AC24:AH24)+AI24 | AK24: =IF(N24<>0,(AB24-N24)/ABS(N24),0) | AL24: =IF(AB24<>0,(AJ24-AB24)/ABS(AB24),0)
A25: Toys and Games | B25: 345.51 | C25: 751.02 | D25: 178.36 | E25: 150.78 | F25: 488.33 | G25: 322.31 | H25: 82.26 | I25: 311.59 | J25: 65.91 | K25: 455.48 | L25: 445.51 | M25: 229.46 | N25: =SUM(B25:M25) | O25: 272.87 | P25: 16.47 | Q25: 417.58 | R25: 44.43 | S25: 553.82 | T25: 372.91 | U25: 274.15 | AA25: =SUM(O25:U25) | AB25: =SUM(O25:Z25) | AC25: 53 | AD25: 53 | AE25: 53 | AF25: 53 | AG25: 53 | AH25: 53 | AI25: =SUM(AC25:AH25) | AJ25: =SUM(AC25:AH25)+AI25 | AK25: =IF(N25<>0,(AB25-N25)/ABS(N25),0) | AL25: =IF(AB25<>0,(AJ25-AB25)/ABS(AB25),0)
A26: Art Materials | N26: =SUM(B26:M26) | O26: 68 | P26: 106.03 | Q26: 139.34 | R26: 75.17 | S26: 133.3 | T26: 104.5 | U26: 50.74 | V26: 76.418 | W26: 102.15816 | X26: 119.418 | Y26: 117.666 | Z26: 99.716 | AA26: =SUM(O26:U26) | AB26: =SUM(O26:Z26) | AC26: 119.23278 | AD26: 113.7308 | AE26: 136.90866 | AF26: 116.22906 | AG26: 90.43442 | AH26: 94.31768 | AI26: =SUM(AC26:AH26) | AJ26: =SUM(AC26:AH26)+AI26 | AK26: =IF(N26<>0,(AB26-N26)/ABS(N26),0) | AL26: =IF(AB26<>0,(AJ26-AB26)/ABS(AB26),0)
A27: Nursery Stationery | B27: 65.62 | C27: 0 | D27: 34.49 | E27: 0 | F27: 10.98 | G27: 60.12 | H27: 75.83 | I27: 75.47 | J27: 37.5 | K27: 39.66 | L27: 17.99 | M27: 26.23 | N27: =SUM(B27:M27) | O27: 34.47 | P27: 5.99 | Q27: 35.57 | R27: 10.58 | S27: 32.1 | T27: 12.04 | U27: 5.04 | AA27: =SUM(O27:U27) | AB27: =SUM(O27:Z27) | AC27: 98 | AD27: 98 | AE27: 98 | AF27: 98 | AG27: 98 | AH27: 98 | AI27: =SUM(AC27:AH27) | AJ27: =SUM(AC27:AH27)+AI27 | AK27: =IF(N27<>0,(AB27-N27)/ABS(N27),0) | AL27: =IF(AB27<>0,(AJ27-AB27)/ABS(AB27),0)
A28: Nursery Equipment | B28: 46.93 | C28: 379.43 | D28: 0 | E28: 296.79 | F28: 5.49 | G28: 42.48 | H28: 146.76 | I28: 139.82 | J28: 78.07 | K28: 255.55 | L28: 279.7 | M28: 94.53 | N28: =SUM(B28:M28) | O28: 18.6 | P28: 0 | Q28: 17.49 | R28: 91.96 | S28: -77.97 | T28: 0 | U28: 7.94 | AA28: =SUM(O28:U28) | AB28: =SUM(O28:Z28) | AC28: 53 | AD28: 53 | AE28: 53 | AF28: 53 | AG28: 53 | AH28: 53 | AI28: =SUM(AC28:AH28) | AJ28: =SUM(AC28:AH28)+AI28 | AK28: =IF(N28<>0,(AB28-N28)/ABS(N28),0) | AL28: =IF(AB28<>0,(AJ28-AB28)/ABS(AB28),0)
A29: Nursery Consumables | N29: =SUM(B29:M29) | O29: 284.34 | P29: 440.32 | Q29: 438.53 | R29: 394.82 | S29: 302.87 | T29: 208.43 | U29: 87.88 | V29: 152.836 | W29: 204.31632 | X29: 238.836 | Y29: 235.332 | Z29: 199.432 | AA29: =SUM(O29:U29) | AB29: =SUM(O29:Z29) | AC29: 238.46556 | AD29: 227.4616 | AE29: 273.81732 | AF29: 232.45812 | AG29: 180.86884 | AH29: 188.63536 | AI29: =SUM(AC29:AH29) | AJ29: =SUM(AC29:AH29)+AI29 | AK29: =IF(N29<>0,(AB29-N29)/ABS(N29),0) | AL29: =IF(AB29<>0,(AJ29-AB29)/ABS(AB29),0)
A30: Total Childcare Costs | B30: =B24+B25+B26+B27+B28+B29 | C30: =C24+C25+C26+C27+C28+C29 | D30: =D24+D25+D26+D27+D28+D29 | E30: =E24+E25+E26+E27+E28+E29 | F30: =F24+F25+F26+F27+F28+F29 | G30: =G24+G25+G26+G27+G28+G29 | H30: =H24+H25+H26+H27+H28+H29 | I30: =I24+I25+I26+I27+I28+I29 | ... AJ30: =AJ24+AJ25+AJ26+AJ27+AJ28+AJ29 | AK30: =IF(N30<>0,(AB30-N30)/ABS(N30),0) | AL30: =IF(AB30<>0,(AJ30-AB30)/ABS(AB30),0)
A32: Premises & Admin
A33: Rent | B33: 4645.83 | C33: 4645.83 | D33: 4645.83 | E33: 4645.83 | F33: 4645.83 | G33: 4645.83 | H33: 4645.84 | I33: 4645.83 | J33: 4645.84 | K33: 4645.83 | L33: 4645.83 | M33: 4645.83 | N33: =SUM(B33:M33) | O33: 4645.84 | P33: 4645.83 | Q33: 4645.83 | R33: 4645.83 | S33: 4645.83 | T33: 4645.84 | U33: 4645.83 | AA33: =SUM(O33:U33) | AB33: =SUM(O33:Z33) | AC33: 0 | AD33: 0 | AE33: 0 | AF33: 0 | AG33: 0 | AH33: 0 | AI33: =SUM(AC33:AH33) | AJ33: =SUM(AC33:AH33)+AI33 | AK33: =IF(N33<>0,(AB33-N33)/ABS(N33),0) | AL33: =IF(AB33<>0,(AJ33-AB33)/ABS(AB33),0)
A34: Business Rates | B34: 3844.75 | C34: 3844.75 | D34: 3844.75 | E34: 3908.13 | F34: 3908.13 | G34: 3908.13 | H34: 3908.13 | I34: 3908.13 | J34: 3908.13 | K34: 3908.13 | L34: 3908.13 | M34: 3908.13 | N34: =SUM(B34:M34) | O34: 3908.11 | P34: 3908.11 | Q34: 3908.11 | R34: 3082.92 | S34: 3082.92 | T34: 3082.92 | U34: 3082.92 | AA34: =SUM(O34:U34) | AB34: =SUM(O34:Z34) | AC34: 3082.92 | AD34: 3082.92 | AE34: 3082.92 | AF34: 3082.92 | AG34: 3082.92 | AH34: 3082.92 | AI34: =SUM(AC34:AH34) | AJ34: =SUM(AC34:AH34)+AI34 | AK34: =IF(N34<>0,(AB34-N34)/ABS(N34),0) | AL34: =IF(AB34<>0,(AJ34-AB34)/ABS(AB34),0)
A35: Utilities | B35: 300 | C35: 300 | D35: 300 | E35: 300 | F35: 300 | G35: 300 | H35: 300 | I35: 300 | J35: 300 | K35: 300 | L35: 300 | M35: 300 | N35: =SUM(B35:M35) | O35: 300 | P35: 300 | Q35: 300 | R35: 300 | S35: 300 | T35: 300 | U35: 300 | AA35: =SUM(O35:U35) | AB35: =SUM(O35:Z35) | AC35: 300 | AD35: 300 | AE35: 300 | AF35: 300 | AG35: 300 | AH35: 300 | AI35: =SUM(AC35:AH35) | AJ35: =SUM(AC35:AH35)+AI35 | AK35: =IF(N35<>0,(AB35-N35)/ABS(N35),0) | AL35: =IF(AB35<>0,(AJ35-AB35)/ABS(AB35),0)
A36: Repairs & Maintenance | B36: 29.52 | C36: 4464.59 | D36: 0 | E36: 0 | F36: 48.2 | G36: 0 | H36: 0 | I36: 36.18 | J36: 48.39 | K36: 21.13 | L36: 40 | M36: 0 | N36: =SUM(B36:M36) | O36: 0 | P36: 80.4 | Q36: 0 | R36: 0 | S36: 0 | T36: 0 | U36: 313.1 | AA36: =SUM(O36:U36) | AB36: =SUM(O36:Z36) | AC36: 0 | AD36: 0 | AE36: 0 | AF36: 0 | AG36: 0 | AH36: 0 | AI36: =SUM(AC36:AH36) | AJ36: =SUM(AC36:AH36)+AI36 | AK36: =IF(N36<>0,(AB36-N36)/ABS(N36),0) | AL36: =IF(AB36<>0,(AJ36-AB36)/ABS(AB36),0)
A37: Cleaning | B37: 1025.16 | C37: 994.67 | D37: 1230.5 | E37: 952.43 | F37: 1083.43 | G37: 1263.91 | H37: 1279.37 | I37: 880.76 | J37: 903.78 | K37: 1337.18 | L37: 906.53 | M37: 956.19 | N37: =SUM(B37:M37) | O37: 1070.49 | P37: 1130.83 | Q37: 1703.53 | R37: 260.51 | S37: 862.84 | T37: 1019.03 | U37: 2198.64 | AA37: =SUM(O37:U37) | AB37: =SUM(O37:Z37) | AC37: 1107 | AD37: 1107 | AE37: 1107 | AF37: 1107 | AG37: 1107 | AH37: 1107 | AI37: =SUM(AC37:AH37) | AJ37: =SUM(AC37:AH37)+AI37 | AK37: =IF(N37<>0,(AB37-N37)/ABS(N37),0) | AL37: =IF(AB37<>0,(AJ37-AB37)/ABS(AB37),0)
A38: Waste Disposal | B38: 335.27 | C38: 416.27 | D38: 437.94 | E38: 344.92 | F38: 406.19 | G38: 426.02 | H38: 372.62 | I38: 437.31 | J38: 655.72 | K38: 386.92 | L38: 388.32 | M38: 441.73 | N38: =SUM(B38:M38) | O38: 427.01 | P38: 402.51 | Q38: 455.91 | R38: 510.55 | S38: 429.51 | T38: 320.85 | U38: 493.58 | AA38: =SUM(O38:U38) | AB38: =SUM(O38:Z38) | AC38: 423 | AD38: 423 | AE38: 423 | AF38: 423 | AG38: 423 | AH38: 423 | AI38: =SUM(AC38:AH38) | AJ38: =SUM(AC38:AH38)+AI38 | AK38: =IF(N38<>0,(AB38-N38)/ABS(N38),0) | AL38: =IF(AB38<>0,(AJ38-AB38)/ABS(AB38),0)
A39: Postage/Printing/Stationery | B39: 108.05 | C39: 44.34 | D39: 32.23 | E39: 12 | F39: 40.39 | G39: 34.34 | H39: 140.57 | I39: 47.51 | J39: 80.85 | K39: 63.14 | L39: 51.95 | M39: 154.14 | N39: =SUM(B39:M39) | O39: 19.19 | P39: 48.62 | Q39: 59.29 | R39: 44.34 | S39: 41.65 | T39: 62.16 | U39: 73.76 | AA39: =SUM(O39:U39) | AB39: =SUM(O39:Z39) | AC39: 0 | AD39: 0 | AE39: 0 | AF39: 0 | AG39: 0 | AH39: 0 | AI39: =SUM(AC39:AH39) | AJ39: =SUM(AC39:AH39)+AI39 | AK39: =IF(N39<>0,(AB39-N39)/ABS(N39),0) | AL39: =IF(AB39<>0,(AJ39-AB39)/ABS(AB39),0)
A40: Telephone | B40: 0 | C40: 0 | D40: 0 | E40: 0 | F40: 0 | G40: 0 | H40: 0 | I40: 0 | J40: 0 | K40: 0 | L40: 0 | M40: 0 | N40: =SUM(B40:M40) | O40: 0 | P40: 0 | Q40: 74 | R40: 50 | S40: 0 | T40: 0 | U40: 0 | AA40: =SUM(O40:U40) | AB40: =SUM(O40:Z40) | AC40: 0 | AD40: 0 | AE40: 0 | AF40: 0 | AG40: 0 | AH40: 0 | AI40: =SUM(AC40:AH40) | AJ40: =SUM(AC40:AH40)+AI40 | AK40: =IF(N40<>0,(AB40-N40)/ABS(N40),0) | AL40: =IF(AB40<>0,(AJ40-AB40)/ABS(AB40),0)
A41: Marketing | B41: 0 | C41: 0 | D41: 0 | E41: 0 | F41: 220 | G41: 45 | H41: 0 | I41: 90 | J41: 0 | K41: 137.5 | L41: 137.5 | M41: 137.5 | N41: =SUM(B41:M41) | O41: 236.5 | P41: 137.5 | Q41: 137.5 | R41: 239.5 | S41: 357.5 | T41: 137.5 | U41: 137.5 | AA41: =SUM(O41:U41) | AB41: =SUM(O41:Z41) | AC41: 100 | AD41: 100 | AE41: 100 | AF41: 100 | AG41: 100 | AH41: 100 | AI41: =SUM(AC41:AH41) | AJ41: =SUM(AC41:AH41)+AI41 | AK41: =IF(N41<>0,(AB41-N41)/ABS(N41),0) | AL41: =IF(AB41<>0,(AJ41-AB41)/ABS(AB41),0)
A42: Total Premises & Admin | B42: =B33+B34+B35+B36+B37+B38+B39+B40+B41 | C42: =C33+C34+C35+C36+C37+C38+C39+C40+C41 | D42: =D33+D34+D35+D36+D37+D38+D39+D40+D41 | E42: =E33+E34+E35+E36+E37+E38+E39+E40+E41 | F42: =F33+F34+F35+F36+F37+F38+F39+F40+F41 | G42: =G33+G34+G35+G36+G37+G38+G39+G40+G41 | H42: =H33+H34+H35+H36+H37+H38+H39+H40+H41 | I42: =I33+I34+I35+I36+I37+I38+I39+I40+I41 | ... AJ42: =AJ33+AJ34+AJ35+AJ36+AJ37+AJ38+AJ39+AJ40+AJ41 | AK42: =IF(N42<>0,(AB42-N42)/ABS(N42),0) | AL42: =IF(AB42<>0,(AJ42-AB42)/ABS(AB42),0)
A44: Total Direct Costs | AK44: =IF(N44<>0,(AB44-N44)/ABS(N44),0) | AL44: =IF(AB44<>0,(AJ44-AB44)/ABS(AB44),0)
A46: CONTRIBUTION | B46: =B7-B44 | C46: =C7-C44 | D46: =D7-D44 | E46: =E7-E44 | F46: =F7-F44 | G46: =G7-G44 | H46: =H7-H44 | I46: =I7-I44 | ... AJ46: =AJ7-AJ44 | AK46: =IF(N46<>0,(AB46-N46)/ABS(N46),0) | AL46: =IF(AB46<>0,(AJ46-AB46)/ABS(AB46),0)

Sheet OD
A1: Our Den | B1: Actuals 2025 | O1: 2026 Actual / Forecast | AC1: 2027 Forecast | AK1: YoY | AL1: YoY
B2: Jan | C2: Feb | D2: Mar | E2: Apr | F2: May | G2: Jun | H2: Jul | I2: Aug | J2: Sep | K2: Oct | L2: Nov | M2: Dec | N2: FY2025 Total | O2: Jan | P2: Feb | Q2: Mar | R2: Apr | S2: May | T2: Jun | U2: Jul | V2: Aug | W2: Sep | X2: Oct | Y2: Nov | Z2: Dec | AA2: YTD | AB2: FY2026 Outlook | AC2: Jan | AD2: Feb | AE2: Mar | AF2: Apr | AG2: May | AH2: Jun | AI2: Jul-Dec Proj. | AJ2: FY2027 | AK2: 25→26 % | AL2: 26→27 %
A3: INCOME
A4: Fee Income Regular | B4: 0 | C4: 0 | D4: 0 | E4: 0 | F4: 0 | G4: 0 | H4: 0 | I4: 0 | J4: 1523.64 | K4: 993.66 | L4: 851.8 | M4: 1363.66 | N4: =SUM(B4:M4) | O4: 0 | P4: 0 | Q4: 0 | R4: 0 | S4: 0 | T4: 0 | U4: 0 | AA4: =SUM(O4:U4) | AB4: =SUM(O4:Z4) | AC4: 29839.75 | AD4: 21836.64 | AE4: 28707.94 | AF4: 22423.44 | AG4: 29115.52 | AH4: 27182.25 | AI4: =SUM(AC4:AH4) | AJ4: =SUM(AC4:AH4)+AI4 | AK4: =IF(N4<>0,(AB4-N4)/ABS(N4),0) | AL4: =IF(AB4<>0,(AJ4-AB4)/ABS(AB4),0)
A5: EEEF Embedded | B5: 0 | C5: 0 | D5: 0 | E5: 0 | F5: 0 | G5: 0 | H5: 0 | I5: 0 | J5: 0 | K5: 0 | L5: 6791.83 | M5: 6791.83 | N5: =SUM(B5:M5) | O5: 0 | P5: 0 | Q5: 0 | R5: 0 | S5: 0 | T5: 0 | U5: 0 | AA5: =SUM(O5:U5) | AB5: =SUM(O5:Z5) | AC5: 0 | AD5: 0 | AE5: 0 | AF5: 0 | AG5: 0 | AH5: 0 | AI5: =SUM(AC5:AH5) | AJ5: =SUM(AC5:AH5)+AI5 | AK5: =IF(N5<>0,(AB5-N5)/ABS(N5),0) | AL5: =IF(AB5<>0,(AJ5-AB5)/ABS(AB5),0)
A6: Other Income | B6: 0 | C6: 0 | D6: 0 | E6: 0 | F6: 0 | G6: 0 | H6: 0 | I6: 0 | J6: 0 | K6: 0 | L6: 0 | M6: 0 | N6: =SUM(B6:M6) | O6: 0 | P6: 0 | Q6: 0 | R6: 0 | S6: 0 | T6: 0 | U6: 0 | AA6: =SUM(O6:U6) | AB6: =SUM(O6:Z6) | AC6: 0 | AD6: 0 | AE6: 0 | AF6: 0 | AG6: 0 | AH6: 0 | AI6: =SUM(AC6:AH6) | AJ6: =SUM(AC6:AH6)+AI6 | AK6: =IF(N6<>0,(AB6-N6)/ABS(N6),0) | AL6: =IF(AB6<>0,(AJ6-AB6)/ABS(AB6),0)
A7: Total Income | B7: =B4+B5+B6 | C7: =C4+C5+C6 | D7: =D4+D5+D6 | E7: =E4+E5+E6 | F7: =F4+F5+F6 | G7: =G4+G5+G6 | H7: =H4+H5+H6 | I7: =I4+I5+I6 | ... AJ7: =AJ4+AJ5+AJ6 | AK7: =IF(N7<>0,(AB7-N7)/ABS(N7),0) | AL7: =IF(AB7<>0,(AJ7-AB7)/ABS(AB7),0)
A9: DIRECT COSTS
A10: Personnel
A11: Nursery Salaries | B11: 0 | C11: 0 | D11: 0 | E11: 0 | F11: 0 | G11: 0 | H11: 0 | I11: 0 | J11: 6448.15 | K11: 6689.36 | L11: 6765.64 | M11: 6815.95 | N11: =SUM(B11:M11) | O11: 0 | P11: 0 | Q11: 0 | R11: 0 | S11: 0 | T11: 0 | U11: 0 | AA11: =SUM(O11:U11) | AB11: =SUM(O11:Z11) | AC11: 9114 | AD11: 9114 | AE11: 9114 | AF11: 9114 | AG11: 9114 | AH11: 9114 | AI11: =SUM(AC11:AH11) | AJ11: =SUM(AC11:AH11)+AI11 | AK11: =IF(N11<>0,(AB11-N11)/ABS(N11),0) | AL11: =IF(AB11<>0,(AJ11-AB11)/ABS(AB11),0)
A12: Nursery NI | B12: 0 | C12: 0 | D12: 0 | E12: 0 | F12: 0 | G12: 0 | H12: 0 | I12: 0 | J12: 654.47 | K12: 753.2 | L12: 764.64 | M12: 772.18 | N12: =SUM(B12:M12) | O12: 0 | P12: 0 | Q12: 0 | R12: 0 | S12: 0 | T12: 0 | U12: 0 | AA12: =SUM(O12:U12) | AB12: =SUM(O12:Z12) | AC12: 871 | AD12: 871 | AE12: 871 | AF12: 871 | AG12: 871 | AH12: 871 | AI12: =SUM(AC12:AH12) | AJ12: =SUM(AC12:AH12)+AI12 | AK12: =IF(N12<>0,(AB12-N12)/ABS(N12),0) | AL12: =IF(AB12<>0,(AJ12-AB12)/ABS(AB12),0)
A13: Nursery Pension | B13: 0 | C13: 0 | D13: 0 | E13: 0 | F13: 0 | G13: 0 | H13: 0 | I13: 0 | J13: 0 | K13: 0 | L13: 140.54 | M13: 142.06 | N13: =SUM(B13:M13) | O13: 0 | P13: 0 | Q13: 0 | R13: 0 | S13: 0 | T13: 0 | U13: 0 | AA13: =SUM(O13:U13) | AB13: =SUM(O13:Z13) | AC13: 143.99 | AD13: 143.99 | AE13: 143.99 | AF13: 143.99 | AG13: 143.99 | AH13: 143.99 | AI13: =SUM(AC13:AH13) | AJ13: =SUM(AC13:AH13)+AI13 | AK13: =IF(N13<>0,(AB13-N13)/ABS(N13),0) | AL13: =IF(AB13<>0,(AJ13-AB13)/ABS(AB13),0)
A14: Uniform | B14: 0 | C14: 0 | D14: 0 | E14: 0 | F14: 0 | G14: 0 | H14: 0 | I14: 0 | J14: 0 | K14: 0 | L14: 0 | M14: 0 | N14: =SUM(B14:M14) | O14: 0 | P14: 0 | Q14: 0 | R14: 0 | S14: 0 | T14: 0 | U14: 0 | AA14: =SUM(O14:U14) | AB14: =SUM(O14:Z14) | AC14: 20 | AD14: 20 | AE14: 20 | AF14: 20 | AG14: 20 | AH14: 20 | AI14: =SUM(AC14:AH14) | AJ14: =SUM(AC14:AH14)+AI14 | AK14: =IF(N14<>0,(AB14-N14)/ABS(N14),0) | AL14: =IF(AB14<>0,(AJ14-AB14)/ABS(AB14),0)
A15: Training | B15: 0 | C15: 0 | D15: 0 | E15: 0 | F15: 0 | G15: 0 | H15: 0 | I15: 0 | J15: 0 | K15: 0 | L15: 114 | M15: 0 | N15: =SUM(B15:M15) | O15: 0 | P15: 0 | Q15: 0 | R15: 0 | S15: 0 | T15: 0 | U15: 0 | AA15: =SUM(O15:U15) | AB15: =SUM(O15:Z15) | AC15: 100 | AD15: 100 | AE15: 100 | AF15: 100 | AG15: 100 | AH15: 100 | AI15: =SUM(AC15:AH15) | AJ15: =SUM(AC15:AH15)+AI15 | AK15: =IF(N15<>0,(AB15-N15)/ABS(N15),0) | AL15: =IF(AB15<>0,(AJ15-AB15)/ABS(AB15),0)
A16: Staff Welfare | B16: 0 | C16: 0 | D16: 0 | E16: 0 | F16: 0 | G16: 0 | H16: 0 | I16: 0 | J16: 25.03 | K16: 25.27 | L16: 11.27 | M16: 0 | N16: =SUM(B16:M16) | O16: 0 | P16: 0 | Q16: 0 | R16: 0 | S16: 0 | T16: 0 | U16: 0 | AA16: =SUM(O16:U16) | AB16: =SUM(O16:Z16) | AC16: 40 | AD16: 40 | AE16: 40 | AF16: 40 | AG16: 40 | AH16: 40 | AI16: =SUM(AC16:AH16) | AJ16: =SUM(AC16:AH16)+AI16 | AK16: =IF(N16<>0,(AB16-N16)/ABS(N16),0) | AL16: =IF(AB16<>0,(AJ16-AB16)/ABS(AB16),0)
A17: Recruitment | B17: 0 | C17: 0 | D17: 0 | E17: 0 | F17: 0 | G17: 0 | H17: 0 | I17: 0 | J17: 0 | K17: 0 | L17: 0 | M17: 0 | N17: =SUM(B17:M17) | O17: 0 | P17: 0 | Q17: 0 | R17: 0 | S17: 0 | T17: 0 | U17: 0 | AA17: =SUM(O17:U17) | AB17: =SUM(O17:Z17) | AC17: 0 | AD17: 0 | AE17: 0 | AF17: 0 | AG17: 0 | AH17: 0 | AI17: =SUM(AC17:AH17) | AJ17: =SUM(AC17:AH17)+AI17 | AK17: =IF(N17<>0,(AB17-N17)/ABS(N17),0) | AL17: =IF(AB17<>0,(AJ17-AB17)/ABS(AB17),0)
A18: Rewards & Recognition | B18: 0 | C18: 0 | D18: 0 | E18: 0 | F18: 0 | G18: 0 | H18: 0 | I18: 0 | J18: 0 | K18: 0 | L18: 0 | M18: 0 | N18: =SUM(B18:M18) | O18: 0 | P18: 0 | Q18: 0 | R18: 0 | S18: 0 | T18: 0 | U18: 0 | AA18: =SUM(O18:U18) | AB18: =SUM(O18:Z18) | AC18: 17 | AD18: 17 | AE18: 17 | AF18: 17 | AG18: 17 | AH18: 17 | AI18: =SUM(AC18:AH18) | AJ18: =SUM(AC18:AH18)+AI18 | AK18: =IF(N18<>0,(AB18-N18)/ABS(N18),0) | AL18: =IF(AB18<>0,(AJ18-AB18)/ABS(AB18),0)
A19: Temps | B19: 0 | C19: 0 | D19: 0 | E19: 0 | F19: 0 | G19: 0 | H19: 0 | I19: 0 | J19: 0 | K19: 0 | L19: 0 | M19: 0 | N19: =SUM(B19:M19) | O19: 0 | P19: 0 | Q19: 0 | R19: 0 | S19: 0 | T19: 0 | U19: 0 | AA19: =SUM(O19:U19) | AB19: =SUM(O19:Z19) | AC19: 0 | AD19: 0 | AE19: 0 | AF19: 0 | AG19: 0 | AH19: 0 | AI19: =SUM(AC19:AH19) | AJ19: =SUM(AC19:AH19)+AI19 | AK19: =IF(N19<>0,(AB19-N19)/ABS(N19),0) | AL19: =IF(AB19<>0,(AJ19-AB19)/ABS(AB19),0)
A20: Total Personnel | B20: =B11+B12+B13+B14+B15+B16+B17+B18+B19 | C20: =C11+C12+C13+C14+C15+C16+C17+C18+C19 | D20: =D11+D12+D13+D14+D15+D16+D17+D18+D19 | E20: =E11+E12+E13+E14+E15+E16+E17+E18+E19 | F20: =F11+F12+F13+F14+F15+F16+F17+F18+F19 | G20: =G11+G12+G13+G14+G15+G16+G17+G18+G19 | H20: =H11+H12+H13+H14+H15+H16+H17+H18+H19 | I20: =I11+I12+I13+I14+I15+I16+I17+I18+I19 | ... AJ20: =AJ11+AJ12+AJ13+AJ14+AJ15+AJ16+AJ17+AJ18+AJ19 | AK20: =IF(N20<>0,(AB20-N20)/ABS(N20),0) | AL20: =IF(AB20<>0,(AJ20-AB20)/ABS(AB20),0)
A21: Sal:Rev | B21: =IF(B7>0,B20/B7,0) | C21: =IF(C7>0,C20/C7,0) | D21: =IF(D7>0,D20/D7,0) | E21: =IF(E7>0,E20/E7,0) | F21: =IF(F7>0,F20/F7,0) | G21: =IF(G7>0,G20/G7,0) | H21: =IF(H7>0,H20/H7,0) | I21: =IF(I7>0,I20/I7,0) | ... AJ21: =IF(AJ7>0,AJ20/AJ7,0)
A23: Childcare
A24: Catering Costs | N24: =SUM(B24:M24) | O24: 0 | P24: 0 | Q24: 0 | R24: 0 | S24: 0 | T24: 0 | U24: 0 | V24: 0 | W24: 727.3656 | X24: 757.0992 | Y24: 946.2648 | Z24: 626.7768 | AA24: =SUM(O24:U24) | AB24: =SUM(O24:Z24) | AC24: 931.0002 | AD24: 681.30317 | AE24: 895.68773 | AF24: 699.61133 | AG24: 908.40422 | AH24: 848.0862 | AI24: =SUM(AC24:AH24) | AJ24: =SUM(AC24:AH24)+AI24 | AK24: =IF(N24<>0,(AB24-N24)/ABS(N24),0) | AL24: =IF(AB24<>0,(AJ24-AB24)/ABS(AB24),0)
A25: Toys and Games | B25: 0 | C25: 0 | D25: 0 | E25: 0 | F25: 0 | G25: 0 | H25: 0 | I25: 0 | J25: 3627.11 | K25: 38.69 | L25: 19.59 | M25: 0 | N25: =SUM(B25:M25) | O25: 0 | P25: 0 | Q25: 0 | R25: 0 | S25: 0 | T25: 0 | U25: 0 | AA25: =SUM(O25:U25) | AB25: =SUM(O25:Z25) | AC25: 58 | AD25: 58 | AE25: 58 | AF25: 58 | AG25: 58 | AH25: 58 | AI25: =SUM(AC25:AH25) | AJ25: =SUM(AC25:AH25)+AI25 | AK25: =IF(N25<>0,(AB25-N25)/ABS(N25),0) | AL25: =IF(AB25<>0,(AJ25-AB25)/ABS(AB25),0)
A26: Art Materials | N26: =SUM(B26:M26) | O26: 0 | P26: 0 | Q26: 0 | R26: 0 | S26: 0 | T26: 0 | U26: 0 | V26: 0 | W26: 48.49104 | X26: 50.47328 | Y26: 63.08432 | Z26: 41.78512 | AA26: =SUM(O26:U26) | AB26: =SUM(O26:Z26) | AC26: 62.06668 | AD26: 45.420211 | AE26: 59.712515 | AF26: 46.640755 | AG26: 60.560282 | AH26: 56.53908 | AI26: =SUM(AC26:AH26) | AJ26: =SUM(AC26:AH26)+AI26 | AK26: =IF(N26<>0,(AB26-N26)/ABS(N26),0) | AL26: =IF(AB26<>0,(AJ26-AB26)/ABS(AB26),0)
A27: Nursery Stationery | B27: 0 | C27: 0 | D27: 0 | E27: 0 | F27: 0 | G27: 0 | H27: 0 | I27: 0 | J27: 0 | K27: 0 | L27: 0 | M27: 0 | N27: =SUM(B27:M27) | O27: 0 | P27: 0 | Q27: 0 | R27: 0 | S27: 0 | T27: 0 | U27: 0 | AA27: =SUM(O27:U27) | AB27: =SUM(O27:Z27) | AC27: 50 | AD27: 50 | AE27: 50 | AF27: 50 | AG27: 50 | AH27: 50 | AI27: =SUM(AC27:AH27) | AJ27: =SUM(AC27:AH27)+AI27 | AK27: =IF(N27<>0,(AB27-N27)/ABS(N27),0) | AL27: =IF(AB27<>0,(AJ27-AB27)/ABS(AB27),0)
A28: Nursery Equipment | B28: 0 | C28: 0 | D28: 0 | E28: 0 | F28: 0 | G28: 0 | H28: 0 | I28: 224.96 | J28: 196.03 | K28: 85.5 | L28: 39.63 | M28: 0 | N28: =SUM(B28:M28) | O28: 0 | P28: 0 | Q28: 0 | R28: 0 | S28: 0 | T28: 0 | U28: 0 | AA28: =SUM(O28:U28) | AB28: =SUM(O28:Z28) | AC28: 50 | AD28: 50 | AE28: 50 | AF28: 50 | AG28: 50 | AH28: 50 | AI28: =SUM(AC28:AH28) | AJ28: =SUM(AC28:AH28)+AI28 | AK28: =IF(N28<>0,(AB28-N28)/ABS(N28),0) | AL28: =IF(AB28<>0,(AJ28-AB28)/ABS(AB28),0)
A29: Nursery Consumables | N29: =SUM(B29:M29) | O29: 0 | P29: 0 | Q29: 0 | R29: 0 | S29: 0 | T29: 0 | U29: 0 | V29: 0 | W29: 96.98208 | X29: 100.94656 | Y29: 126.16864 | Z29: 83.57024 | AA29: =SUM(O29:U29) | AB29: =SUM(O29:Z29) | AC29: 124.13336 | AD29: 90.840422 | AE29: 119.42503 | AF29: 93.28151 | AG29: 121.12056 | AH29: 113.07816 | AI29: =SUM(AC29:AH29) | AJ29: =SUM(AC29:AH29)+AI29 | AK29: =IF(N29<>0,(AB29-N29)/ABS(N29),0) | AL29: =IF(AB29<>0,(AJ29-AB29)/ABS(AB29),0)
A30: Total Childcare Costs | B30: =B24+B25+B26+B27+B28+B29 | C30: =C24+C25+C26+C27+C28+C29 | D30: =D24+D25+D26+D27+D28+D29 | E30: =E24+E25+E26+E27+E28+E29 | F30: =F24+F25+F26+F27+F28+F29 | G30: =G24+G25+G26+G27+G28+G29 | H30: =H24+H25+H26+H27+H28+H29 | I30: =I24+I25+I26+I27+I28+I29 | ... AJ30: =AJ24+AJ25+AJ26+AJ27+AJ28+AJ29 | AK30: =IF(N30<>0,(AB30-N30)/ABS(N30),0) | AL30: =IF(AB30<>0,(AJ30-AB30)/ABS(AB30),0)
A32: Premises & Admin
A33: Rent | B33: 352.17 | C33: 352.17 | D33: 352.17 | E33: 352.17 | F33: 352.16 | G33: 352.17 | H33: 352.17 | I33: 352.17 | J33: 352.16 | K33: 352.17 | L33: 352.17 | M33: 352.17 | N33: =SUM(B33:M33) | O33: 0 | P33: 0 | Q33: 0 | R33: 0 | S33: 0 | T33: 0 | U33: 0 | AA33: =SUM(O33:U33) | AB33: =SUM(O33:Z33) | AC33: 0 | AD33: 0 | AE33: 0 | AF33: 0 | AG33: 0 | AH33: 0 | AI33: =SUM(AC33:AH33) | AJ33: =SUM(AC33:AH33)+AI33 | AK33: =IF(N33<>0,(AB33-N33)/ABS(N33),0) | AL33: =IF(AB33<>0,(AJ33-AB33)/ABS(AB33),0)
A34: Business Rates | B34: 336.83 | C34: 336.83 | D34: 336.83 | E34: 336.83 | F34: 336.82 | G34: 336.83 | H34: 336.83 | I34: 336.83 | J34: 336.83 | K34: 336.83 | L34: 336.83 | M34: 336.83 | N34: =SUM(B34:M34) | O34: 0 | P34: 0 | Q34: 0 | R34: 0 | S34: 0 | T34: 0 | U34: 0 | AA34: =SUM(O34:U34) | AB34: =SUM(O34:Z34) | AC34: 459 | AD34: 459 | AE34: 459 | AF34: 459 | AG34: 459 | AH34: 459 | AI34: =SUM(AC34:AH34) | AJ34: =SUM(AC34:AH34)+AI34 | AK34: =IF(N34<>0,(AB34-N34)/ABS(N34),0) | AL34: =IF(AB34<>0,(AJ34-AB34)/ABS(AB34),0)
A35: Utilities | B35: 33.48 | C35: -23.93 | D35: 0 | E35: 0 | F35: -219.14 | G35: 27.29 | H35: 26.41 | I35: 27.29 | J35: 26.05 | K35: 213.56 | L35: 334.75 | M35: -109.84 | N35: =SUM(B35:M35) | O35: 0 | P35: 0 | Q35: 0 | R35: 0 | S35: 0 | T35: 0 | U35: 0 | AA35: =SUM(O35:U35) | AB35: =SUM(O35:Z35) | AC35: 260 | AD35: 260 | AE35: 260 | AF35: 260 | AG35: 260 | AH35: 260 | AI35: =SUM(AC35:AH35) | AJ35: =SUM(AC35:AH35)+AI35 | AK35: =IF(N35<>0,(AB35-N35)/ABS(N35),0) | AL35: =IF(AB35<>0,(AJ35-AB35)/ABS(AB35),0)
A36: Repairs & Maintenance | B36: 0 | C36: 0 | D36: 0 | E36: 0 | F36: 0 | G36: 8439.74 | H36: 3019.4 | I36: 850.47 | J36: 185.01 | K36: 0 | L36: 0 | M36: 108 | N36: =SUM(B36:M36) | O36: 0 | P36: 0 | Q36: 0 | R36: 0 | S36: 0 | T36: 0 | U36: 0 | AA36: =SUM(O36:U36) | AB36: =SUM(O36:Z36) | AC36: 0 | AD36: 0 | AE36: 0 | AF36: 0 | AG36: 0 | AH36: 0 | AI36: =SUM(AC36:AH36) | AJ36: =SUM(AC36:AH36)+AI36 | AK36: =IF(N36<>0,(AB36-N36)/ABS(N36),0) | AL36: =IF(AB36<>0,(AJ36-AB36)/ABS(AB36),0)
A37: Cleaning | B37: 0 | C37: 0 | D37: 0 | E37: 0 | F37: 0 | G37: 0 | H37: 0 | I37: 0 | J37: 157.02 | K37: 0 | L37: 0 | M37: 0 | N37: =SUM(B37:M37) | O37: 0 | P37: 0 | Q37: 0 | R37: 0 | S37: 0 | T37: 0 | U37: 0 | AA37: =SUM(O37:U37) | AB37: =SUM(O37:Z37) | AC37: 160 | AD37: 160 | AE37: 160 | AF37: 160 | AG37: 160 | AH37: 160 | AI37: =SUM(AC37:AH37) | AJ37: =SUM(AC37:AH37)+AI37 | AK37: =IF(N37<>0,(AB37-N37)/ABS(N37),0) | AL37: =IF(AB37<>0,(AJ37-AB37)/ABS(AB37),0)
A38: Waste Disposal | B38: 0 | C38: 0 | D38: 0 | E38: 0 | F38: 0 | G38: 0 | H38: 0 | I38: 0 | J38: 469.6 | K38: 129.62 | L38: 323.75 | M38: 335.15 | N38: =SUM(B38:M38) | O38: 0 | P38: 0 | Q38: 0 | R38: 0 | S38: 0 | T38: 0 | U38: 0 | AA38: =SUM(O38:U38) | AB38: =SUM(O38:Z38) | AC38: 200 | AD38: 200 | AE38: 200 | AF38: 200 | AG38: 200 | AH38: 200 | AI38: =SUM(AC38:AH38) | AJ38: =SUM(AC38:AH38)+AI38 | AK38: =IF(N38<>0,(AB38-N38)/ABS(N38),0) | AL38: =IF(AB38<>0,(AJ38-AB38)/ABS(AB38),0)
A39: Postage/Printing/Stationery | B39: 0 | C39: 0 | D39: 0 | E39: 0 | F39: 0 | G39: 0 | H39: 0 | I39: 227.2 | J39: 131.95 | K39: 0 | L39: 19.19 | M39: 0 | N39: =SUM(B39:M39) | O39: 0 | P39: 0 | Q39: 0 | R39: 0 | S39: 0 | T39: 0 | U39: 0 | AA39: =SUM(O39:U39) | AB39: =SUM(O39:Z39) | AC39: 0 | AD39: 0 | AE39: 0 | AF39: 0 | AG39: 0 | AH39: 0 | AI39: =SUM(AC39:AH39) | AJ39: =SUM(AC39:AH39)+AI39 | AK39: =IF(N39<>0,(AB39-N39)/ABS(N39),0) | AL39: =IF(AB39<>0,(AJ39-AB39)/ABS(AB39),0)
A40: Telephone | B40: 0 | C40: 0 | D40: 0 | E40: 0 | F40: 0 | G40: 0 | H40: 0 | I40: 0 | J40: 0 | K40: 10 | L40: 10 | M40: 10 | N40: =SUM(B40:M40) | O40: 0 | P40: 0 | Q40: 0 | R40: 0 | S40: 0 | T40: 0 | U40: 0 | AA40: =SUM(O40:U40) | AB40: =SUM(O40:Z40) | AC40: 10 | AD40: 10 | AE40: 10 | AF40: 10 | AG40: 10 | AH40: 10 | AI40: =SUM(AC40:AH40) | AJ40: =SUM(AC40:AH40)+AI40 | AK40: =IF(N40<>0,(AB40-N40)/ABS(N40),0) | AL40: =IF(AB40<>0,(AJ40-AB40)/ABS(AB40),0)
A41: Marketing | B41: 0 | C41: 0 | D41: 0 | E41: 0 | F41: 0 | G41: 0 | H41: 0 | I41: 348 | J41: 0 | K41: 0 | L41: 0 | M41: 0 | N41: =SUM(B41:M41) | O41: 0 | P41: 0 | Q41: 0 | R41: 0 | S41: 0 | T41: 0 | U41: 0 | AA41: =SUM(O41:U41) | AB41: =SUM(O41:Z41) | AC41: 100 | AD41: 100 | AE41: 100 | AF41: 100 | AG41: 100 | AH41: 100 | AI41: =SUM(AC41:AH41) | AJ41: =SUM(AC41:AH41)+AI41 | AK41: =IF(N41<>0,(AB41-N41)/ABS(N41),0) | AL41: =IF(AB41<>0,(AJ41-AB41)/ABS(AB41),0)
A42: Total Premises & Admin | B42: =B33+B34+B35+B36+B37+B38+B39+B40+B41 | C42: =C33+C34+C35+C36+C37+C38+C39+C40+C41 | D42: =D33+D34+D35+D36+D37+D38+D39+D40+D41 | E42: =E33+E34+E35+E36+E37+E38+E39+E40+E41 | F42: =F33+F34+F35+F36+F37+F38+F39+F40+F41 | G42: =G33+G34+G35+G36+G37+G38+G39+G40+G41 | H42: =H33+H34+H35+H36+H37+H38+H39+H40+H41 | I42: =I33+I34+I35+I36+I37+I38+I39+I40+I41 | ... AJ42: =AJ33+AJ34+AJ35+AJ36+AJ37+AJ38+AJ39+AJ40+AJ41 | AK42: =IF(N42<>0,(AB42-N42)/ABS(N42),0) | AL42: =IF(AB42<>0,(AJ42-AB42)/ABS(AB42),0)
A44: Total Direct Costs | AK44: =IF(N44<>0,(AB44-N44)/ABS(N44),0) | AL44: =IF(AB44<>0,(AJ44-AB44)/ABS(AB44),0)
A46: CONTRIBUTION | B46: =B7-B44 | C46: =C7-C44 | D46: =D7-D44 | E46: =E7-E44 | F46: =F7-F44 | G46: =G7-G44 | H46: =H7-H44 | I46: =I7-I44 | ... AJ46: =AJ7-AJ44 | AK46: =IF(N46<>0,(AB46-N46)/ABS(N46),0) | AL46: =IF(AB46<>0,(AJ46-AB46)/ABS(AB46),0)

Sheet HDN
A1: Happitots | B1: Actuals 2025 | O1: 2026 Actual / Forecast | AC1: 2027 Forecast | AK1: YoY | AL1: YoY
B2: Jan | C2: Feb | D2: Mar | E2: Apr | F2: May | G2: Jun | H2: Jul | I2: Aug | J2: Sep | K2: Oct | L2: Nov | M2: Dec | N2: FY2025 Total | O2: Jan | P2: Feb | Q2: Mar | R2: Apr | S2: May | T2: Jun | U2: Jul | V2: Aug | W2: Sep | X2: Oct | Y2: Nov | Z2: Dec | AA2: YTD | AB2: FY2026 Outlook | AC2: Jan | AD2: Feb | AE2: Mar | AF2: Apr | AG2: May | AH2: Jun | AI2: Jul-Dec Proj. | AJ2: FY2027 | AK2: 25→26 % | AL2: 26→27 %
A3: INCOME
A4: Fee Income Regular | B4: 45921.31 | C4: 38098.84 | D4: 46565.41 | E4: 57238.21 | F4: 49192.7 | G4: 46788.82 | H4: 62639.28 | I4: 56769.19 | J4: 40329.92 | K4: 40153.78 | L4: 34561.24 | M4: 45835.67 | N4: =SUM(B4:M4) | O4: 34024.2 | P4: 34520.9 | Q4: 44678.8 | R4: 46928.2 | S4: 40486.3 | T4: 45145.1 | U4: 56928.34 | AA4: =SUM(O4:U4) | AB4: =SUM(O4:Z4) | AC4: 63267.18 | AD4: 60274.57 | AE4: 75362.87 | AF4: 69288.22 | AG4: 72843.58 | AH4: 75234.79 | AI4: =SUM(AC4:AH4) | AJ4: =SUM(AC4:AH4)+AI4 | AK4: =IF(N4<>0,(AB4-N4)/ABS(N4),0) | AL4: =IF(AB4<>0,(AJ4-AB4)/ABS(AB4),0)
A5: EEEF Embedded | B5: 14880.4 | C5: 14880.4 | D5: 22868.72 | E5: 11910.48 | F5: 11910.4 | G5: 11910.48 | H5: 28251.59 | I5: 0 | J5: 12726.08 | K5: 12726.08 | L5: 28161.67 | M5: 28507.8 | N5: =SUM(B5:M5) | O5: 20522.7 | P5: 20522.7 | Q5: 21690.4 | R5: 22674.8 | S5: 22674.7 | T5: 24039.4 | U5: 23129.63 | AA5: =SUM(O5:U5) | AB5: =SUM(O5:Z5) | AC5: 0 | AD5: 0 | AE5: 0 | AF5: 0 | AG5: 0 | AH5: 0 | AI5: =SUM(AC5:AH5) | AJ5: =SUM(AC5:AH5)+AI5 | AK5: =IF(N5<>0,(AB5-N5)/ABS(N5),0) | AL5: =IF(AB5<>0,(AJ5-AB5)/ABS(AB5),0)
A6: Other Income | B6: 200 | C6: 200 | D6: 300 | E6: 300 | F6: 300 | G6: 360 | H6: 300 | I6: 3279.07 | J6: 0 | K6: 0 | L6: 0 | M6: 0 | N6: =SUM(B6:M6) | O6: 0 | P6: 0 | Q6: 339.3 | R6: 0 | S6: 0 | T6: 0 | U6: 0 | AA6: =SUM(O6:U6) | AB6: =SUM(O6:Z6) | AC6: 0 | AD6: 0 | AE6: 0 | AF6: 0 | AG6: 0 | AH6: 0 | AI6: =SUM(AC6:AH6) | AJ6: =SUM(AC6:AH6)+AI6 | AK6: =IF(N6<>0,(AB6-N6)/ABS(N6),0) | AL6: =IF(AB6<>0,(AJ6-AB6)/ABS(AB6),0)
A7: Total Income | B7: =B4+B5+B6 | C7: =C4+C5+C6 | D7: =D4+D5+D6 | E7: =E4+E5+E6 | F7: =F4+F5+F6 | G7: =G4+G5+G6 | H7: =H4+H5+H6 | I7: =I4+I5+I6 | ... AJ7: =AJ4+AJ5+AJ6 | AK7: =IF(N7<>0,(AB7-N7)/ABS(N7),0) | AL7: =IF(AB7<>0,(AJ7-AB7)/ABS(AB7),0)
A9: DIRECT COSTS
A10: Personnel
A11: Nursery Salaries | B11: 27199.35 | C11: 26969.3 | D11: 28313.5 | E11: 31211.69 | F11: 29845.91 | G11: 29990.87 | H11: 35763.1 | I11: 33092 | J11: 32840.54 | K11: 36158.05 | L11: 35650.18 | M11: 36557.18 | N11: =SUM(B11:M11) | O11: 38698.39 | P11: 34009.54 | Q11: 40961.75 | R11: 37699.5 | S11: 34150.91 | T11: 33439.28 | U11: 33483.36 | AA11: =SUM(O11:U11) | AB11: =SUM(O11:Z11) | AC11: 33483.36 | AD11: 33483.36 | AE11: 33483.36 | AF11: 33483.36 | AG11: 33483.36 | AH11: 33483.36 | AI11: =SUM(AC11:AH11) | AJ11: =SUM(AC11:AH11)+AI11 | AK11: =IF(N11<>0,(AB11-N11)/ABS(N11),0) | AL11: =IF(AB11<>0,(AJ11-AB11)/ABS(AB11),0)
A12: Nursery NI | B12: 2322.12 | C12: 2227.41 | D12: 2346.82 | E12: 3631.01 | F12: 3444.09 | G12: 3284.69 | H12: 4309.29 | I12: 3776.98 | J12: 3745.07 | K12: 4183.86 | L12: 4085.43 | M12: 4232.64 | N12: =SUM(B12:M12) | O12: 4242.54 | P12: 3578.41 | Q12: 4366.65 | R12: 4174.09 | S12: 3821.87 | T12: 3932.6 | U12: 3939.99 | AA12: =SUM(O12:U12) | AB12: =SUM(O12:Z12) | AC12: 3939.99 | AD12: 3939.99 | AE12: 3939.99 | AF12: 3939.99 | AG12: 3939.99 | AH12: 3939.99 | AI12: =SUM(AC12:AH12) | AJ12: =SUM(AC12:AH12)+AI12 | AK12: =IF(N12<>0,(AB12-N12)/ABS(N12),0) | AL12: =IF(AB12<>0,(AJ12-AB12)/ABS(AB12),0)
A13: Nursery Pension | B13: 590.44 | C13: 569.19 | D13: 575.7 | E13: 603.08 | F13: 604.72 | G13: 616.71 | H13: 779.69 | I13: 683.8 | J13: 705.68 | K13: 790.33 | L13: 770.66 | M13: 799.93 | N13: =SUM(B13:M13) | O13: 804.22 | P13: 675.46 | Q13: 775.88 | R13: 737.62 | S13: 724.15 | T13: 746.31 | U13: 747.79 | AA13: =SUM(O13:U13) | AB13: =SUM(O13:Z13) | AC13: 747.79 | AD13: 747.79 | AE13: 747.79 | AF13: 747.79 | AG13: 747.79 | AH13: 747.79 | AI13: =SUM(AC13:AH13) | AJ13: =SUM(AC13:AH13)+AI13 | AK13: =IF(N13<>0,(AB13-N13)/ABS(N13),0) | AL13: =IF(AB13<>0,(AJ13-AB13)/ABS(AB13),0)
A14: Uniform | B14: 0 | C14: 286.7 | D14: 5.99 | E14: 251.62 | F14: 91.02 | G14: 0 | H14: 0 | I14: 0 | J14: 0 | K14: 163.98 | L14: 0 | M14: 0 | N14: =SUM(B14:M14) | O14: 186.09 | P14: 0 | Q14: 0 | R14: 0 | S14: 207.84 | T14: 0 | U14: 0 | AA14: =SUM(O14:U14) | AB14: =SUM(O14:Z14) | AC14: 83 | AD14: 83 | AE14: 83 | AF14: 83 | AG14: 83 | AH14: 83 | AI14: =SUM(AC14:AH14) | AJ14: =SUM(AC14:AH14)+AI14 | AK14: =IF(N14<>0,(AB14-N14)/ABS(N14),0) | AL14: =IF(AB14<>0,(AJ14-AB14)/ABS(AB14),0)
A15: Training | B15: 48 | C15: 0 | D15: 0 | E15: 0 | F15: 0 | G15: 54 | H15: 24 | I15: 0 | J15: 102 | K15: 0 | L15: 37.2 | M15: 0 | N15: =SUM(B15:M15) | O15: 0 | P15: 720 | Q15: 0 | R15: 335 | S15: 0 | T15: 0 | U15: 37.2 | AA15: =SUM(O15:U15) | AB15: =SUM(O15:Z15) | AC15: 100 | AD15: 100 | AE15: 100 | AF15: 100 | AG15: 100 | AH15: 100 | AI15: =SUM(AC15:AH15) | AJ15: =SUM(AC15:AH15)+AI15 | AK15: =IF(N15<>0,(AB15-N15)/ABS(N15),0) | AL15: =IF(AB15<>0,(AJ15-AB15)/ABS(AB15),0)
A16: Staff Welfare | B16: 220.6 | C16: 225.71 | D16: 115.95 | E16: 324.79 | F16: 102.62 | G16: 41.39 | H16: 456.77 | I16: 117.13 | J16: 158.17 | K16: 329.93 | L16: 60.13 | M16: 69.8 | N16: =SUM(B16:M16) | O16: 200.05 | P16: 80.63 | Q16: 225.8 | R16: 44.26 | S16: 190.63 | T16: 243.97 | U16: 169.85 | AA16: =SUM(O16:U16) | AB16: =SUM(O16:Z16) | AC16: 170 | AD16: 170 | AE16: 170 | AF16: 170 | AG16: 170 | AH16: 170 | AI16: =SUM(AC16:AH16) | AJ16: =SUM(AC16:AH16)+AI16 | AK16: =IF(N16<>0,(AB16-N16)/ABS(N16),0) | AL16: =IF(AB16<>0,(AJ16-AB16)/ABS(AB16),0)
A17: Recruitment | B17: 0 | C17: 0 | D17: 0 | E17: 0 | F17: 0 | G17: 0 | H17: 0 | I17: 0 | J17: 0 | K17: 0 | L17: 0 | M17: 0 | N17: =SUM(B17:M17) | O17: 0 | P17: 0 | Q17: 0 | R17: 0 | S17: 0 | T17: 0 | U17: 0 | V17: 0 | W17: 0 | X17: 0 | Y17: 0 | Z17: 0 | AA17: =SUM(O17:U17) | AB17: =SUM(O17:Z17) | AC17: 0 | AD17: 0 | AE17: 0 | AF17: 0 | AG17: 0 | AH17: 0 | AI17: =SUM(AC17:AH17) | AJ17: =SUM(AC17:AH17)+AI17 | AK17: =IF(N17<>0,(AB17-N17)/ABS(N17),0) | AL17: =IF(AB17<>0,(AJ17-AB17)/ABS(AB17),0)
A18: Rewards & Recognition | B18: 0 | C18: 0 | D18: 0 | E18: 0 | F18: 0 | G18: 0 | H18: 48.47 | I18: 27.5 | J18: 73.47 | K18: 0 | L18: 35.97 | M18: 7.99 | N18: =SUM(B18:M18) | O18: 13.98 | P18: 18.97 | Q18: 11.99 | R18: 0 | S18: 29.98 | T18: 0 | U18: 43.8 | AA18: =SUM(O18:U18) | AB18: =SUM(O18:Z18) | AC18: 71 | AD18: 71 | AE18: 71 | AF18: 71 | AG18: 71 | AH18: 71 | AI18: =SUM(AC18:AH18) | AJ18: =SUM(AC18:AH18)+AI18 | AK18: =IF(N18<>0,(AB18-N18)/ABS(N18),0) | AL18: =IF(AB18<>0,(AJ18-AB18)/ABS(AB18),0)
A19: Temps | B19: 0 | C19: 217.33 | D19: 0 | E19: 0 | F19: 0 | G19: 0 | H19: 0 | I19: 0 | J19: 0 | K19: 0 | L19: 0 | M19: 0 | N19: =SUM(B19:M19) | O19: 0 | P19: 0 | Q19: 0 | R19: 0 | S19: 0 | T19: 0 | U19: 0 | V19: 0 | W19: 0 | X19: 0 | Y19: 0 | Z19: 0 | AA19: =SUM(O19:U19) | AB19: =SUM(O19:Z19) | AC19: 0 | AD19: 0 | AE19: 0 | AF19: 0 | AG19: 0 | AH19: 0 | AI19: =SUM(AC19:AH19) | AJ19: =SUM(AC19:AH19)+AI19 | AK19: =IF(N19<>0,(AB19-N19)/ABS(N19),0) | AL19: =IF(AB19<>0,(AJ19-AB19)/ABS(AB19),0)
A20: Total Personnel | B20: =B11+B12+B13+B14+B15+B16+B17+B18+B19 | C20: =C11+C12+C13+C14+C15+C16+C17+C18+C19 | D20: =D11+D12+D13+D14+D15+D16+D17+D18+D19 | E20: =E11+E12+E13+E14+E15+E16+E17+E18+E19 | F20: =F11+F12+F13+F14+F15+F16+F17+F18+F19 | G20: =G11+G12+G13+G14+G15+G16+G17+G18+G19 | H20: =H11+H12+H13+H14+H15+H16+H17+H18+H19 | I20: =I11+I12+I13+I14+I15+I16+I17+I18+I19 | ... AJ20: =AJ11+AJ12+AJ13+AJ14+AJ15+AJ16+AJ17+AJ18+AJ19 | AK20: =IF(N20<>0,(AB20-N20)/ABS(N20),0) | AL20: =IF(AB20<>0,(AJ20-AB20)/ABS(AB20),0)
A21: Sal:Rev | B21: =IF(B7>0,B20/B7,0) | C21: =IF(C7>0,C20/C7,0) | D21: =IF(D7>0,D20/D7,0) | E21: =IF(E7>0,E20/E7,0) | F21: =IF(F7>0,F20/F7,0) | G21: =IF(G7>0,G20/G7,0) | H21: =IF(H7>0,H20/H7,0) | I21: =IF(I7>0,I20/I7,0) | ... AJ21: =IF(AJ7>0,AJ20/AJ7,0)
A23: Childcare
A24: Catering Costs | N24: =SUM(B24:M24) | O24: 1263.34 | P24: 1271.59 | Q24: 1506.32 | R24: 1840.45 | S24: 1559.5 | T24: 1526.24 | U24: 1904.53 | V24: 1531.7381 | W24: 1676.7713 | X24: 1805.8582 | Y24: 1785.9445 | Z24: 1754.8995 | AA24: =SUM(O24:U24) | AB24: =SUM(O24:Z24) | AC24: 1973.936 | AD24: 1880.5666 | AE24: 2351.3215 | AF24: 2161.7925 | AG24: 2272.7197 | AH24: 2347.3254 | AI24: =SUM(AC24:AH24) | AJ24: =SUM(AC24:AH24)+AI24 | AK24: =IF(N24<>0,(AB24-N24)/ABS(N24),0) | AL24: =IF(AB24<>0,(AJ24-AB24)/ABS(AB24),0)
A25: Toys and Games | B25: 239.5 | C25: 130.44 | D25: 274.74 | E25: 380.74 | F25: 1073 | G25: 48.17 | H25: 581.19 | I25: 236.38 | J25: 393.6 | K25: 22.42 | L25: 14.95 | M25: 53.27 | N25: =SUM(B25:M25) | O25: 113.98 | P25: 728.66 | Q25: 134.78 | R25: 47.99 | S25: 65.32 | T25: 23.67 | U25: 111.13 | AA25: =SUM(O25:U25) | AB25: =SUM(O25:Z25) | AC25: 100 | AD25: 100 | AE25: 100 | AF25: 100 | AG25: 100 | AH25: 100 | AI25: =SUM(AC25:AH25) | AJ25: =SUM(AC25:AH25)+AI25 | AK25: =IF(N25<>0,(AB25-N25)/ABS(N25),0) | AL25: =IF(AB25<>0,(AJ25-AB25)/ABS(AB25),0)
A26: Art Materials | N26: =SUM(B26:M26) | O26: 9.99 | P26: 147.8 | Q26: 26.31 | R26: 70.34 | S26: 0 | T26: 114.28 | U26: 137.9 | V26: 153.17381 | W26: 167.67713 | X26: 180.58582 | Y26: 178.59445 | Z26: 175.48995 | AA26: =SUM(O26:U26) | AB26: =SUM(O26:Z26) | AC26: 197.3936 | AD26: 188.05666 | AE26: 235.13215 | AF26: 216.17925 | AG26: 227.27197 | AH26: 234.73254 | AI26: =SUM(AC26:AH26) | AJ26: =SUM(AC26:AH26)+AI26 | AK26: =IF(N26<>0,(AB26-N26)/ABS(N26),0) | AL26: =IF(AB26<>0,(AJ26-AB26)/ABS(AB26),0)
A27: Nursery Stationery | B27: 0 | C27: 0 | D27: 0 | E27: 0 | F27: 0 | G27: 0 | H27: 0 | I27: 0 | J27: 0 | K27: 0 | L27: 0 | M27: 0 | N27: =SUM(B27:M27) | O27: 0 | P27: 0 | Q27: 0 | R27: 0 | S27: 0 | T27: 0 | U27: 47.19 | AA27: =SUM(O27:U27) | AB27: =SUM(O27:Z27) | AC27: 100 | AD27: 100 | AE27: 100 | AF27: 100 | AG27: 100 | AH27: 100 | AI27: =SUM(AC27:AH27) | AJ27: =SUM(AC27:AH27)+AI27 | AK27: =IF(N27<>0,(AB27-N27)/ABS(N27),0) | AL27: =IF(AB27<>0,(AJ27-AB27)/ABS(AB27),0)
A28: Nursery Equipment | B28: 134.61 | C28: 25.96 | D28: 134.14 | E28: 13.99 | F28: 0 | G28: 166.09 | H28: 0 | I28: 0 | J28: 0 | K28: 524.03 | L28: 0 | M28: 12.98 | N28: =SUM(B28:M28) | O28: 59.34 | P28: 29.69 | Q28: 27.81 | R28: 308 | S28: 0 | T28: 219.9 | U28: 0 | AA28: =SUM(O28:U28) | AB28: =SUM(O28:Z28) | AC28: 50 | AD28: 50 | AE28: 50 | AF28: 50 | AG28: 50 | AH28: 50 | AI28: =SUM(AC28:AH28) | AJ28: =SUM(AC28:AH28)+AI28 | AK28: =IF(N28<>0,(AB28-N28)/ABS(N28),0) | AL28: =IF(AB28<>0,(AJ28-AB28)/ABS(AB28),0)
A29: Nursery Consumables | N29: =SUM(B29:M29) | O29: 110.81 | P29: 287.51 | Q29: 61.94 | R29: 405.44 | S29: 129.82 | T29: 300.5 | U29: 213.47 | V29: 255.28968 | W29: 279.46188 | X29: 300.97636 | Y29: 297.65741 | Z29: 292.48326 | AA29: =SUM(O29:U29) | AB29: =SUM(O29:Z29) | AC29: 328.98934 | AD29: 313.42776 | AE29: 391.88692 | AF29: 360.29874 | AG29: 378.78662 | AH29: 391.22091 | AI29: =SUM(AC29:AH29) | AJ29: =SUM(AC29:AH29)+AI29 | AK29: =IF(N29<>0,(AB29-N29)/ABS(N29),0) | AL29: =IF(AB29<>0,(AJ29-AB29)/ABS(AB29),0)
A30: Total Childcare Costs | B30: =B24+B25+B26+B27+B28+B29 | C30: =C24+C25+C26+C27+C28+C29 | D30: =D24+D25+D26+D27+D28+D29 | E30: =E24+E25+E26+E27+E28+E29 | F30: =F24+F25+F26+F27+F28+F29 | G30: =G24+G25+G26+G27+G28+G29 | H30: =H24+H25+H26+H27+H28+H29 | I30: =I24+I25+I26+I27+I28+I29 | ... AJ30: =AJ24+AJ25+AJ26+AJ27+AJ28+AJ29 | AK30: =IF(N30<>0,(AB30-N30)/ABS(N30),0) | AL30: =IF(AB30<>0,(AJ30-AB30)/ABS(AB30),0)
A32: Premises & Admin
A33: Rent | B33: 0 | C33: 0 | D33: 0 | E33: 0 | F33: 0 | G33: 0 | H33: 0 | I33: 0 | J33: 0 | K33: 0 | L33: 0 | M33: 0 | N33: =SUM(B33:M33) | O33: 0 | P33: 0 | Q33: 0 | R33: 0 | S33: 0 | T33: 0 | U33: 0 | V33: 0 | W33: 0 | X33: 0 | Y33: 0 | Z33: 0 | AA33: =SUM(O33:U33) | AB33: =SUM(O33:Z33) | AC33: 0 | AD33: 0 | AE33: 0 | AF33: 0 | AG33: 0 | AH33: 0 | AI33: =SUM(AC33:AH33) | AJ33: =SUM(AC33:AH33)+AI33 | AK33: =IF(N33<>0,(AB33-N33)/ABS(N33),0) | AL33: =IF(AB33<>0,(AJ33-AB33)/ABS(AB33),0)
A34: Business Rates | B34: 1850.46 | C34: 1850.46 | D34: 1850.46 | E34: 1850.42 | F34: 1850.42 | G34: 1850.42 | H34: 1850.42 | I34: 1850.42 | J34: 1850.42 | K34: 1850.42 | L34: 1850.42 | M34: 1850.42 | N34: =SUM(B34:M34) | O34: 1850.43 | P34: 1850.42 | Q34: 1850.42 | R34: 2128.03 | S34: 2128.03 | T34: 2128.03 | U34: 2128.03 | AA34: =SUM(O34:U34) | AB34: =SUM(O34:Z34) | AC34: 2128.03 | AD34: 2128.03 | AE34: 2128.03 | AF34: 2128.03 | AG34: 2128.03 | AH34: 2128.03 | AI34: =SUM(AC34:AH34) | AJ34: =SUM(AC34:AH34)+AI34 | AK34: =IF(N34<>0,(AB34-N34)/ABS(N34),0) | AL34: =IF(AB34<>0,(AJ34-AB34)/ABS(AB34),0)
A35: Utilities | B35: 2368.8 | C35: 1729.63 | D35: 1859.19 | E35: 2094.4 | F35: 2433.41 | G35: 1489.28 | H35: 704.83 | I35: -1889.83 | J35: 2474.2 | K35: 1184.78 | L35: 1550.31 | M35: 1669.51 | N35: =SUM(B35:M35) | O35: 5880.54 | P35: 3499.35 | Q35: 2725.01 | R35: 1670.17 | S35: 1407.25 | T35: 2084.82 | U35: 594.31 | AA35: =SUM(O35:U35) | AB35: =SUM(O35:Z35) | AC35: 1625 | AD35: 1625 | AE35: 1625 | AF35: 1625 | AG35: 1625 | AH35: 1625 | AI35: =SUM(AC35:AH35) | AJ35: =SUM(AC35:AH35)+AI35 | AK35: =IF(N35<>0,(AB35-N35)/ABS(N35),0) | AL35: =IF(AB35<>0,(AJ35-AB35)/ABS(AB35),0)
A36: Repairs & Maintenance | B36: 3031.86 | C36: 98.95 | D36: 578.95 | E36: 430.94 | F36: 435.02 | G36: 251.22 | H36: 107.95 | I36: 1347.21 | J36: 1756.7 | K36: 943.72 | L36: 994.78 | M36: 268.1 | N36: =SUM(B36:M36) | O36: 1554.62 | P36: 72.67 | Q36: 140.01 | R36: 156.47 | S36: 45.49 | T36: 559.77 | U36: 1555.73 | AA36: =SUM(O36:U36) | AB36: =SUM(O36:Z36) | AC36: 0 | AD36: 0 | AE36: 0 | AF36: 0 | AG36: 0 | AH36: 0 | AI36: =SUM(AC36:AH36) | AJ36: =SUM(AC36:AH36)+AI36 | AK36: =IF(N36<>0,(AB36-N36)/ABS(N36),0) | AL36: =IF(AB36<>0,(AJ36-AB36)/ABS(AB36),0)
A37: Cleaning | B37: 309.94 | C37: 0 | D37: 277.05 | E37: 362.46 | F37: 318.28 | G37: 106.85 | H37: 241.78 | I37: 110.35 | J37: 265.47 | K37: 161.46 | L37: 302.11 | M37: 146.87 | N37: =SUM(B37:M37) | O37: 136.54 | P37: 125.08 | Q37: 172.92 | R37: 115.14 | S37: 0 | T37: 164.48 | U37: 221.88 | AA37: =SUM(O37:U37) | AB37: =SUM(O37:Z37) | AC37: 221 | AD37: 221 | AE37: 221 | AF37: 221 | AG37: 221 | AH37: 221 | AI37: =SUM(AC37:AH37) | AJ37: =SUM(AC37:AH37)+AI37 | AK37: =IF(N37<>0,(AB37-N37)/ABS(N37),0) | AL37: =IF(AB37<>0,(AJ37-AB37)/ABS(AB37),0)
A38: Waste Disposal | B38: 379.15 | C38: 413.35 | D38: 531.62 | E38: 296.93 | F38: 430.74 | G38: 394.55 | H38: 313.24 | I38: 298.24 | J38: 444.35 | K38: 307.21 | L38: 426.55 | M38: 379.16 | N38: =SUM(B38:M38) | O38: 348.17 | P38: 426.54 | Q38: 428.49 | R38: 433.79 | S38: 338.45 | T38: 271.95 | U38: 551.62 | AA38: =SUM(O38:U38) | AB38: =SUM(O38:Z38) | AC38: 389 | AD38: 389 | AE38: 389 | AF38: 389 | AG38: 389 | AH38: 389 | AI38: =SUM(AC38:AH38) | AJ38: =SUM(AC38:AH38)+AI38 | AK38: =IF(N38<>0,(AB38-N38)/ABS(N38),0) | AL38: =IF(AB38<>0,(AJ38-AB38)/ABS(AB38),0)
A39: Postage/Printing/Stationery | B39: 134.31 | C39: 193.15 | D39: 108.59 | E39: 158.57 | F39: 40.91 | G39: 188.02 | H39: 36.03 | I39: 140.04 | J39: 159.8 | K39: 546.86 | L39: 154.65 | M39: 163.62 | N39: =SUM(B39:M39) | O39: 66.11 | P39: 90 | Q39: 78.9 | R39: 109.06 | S39: 91.4 | T39: 94.32 | U39: 19.99 | AA39: =SUM(O39:U39) | AB39: =SUM(O39:Z39) | AC39: 0 | AD39: 0 | AE39: 0 | AF39: 0 | AG39: 0 | AH39: 0 | AI39: =SUM(AC39:AH39) | AJ39: =SUM(AC39:AH39)+AI39 | AK39: =IF(N39<>0,(AB39-N39)/ABS(N39),0) | AL39: =IF(AB39<>0,(AJ39-AB39)/ABS(AB39),0)
A40: Telephone | B40: 0 | C40: 0 | D40: 0 | E40: 0 | F40: 0 | G40: 0 | H40: 0 | I40: 0 | J40: 0 | K40: 0 | L40: 0 | M40: 0 | N40: =SUM(B40:M40) | O40: 14.2 | P40: 63.62 | Q40: 7.75 | R40: 215.54 | S40: 84.84 | T40: 311.31 | U40: 0 | AA40: =SUM(O40:U40) | AB40: =SUM(O40:Z40) | AC40: 0 | AD40: 0 | AE40: 0 | AF40: 0 | AG40: 0 | AH40: 0 | AI40: =SUM(AC40:AH40) | AJ40: =SUM(AC40:AH40)+AI40 | AK40: =IF(N40<>0,(AB40-N40)/ABS(N40),0) | AL40: =IF(AB40<>0,(AJ40-AB40)/ABS(AB40),0)
A41: Marketing | B41: 0 | C41: 0 | D41: 0 | E41: 0 | F41: 0 | G41: 0 | H41: 0 | I41: 0 | J41: 0 | K41: 0 | L41: 29.98 | M41: 0 | N41: =SUM(B41:M41) | O41: 0 | P41: 0 | Q41: 0 | R41: 0 | S41: 0 | T41: 0 | U41: 0 | V41: 0 | W41: 0 | X41: 0 | Y41: 0 | Z41: 0 | AA41: =SUM(O41:U41) | AB41: =SUM(O41:Z41) | AC41: 100 | AD41: 100 | AE41: 100 | AF41: 100 | AG41: 100 | AH41: 100 | AI41: =SUM(AC41:AH41) | AJ41: =SUM(AC41:AH41)+AI41 | AK41: =IF(N41<>0,(AB41-N41)/ABS(N41),0) | AL41: =IF(AB41<>0,(AJ41-AB41)/ABS(AB41),0)
A42: Total Premises & Admin | B42: =B33+B34+B35+B36+B37+B38+B39+B40+B41 | C42: =C33+C34+C35+C36+C37+C38+C39+C40+C41 | D42: =D33+D34+D35+D36+D37+D38+D39+D40+D41 | E42: =E33+E34+E35+E36+E37+E38+E39+E40+E41 | F42: =F33+F34+F35+F36+F37+F38+F39+F40+F41 | G42: =G33+G34+G35+G36+G37+G38+G39+G40+G41 | H42: =H33+H34+H35+H36+H37+H38+H39+H40+H41 | I42: =I33+I34+I35+I36+I37+I38+I39+I40+I41 | ... AJ42: =AJ33+AJ34+AJ35+AJ36+AJ37+AJ38+AJ39+AJ40+AJ41 | AK42: =IF(N42<>0,(AB42-N42)/ABS(N42),0) | AL42: =IF(AB42<>0,(AJ42-AB42)/ABS(AB42),0)
A44: Total Direct Costs | AK44: =IF(N44<>0,(AB44-N44)/ABS(N44),0) | AL44: =IF(AB44<>0,(AJ44-AB44)/ABS(AB44),0)
A46: CONTRIBUTION | B46: =B7-B44 | C46: =C7-C44 | D46: =D7-D44 | E46: =E7-E44 | F46: =F7-F44 | G46: =G7-G44 | H46: =H7-H44 | I46: =I7-I44 | ... AJ46: =AJ7-AJ44 | AK46: =IF(N46<>0,(AB46-N46)/ABS(N46),0) | AL46: =IF(AB46<>0,(AJ46-AB46)/ABS(AB46),0)

Sheet KIN
A1: Kingsclere | B1: Actuals 2025 | O1: 2026 Actual / Forecast | AC1: 2027 Forecast | AK1: YoY | AL1: YoY
B2: Jan | C2: Feb | D2: Mar | E2: Apr | F2: May | G2: Jun | H2: Jul | I2: Aug | J2: Sep | K2: Oct | L2: Nov | M2: Dec | N2: FY2025 Total | O2: Jan | P2: Feb | Q2: Mar | R2: Apr | S2: May | T2: Jun | U2: Jul | V2: Aug | W2: Sep | X2: Oct | Y2: Nov | Z2: Dec | AA2: YTD | AB2: FY2026 Outlook | AC2: Jan | AD2: Feb | AE2: Mar | AF2: Apr | AG2: May | AH2: Jun | AI2: Jul-Dec Proj. | AJ2: FY2027 | AK2: 25→26 % | AL2: 26→27 %
A3: INCOME
A4: Fee Income Regular | B4: 22870.34 | C4: 20355.4 | D4: 23704.42 | E4: 26731.27 | F4: 24249.3 | G4: 26195.06 | H4: 34918.49 | I4: 29544.89 | J4: 19810.11 | K4: 19723.77 | L4: 17281.63 | M4: 23883.61 | N4: =SUM(B4:M4) | O4: 15245.31 | P4: 15771.12 | Q4: 20469.42 | R4: 22519.66 | S4: 20135.17 | T4: 22751.51 | U4: 32640.36 | AA4: =SUM(O4:U4) | AB4: =SUM(O4:Z4) | AC4: 39926.56 | AD4: 37674.64 | AE4: 44411.48 | AF4: 42605.35 | AG4: 42601.69 | AH4: 43952.64 | AI4: =SUM(AC4:AH4) | AJ4: =SUM(AC4:AH4)+AI4 | AK4: =IF(N4<>0,(AB4-N4)/ABS(N4),0) | AL4: =IF(AB4<>0,(AJ4-AB4)/ABS(AB4),0)
A5: EEEF Embedded | B5: 6489.72 | C5: 6489.72 | D5: 6776.32 | E5: 7503.04 | F5: 7503.04 | G5: 7503.04 | H5: 15996.92 | I5: 0 | J5: 6466.01 | K5: 6466.01 | L5: 17054.35 | M5: 17215.99 | N5: =SUM(B5:M5) | O5: 11761.35 | P5: 11761.35 | Q5: 14620.91 | R5: 13713.51 | S5: 13713.51 | T5: 13663.92 | U5: 13696.98 | AA5: =SUM(O5:U5) | AB5: =SUM(O5:Z5) | AC5: 0 | AD5: 0 | AE5: 0 | AF5: 0 | AG5: 0 | AH5: 0 | AI5: =SUM(AC5:AH5) | AJ5: =SUM(AC5:AH5)+AI5 | AK5: =IF(N5<>0,(AB5-N5)/ABS(N5),0) | AL5: =IF(AB5<>0,(AJ5-AB5)/ABS(AB5),0)
A6: Other Income | B6: 0 | C6: 0 | D6: 0 | E6: 0 | F6: 0 | G6: 0 | H6: 0 | I6: 1724.64 | J6: 0 | K6: 0 | L6: 0 | M6: 0 | N6: =SUM(B6:M6) | O6: 500 | P6: 0 | Q6: 0 | R6: 0 | S6: 0 | T6: 0 | U6: 0 | AA6: =SUM(O6:U6) | AB6: =SUM(O6:Z6) | AC6: 0 | AD6: 0 | AE6: 0 | AF6: 0 | AG6: 0 | AH6: 0 | AI6: =SUM(AC6:AH6) | AJ6: =SUM(AC6:AH6)+AI6 | AK6: =IF(N6<>0,(AB6-N6)/ABS(N6),0) | AL6: =IF(AB6<>0,(AJ6-AB6)/ABS(AB6),0)
A7: Total Income | B7: =B4+B5+B6 | C7: =C4+C5+C6 | D7: =D4+D5+D6 | E7: =E4+E5+E6 | F7: =F4+F5+F6 | G7: =G4+G5+G6 | H7: =H4+H5+H6 | I7: =I4+I5+I6 | ... AJ7: =AJ4+AJ5+AJ6 | AK7: =IF(N7<>0,(AB7-N7)/ABS(N7),0) | AL7: =IF(AB7<>0,(AJ7-AB7)/ABS(AB7),0)
A9: DIRECT COSTS
A10: Personnel
A11: Nursery Salaries | B11: 13592.8 | C11: 16596.28 | D11: 16290.85 | E11: 16097.89 | F11: 16253.33 | G11: 16542.65 | H11: 16564.15 | I11: 15091.52 | J11: 15920.49 | K11: 15616.67 | L11: 15962.02 | M11: 14849.14 | N11: =SUM(B11:M11) | O11: 20041.17 | P11: 18133.19 | Q11: 15924.14 | R11: 16140.24 | S11: 15928.26 | T11: 17171.98 | U11: 16231.3 | AA11: =SUM(O11:U11) | AB11: =SUM(O11:Z11) | AC11: 16231.3 | AD11: 16231.3 | AE11: 16231.3 | AF11: 16231.3 | AG11: 16231.3 | AH11: 16231.3 | AI11: =SUM(AC11:AH11) | AJ11: =SUM(AC11:AH11)+AI11 | AK11: =IF(N11<>0,(AB11-N11)/ABS(N11),0) | AL11: =IF(AB11<>0,(AJ11-AB11)/ABS(AB11),0)
A12: Nursery NI | B12: 996.45 | C12: 1024.17 | D12: 1057.44 | E12: 1332.69 | F12: 1575.02 | G12: 1629.49 | H12: 1641.72 | I12: 1473.5 | J12: 1458.61 | K12: 1759.2 | L12: 1810.4 | M12: 1642.86 | N12: =SUM(B12:M12) | O12: 2355.2 | P12: 2183.14 | Q12: 1783.6 | R12: 1777.72 | S12: 1615.62 | T12: 1700.15 | U12: 1608.31 | AA12: =SUM(O12:U12) | AB12: =SUM(O12:Z12) | AC12: 1608.31 | AD12: 1608.31 | AE12: 1608.31 | AF12: 1608.31 | AG12: 1608.31 | AH12: 1608.31 | AI12: =SUM(AC12:AH12) | AJ12: =SUM(AC12:AH12)+AI12 | AK12: =IF(N12<>0,(AB12-N12)/ABS(N12),0) | AL12: =IF(AB12<>0,(AJ12-AB12)/ABS(AB12),0)
A13: Nursery Pension | B13: 245.17 | C13: 251.2 | D13: 244.04 | E13: 193.55 | F13: 236.58 | G13: 310.42 | H13: 312.87 | I13: 279.23 | J13: 273.16 | K13: 280.62 | L13: 291.55 | M13: 252.72 | N13: =SUM(B13:M13) | O13: 293.1 | P13: 253.75 | Q13: 295.81 | R13: 306.68 | S13: 301.09 | T13: 321.47 | U13: 303.09 | AA13: =SUM(O13:U13) | AB13: =SUM(O13:Z13) | AC13: 303.09 | AD13: 303.09 | AE13: 303.09 | AF13: 303.09 | AG13: 303.09 | AH13: 303.09 | AI13: =SUM(AC13:AH13) | AJ13: =SUM(AC13:AH13)+AI13 | AK13: =IF(N13<>0,(AB13-N13)/ABS(N13),0) | AL13: =IF(AB13<>0,(AJ13-AB13)/ABS(AB13),0)
A14: Uniform | B14: 50.22 | C14: 0 | D14: 0 | E14: 0 | F14: 57.3 | G14: 0 | H14: 160.14 | I14: 0 | J14: 185.22 | K14: 70.14 | L14: 28.68 | M14: 7.99 | N14: =SUM(B14:M14) | O14: 116.64 | P14: 0 | Q14: 0 | R14: 0 | S14: 124.2 | T14: 27.98 | U14: 0 | AA14: =SUM(O14:U14) | AB14: =SUM(O14:Z14) | AC14: 50 | AD14: 50 | AE14: 50 | AF14: 50 | AG14: 50 | AH14: 50 | AI14: =SUM(AC14:AH14) | AJ14: =SUM(AC14:AH14)+AI14 | AK14: =IF(N14<>0,(AB14-N14)/ABS(N14),0) | AL14: =IF(AB14<>0,(AJ14-AB14)/ABS(AB14),0)
A15: Training | B15: 56 | C15: 0 | D15: 0 | E15: 46.2 | F15: 18 | G15: 20 | H15: 0 | I15: 70.5 | J15: 0 | K15: 0 | L15: 542.9 | M15: 0 | N15: =SUM(B15:M15) | O15: 0 | P15: 191.99 | Q15: 336 | R15: 0 | S15: 0 | T15: 24 | U15: 0 | AA15: =SUM(O15:U15) | AB15: =SUM(O15:Z15) | AC15: 50 | AD15: 50 | AE15: 50 | AF15: 50 | AG15: 50 | AH15: 50 | AI15: =SUM(AC15:AH15) | AJ15: =SUM(AC15:AH15)+AI15 | AK15: =IF(N15<>0,(AB15-N15)/ABS(N15),0) | AL15: =IF(AB15<>0,(AJ15-AB15)/ABS(AB15),0)
A16: Staff Welfare | B16: 84.36 | C16: 530.31 | D16: 35.12 | E16: 69.5 | F16: 103.74 | G16: 23.19 | H16: 104.06 | I16: 211.05 | J16: 87.06 | K16: 323.12 | L16: 235.68 | M16: 142.07 | N16: =SUM(B16:M16) | O16: 186.99 | P16: 196.28 | Q16: 26.69 | R16: 65 | S16: 48.38 | T16: 191.64 | U16: 231.86 | AA16: =SUM(O16:U16) | AB16: =SUM(O16:Z16) | AC16: 80 | AD16: 80 | AE16: 80 | AF16: 80 | AG16: 80 | AH16: 80 | AI16: =SUM(AC16:AH16) | AJ16: =SUM(AC16:AH16)+AI16 | AK16: =IF(N16<>0,(AB16-N16)/ABS(N16),0) | AL16: =IF(AB16<>0,(AJ16-AB16)/ABS(AB16),0)
A17: Recruitment | B17: 0 | C17: 0 | D17: 0 | E17: 0 | F17: 0 | G17: 0 | H17: 0 | I17: 0 | J17: 0 | K17: 0 | L17: 0 | M17: 0 | N17: =SUM(B17:M17) | O17: 0 | P17: 0 | Q17: 0 | R17: 0 | S17: 0 | T17: 0 | U17: 0 | V17: 0 | W17: 0 | X17: 0 | Y17: 0 | Z17: 0 | AA17: =SUM(O17:U17) | AB17: =SUM(O17:Z17) | AC17: 0 | AD17: 0 | AE17: 0 | AF17: 0 | AG17: 0 | AH17: 0 | AI17: =SUM(AC17:AH17) | AJ17: =SUM(AC17:AH17)+AI17 | AK17: =IF(N17<>0,(AB17-N17)/ABS(N17),0) | AL17: =IF(AB17<>0,(AJ17-AB17)/ABS(AB17),0)
A18: Rewards & Recognition | B18: 0 | C18: 0 | D18: 0 | E18: 0 | F18: 0 | G18: 0 | H18: 13.9 | I18: 55.46 | J18: 0 | K18: 0 | L18: 72.24 | M18: 0 | N18: =SUM(B18:M18) | O18: 75.96 | P18: 51.55 | Q18: 37.88 | R18: 3.99 | S18: 0 | T18: 0 | U18: 82.06 | AA18: =SUM(O18:U18) | AB18: =SUM(O18:Z18) | AC18: 33 | AD18: 33 | AE18: 33 | AF18: 33 | AG18: 33 | AH18: 33 | AI18: =SUM(AC18:AH18) | AJ18: =SUM(AC18:AH18)+AI18 | AK18: =IF(N18<>0,(AB18-N18)/ABS(N18),0) | AL18: =IF(AB18<>0,(AJ18-AB18)/ABS(AB18),0)
A19: Temps | B19: 0 | C19: 0 | D19: 0 | E19: 0 | F19: 0 | G19: 0 | H19: 0 | I19: 0 | J19: 1410.72 | K19: 483.23 | L19: 0 | M19: 0 | N19: =SUM(B19:M19) | O19: 0 | P19: 0 | Q19: 0 | R19: 0 | S19: 0 | T19: 0 | U19: 0 | V19: 0 | W19: 0 | X19: 0 | Y19: 0 | Z19: 0 | AA19: =SUM(O19:U19) | AB19: =SUM(O19:Z19) | AC19: 0 | AD19: 0 | AE19: 0 | AF19: 0 | AG19: 0 | AH19: 0 | AI19: =SUM(AC19:AH19) | AJ19: =SUM(AC19:AH19)+AI19 | AK19: =IF(N19<>0,(AB19-N19)/ABS(N19),0) | AL19: =IF(AB19<>0,(AJ19-AB19)/ABS(AB19),0)
A20: Total Personnel | B20: =B11+B12+B13+B14+B15+B16+B17+B18+B19 | C20: =C11+C12+C13+C14+C15+C16+C17+C18+C19 | D20: =D11+D12+D13+D14+D15+D16+D17+D18+D19 | E20: =E11+E12+E13+E14+E15+E16+E17+E18+E19 | F20: =F11+F12+F13+F14+F15+F16+F17+F18+F19 | G20: =G11+G12+G13+G14+G15+G16+G17+G18+G19 | H20: =H11+H12+H13+H14+H15+H16+H17+H18+H19 | I20: =I11+I12+I13+I14+I15+I16+I17+I18+I19 | ... AJ20: =AJ11+AJ12+AJ13+AJ14+AJ15+AJ16+AJ17+AJ18+AJ19 | AK20: =IF(N20<>0,(AB20-N20)/ABS(N20),0) | AL20: =IF(AB20<>0,(AJ20-AB20)/ABS(AB20),0)
A21: Sal:Rev | B21: =IF(B7>0,B20/B7,0) | C21: =IF(C7>0,C20/C7,0) | D21: =IF(D7>0,D20/D7,0) | E21: =IF(E7>0,E20/E7,0) | F21: =IF(F7>0,F20/F7,0) | G21: =IF(G7>0,G20/G7,0) | H21: =IF(H7>0,H20/H7,0) | I21: =IF(I7>0,I20/I7,0) | ... AJ21: =IF(AJ7>0,AJ20/AJ7,0)
A23: Childcare
A24: Catering Costs | N24: =SUM(B24:M24) | O24: 869.56 | P24: 1160.27 | Q24: 913.08 | R24: 1206.8 | S24: 1861.79 | T24: 1094.42 | U24: 1315.06 | V24: 929.55 | W24: 1152.06 | X24: 1189.11 | Y24: 1197.21 | Z24: 1163.67 | AA24: =SUM(O24:U24) | AB24: =SUM(O24:Z24) | AC24: 1197.7968 | AD24: 1130.2392 | AE24: 1332.3444 | AF24: 1278.1605 | AG24: 1278.0507 | AH24: 1318.5792 | AI24: =SUM(AC24:AH24) | AJ24: =SUM(AC24:AH24)+AI24 | AK24: =IF(N24<>0,(AB24-N24)/ABS(N24),0) | AL24: =IF(AB24<>0,(AJ24-AB24)/ABS(AB24),0)
A25: Toys and Games | B25: 67.66 | C25: 15.5 | D25: 101.01 | E25: 148.99 | F25: 199.49 | G25: 26.91 | H25: 73.44 | I25: 738 | J25: 21.8 | K25: 28.47 | L25: 0 | M25: 113.69 | N25: =SUM(B25:M25) | O25: 0 | P25: 260.81 | Q25: 38.98 | R25: 69.73 | S25: 77.26 | T25: 44.32 | U25: 57.69 | AA25: =SUM(O25:U25) | AB25: =SUM(O25:Z25) | AC25: 50 | AD25: 50 | AE25: 50 | AF25: 50 | AG25: 50 | AH25: 50 | AI25: =SUM(AC25:AH25) | AJ25: =SUM(AC25:AH25)+AI25 | AK25: =IF(N25<>0,(AB25-N25)/ABS(N25),0) | AL25: =IF(AB25<>0,(AJ25-AB25)/ABS(AB25),0)
A26: Art Materials | N26: =SUM(B26:M26) | O26: 94.07 | P26: 60.89 | Q26: 64.43 | R26: 32.94 | S26: 8.48 | T26: 333.48 | U26: 27.94 | V26: 123.94 | W26: 153.608 | X26: 158.548 | Y26: 159.628 | Z26: 155.156 | AA26: =SUM(O26:U26) | AB26: =SUM(O26:Z26) | AC26: 159.70624 | AD26: 150.69856 | AE26: 177.64592 | AF26: 170.4214 | AG26: 170.40676 | AH26: 175.81056 | AI26: =SUM(AC26:AH26) | AJ26: =SUM(AC26:AH26)+AI26 | AK26: =IF(N26<>0,(AB26-N26)/ABS(N26),0) | AL26: =IF(AB26<>0,(AJ26-AB26)/ABS(AB26),0)
A27: Nursery Stationery | B27: 36.35 | C27: 28.59 | D27: 0 | E27: 16.15 | F27: 21.12 | G27: 0 | H27: 14.52 | I27: 18.44 | J27: 7.88 | K27: 0 | L27: 4.99 | M27: 57.13 | N27: =SUM(B27:M27) | O27: 60.4 | P27: 7.69 | Q27: 0 | R27: 24.32 | S27: 0 | T27: 0 | U27: 0 | AA27: =SUM(O27:U27) | AB27: =SUM(O27:Z27) | AC27: 75 | AD27: 75 | AE27: 75 | AF27: 75 | AG27: 75 | AH27: 75 | AI27: =SUM(AC27:AH27) | AJ27: =SUM(AC27:AH27)+AI27 | AK27: =IF(N27<>0,(AB27-N27)/ABS(N27),0) | AL27: =IF(AB27<>0,(AJ27-AB27)/ABS(AB27),0)
A28: Nursery Equipment | B28: 37.02 | C28: 112.99 | D28: 13.99 | E28: 53.88 | F28: 650.18 | G28: 57.55 | H28: 14.48 | I28: 16 | J28: 121.89 | K28: 116.71 | L28: 84.96 | M28: 51.93 | N28: =SUM(B28:M28) | O28: 40.43 | P28: 0 | Q28: 0 | R28: 171.31 | S28: 0 | T28: 54.31 | U28: 78.27 | AA28: =SUM(O28:U28) | AB28: =SUM(O28:Z28) | AC28: 50 | AD28: 50 | AE28: 50 | AF28: 50 | AG28: 50 | AH28: 50 | AI28: =SUM(AC28:AH28) | AJ28: =SUM(AC28:AH28)+AI28 | AK28: =IF(N28<>0,(AB28-N28)/ABS(N28),0) | AL28: =IF(AB28<>0,(AJ28-AB28)/ABS(AB28),0)
A29: Nursery Consumables | N29: =SUM(B29:M29) | O29: 77.58 | P29: 87.23 | Q29: 115.59 | R29: 129.41 | S29: 308.12 | T29: 279.57 | U29: 251.68 | V29: 185.91 | W29: 230.412 | X29: 237.822 | Y29: 239.442 | Z29: 232.734 | AA29: =SUM(O29:U29) | AB29: =SUM(O29:Z29) | AC29: 239.55936 | AD29: 226.04784 | AE29: 266.46888 | AF29: 255.6321 | AG29: 255.61014 | AH29: 263.71584 | AI29: =SUM(AC29:AH29) | AJ29: =SUM(AC29:AH29)+AI29 | AK29: =IF(N29<>0,(AB29-N29)/ABS(N29),0) | AL29: =IF(AB29<>0,(AJ29-AB29)/ABS(AB29),0)
A30: Total Childcare Costs | B30: =B24+B25+B26+B27+B28+B29 | C30: =C24+C25+C26+C27+C28+C29 | D30: =D24+D25+D26+D27+D28+D29 | E30: =E24+E25+E26+E27+E28+E29 | F30: =F24+F25+F26+F27+F28+F29 | G30: =G24+G25+G26+G27+G28+G29 | H30: =H24+H25+H26+H27+H28+H29 | I30: =I24+I25+I26+I27+I28+I29 | ... AJ30: =AJ24+AJ25+AJ26+AJ27+AJ28+AJ29 | AK30: =IF(N30<>0,(AB30-N30)/ABS(N30),0) | AL30: =IF(AB30<>0,(AJ30-AB30)/ABS(AB30),0)
A32: Premises & Admin
A33: Rent | B33: 0 | C33: 0 | D33: 0 | E33: 0 | F33: 0 | G33: 0 | H33: 0 | I33: 0 | J33: 0 | K33: 0 | L33: 0 | M33: 0 | N33: =SUM(B33:M33) | O33: 0 | P33: 0 | Q33: 0 | R33: 0 | S33: 0 | T33: 0 | U33: 0 | V33: 0 | W33: 0 | X33: 0 | Y33: 0 | Z33: 0 | AA33: =SUM(O33:U33) | AB33: =SUM(O33:Z33) | AC33: 0 | AD33: 0 | AE33: 0 | AF33: 0 | AG33: 0 | AH33: 0 | AI33: =SUM(AC33:AH33) | AJ33: =SUM(AC33:AH33)+AI33 | AK33: =IF(N33<>0,(AB33-N33)/ABS(N33),0) | AL33: =IF(AB33<>0,(AJ33-AB33)/ABS(AB33),0)
A34: Business Rates | B34: 758.9 | C34: 758.9 | D34: 758.9 | E34: 758.9 | F34: 758.9 | G34: 758.9 | H34: 758.9 | I34: 758.9 | J34: 758.9 | K34: 758.9 | L34: 758.9 | M34: 758.9 | N34: =SUM(B34:M34) | O34: 758.89 | P34: 758.88 | Q34: 758.88 | R34: 681.42 | S34: 681.42 | T34: 681.42 | U34: 681.42 | AA34: =SUM(O34:U34) | AB34: =SUM(O34:Z34) | AC34: 682 | AD34: 682 | AE34: 682 | AF34: 682 | AG34: 682 | AH34: 682 | AI34: =SUM(AC34:AH34) | AJ34: =SUM(AC34:AH34)+AI34 | AK34: =IF(N34<>0,(AB34-N34)/ABS(N34),0) | AL34: =IF(AB34<>0,(AJ34-AB34)/ABS(AB34),0)
A35: Utilities | B35: 872.46 | C35: 507.52 | D35: 466.58 | E35: 2967.25 | F35: 84.62 | G35: 279.5 | H35: 221.45 | I35: 960.99 | J35: 501.45 | K35: 437.86 | L35: 626.24 | M35: 739.01 | N35: =SUM(B35:M35) | O35: 781.29 | P35: 896.36 | Q35: 481.44 | R35: 822.63 | S35: 608.29 | T35: 359.85 | U35: 564.25 | AA35: =SUM(O35:U35) | AB35: =SUM(O35:Z35) | AC35: 755 | AD35: 755 | AE35: 755 | AF35: 755 | AG35: 755 | AH35: 755 | AI35: =SUM(AC35:AH35) | AJ35: =SUM(AC35:AH35)+AI35 | AK35: =IF(N35<>0,(AB35-N35)/ABS(N35),0) | AL35: =IF(AB35<>0,(AJ35-AB35)/ABS(AB35),0)
A36: Repairs & Maintenance | B36: 387.14 | C36: 108.38 | D36: 277.96 | E36: 372.75 | F36: 389.89 | G36: 0 | H36: 421.2 | I36: 252 | J36: 69.92 | K36: 0 | L36: 147.46 | M36: 108 | N36: =SUM(B36:M36) | O36: 0 | P36: 0 | Q36: 33.29 | R36: 0 | S36: 0 | T36: 0 | U36: 108 | AA36: =SUM(O36:U36) | AB36: =SUM(O36:Z36) | AC36: 0 | AD36: 0 | AE36: 0 | AF36: 0 | AG36: 0 | AH36: 0 | AI36: =SUM(AC36:AH36) | AJ36: =SUM(AC36:AH36)+AI36 | AK36: =IF(N36<>0,(AB36-N36)/ABS(N36),0) | AL36: =IF(AB36<>0,(AJ36-AB36)/ABS(AB36),0)
A37: Cleaning | B37: 165.33 | C37: 90.19 | D37: 168.34 | E37: 290 | F37: 234.76 | G37: 142.75 | H37: 227.02 | I37: 220.38 | J37: 109.95 | K37: 206.87 | L37: 200.81 | M37: 0 | N37: =SUM(B37:M37) | O37: 247.78 | P37: 16.8 | Q37: 358.17 | R37: 7.4 | S37: 129.71 | T37: 284.27 | U37: 326.19 | AA37: =SUM(O37:U37) | AB37: =SUM(O37:Z37) | AC37: 185 | AD37: 185 | AE37: 185 | AF37: 185 | AG37: 185 | AH37: 185 | AI37: =SUM(AC37:AH37) | AJ37: =SUM(AC37:AH37)+AI37 | AK37: =IF(N37<>0,(AB37-N37)/ABS(N37),0) | AL37: =IF(AB37<>0,(AJ37-AB37)/ABS(AB37),0)
A38: Waste Disposal | B38: 403.55 | C38: 655.55 | D38: 533.88 | E38: 385.87 | F38: 337.46 | G38: 361.96 | H38: 308.55 | I38: 322.85 | J38: 483.96 | K38: 430.55 | L38: 322.85 | M38: 376.26 | N38: =SUM(B38:M38) | O38: 340.84 | P38: 332.16 | Q38: 385.56 | R38: 440.2 | S38: 359.16 | T38: 250.5 | U38: 428.86 | AA38: =SUM(O38:U38) | AB38: =SUM(O38:Z38) | AC38: 422 | AD38: 422 | AE38: 422 | AF38: 422 | AG38: 422 | AH38: 422 | AI38: =SUM(AC38:AH38) | AJ38: =SUM(AC38:AH38)+AI38 | AK38: =IF(N38<>0,(AB38-N38)/ABS(N38),0) | AL38: =IF(AB38<>0,(AJ38-AB38)/ABS(AB38),0)
A39: Postage/Printing/Stationery | B39: 43.45 | C39: 71.9 | D39: 34.49 | E39: 38.27 | F39: 56.39 | G39: 29.28 | H39: 17.79 | I39: 23.77 | J39: 49.73 | K39: 24.86 | L39: 23.78 | M39: 25.28 | N39: =SUM(B39:M39) | O39: 57.89 | P39: 24.87 | Q39: 24.88 | R39: 25.12 | S39: 37.12 | T39: 63.19 | U39: 39.28 | AA39: =SUM(O39:U39) | AB39: =SUM(O39:Z39) | AC39: 0 | AD39: 0 | AE39: 0 | AF39: 0 | AG39: 0 | AH39: 0 | AI39: =SUM(AC39:AH39) | AJ39: =SUM(AC39:AH39)+AI39 | AK39: =IF(N39<>0,(AB39-N39)/ABS(N39),0) | AL39: =IF(AB39<>0,(AJ39-AB39)/ABS(AB39),0)
A40: Telephone | B40: 0 | C40: 0 | D40: 0 | E40: 0 | F40: 0 | G40: 0 | H40: 0 | I40: 0 | J40: 0 | K40: 0 | L40: 0 | M40: 0 | N40: =SUM(B40:M40) | O40: 0 | P40: 0 | Q40: 72 | R40: 24 | S40: 0 | T40: 0 | U40: 0 | AA40: =SUM(O40:U40) | AB40: =SUM(O40:Z40) | AC40: 0 | AD40: 0 | AE40: 0 | AF40: 0 | AG40: 0 | AH40: 0 | AI40: =SUM(AC40:AH40) | AJ40: =SUM(AC40:AH40)+AI40 | AK40: =IF(N40<>0,(AB40-N40)/ABS(N40),0) | AL40: =IF(AB40<>0,(AJ40-AB40)/ABS(AB40),0)
A41: Marketing | B41: 7.99 | C41: 0 | D41: 143.21 | E41: 0 | F41: 0 | G41: 265 | H41: 0 | I41: 45 | J41: 0 | K41: 0 | L41: 0 | M41: 0 | N41: =SUM(B41:M41) | O41: 48 | P41: 0 | Q41: 0 | R41: 48 | S41: 0 | T41: 220 | U41: 0 | AA41: =SUM(O41:U41) | AB41: =SUM(O41:Z41) | AC41: 100 | AD41: 100 | AE41: 100 | AF41: 100 | AG41: 100 | AH41: 100 | AI41: =SUM(AC41:AH41) | AJ41: =SUM(AC41:AH41)+AI41 | AK41: =IF(N41<>0,(AB41-N41)/ABS(N41),0) | AL41: =IF(AB41<>0,(AJ41-AB41)/ABS(AB41),0)
A42: Total Premises & Admin | B42: =B33+B34+B35+B36+B37+B38+B39+B40+B41 | C42: =C33+C34+C35+C36+C37+C38+C39+C40+C41 | D42: =D33+D34+D35+D36+D37+D38+D39+D40+D41 | E42: =E33+E34+E35+E36+E37+E38+E39+E40+E41 | F42: =F33+F34+F35+F36+F37+F38+F39+F40+F41 | G42: =G33+G34+G35+G36+G37+G38+G39+G40+G41 | H42: =H33+H34+H35+H36+H37+H38+H39+H40+H41 | I42: =I33+I34+I35+I36+I37+I38+I39+I40+I41 | ... AJ42: =AJ33+AJ34+AJ35+AJ36+AJ37+AJ38+AJ39+AJ40+AJ41 | AK42: =IF(N42<>0,(AB42-N42)/ABS(N42),0) | AL42: =IF(AB42<>0,(AJ42-AB42)/ABS(AB42),0)
A44: Total Direct Costs | AK44: =IF(N44<>0,(AB44-N44)/ABS(N44),0) | AL44: =IF(AB44<>0,(AJ44-AB44)/ABS(AB44),0)
A46: CONTRIBUTION | B46: =B7-B44 | C46: =C7-C44 | D46: =D7-D44 | E46: =E7-E44 | F46: =F7-F44 | G46: =G7-G44 | H46: =H7-H44 | I46: =I7-I44 | ... AJ46: =AJ7-AJ44 | AK46: =IF(N46<>0,(AB46-N46)/ABS(N46),0) | AL46: =IF(AB46<>0,(AJ46-AB46)/ABS(AB46),0)

Sheet LE
A1: Lower Earley | B1: Actuals 2025 | O1: 2026 Actual / Forecast | AC1: 2027 Forecast | AK1: YoY | AL1: YoY
B2: Jan | C2: Feb | D2: Mar | E2: Apr | F2: May | G2: Jun | H2: Jul | I2: Aug | J2: Sep | K2: Oct | L2: Nov | M2: Dec | N2: FY2025 Total | O2: Jan | P2: Feb | Q2: Mar | R2: Apr | S2: May | T2: Jun | U2: Jul | V2: Aug | W2: Sep | X2: Oct | Y2: Nov | Z2: Dec | AA2: YTD | AB2: FY2026 Outlook | AC2: Jan | AD2: Feb | AE2: Mar | AF2: Apr | AG2: May | AH2: Jun | AI2: Jul-Dec Proj. | AJ2: FY2027 | AK2: 25→26 % | AL2: 26→27 %
A3: INCOME
A4: Fee Income Regular | B4: 30963.16 | C4: 27021.59 | D4: 29812.55 | E4: 31949.87 | F4: 31063.91 | G4: 30350.6 | H4: 34021.43 | I4: 29196.77 | J4: 21455.14 | K4: 24315.15 | L4: 18923.36 | M4: 19499.29 | N4: =SUM(B4:M4) | O4: 20503.25 | P4: 20213.24 | Q4: 18535.67 | R4: 21408.1 | S4: 20206.17 | T4: 20812.27 | U4: 21997.47 | AA4: =SUM(O4:U4) | AB4: =SUM(O4:Z4) | AC4: 27908.68 | AD4: 30111.53 | AE4: 36903.62 | AF4: 34701.33 | AG4: 32867.54 | AH4: 36606.08 | AI4: =SUM(AC4:AH4) | AJ4: =SUM(AC4:AH4)+AI4 | AK4: =IF(N4<>0,(AB4-N4)/ABS(N4),0) | AL4: =IF(AB4<>0,(AJ4-AB4)/ABS(AB4),0)
A5: EEEF Embedded | B5: 11065.6 | C5: 11065.6 | D5: 14478.45 | E5: 8307.69 | F5: 8307.69 | G5: 8307.69 | H5: 22440.35 | I5: 0 | J5: 7068.51 | K5: 7068.51 | L5: 17784.49 | M5: 17975.48 | N5: =SUM(B5:M5) | O5: 13761.14 | P5: 13761.14 | Q5: 24206.13 | R5: 14877.62 | S5: 14877.62 | T5: 13485.23 | U5: 14413.49 | AA5: =SUM(O5:U5) | AB5: =SUM(O5:Z5) | AC5: 0 | AD5: 0 | AE5: 0 | AF5: 0 | AG5: 0 | AH5: 0 | AI5: =SUM(AC5:AH5) | AJ5: =SUM(AC5:AH5)+AI5 | AK5: =IF(N5<>0,(AB5-N5)/ABS(N5),0) | AL5: =IF(AB5<>0,(AJ5-AB5)/ABS(AB5),0)
A6: Other Income | B6: 0 | C6: 0 | D6: 0 | E6: 0 | F6: 0 | G6: 0 | H6: 0 | I6: 2075.37 | J6: 0 | K6: 0 | L6: 0 | M6: 0 | N6: =SUM(B6:M6) | O6: 0 | P6: 0 | Q6: 0 | R6: 0 | S6: 0 | T6: 0 | U6: 0 | V6: 0 | W6: 0 | X6: 0 | Y6: 0 | Z6: 0 | AA6: =SUM(O6:U6) | AB6: =SUM(O6:Z6) | AC6: 0 | AD6: 0 | AE6: 0 | AF6: 0 | AG6: 0 | AH6: 0 | AI6: =SUM(AC6:AH6) | AJ6: =SUM(AC6:AH6)+AI6 | AK6: =IF(N6<>0,(AB6-N6)/ABS(N6),0) | AL6: =IF(AB6<>0,(AJ6-AB6)/ABS(AB6),0)
A7: Total Income | B7: =B4+B5+B6 | C7: =C4+C5+C6 | D7: =D4+D5+D6 | E7: =E4+E5+E6 | F7: =F4+F5+F6 | G7: =G4+G5+G6 | H7: =H4+H5+H6 | I7: =I4+I5+I6 | ... AJ7: =AJ4+AJ5+AJ6 | AK7: =IF(N7<>0,(AB7-N7)/ABS(N7),0) | AL7: =IF(AB7<>0,(AJ7-AB7)/ABS(AB7),0)
A9: DIRECT COSTS
A10: Personnel
A11: Nursery Salaries | B11: 20563.42 | C11: 20213.37 | D11: 21470.65 | E11: 24892.98 | F11: 23314.35 | G11: 22997.77 | H11: 23503.46 | I11: 18431.22 | J11: 18936.09 | K11: 19115.71 | L11: 19409.15 | M11: 19644.59 | N11: =SUM(B11:M11) | O11: 22397.82 | P11: 20915.8 | Q11: 21228.23 | R11: 24553.16 | S11: 23927.03 | T11: 24496.41 | U11: 24453.12 | AA11: =SUM(O11:U11) | AB11: =SUM(O11:Z11) | AC11: 24326 | AD11: 24326 | AE11: 24326 | AF11: 24326 | AG11: 24326 | AH11: 24326 | AI11: =SUM(AC11:AH11) | AJ11: =SUM(AC11:AH11)+AI11 | AK11: =IF(N11<>0,(AB11-N11)/ABS(N11),0) | AL11: =IF(AB11<>0,(AJ11-AB11)/ABS(AB11),0)
A12: Nursery NI | B12: 1779.03 | C12: 1715.81 | D12: 1827.23 | E12: 2853.52 | F12: 2716.71 | G12: 2671.16 | H12: 2750.72 | I12: 2020.55 | J12: 2022.69 | K12: 2177.05 | L12: 2121.95 | M12: 2160.08 | N12: =SUM(B12:M12) | O12: 2569.78 | P12: 2333.89 | Q12: 2397.63 | R12: 2810.47 | S12: 2678.16 | T12: 2699.89 | U12: 2746.09 | AA12: =SUM(O12:U12) | AB12: =SUM(O12:Z12) | AC12: 2730 | AD12: 2730 | AE12: 2730 | AF12: 2730 | AG12: 2730 | AH12: 2730 | AI12: =SUM(AC12:AH12) | AJ12: =SUM(AC12:AH12)+AI12 | AK12: =IF(N12<>0,(AB12-N12)/ABS(N12),0) | AL12: =IF(AB12<>0,(AJ12-AB12)/ABS(AB12),0)
A13: Nursery Pension | B13: 442.12 | C13: 430.09 | D13: 405.36 | E13: 485.36 | F13: 515.48 | G13: 506.37 | H13: 516.35 | I13: 385.54 | J13: 331.38 | K13: 338.82 | L13: 396.08 | M13: 395.76 | N13: =SUM(B13:M13) | O13: 478.5 | P13: 445.11 | Q13: 456.21 | R13: 473.88 | S13: 461.27 | T13: 447.41 | U13: 462.52 | AA13: =SUM(O13:U13) | AB13: =SUM(O13:Z13) | AC13: 478.5 | AD13: 478.5 | AE13: 478.5 | AF13: 478.5 | AG13: 478.5 | AH13: 478.5 | AI13: =SUM(AC13:AH13) | AJ13: =SUM(AC13:AH13)+AI13 | AK13: =IF(N13<>0,(AB13-N13)/ABS(N13),0) | AL13: =IF(AB13<>0,(AJ13-AB13)/ABS(AB13),0)
A14: Uniform | B14: 0 | C14: 219.84 | D14: 166.92 | E14: 106.38 | F14: 92.34 | G14: 0 | H14: 0 | I14: 91.14 | J14: 13.98 | K14: 534 | L14: 0 | M14: 35.82 | N14: =SUM(B14:M14) | O14: 0 | P14: 0 | Q14: 0 | R14: 0 | S14: 0 | T14: 0 | U14: 113.94 | AA14: =SUM(O14:U14) | AB14: =SUM(O14:Z14) | AC14: 39 | AD14: 39 | AE14: 39 | AF14: 39 | AG14: 39 | AH14: 39 | AI14: =SUM(AC14:AH14) | AJ14: =SUM(AC14:AH14)+AI14 | AK14: =IF(N14<>0,(AB14-N14)/ABS(N14),0) | AL14: =IF(AB14<>0,(AJ14-AB14)/ABS(AB14),0)
A15: Training | B15: 48 | C15: 0 | D15: 0 | E15: 0 | F15: 61.2 | G15: 0 | H15: 37.2 | I15: 307.19 | J15: 0 | K15: 0 | L15: 114 | M15: 0 | N15: =SUM(B15:M15) | O15: 0 | P15: -422 | Q15: 0 | R15: 0 | S15: 78 | T15: 252 | U15: 0 | AA15: =SUM(O15:U15) | AB15: =SUM(O15:Z15) | AC15: 50 | AD15: 50 | AE15: 50 | AF15: 50 | AG15: 50 | AH15: 50 | AI15: =SUM(AC15:AH15) | AJ15: =SUM(AC15:AH15)+AI15 | AK15: =IF(N15<>0,(AB15-N15)/ABS(N15),0) | AL15: =IF(AB15<>0,(AJ15-AB15)/ABS(AB15),0)
A16: Staff Welfare | B16: 130.26 | C16: 218.62 | D16: 222.99 | E16: 233.98 | F16: 99.15 | G16: 189.15 | H16: 126.5 | I16: 176.63 | J16: 64.9 | K16: 212.8 | L16: 68.61 | M16: 23.31 | N16: =SUM(B16:M16) | O16: 93.25 | P16: 12.5 | Q16: 167.27 | R16: 161.9 | S16: 163.43 | T16: 23.54 | U16: 191.12 | AA16: =SUM(O16:U16) | AB16: =SUM(O16:Z16) | AC16: 80 | AD16: 80 | AE16: 80 | AF16: 80 | AG16: 80 | AH16: 80 | AI16: =SUM(AC16:AH16) | AJ16: =SUM(AC16:AH16)+AI16 | AK16: =IF(N16<>0,(AB16-N16)/ABS(N16),0) | AL16: =IF(AB16<>0,(AJ16-AB16)/ABS(AB16),0)
A17: Recruitment | B17: 0 | C17: 0 | D17: 0 | E17: 0 | F17: 0 | G17: 0 | H17: 0 | I17: 0 | J17: 0 | K17: 0 | L17: 0 | M17: 0 | N17: =SUM(B17:M17) | O17: 0 | P17: 0 | Q17: 0 | R17: 0 | S17: 0 | T17: 0 | U17: 0 | V17: 0 | W17: 0 | X17: 0 | Y17: 0 | Z17: 0 | AA17: =SUM(O17:U17) | AB17: =SUM(O17:Z17) | AC17: 0 | AD17: 0 | AE17: 0 | AF17: 0 | AG17: 0 | AH17: 0 | AI17: =SUM(AC17:AH17) | AJ17: =SUM(AC17:AH17)+AI17 | AK17: =IF(N17<>0,(AB17-N17)/ABS(N17),0) | AL17: =IF(AB17<>0,(AJ17-AB17)/ABS(AB17),0)
A18: Rewards & Recognition | B18: 0 | C18: 0 | D18: 0 | E18: 0 | F18: 0 | G18: 0 | H18: 33 | I18: 0 | J18: 31.5 | K18: 0 | L18: 0 | M18: 0 | N18: =SUM(B18:M18) | O18: 16.5 | P18: 50.23 | Q18: 15.28 | R18: 0 | S18: 16.5 | T18: 0 | U18: 31.9 | AA18: =SUM(O18:U18) | AB18: =SUM(O18:Z18) | AC18: 33 | AD18: 33 | AE18: 33 | AF18: 33 | AG18: 33 | AH18: 33 | AI18: =SUM(AC18:AH18) | AJ18: =SUM(AC18:AH18)+AI18 | AK18: =IF(N18<>0,(AB18-N18)/ABS(N18),0) | AL18: =IF(AB18<>0,(AJ18-AB18)/ABS(AB18),0)
A19: Temps | B19: 0 | C19: 0 | D19: 0 | E19: 0 | F19: 0 | G19: 0 | H19: 0 | I19: 0 | J19: 0 | K19: 0 | L19: 0 | M19: 0 | N19: =SUM(B19:M19) | O19: 0 | P19: 0 | Q19: 0 | R19: 0 | S19: 0 | T19: 0 | U19: 0 | V19: 0 | W19: 0 | X19: 0 | Y19: 0 | Z19: 0 | AA19: =SUM(O19:U19) | AB19: =SUM(O19:Z19) | AC19: 0 | AD19: 0 | AE19: 0 | AF19: 0 | AG19: 0 | AH19: 0 | AI19: =SUM(AC19:AH19) | AJ19: =SUM(AC19:AH19)+AI19 | AK19: =IF(N19<>0,(AB19-N19)/ABS(N19),0) | AL19: =IF(AB19<>0,(AJ19-AB19)/ABS(AB19),0)
A20: Total Personnel | B20: =B11+B12+B13+B14+B15+B16+B17+B18+B19 | C20: =C11+C12+C13+C14+C15+C16+C17+C18+C19 | D20: =D11+D12+D13+D14+D15+D16+D17+D18+D19 | E20: =E11+E12+E13+E14+E15+E16+E17+E18+E19 | F20: =F11+F12+F13+F14+F15+F16+F17+F18+F19 | G20: =G11+G12+G13+G14+G15+G16+G17+G18+G19 | H20: =H11+H12+H13+H14+H15+H16+H17+H18+H19 | I20: =I11+I12+I13+I14+I15+I16+I17+I18+I19 | ... AJ20: =AJ11+AJ12+AJ13+AJ14+AJ15+AJ16+AJ17+AJ18+AJ19 | AK20: =IF(N20<>0,(AB20-N20)/ABS(N20),0) | AL20: =IF(AB20<>0,(AJ20-AB20)/ABS(AB20),0)
A21: Sal:Rev | B21: =IF(B7>0,B20/B7,0) | C21: =IF(C7>0,C20/C7,0) | D21: =IF(D7>0,D20/D7,0) | E21: =IF(E7>0,E20/E7,0) | F21: =IF(F7>0,F20/F7,0) | G21: =IF(G7>0,G20/G7,0) | H21: =IF(H7>0,H20/H7,0) | I21: =IF(I7>0,I20/I7,0) | ... AJ21: =IF(AJ7>0,AJ20/AJ7,0)
A23: Childcare
A24: Catering Costs | N24: =SUM(B24:M24) | O24: 1428.67 | P24: 1894.54 | Q24: 1660.07 | R24: 2099.27 | S24: 1513.13 | T24: 1672.02 | U24: 1682.53 | V24: 1396.4496 | W24: 1431.9552 | X24: 1649.544 | Y24: 1689.1056 | Z24: 1688.6688 | AA24: =SUM(O24:U24) | AB24: =SUM(O24:Z24) | AC24: 1741.5016 | AD24: 1878.9595 | AE24: 2302.7859 | AF24: 2165.363 | AG24: 2050.9345 | AH24: 2284.2194 | AI24: =SUM(AC24:AH24) | AJ24: =SUM(AC24:AH24)+AI24 | AK24: =IF(N24<>0,(AB24-N24)/ABS(N24),0) | AL24: =IF(AB24<>0,(AJ24-AB24)/ABS(AB24),0)
A25: Toys and Games | B25: 29.48 | C25: 98.81 | D25: 209.15 | E25: 106.54 | F25: 197.64 | G25: 67.42 | H25: 179.26 | I25: 51.75 | J25: 224.25 | K25: 49.58 | L25: 71.05 | M25: 37.21 | N25: =SUM(B25:M25) | O25: 73.15 | P25: 25.18 | Q25: 58.1 | R25: 7.19 | S25: 59.06 | T25: 5.49 | U25: 31.95 | AA25: =SUM(O25:U25) | AB25: =SUM(O25:Z25) | AC25: 58 | AD25: 58 | AE25: 58 | AF25: 58 | AG25: 58 | AH25: 58 | AI25: =SUM(AC25:AH25) | AJ25: =SUM(AC25:AH25)+AI25 | AK25: =IF(N25<>0,(AB25-N25)/ABS(N25),0) | AL25: =IF(AB25<>0,(AJ25-AB25)/ABS(AB25),0)
A26: Art Materials | N26: =SUM(B26:M26) | O26: 0 | P26: 95.16 | Q26: 324.34 | R26: 9.12 | S26: 36.43 | T26: 115.48 | U26: 18.98 | V26: 46.54832 | W26: 47.73184 | X26: 54.9848 | Y26: 56.30352 | Z26: 56.28896 | AA26: =SUM(O26:U26) | AB26: =SUM(O26:Z26) | AC26: 58.050054 | AD26: 62.631982 | AE26: 76.75953 | AF26: 72.178766 | AG26: 68.364483 | AH26: 76.140646 | AI26: =SUM(AC26:AH26) | AJ26: =SUM(AC26:AH26)+AI26 | AK26: =IF(N26<>0,(AB26-N26)/ABS(N26),0) | AL26: =IF(AB26<>0,(AJ26-AB26)/ABS(AB26),0)
A27: Nursery Stationery | B27: 0 | C27: 0 | D27: 0 | E27: 0 | F27: 0 | G27: 0 | H27: 0 | I27: 0 | J27: 0 | K27: 0 | L27: 0 | M27: 0 | N27: =SUM(B27:M27) | O27: 0 | P27: 0 | Q27: 0 | R27: 0 | S27: 0 | T27: 0 | U27: 0 | V27: 0 | W27: 0 | X27: 0 | Y27: 0 | Z27: 0 | AA27: =SUM(O27:U27) | AB27: =SUM(O27:Z27) | AC27: 100 | AD27: 100 | AE27: 100 | AF27: 100 | AG27: 100 | AH27: 100 | AI27: =SUM(AC27:AH27) | AJ27: =SUM(AC27:AH27)+AI27 | AK27: =IF(N27<>0,(AB27-N27)/ABS(N27),0) | AL27: =IF(AB27<>0,(AJ27-AB27)/ABS(AB27),0)
A28: Nursery Equipment | B28: 0 | C28: 3.99 | D28: 201.16 | E28: 91.98 | F28: 114.68 | G28: 25 | H28: 28.7 | I28: 396.21 | J28: 169.37 | K28: 48.97 | L28: 35.92 | M28: 151.68 | N28: =SUM(B28:M28) | O28: 13.98 | P28: 79.02 | Q28: 33.43 | R28: 46 | S28: 25.88 | T28: 47.97 | U28: 0 | AA28: =SUM(O28:U28) | AB28: =SUM(O28:Z28) | AC28: 50 | AD28: 50 | AE28: 50 | AF28: 50 | AG28: 50 | AH28: 50 | AI28: =SUM(AC28:AH28) | AJ28: =SUM(AC28:AH28)+AI28 | AK28: =IF(N28<>0,(AB28-N28)/ABS(N28),0) | AL28: =IF(AB28<>0,(AJ28-AB28)/ABS(AB28),0)
A29: Nursery Consumables | N29: =SUM(B29:M29) | O29: 120.47 | P29: 153.08 | Q29: 198.65 | R29: 181.3 | S29: 115.66 | T29: 241.42 | U29: 125.04 | V29: 93.09664 | W29: 95.46368 | X29: 109.9696 | Y29: 112.60704 | Z29: 112.57792 | AA29: =SUM(O29:U29) | AB29: =SUM(O29:Z29) | AC29: 116.10011 | AD29: 125.26396 | AE29: 153.51906 | AF29: 144.35753 | AG29: 136.72897 | AH29: 152.28129 | AI29: =SUM(AC29:AH29) | AJ29: =SUM(AC29:AH29)+AI29 | AK29: =IF(N29<>0,(AB29-N29)/ABS(N29),0) | AL29: =IF(AB29<>0,(AJ29-AB29)/ABS(AB29),0)
A30: Total Childcare Costs | B30: =B24+B25+B26+B27+B28+B29 | C30: =C24+C25+C26+C27+C28+C29 | D30: =D24+D25+D26+D27+D28+D29 | E30: =E24+E25+E26+E27+E28+E29 | F30: =F24+F25+F26+F27+F28+F29 | G30: =G24+G25+G26+G27+G28+G29 | H30: =H24+H25+H26+H27+H28+H29 | I30: =I24+I25+I26+I27+I28+I29 | ... AJ30: =AJ24+AJ25+AJ26+AJ27+AJ28+AJ29 | AK30: =IF(N30<>0,(AB30-N30)/ABS(N30),0) | AL30: =IF(AB30<>0,(AJ30-AB30)/ABS(AB30),0)
A32: Premises & Admin
A33: Rent | B33: 541.67 | C33: 541.67 | D33: 541.67 | E33: 541.67 | F33: 541.67 | G33: 541.67 | H33: 541.67 | I33: 541.67 | J33: 541.66 | K33: 541.67 | L33: 541.67 | M33: 541.66 | N33: =SUM(B33:M33) | O33: 0 | P33: 0 | Q33: -0.01 | R33: 0 | S33: 0 | T33: 0 | U33: 0 | AA33: =SUM(O33:U33) | AB33: =SUM(O33:Z33) | AC33: 0 | AD33: 0 | AE33: 0 | AF33: 0 | AG33: 0 | AH33: 0 | AI33: =SUM(AC33:AH33) | AJ33: =SUM(AC33:AH33)+AI33 | AK33: =IF(N33<>0,(AB33-N33)/ABS(N33),0) | AL33: =IF(AB33<>0,(AJ33-AB33)/ABS(AB33),0)
A34: Business Rates | B34: 426.23 | C34: 426.23 | D34: 426.23 | E34: 426.23 | F34: 426.23 | G34: 426.23 | H34: 426.23 | I34: 426.23 | J34: 426.23 | K34: 426.23 | L34: 426.23 | M34: 426.23 | N34: =SUM(B34:M34) | O34: 426.23 | P34: 426.23 | Q34: 426.22 | R34: 447.54 | S34: 447.54 | T34: 447.54 | U34: 447.54 | AA34: =SUM(O34:U34) | AB34: =SUM(O34:Z34) | AC34: 0 | AD34: 0 | AE34: 0 | AF34: 0 | AG34: 0 | AH34: 0 | AI34: =SUM(AC34:AH34) | AJ34: =SUM(AC34:AH34)+AI34 | AK34: =IF(N34<>0,(AB34-N34)/ABS(N34),0) | AL34: =IF(AB34<>0,(AJ34-AB34)/ABS(AB34),0)
A35: Utilities | B35: 1144.51 | C35: 1876.52 | D35: 3731.16 | E35: 2446.87 | F35: -507.16 | G35: 852.76 | H35: 771.11 | I35: 2306.56 | J35: 853.06 | K35: 2101.48 | L35: 2463.12 | M35: 3402.53 | N35: =SUM(B35:M35) | O35: 2109.25 | P35: 2316.27 | Q35: 1417.04 | R35: 1804.14 | S35: 1026.04 | T35: 1890.08 | U35: 1648.84 | AA35: =SUM(O35:U35) | AB35: =SUM(O35:Z35) | AC35: 0 | AD35: 0 | AE35: 0 | AF35: 0 | AG35: 0 | AH35: 0 | AI35: =SUM(AC35:AH35) | AJ35: =SUM(AC35:AH35)+AI35 | AK35: =IF(N35<>0,(AB35-N35)/ABS(N35),0) | AL35: =IF(AB35<>0,(AJ35-AB35)/ABS(AB35),0)
A36: Repairs & Maintenance | B36: 0 | C36: 14.36 | D36: 327.5 | E36: 305.35 | F36: 370.59 | G36: 26.58 | H36: 0 | I36: 32.82 | J36: 0 | K36: 0 | L36: 27.8 | M36: 268.7 | N36: =SUM(B36:M36) | O36: 0 | P36: 90.6 | Q36: 0 | R36: 279 | S36: 0 | T36: 0 | U36: 369.46 | AA36: =SUM(O36:U36) | AB36: =SUM(O36:Z36) | AC36: 0 | AD36: 0 | AE36: 0 | AF36: 0 | AG36: 0 | AH36: 0 | AI36: =SUM(AC36:AH36) | AJ36: =SUM(AC36:AH36)+AI36 | AK36: =IF(N36<>0,(AB36-N36)/ABS(N36),0) | AL36: =IF(AB36<>0,(AJ36-AB36)/ABS(AB36),0)
A37: Cleaning | B37: 341.18 | C37: 0 | D37: 495.47 | E37: 147.98 | F37: 216.21 | G37: 0 | H37: 42.92 | I37: 219.35 | J37: 417.65 | K37: 206.69 | L37: 0 | M37: 146.16 | N37: =SUM(B37:M37) | O37: 0 | P37: 670.87 | Q37: 178.99 | R37: 6.98 | S37: 0 | T37: 239.77 | U37: 277.39 | AA37: =SUM(O37:U37) | AB37: =SUM(O37:Z37) | AC37: 200 | AD37: 200 | AE37: 200 | AF37: 200 | AG37: 200 | AH37: 200 | AI37: =SUM(AC37:AH37) | AJ37: =SUM(AC37:AH37)+AI37 | AK37: =IF(N37<>0,(AB37-N37)/ABS(N37),0) | AL37: =IF(AB37<>0,(AJ37-AB37)/ABS(AB37),0)
A38: Waste Disposal | B38: 346.68 | C38: 537.66 | D38: 397.68 | E38: 356.33 | F38: 380.74 | G38: 446.01 | H38: 380.74 | I38: 551.72 | J38: 434.15 | K38: 431.14 | L38: 389.72 | M38: 443.13 | N38: =SUM(B38:M38) | O38: 389.73 | P38: 389.73 | Q38: 478.53 | R38: 548.17 | S38: 467.13 | T38: 281.67 | U38: 571.89 | AA38: =SUM(O38:U38) | AB38: =SUM(O38:Z38) | AC38: 426 | AD38: 426 | AE38: 426 | AF38: 426 | AG38: 426 | AH38: 426 | AI38: =SUM(AC38:AH38) | AJ38: =SUM(AC38:AH38)+AI38 | AK38: =IF(N38<>0,(AB38-N38)/ABS(N38),0) | AL38: =IF(AB38<>0,(AJ38-AB38)/ABS(AB38),0)
A39: Postage/Printing/Stationery | B39: 27.13 | C39: 39.52 | D39: 37.15 | E39: 84.5 | F39: 28.99 | G39: 32.1 | H39: 23.58 | I39: 0 | J39: 166.43 | K39: 695.5 | L39: 0 | M39: -413.13 | N39: =SUM(B39:M39) | O39: 0 | P39: 20.39 | Q39: 0 | R39: 0 | S39: 0 | T39: 132.04 | U39: 78.32 | AA39: =SUM(O39:U39) | AB39: =SUM(O39:Z39) | AC39: 0 | AD39: 0 | AE39: 0 | AF39: 0 | AG39: 0 | AH39: 0 | AI39: =SUM(AC39:AH39) | AJ39: =SUM(AC39:AH39)+AI39 | AK39: =IF(N39<>0,(AB39-N39)/ABS(N39),0) | AL39: =IF(AB39<>0,(AJ39-AB39)/ABS(AB39),0)
A40: Telephone | B40: 0 | C40: 0 | D40: 0 | E40: 0 | F40: 0 | G40: 0 | H40: 0 | I40: 0 | J40: 20 | K40: 0 | L40: 0 | M40: 0 | N40: =SUM(B40:M40) | O40: 32 | P40: 73.3 | Q40: 0 | R40: 20 | S40: 0 | T40: 4.95 | U40: 28 | AA40: =SUM(O40:U40) | AB40: =SUM(O40:Z40) | AC40: 0 | AD40: 0 | AE40: 0 | AF40: 0 | AG40: 0 | AH40: 0 | AI40: =SUM(AC40:AH40) | AJ40: =SUM(AC40:AH40)+AI40 | AK40: =IF(N40<>0,(AB40-N40)/ABS(N40),0) | AL40: =IF(AB40<>0,(AJ40-AB40)/ABS(AB40),0)
A41: Marketing | B41: 0 | C41: 0 | D41: 0 | E41: 0 | F41: 0 | G41: 0 | H41: 0 | I41: 0 | J41: 0 | K41: 0 | L41: 0 | M41: 0 | N41: =SUM(B41:M41) | O41: 0 | P41: 0 | Q41: 0 | R41: 0 | S41: 0 | T41: 0 | U41: 0 | V41: 0 | W41: 0 | X41: 0 | Y41: 0 | Z41: 0 | AA41: =SUM(O41:U41) | AB41: =SUM(O41:Z41) | AC41: 100 | AD41: 100 | AE41: 100 | AF41: 100 | AG41: 100 | AH41: 100 | AI41: =SUM(AC41:AH41) | AJ41: =SUM(AC41:AH41)+AI41 | AK41: =IF(N41<>0,(AB41-N41)/ABS(N41),0) | AL41: =IF(AB41<>0,(AJ41-AB41)/ABS(AB41),0)
A42: Total Premises & Admin | B42: =B33+B34+B35+B36+B37+B38+B39+B40+B41 | C42: =C33+C34+C35+C36+C37+C38+C39+C40+C41 | D42: =D33+D34+D35+D36+D37+D38+D39+D40+D41 | E42: =E33+E34+E35+E36+E37+E38+E39+E40+E41 | F42: =F33+F34+F35+F36+F37+F38+F39+F40+F41 | G42: =G33+G34+G35+G36+G37+G38+G39+G40+G41 | H42: =H33+H34+H35+H36+H37+H38+H39+H40+H41 | I42: =I33+I34+I35+I36+I37+I38+I39+I40+I41 | ... AJ42: =AJ33+AJ34+AJ35+AJ36+AJ37+AJ38+AJ39+AJ40+AJ41 | AK42: =IF(N42<>0,(AB42-N42)/ABS(N42),0) | AL42: =IF(AB42<>0,(AJ42-AB42)/ABS(AB42),0)
A44: Total Direct Costs | AK44: =IF(N44<>0,(AB44-N44)/ABS(N44),0) | AL44: =IF(AB44<>0,(AJ44-AB44)/ABS(AB44),0)
A46: CONTRIBUTION | B46: =B7-B44 | C46: =C7-C44 | D46: =D7-D44 | E46: =E7-E44 | F46: =F7-F44 | G46: =G7-G44 | H46: =H7-H44 | I46: =I7-I44 | ... AJ46: =AJ7-AJ44 | AK46: =IF(N46<>0,(AB46-N46)/ABS(N46),0) | AL46: =IF(AB46<>0,(AJ46-AB46)/ABS(AB46),0)

Sheet MER
A1: Merrydale | B1: Actuals 2025 | O1: 2026 Actual / Forecast | AC1: 2027 Forecast | AK1: YoY | AL1: YoY
B2: Jan | C2: Feb | D2: Mar | E2: Apr | F2: May | G2: Jun | H2: Jul | I2: Aug | J2: Sep | K2: Oct | L2: Nov | M2: Dec | N2: FY2025 Total | O2: Jan | P2: Feb | Q2: Mar | R2: Apr | S2: May | T2: Jun | U2: Jul | V2: Aug | W2: Sep | X2: Oct | Y2: Nov | Z2: Dec | AA2: YTD | AB2: FY2026 Outlook | AC2: Jan | AD2: Feb | AE2: Mar | AF2: Apr | AG2: May | AH2: Jun | AI2: Jul-Dec Proj. | AJ2: FY2027 | AK2: 25→26 % | AL2: 26→27 %
A3: INCOME
A4: Fee Income Regular | B4: 71748.46 | C4: 62355.58 | D4: 73377.48 | E4: 84905.42 | F4: 78933.88 | G4: 76038.8 | H4: 94722.26 | I4: 81393.89 | J4: 67283.54 | K4: 63773.81 | L4: 55368.1 | M4: 74284.69 | N4: =SUM(B4:M4) | O4: 58533.16 | P4: 52500.16 | Q4: 60298.97 | R4: 61812.6 | S4: 52015.74 | T4: 55797.24 | U4: 74838.93 | AA4: =SUM(O4:U4) | AB4: =SUM(O4:Z4) | AC4: 79907.43 | AD4: 74377.98 | AE4: 90136.04 | AF4: 81715.39 | AG4: 85494.06 | AH4: 91076.72 | AI4: =SUM(AC4:AH4) | AJ4: =SUM(AC4:AH4)+AI4 | AK4: =IF(N4<>0,(AB4-N4)/ABS(N4),0) | AL4: =IF(AB4<>0,(AJ4-AB4)/ABS(AB4),0)
A5: EEEF Embedded | B5: 27056.38 | C5: 27056.38 | D5: 27641.21 | E5: 20062.71 | F5: 20062.71 | G5: 20062.71 | H5: 53755.95 | I5: 0 | J5: 24868.19 | K5: 24868.19 | L5: 53954.23 | M5: 54512.01 | N5: =SUM(B5:M5) | O5: 38841.31 | P5: 38841.31 | Q5: 40377.93 | R5: 32949.32 | S5: 32949.32 | T5: 33336.41 | U5: 33078.35 | AA5: =SUM(O5:U5) | AB5: =SUM(O5:Z5) | AC5: 0 | AD5: 0 | AE5: 0 | AF5: 0 | AG5: 0 | AH5: 0 | AI5: =SUM(AC5:AH5) | AJ5: =SUM(AC5:AH5)+AI5 | AK5: =IF(N5<>0,(AB5-N5)/ABS(N5),0) | AL5: =IF(AB5<>0,(AJ5-AB5)/ABS(AB5),0)
A6: Other Income | B6: 250 | C6: 150 | D6: 400 | E6: 559.14 | F6: 300 | G6: 300 | H6: 150 | I6: 5287.55 | J6: 150 | K6: 150 | L6: 0 | M6: 300 | N6: =SUM(B6:M6) | O6: 150 | P6: 0 | Q6: 300 | R6: 150 | S6: 0 | T6: 300 | U6: 150 | AA6: =SUM(O6:U6) | AB6: =SUM(O6:Z6) | AC6: 0 | AD6: 0 | AE6: 0 | AF6: 0 | AG6: 0 | AH6: 0 | AI6: =SUM(AC6:AH6) | AJ6: =SUM(AC6:AH6)+AI6 | AK6: =IF(N6<>0,(AB6-N6)/ABS(N6),0) | AL6: =IF(AB6<>0,(AJ6-AB6)/ABS(AB6),0)
A7: Total Income | B7: =B4+B5+B6 | C7: =C4+C5+C6 | D7: =D4+D5+D6 | E7: =E4+E5+E6 | F7: =F4+F5+F6 | G7: =G4+G5+G6 | H7: =H4+H5+H6 | I7: =I4+I5+I6 | ... AJ7: =AJ4+AJ5+AJ6 | AK7: =IF(N7<>0,(AB7-N7)/ABS(N7),0) | AL7: =IF(AB7<>0,(AJ7-AB7)/ABS(AB7),0)
A9: DIRECT COSTS
A10: Personnel
A11: Nursery Salaries | B11: 31604.86 | C11: 32120.62 | D11: 33783.29 | E11: 39088.61 | F11: 35853.61 | G11: 32713.57 | H11: 38084.64 | I11: 39688.59 | J11: 39229.98 | K11: 38640.36 | L11: 31254.13 | M11: 33683.63 | N11: =SUM(B11:M11) | O11: 31828.8 | P11: 33935.64 | Q11: 36037.77 | R11: 34623.48 | S11: 37995.21 | T11: 37118.77 | U11: 38831.14 | AA11: =SUM(O11:U11) | AB11: =SUM(O11:Z11) | AC11: 38831.14 | AD11: 38831.14 | AE11: 38831.14 | AF11: 38831.14 | AG11: 38831.14 | AH11: 38831.14 | AI11: =SUM(AC11:AH11) | AJ11: =SUM(AC11:AH11)+AI11 | AK11: =IF(N11<>0,(AB11-N11)/ABS(N11),0) | AL11: =IF(AB11<>0,(AJ11-AB11)/ABS(AB11),0)
A12: Nursery NI | B12: 2507.7 | C12: 2502.98 | D12: 2767.29 | E12: 4489.64 | F12: 3897.7 | G12: 3435.72 | H12: 3882.52 | I12: 3661.25 | J12: 3574.09 | K12: 3581.38 | L12: 2779.53 | M12: 3180.07 | N12: =SUM(B12:M12) | O12: 2814.7 | P12: 2809.23 | Q12: 3029.45 | R12: 2929.49 | S12: 3346.09 | T12: 3339.3 | U12: 3476.28 | AA12: =SUM(O12:U12) | AB12: =SUM(O12:Z12) | AC12: 3476.28 | AD12: 3476.28 | AE12: 3476.28 | AF12: 3476.28 | AG12: 3476.28 | AH12: 3476.28 | AI12: =SUM(AC12:AH12) | AJ12: =SUM(AC12:AH12)+AI12 | AK12: =IF(N12<>0,(AB12-N12)/ABS(N12),0) | AL12: =IF(AB12<>0,(AJ12-AB12)/ABS(AB12),0)
A13: Nursery Pension | B13: 578.26 | C13: 576.6 | D13: 553.41 | E13: 642.37 | F13: 614.2 | G13: 527.56 | H13: 611.47 | I13: 558.66 | J13: 482.76 | K13: 259.94 | L13: 246.15 | M13: 444.9 | N13: =SUM(B13:M13) | O13: 382.29 | P13: 365.94 | Q13: 332.41 | R13: 422.05 | S13: 453.76 | T13: 473.26 | U13: 523.85 | AA13: =SUM(O13:U13) | AB13: =SUM(O13:Z13) | AC13: 523.85 | AD13: 523.85 | AE13: 523.85 | AF13: 523.85 | AG13: 523.85 | AH13: 523.85 | AI13: =SUM(AC13:AH13) | AJ13: =SUM(AC13:AH13)+AI13 | AK13: =IF(N13<>0,(AB13-N13)/ABS(N13),0) | AL13: =IF(AB13<>0,(AJ13-AB13)/ABS(AB13),0)
A14: Uniform | B14: 108.42 | C14: 232.56 | D14: 0 | E14: 98.82 | F14: 126.27 | G14: 106.73 | H14: 101.82 | I14: 0 | J14: 119.88 | K14: 408.72 | L14: 115.32 | M14: 114.6 | N14: =SUM(B14:M14) | O14: 0 | P14: 148.85 | Q14: 239.4 | R14: 133.86 | S14: 0 | T14: 133.8 | U14: 34.7 | AA14: =SUM(O14:U14) | AB14: =SUM(O14:Z14) | AC14: 88 | AD14: 88 | AE14: 88 | AF14: 88 | AG14: 88 | AH14: 88 | AI14: =SUM(AC14:AH14) | AJ14: =SUM(AC14:AH14)+AI14 | AK14: =IF(N14<>0,(AB14-N14)/ABS(N14),0) | AL14: =IF(AB14<>0,(AJ14-AB14)/ABS(AB14),0)
A15: Training | B15: 68.22 | C15: 50 | D15: 0 | E15: 0 | F15: 31.2 | G15: 11.35 | H15: 37.2 | I15: 0 | J15: 114 | K15: 0 | L15: 114 | M15: -11.29 | N15: =SUM(B15:M15) | O15: 150 | P15: 0 | Q15: 0 | R15: 750 | S15: 0 | T15: 60 | U15: 361.26 | AA15: =SUM(O15:U15) | AB15: =SUM(O15:Z15) | AC15: 50 | AD15: 50 | AE15: 50 | AF15: 50 | AG15: 50 | AH15: 50 | AI15: =SUM(AC15:AH15) | AJ15: =SUM(AC15:AH15)+AI15 | AK15: =IF(N15<>0,(AB15-N15)/ABS(N15),0) | AL15: =IF(AB15<>0,(AJ15-AB15)/ABS(AB15),0)
A16: Staff Welfare | B16: 304.95 | C16: 264.71 | D16: 188.52 | E16: 236.83 | F16: 480.61 | G16: 227.41 | H16: 311.65 | I16: 17.06 | J16: 76.79 | K16: 131.31 | L16: 263.85 | M16: 64.3 | N16: =SUM(B16:M16) | O16: 364.02 | P16: 154.27 | Q16: 156.87 | R16: 236.43 | S16: 152.97 | T16: 284.9 | U16: 149.53 | AA16: =SUM(O16:U16) | AB16: =SUM(O16:Z16) | AC16: 180 | AD16: 180 | AE16: 180 | AF16: 180 | AG16: 180 | AH16: 180 | AI16: =SUM(AC16:AH16) | AJ16: =SUM(AC16:AH16)+AI16 | AK16: =IF(N16<>0,(AB16-N16)/ABS(N16),0) | AL16: =IF(AB16<>0,(AJ16-AB16)/ABS(AB16),0)
A17: Recruitment | B17: 0 | C17: 0 | D17: 0 | E17: 0 | F17: 3352.38 | G17: 0 | H17: 0 | I17: 0 | J17: 0 | K17: 0 | L17: 0 | M17: 0 | N17: =SUM(B17:M17) | O17: 0 | P17: 3528.1 | Q17: 0 | R17: 0 | S17: 0 | T17: 0 | U17: 0 | AA17: =SUM(O17:U17) | AB17: =SUM(O17:Z17) | AC17: 0 | AD17: 0 | AE17: 0 | AF17: 0 | AG17: 0 | AH17: 0 | AI17: =SUM(AC17:AH17) | AJ17: =SUM(AC17:AH17)+AI17 | AK17: =IF(N17<>0,(AB17-N17)/ABS(N17),0) | AL17: =IF(AB17<>0,(AJ17-AB17)/ABS(AB17),0)
A18: Rewards & Recognition | B18: 0 | C18: 0 | D18: 0 | E18: 0 | F18: 0 | G18: 0 | H18: 8.11 | I18: 0 | J18: 23.49 | K18: 6.28 | L18: 0 | M18: 95.38 | N18: =SUM(B18:M18) | O18: 45.76 | P18: 81.02 | Q18: 37.24 | R18: 94.41 | S18: 80.88 | T18: 56.6 | U18: 122.2 | AA18: =SUM(O18:U18) | AB18: =SUM(O18:Z18) | AC18: 75 | AD18: 75 | AE18: 75 | AF18: 75 | AG18: 75 | AH18: 75 | AI18: =SUM(AC18:AH18) | AJ18: =SUM(AC18:AH18)+AI18 | AK18: =IF(N18<>0,(AB18-N18)/ABS(N18),0) | AL18: =IF(AB18<>0,(AJ18-AB18)/ABS(AB18),0)
A19: Temps | B19: 0 | C19: 0 | D19: 0 | E19: 0 | F19: 226.03 | G19: 0 | H19: 249.41 | I19: 0 | J19: 0 | K19: 4590.68 | L19: 3008.5 | M19: 0 | N19: =SUM(B19:M19) | O19: 1286.01 | P19: 0 | Q19: 0 | R19: 0 | S19: 0 | T19: 0 | U19: 0 | AA19: =SUM(O19:U19) | AB19: =SUM(O19:Z19) | AC19: 0 | AD19: 0 | AE19: 0 | AF19: 0 | AG19: 0 | AH19: 0 | AI19: =SUM(AC19:AH19) | AJ19: =SUM(AC19:AH19)+AI19 | AK19: =IF(N19<>0,(AB19-N19)/ABS(N19),0) | AL19: =IF(AB19<>0,(AJ19-AB19)/ABS(AB19),0)
A20: Total Personnel | B20: =B11+B12+B13+B14+B15+B16+B17+B18+B19 | C20: =C11+C12+C13+C14+C15+C16+C17+C18+C19 | D20: =D11+D12+D13+D14+D15+D16+D17+D18+D19 | E20: =E11+E12+E13+E14+E15+E16+E17+E18+E19 | F20: =F11+F12+F13+F14+F15+F16+F17+F18+F19 | G20: =G11+G12+G13+G14+G15+G16+G17+G18+G19 | H20: =H11+H12+H13+H14+H15+H16+H17+H18+H19 | I20: =I11+I12+I13+I14+I15+I16+I17+I18+I19 | ... AJ20: =AJ11+AJ12+AJ13+AJ14+AJ15+AJ16+AJ17+AJ18+AJ19 | AK20: =IF(N20<>0,(AB20-N20)/ABS(N20),0) | AL20: =IF(AB20<>0,(AJ20-AB20)/ABS(AB20),0)
A21: Sal:Rev | B21: =IF(B7>0,B20/B7,0) | C21: =IF(C7>0,C20/C7,0) | D21: =IF(D7>0,D20/D7,0) | E21: =IF(E7>0,E20/E7,0) | F21: =IF(F7>0,F20/F7,0) | G21: =IF(G7>0,G20/G7,0) | H21: =IF(H7>0,H20/H7,0) | I21: =IF(I7>0,I20/I7,0) | ... AJ21: =IF(AJ7>0,AJ20/AJ7,0)
A23: Childcare
A24: Catering Costs | N24: =SUM(B24:M24) | O24: 1461.98 | P24: 1803.02 | Q24: 1441.43 | R24: 1269.6 | S24: 1831.11 | T24: 2098.22 | U24: 2298.43 | V24: 2129.4 | W24: 2291.7024 | X24: 2456.7816 | Y24: 2477.3112 | Z24: 2420.9016 | AA24: =SUM(O24:U24) | AB24: =SUM(O24:Z24) | AC24: 2493.1118 | AD24: 2320.593 | AE24: 2812.2444 | AF24: 2549.5202 | AG24: 2667.4147 | AH24: 2841.5937 | AI24: =SUM(AC24:AH24) | AJ24: =SUM(AC24:AH24)+AI24 | AK24: =IF(N24<>0,(AB24-N24)/ABS(N24),0) | AL24: =IF(AB24<>0,(AJ24-AB24)/ABS(AB24),0)
A25: Toys and Games | B25: 150.47 | C25: 158.38 | D25: 149.6 | E25: 525.93 | F25: 276.46 | G25: 459.81 | H25: 618.96 | I25: 0 | J25: 157.63 | K25: 157.78 | L25: 433.98 | M25: 160.93 | N25: =SUM(B25:M25) | O25: 322.01 | P25: 20.41 | Q25: 909.8 | R25: 451.03 | S25: 117.11 | T25: 27.56 | U25: 155.11 | AA25: =SUM(O25:U25) | AB25: =SUM(O25:Z25) | AC25: 50 | AD25: 50 | AE25: 50 | AF25: 50 | AG25: 50 | AH25: 50 | AI25: =SUM(AC25:AH25) | AJ25: =SUM(AC25:AH25)+AI25 | AK25: =IF(N25<>0,(AB25-N25)/ABS(N25),0) | AL25: =IF(AB25<>0,(AJ25-AB25)/ABS(AB25),0)
A26: Art Materials | N26: =SUM(B26:M26) | O26: 13.68 | P26: 256.29 | Q26: 62.83 | R26: 37.49 | S26: 11.09 | T26: 150.56 | U26: 175.69 | V26: 283.92 | W26: 305.56032 | X26: 327.57088 | Y26: 330.30816 | Z26: 322.78688 | AA26: =SUM(O26:U26) | AB26: =SUM(O26:Z26) | AC26: 332.41491 | AD26: 309.4124 | AE26: 374.96593 | AF26: 339.93602 | AG26: 355.65529 | AH26: 378.87916 | AI26: =SUM(AC26:AH26) | AJ26: =SUM(AC26:AH26)+AI26 | AK26: =IF(N26<>0,(AB26-N26)/ABS(N26),0) | AL26: =IF(AB26<>0,(AJ26-AB26)/ABS(AB26),0)
A27: Nursery Stationery | B27: 28.68 | C27: 99.43 | D27: 62.8 | E27: 18.53 | F27: 58.69 | G27: 7.64 | H27: 76.06 | I27: 48.85 | J27: 0 | K27: 112.19 | L27: 108.87 | M27: 0 | N27: =SUM(B27:M27) | O27: 58.06 | P27: 58.6 | Q27: 46.33 | R27: 12.97 | S27: 120.18 | T27: 22.92 | U27: 43.05 | AA27: =SUM(O27:U27) | AB27: =SUM(O27:Z27) | AC27: 90 | AD27: 90 | AE27: 90 | AF27: 90 | AG27: 90 | AH27: 90 | AI27: =SUM(AC27:AH27) | AJ27: =SUM(AC27:AH27)+AI27 | AK27: =IF(N27<>0,(AB27-N27)/ABS(N27),0) | AL27: =IF(AB27<>0,(AJ27-AB27)/ABS(AB27),0)
A28: Nursery Equipment | B28: 160.7 | C28: 123.84 | D28: 222.23 | E28: 28.49 | F28: 71.57 | G28: 71.32 | H28: 80.71 | I28: 3.95 | J28: 12.98 | K28: 267.22 | L28: 151.94 | M28: 10.99 | N28: =SUM(B28:M28) | O28: 84.18 | P28: 56.22 | Q28: 65.83 | R28: 102.29 | S28: 259.6 | T28: 44.01 | U28: 53.56 | AA28: =SUM(O28:U28) | AB28: =SUM(O28:Z28) | AC28: 50 | AD28: 50 | AE28: 50 | AF28: 50 | AG28: 50 | AH28: 50 | AI28: =SUM(AC28:AH28) | AJ28: =SUM(AC28:AH28)+AI28 | AK28: =IF(N28<>0,(AB28-N28)/ABS(N28),0) | AL28: =IF(AB28<>0,(AJ28-AB28)/ABS(AB28),0)
A29: Nursery Consumables | N29: =SUM(B29:M29) | O29: 511.53 | P29: 341.6 | Q29: 320.13 | R29: 615.91 | S29: 581.79 | T29: 474.05 | U29: 146.24 | V29: 354.9 | W29: 381.9504 | X29: 409.4636 | Y29: 412.8852 | Z29: 403.4836 | AA29: =SUM(O29:U29) | AB29: =SUM(O29:Z29) | AC29: 415.51864 | AD29: 386.7655 | AE29: 468.70741 | AF29: 424.92003 | AG29: 444.56911 | AH29: 473.59894 | AI29: =SUM(AC29:AH29) | AJ29: =SUM(AC29:AH29)+AI29 | AK29: =IF(N29<>0,(AB29-N29)/ABS(N29),0) | AL29: =IF(AB29<>0,(AJ29-AB29)/ABS(AB29),0)
A30: Total Childcare Costs | B30: =B24+B25+B26+B27+B28+B29 | C30: =C24+C25+C26+C27+C28+C29 | D30: =D24+D25+D26+D27+D28+D29 | E30: =E24+E25+E26+E27+E28+E29 | F30: =F24+F25+F26+F27+F28+F29 | G30: =G24+G25+G26+G27+G28+G29 | H30: =H24+H25+H26+H27+H28+H29 | I30: =I24+I25+I26+I27+I28+I29 | ... AJ30: =AJ24+AJ25+AJ26+AJ27+AJ28+AJ29 | AK30: =IF(N30<>0,(AB30-N30)/ABS(N30),0) | AL30: =IF(AB30<>0,(AJ30-AB30)/ABS(AB30),0)
A32: Premises & Admin
A33: Rent | B33: 0 | C33: 0 | D33: 0 | E33: 0 | F33: 0 | G33: 0 | H33: 0 | I33: 0 | J33: 0 | K33: 0 | L33: 0 | M33: 0 | N33: =SUM(B33:M33) | O33: 0 | P33: 0 | Q33: 0 | R33: 0 | S33: 0 | T33: 0 | U33: 0 | V33: 0 | W33: 0 | X33: 0 | Y33: 0 | Z33: 0 | AA33: =SUM(O33:U33) | AB33: =SUM(O33:Z33) | AC33: 0 | AD33: 0 | AE33: 0 | AF33: 0 | AG33: 0 | AH33: 0 | AI33: =SUM(AC33:AH33) | AJ33: =SUM(AC33:AH33)+AI33 | AK33: =IF(N33<>0,(AB33-N33)/ABS(N33),0) | AL33: =IF(AB33<>0,(AJ33-AB33)/ABS(AB33),0)
A34: Business Rates | B34: 3094 | C34: 3094 | D34: 3094 | E34: 3145 | F34: 3145 | G34: 3145 | H34: 3145 | I34: 3145 | J34: 3145 | K34: 3145 | L34: 3145 | M34: 3145 | N34: =SUM(B34:M34) | O34: 3145 | P34: 3145 | Q34: 3145 | R34: 3021.67 | S34: 3021.67 | T34: 3021.67 | U34: 3021.67 | AA34: =SUM(O34:U34) | AB34: =SUM(O34:Z34) | AC34: 3022 | AD34: 3022 | AE34: 3022 | AF34: 3022 | AG34: 3022 | AH34: 3022 | AI34: =SUM(AC34:AH34) | AJ34: =SUM(AC34:AH34)+AI34 | AK34: =IF(N34<>0,(AB34-N34)/ABS(N34),0) | AL34: =IF(AB34<>0,(AJ34-AB34)/ABS(AB34),0)
A35: Utilities | B35: 1090.6 | C35: 72 | D35: 2060.91 | E35: 1227.22 | F35: 800.88 | G35: 1086.41 | H35: 648.46 | I35: 655.6 | J35: 1518.48 | K35: 795.67 | L35: 740.6 | M35: 1205.02 | N35: =SUM(B35:M35) | O35: 985.79 | P35: 1036.83 | Q35: 1302.1 | R35: 1010.56 | S35: 808.67 | T35: 470.01 | U35: 732.4 | AA35: =SUM(O35:U35) | AB35: =SUM(O35:Z35) | AC35: 996 | AD35: 996 | AE35: 996 | AF35: 996 | AG35: 996 | AH35: 996 | AI35: =SUM(AC35:AH35) | AJ35: =SUM(AC35:AH35)+AI35 | AK35: =IF(N35<>0,(AB35-N35)/ABS(N35),0) | AL35: =IF(AB35<>0,(AJ35-AB35)/ABS(AB35),0)
A36: Repairs & Maintenance | B36: 222 | C36: 0 | D36: 2295.47 | E36: 59.2 | F36: 102.84 | G36: 156.31 | H36: 269.93 | I36: 7.38 | J36: 10.62 | K36: 114.23 | L36: 36 | M36: 108 | N36: =SUM(B36:M36) | O36: 0 | P36: 3635.32 | Q36: 1337.4 | R36: 110.18 | S36: 120.98 | T36: 0 | U36: 917.12 | AA36: =SUM(O36:U36) | AB36: =SUM(O36:Z36) | AC36: 0 | AD36: 0 | AE36: 0 | AF36: 0 | AG36: 0 | AH36: 0 | AI36: =SUM(AC36:AH36) | AJ36: =SUM(AC36:AH36)+AI36 | AK36: =IF(N36<>0,(AB36-N36)/ABS(N36),0) | AL36: =IF(AB36<>0,(AJ36-AB36)/ABS(AB36),0)
A37: Cleaning | B37: 910.9 | C37: 436.73 | D37: 608.49 | E37: 631.55 | F37: 660.93 | G37: 1356.2 | H37: 461 | I37: 439.54 | J37: 1191.48 | K37: 462.57 | L37: 228.42 | M37: 464.64 | N37: =SUM(B37:M37) | O37: 354.19 | P37: 49.12 | Q37: 456.79 | R37: 280.03 | S37: 401.15 | T37: 459.4 | U37: 5.63 | AA37: =SUM(O37:U37) | AB37: =SUM(O37:Z37) | AC37: 333 | AD37: 333 | AE37: 333 | AF37: 333 | AG37: 333 | AH37: 333 | AI37: =SUM(AC37:AH37) | AJ37: =SUM(AC37:AH37)+AI37 | AK37: =IF(N37<>0,(AB37-N37)/ABS(N37),0) | AL37: =IF(AB37<>0,(AJ37-AB37)/ABS(AB37),0)
A38: Waste Disposal | B38: 377.59 | C38: 583.16 | D38: 730.23 | E38: 334.81 | F38: 283.57 | G38: 414.48 | H38: 361.07 | I38: 449.9 | J38: 780.81 | K38: 411.19 | L38: 428.31 | M38: 481.72 | N38: =SUM(B38:M38) | O38: 428.3 | P38: 529.11 | Q38: 481.72 | R38: 536.35 | S38: 455.32 | T38: 346.66 | U38: 620.08 | AA38: =SUM(O38:U38) | AB38: =SUM(O38:Z38) | AC38: 474 | AD38: 474 | AE38: 474 | AF38: 474 | AG38: 474 | AH38: 474 | AI38: =SUM(AC38:AH38) | AJ38: =SUM(AC38:AH38)+AI38 | AK38: =IF(N38<>0,(AB38-N38)/ABS(N38),0) | AL38: =IF(AB38<>0,(AJ38-AB38)/ABS(AB38),0)
A39: Postage/Printing/Stationery | B39: 71.1 | C39: 84.2 | D39: 53.57 | E39: 40.14 | F39: 67.65 | G39: 49.08 | H39: 71.49 | I39: 270.78 | J39: 102.83 | K39: 91.92 | L39: 54.05 | M39: 43.75 | N39: =SUM(B39:M39) | O39: 86.89 | P39: 86.22 | Q39: 84.04 | R39: 78.89 | S39: 111.28 | T39: 81.9 | U39: 104.47 | AA39: =SUM(O39:U39) | AB39: =SUM(O39:Z39) | AC39: 0 | AD39: 0 | AE39: 0 | AF39: 0 | AG39: 0 | AH39: 0 | AI39: =SUM(AC39:AH39) | AJ39: =SUM(AC39:AH39)+AI39 | AK39: =IF(N39<>0,(AB39-N39)/ABS(N39),0) | AL39: =IF(AB39<>0,(AJ39-AB39)/ABS(AB39),0)
A40: Telephone | B40: 0 | C40: 0 | D40: 0 | E40: 0 | F40: 0 | G40: 0 | H40: 0 | I40: 0 | J40: 0 | K40: 0 | L40: 0 | M40: 0 | N40: =SUM(B40:M40) | O40: 382 | P40: 485 | Q40: 290 | R40: 252 | S40: 174 | T40: 0 | U40: 0 | AA40: =SUM(O40:U40) | AB40: =SUM(O40:Z40) | AC40: 0 | AD40: 0 | AE40: 0 | AF40: 0 | AG40: 0 | AH40: 0 | AI40: =SUM(AC40:AH40) | AJ40: =SUM(AC40:AH40)+AI40 | AK40: =IF(N40<>0,(AB40-N40)/ABS(N40),0) | AL40: =IF(AB40<>0,(AJ40-AB40)/ABS(AB40),0)
A41: Marketing | B41: 0 | C41: 0 | D41: 270.44 | E41: 0 | F41: 0 | G41: 265 | H41: 0 | I41: 45 | J41: 41.25 | K41: 0 | L41: 0 | M41: 0 | N41: =SUM(B41:M41) | O41: 174 | P41: 0 | Q41: 0 | R41: 171 | S41: 0 | T41: 220 | U41: 13.5 | AA41: =SUM(O41:U41) | AB41: =SUM(O41:Z41) | AC41: 100 | AD41: 100 | AE41: 100 | AF41: 100 | AG41: 100 | AH41: 100 | AI41: =SUM(AC41:AH41) | AJ41: =SUM(AC41:AH41)+AI41 | AK41: =IF(N41<>0,(AB41-N41)/ABS(N41),0) | AL41: =IF(AB41<>0,(AJ41-AB41)/ABS(AB41),0)
A42: Total Premises & Admin | B42: =B33+B34+B35+B36+B37+B38+B39+B40+B41 | C42: =C33+C34+C35+C36+C37+C38+C39+C40+C41 | D42: =D33+D34+D35+D36+D37+D38+D39+D40+D41 | E42: =E33+E34+E35+E36+E37+E38+E39+E40+E41 | F42: =F33+F34+F35+F36+F37+F38+F39+F40+F41 | G42: =G33+G34+G35+G36+G37+G38+G39+G40+G41 | H42: =H33+H34+H35+H36+H37+H38+H39+H40+H41 | I42: =I33+I34+I35+I36+I37+I38+I39+I40+I41 | ... AJ42: =AJ33+AJ34+AJ35+AJ36+AJ37+AJ38+AJ39+AJ40+AJ41 | AK42: =IF(N42<>0,(AB42-N42)/ABS(N42),0) | AL42: =IF(AB42<>0,(AJ42-AB42)/ABS(AB42),0)
A44: Total Direct Costs | AK44: =IF(N44<>0,(AB44-N44)/ABS(N44),0) | AL44: =IF(AB44<>0,(AJ44-AB44)/ABS(AB44),0)
A46: CONTRIBUTION | B46: =B7-B44 | C46: =C7-C44 | D46: =D7-D44 | E46: =E7-E44 | F46: =F7-F44 | G46: =G7-G44 | H46: =H7-H44 | I46: =I7-I44 | ... AJ46: =AJ7-AJ44 | AK46: =IF(N46<>0,(AB46-N46)/ABS(N46),0) | AL46: =IF(AB46<>0,(AJ46-AB46)/ABS(AB46),0)

Sheet NDN
A1: Northumberland | B1: Actuals 2025 | O1: 2026 Actual / Forecast | AC1: 2027 Forecast | AK1: YoY | AL1: YoY
B2: Jan | C2: Feb | D2: Mar | E2: Apr | F2: May | G2: Jun | H2: Jul | I2: Aug | J2: Sep | K2: Oct | L2: Nov | M2: Dec | N2: FY2025 Total | O2: Jan | P2: Feb | Q2: Mar | R2: Apr | S2: May | T2: Jun | U2: Jul | V2: Aug | W2: Sep | X2: Oct | Y2: Nov | Z2: Dec | AA2: YTD | AB2: FY2026 Outlook | AC2: Jan | AD2: Feb | AE2: Mar | AF2: Apr | AG2: May | AH2: Jun | AI2: Jul-Dec Proj. | AJ2: FY2027 | AK2: 25→26 % | AL2: 26→27 %
A3: INCOME
A4: Fee Income Regular | B4: 9069.94 | C4: 18430.57 | D4: 17723.33 | E4: 21760.34 | F4: 17055.59 | G4: 16125.92 | H4: 23858.59 | I4: 22339.21 | J4: 12468.85 | K4: 12041.45 | L4: 10680.4 | M4: 13644.19 | N4: =SUM(B4:M4) | O4: 8949.66 | P4: 9181.28 | Q4: 11609.4 | R4: 13485.1 | S4: 10334.4 | T4: 12530 | U4: 18402.22 | AA4: =SUM(O4:U4) | AB4: =SUM(O4:Z4) | AC4: 34239.39 | AD4: 30110.59 | AE4: 36653.68 | AF4: 33019.73 | AG4: 38452 | AH4: 38834.29 | AI4: =SUM(AC4:AH4) | AJ4: =SUM(AC4:AH4)+AI4 | AK4: =IF(N4<>0,(AB4-N4)/ABS(N4),0) | AL4: =IF(AB4<>0,(AJ4-AB4)/ABS(AB4),0)
A5: EEEF Embedded | B5: 8345.08 | C5: 5508.8 | D5: 18679.4 | E5: 7516.08 | F5: 7516.08 | G5: 15698.85 | H5: 15698.85 | I5: 0 | J5: 10762.08 | K5: 10762.08 | L5: 12208.56 | M5: 12628.56 | N5: =SUM(B5:M5) | O5: 10719.8 | P5: 13055.3 | Q5: 13055.3 | R5: 8798.4 | S5: 8798.4 | T5: 12706.2 | U5: 10101 | AA5: =SUM(O5:U5) | AB5: =SUM(O5:Z5) | AC5: 0 | AD5: 0 | AE5: 0 | AF5: 0 | AG5: 0 | AH5: 0 | AI5: =SUM(AC5:AH5) | AJ5: =SUM(AC5:AH5)+AI5 | AK5: =IF(N5<>0,(AB5-N5)/ABS(N5),0) | AL5: =IF(AB5<>0,(AJ5-AB5)/ABS(AB5),0)
A6: Other Income | B6: 0 | C6: 0 | D6: 0 | E6: 0 | F6: 0 | G6: 0 | H6: 0 | I6: 1570.68 | J6: 0 | K6: 0 | L6: 0 | M6: 0 | N6: =SUM(B6:M6) | O6: 0 | P6: 0 | Q6: 0 | R6: 0 | S6: 0 | T6: 0 | U6: 0 | V6: 0 | W6: 0 | X6: 0 | Y6: 0 | Z6: 0 | AA6: =SUM(O6:U6) | AB6: =SUM(O6:Z6) | AC6: 0 | AD6: 0 | AE6: 0 | AF6: 0 | AG6: 0 | AH6: 0 | AI6: =SUM(AC6:AH6) | AJ6: =SUM(AC6:AH6)+AI6 | AK6: =IF(N6<>0,(AB6-N6)/ABS(N6),0) | AL6: =IF(AB6<>0,(AJ6-AB6)/ABS(AB6),0)
A7: Total Income | B7: =B4+B5+B6 | C7: =C4+C5+C6 | D7: =D4+D5+D6 | E7: =E4+E5+E6 | F7: =F4+F5+F6 | G7: =G4+G5+G6 | H7: =H4+H5+H6 | I7: =I4+I5+I6 | ... AJ7: =AJ4+AJ5+AJ6 | AK7: =IF(N7<>0,(AB7-N7)/ABS(N7),0) | AL7: =IF(AB7<>0,(AJ7-AB7)/ABS(AB7),0)
A9: DIRECT COSTS
A10: Personnel
A11: Nursery Salaries | B11: 15019.61 | C11: 16737.5 | D11: 20296.41 | E11: 19844.91 | F11: 20514.57 | G11: 18806.18 | H11: 18874.99 | I11: 15404.24 | J11: 13827.73 | K11: 12859 | L11: 12573.97 | M11: 13485.76 | N11: =SUM(B11:M11) | O11: 14774.04 | P11: 13940.85 | Q11: 17482.69 | R11: 18467.07 | S11: 19414.37 | T11: 20554.86 | U11: 20507.25 | AA11: =SUM(O11:U11) | AB11: =SUM(O11:Z11) | AC11: 20507.25 | AD11: 20507.25 | AE11: 20507.25 | AF11: 20507.25 | AG11: 20507.25 | AH11: 20507.25 | AI11: =SUM(AC11:AH11) | AJ11: =SUM(AC11:AH11)+AI11 | AK11: =IF(N11<>0,(AB11-N11)/ABS(N11),0) | AL11: =IF(AB11<>0,(AJ11-AB11)/ABS(AB11),0)
A12: Nursery NI | B12: 1126.07 | C12: 1360.14 | D12: 1404.5 | E12: 1975.71 | F12: 2049.66 | G12: 1811.17 | H12: 1985.01 | I12: 1552.22 | J12: 1459.53 | K12: 1396.13 | L12: 1362.29 | M12: 1508.86 | N12: =SUM(B12:M12) | O12: 1686 | P12: 1501.44 | Q12: 1885.63 | R12: 1894.36 | S12: 1931.05 | T12: 1993.72 | U12: 2095.05 | AA12: =SUM(O12:U12) | AB12: =SUM(O12:Z12) | AC12: 2095.05 | AD12: 2095.05 | AE12: 2095.05 | AF12: 2095.05 | AG12: 2095.05 | AH12: 2095.05 | AI12: =SUM(AC12:AH12) | AJ12: =SUM(AC12:AH12)+AI12 | AK12: =IF(N12<>0,(AB12-N12)/ABS(N12),0) | AL12: =IF(AB12<>0,(AJ12-AB12)/ABS(AB12),0)
A13: Nursery Pension | B13: 301.87 | C13: 352.12 | D13: 362.42 | E13: 373.48 | F13: 388.28 | G13: 340.58 | H13: 375.35 | I13: 275.05 | J13: 234.69 | K13: 230.34 | L13: 251.05 | M13: 230.68 | N13: =SUM(B13:M13) | O13: 318.63 | P13: 261.27 | Q13: 299.64 | R13: 303.21 | S13: 364.56 | T13: 361.3 | U13: 345.35 | AA13: =SUM(O13:U13) | AB13: =SUM(O13:Z13) | AC13: 345.35 | AD13: 345.35 | AE13: 345.35 | AF13: 345.35 | AG13: 345.35 | AH13: 345.35 | AI13: =SUM(AC13:AH13) | AJ13: =SUM(AC13:AH13)+AI13 | AK13: =IF(N13<>0,(AB13-N13)/ABS(N13),0) | AL13: =IF(AB13<>0,(AJ13-AB13)/ABS(AB13),0)
A14: Uniform | B14: 0 | C14: 244.02 | D14: 69.48 | E14: 0 | F14: 0 | G14: 0 | H14: 0 | I14: 0 | J14: 128.12 | K14: 0 | L14: 0 | M14: 0 | N14: =SUM(B14:M14) | O14: 49.74 | P14: 0 | Q14: 8.99 | R14: 118.56 | S14: 0 | T14: 0 | U14: 0 | AA14: =SUM(O14:U14) | AB14: =SUM(O14:Z14) | AC14: 34 | AD14: 34 | AE14: 34 | AF14: 34 | AG14: 34 | AH14: 34 | AI14: =SUM(AC14:AH14) | AJ14: =SUM(AC14:AH14)+AI14 | AK14: =IF(N14<>0,(AB14-N14)/ABS(N14),0) | AL14: =IF(AB14<>0,(AJ14-AB14)/ABS(AB14),0)
A15: Training | B15: 81 | C15: 0 | D15: 0 | E15: 0 | F15: 40 | G15: 0 | H15: 0 | I15: 120.3 | J15: 0 | K15: 0 | L15: 0 | M15: 0 | N15: =SUM(B15:M15) | O15: 29.97 | P15: 0 | Q15: 59 | R15: 780 | S15: 546 | T15: 0 | U15: 125.82 | AA15: =SUM(O15:U15) | AB15: =SUM(O15:Z15) | AC15: 100 | AD15: 100 | AE15: 100 | AF15: 100 | AG15: 100 | AH15: 100 | AI15: =SUM(AC15:AH15) | AJ15: =SUM(AC15:AH15)+AI15 | AK15: =IF(N15<>0,(AB15-N15)/ABS(N15),0) | AL15: =IF(AB15<>0,(AJ15-AB15)/ABS(AB15),0)
A16: Staff Welfare | B16: 277.83 | C16: 334.72 | D16: 322.62 | E16: 420.75 | F16: 276.6 | G16: 178.34 | H16: 238.53 | I16: 222.62 | J16: 549.52 | K16: 451.66 | L16: 61.96 | M16: 221.31 | N16: =SUM(B16:M16) | O16: 155.65 | P16: 87.29 | Q16: 19.06 | R16: 176.18 | S16: 116.69 | T16: 172.18 | U16: 283.13 | AA16: =SUM(O16:U16) | AB16: =SUM(O16:Z16) | AC16: 70 | AD16: 70 | AE16: 70 | AF16: 70 | AG16: 70 | AH16: 70 | AI16: =SUM(AC16:AH16) | AJ16: =SUM(AC16:AH16)+AI16 | AK16: =IF(N16<>0,(AB16-N16)/ABS(N16),0) | AL16: =IF(AB16<>0,(AJ16-AB16)/ABS(AB16),0)
A17: Recruitment | B17: 0 | C17: 0 | D17: 0 | E17: 0 | F17: 0 | G17: 0 | H17: 0 | I17: 0 | J17: 0 | K17: 0 | L17: 0 | M17: 0 | N17: =SUM(B17:M17) | O17: 0 | P17: 0 | Q17: 0 | R17: 0 | S17: 0 | T17: 0 | U17: 0 | V17: 0 | W17: 0 | X17: 0 | Y17: 0 | Z17: 0 | AA17: =SUM(O17:U17) | AB17: =SUM(O17:Z17) | AC17: 0 | AD17: 0 | AE17: 0 | AF17: 0 | AG17: 0 | AH17: 0 | AI17: =SUM(AC17:AH17) | AJ17: =SUM(AC17:AH17)+AI17 | AK17: =IF(N17<>0,(AB17-N17)/ABS(N17),0) | AL17: =IF(AB17<>0,(AJ17-AB17)/ABS(AB17),0)
A18: Rewards & Recognition | B18: 0 | C18: 0 | D18: 0 | E18: 0 | F18: 0 | G18: 0 | H18: 94.32 | I18: 111.25 | J18: 84.99 | K18: 31.36 | L18: 91.53 | M18: 71 | N18: =SUM(B18:M18) | O18: 20 | P18: 0 | Q18: 0 | R18: 0 | S18: 0 | T18: 0 | U18: 0 | AA18: =SUM(O18:U18) | AB18: =SUM(O18:Z18) | AC18: 29 | AD18: 29 | AE18: 29 | AF18: 29 | AG18: 29 | AH18: 29 | AI18: =SUM(AC18:AH18) | AJ18: =SUM(AC18:AH18)+AI18 | AK18: =IF(N18<>0,(AB18-N18)/ABS(N18),0) | AL18: =IF(AB18<>0,(AJ18-AB18)/ABS(AB18),0)
A19: Temps | B19: 0 | C19: 0 | D19: 0 | E19: 0 | F19: 0 | G19: 0 | H19: 0 | I19: 0 | J19: 0 | K19: 662.49 | L19: 0 | M19: 0 | N19: =SUM(B19:M19) | O19: 0 | P19: 0 | Q19: 0 | R19: 0 | S19: 0 | T19: 0 | U19: 0 | V19: 0 | W19: 0 | X19: 0 | Y19: 0 | Z19: 0 | AA19: =SUM(O19:U19) | AB19: =SUM(O19:Z19) | AC19: 0 | AD19: 0 | AE19: 0 | AF19: 0 | AG19: 0 | AH19: 0 | AI19: =SUM(AC19:AH19) | AJ19: =SUM(AC19:AH19)+AI19 | AK19: =IF(N19<>0,(AB19-N19)/ABS(N19),0) | AL19: =IF(AB19<>0,(AJ19-AB19)/ABS(AB19),0)
A20: Total Personnel | B20: =B11+B12+B13+B14+B15+B16+B17+B18+B19 | C20: =C11+C12+C13+C14+C15+C16+C17+C18+C19 | D20: =D11+D12+D13+D14+D15+D16+D17+D18+D19 | E20: =E11+E12+E13+E14+E15+E16+E17+E18+E19 | F20: =F11+F12+F13+F14+F15+F16+F17+F18+F19 | G20: =G11+G12+G13+G14+G15+G16+G17+G18+G19 | H20: =H11+H12+H13+H14+H15+H16+H17+H18+H19 | I20: =I11+I12+I13+I14+I15+I16+I17+I18+I19 | ... AJ20: =AJ11+AJ12+AJ13+AJ14+AJ15+AJ16+AJ17+AJ18+AJ19 | AK20: =IF(N20<>0,(AB20-N20)/ABS(N20),0) | AL20: =IF(AB20<>0,(AJ20-AB20)/ABS(AB20),0)
A21: Sal:Rev | B21: =IF(B7>0,B20/B7,0) | C21: =IF(C7>0,C20/C7,0) | D21: =IF(D7>0,D20/D7,0) | E21: =IF(E7>0,E20/E7,0) | F21: =IF(F7>0,F20/F7,0) | G21: =IF(G7>0,G20/G7,0) | H21: =IF(H7>0,H20/H7,0) | I21: =IF(I7>0,I20/I7,0) | ... AJ21: =IF(AJ7>0,AJ20/AJ7,0)
A23: Childcare
A24: Catering Costs | N24: =SUM(B24:M24) | O24: 894.32 | P24: 587.8 | Q24: 693.19 | R24: 726.12 | S24: 627.51 | T24: 765.63 | U24: 977.42 | V24: 590.48714 | W24: 986.8872 | X24: 1094.5272 | Y24: 1044.3888 | Z24: 851.6352 | AA24: =SUM(O24:U24) | AB24: =SUM(O24:Z24) | AC24: 1068.269 | AD24: 939.45041 | AE24: 1143.5948 | AF24: 1030.2156 | AG24: 1199.7024 | AH24: 1211.6298 | AI24: =SUM(AC24:AH24) | AJ24: =SUM(AC24:AH24)+AI24 | AK24: =IF(N24<>0,(AB24-N24)/ABS(N24),0) | AL24: =IF(AB24<>0,(AJ24-AB24)/ABS(AB24),0)
A25: Toys and Games | B25: 29.07 | C25: 176.61 | D25: 111.88 | E25: 203.06 | F25: 178.9 | G25: 67.29 | H25: 38 | I25: 105.13 | J25: 220.74 | K25: 4.23 | L25: 126.27 | M25: 48.49 | N25: =SUM(B25:M25) | O25: 12.23 | P25: 0 | Q25: 65.03 | R25: 131.86 | S25: 70.85 | T25: 80.06 | U25: 12 | AA25: =SUM(O25:U25) | AB25: =SUM(O25:Z25) | AC25: 50 | AD25: 50 | AE25: 50 | AF25: 50 | AG25: 50 | AH25: 50 | AI25: =SUM(AC25:AH25) | AJ25: =SUM(AC25:AH25)+AI25 | AK25: =IF(N25<>0,(AB25-N25)/ABS(N25),0) | AL25: =IF(AB25<>0,(AJ25-AB25)/ABS(AB25),0)
A26: Art Materials | N26: =SUM(B26:M26) | O26: 30.16 | P26: 0 | Q26: 232.14 | R26: 15.48 | S26: 30.74 | T26: 63.52 | U26: 12.37 | V26: 39.36581 | W26: 65.79248 | X26: 72.96848 | Y26: 69.62592 | Z26: 56.77568 | AA26: =SUM(O26:U26) | AB26: =SUM(O26:Z26) | AC26: 71.217931 | AD26: 62.630027 | AE26: 76.239654 | AF26: 68.681038 | AG26: 79.98016 | AH26: 80.775323 | AI26: =SUM(AC26:AH26) | AJ26: =SUM(AC26:AH26)+AI26 | AK26: =IF(N26<>0,(AB26-N26)/ABS(N26),0) | AL26: =IF(AB26<>0,(AJ26-AB26)/ABS(AB26),0)
A27: Nursery Stationery | B27: 0 | C27: 0 | D27: 0 | E27: 0 | F27: 0 | G27: 0 | H27: 0 | I27: 0 | J27: 0 | K27: 0 | L27: 0 | M27: 0 | N27: =SUM(B27:M27) | O27: 0 | P27: 0 | Q27: 0 | R27: 0 | S27: 0 | T27: 0 | U27: 76.09 | AA27: =SUM(O27:U27) | AB27: =SUM(O27:Z27) | AC27: 100 | AD27: 100 | AE27: 100 | AF27: 100 | AG27: 100 | AH27: 100 | AI27: =SUM(AC27:AH27) | AJ27: =SUM(AC27:AH27)+AI27 | AK27: =IF(N27<>0,(AB27-N27)/ABS(N27),0) | AL27: =IF(AB27<>0,(AJ27-AB27)/ABS(AB27),0)
A28: Nursery Equipment | B28: 18.98 | C28: 117.79 | D28: 179.68 | E28: 95.6 | F28: 321.81 | G28: 0 | H28: 95.58 | I28: 134.96 | J28: 0 | K28: 81.07 | L28: 40.2 | M28: 117.6 | N28: =SUM(B28:M28) | O28: 0 | P28: 258.16 | Q28: 0 | R28: 44.43 | S28: 39.47 | T28: 167.46 | U28: 0 | AA28: =SUM(O28:U28) | AB28: =SUM(O28:Z28) | AC28: 50 | AD28: 50 | AE28: 50 | AF28: 50 | AG28: 50 | AH28: 50 | AI28: =SUM(AC28:AH28) | AJ28: =SUM(AC28:AH28)+AI28 | AK28: =IF(N28<>0,(AB28-N28)/ABS(N28),0) | AL28: =IF(AB28<>0,(AJ28-AB28)/ABS(AB28),0)
A29: Nursery Consumables | N29: =SUM(B29:M29) | O29: 109.85 | P29: 126.99 | Q29: 68.91 | R29: 188.57 | S29: 185.38 | T29: 81.99 | U29: 56.14 | V29: 78.731619 | W29: 131.58496 | X29: 145.93696 | Y29: 139.25184 | Z29: 113.55136 | AA29: =SUM(O29:U29) | AB29: =SUM(O29:Z29) | AC29: 142.43586 | AD29: 125.26005 | AE29: 152.47931 | AF29: 137.36208 | AG29: 159.96032 | AH29: 161.55065 | AI29: =SUM(AC29:AH29) | AJ29: =SUM(AC29:AH29)+AI29 | AK29: =IF(N29<>0,(AB29-N29)/ABS(N29),0) | AL29: =IF(AB29<>0,(AJ29-AB29)/ABS(AB29),0)
A30: Total Childcare Costs | B30: =B24+B25+B26+B27+B28+B29 | C30: =C24+C25+C26+C27+C28+C29 | D30: =D24+D25+D26+D27+D28+D29 | E30: =E24+E25+E26+E27+E28+E29 | F30: =F24+F25+F26+F27+F28+F29 | G30: =G24+G25+G26+G27+G28+G29 | H30: =H24+H25+H26+H27+H28+H29 | I30: =I24+I25+I26+I27+I28+I29 | ... AJ30: =AJ24+AJ25+AJ26+AJ27+AJ28+AJ29 | AK30: =IF(N30<>0,(AB30-N30)/ABS(N30),0) | AL30: =IF(AB30<>0,(AJ30-AB30)/ABS(AB30),0)
A32: Premises & Admin
A33: Rent | B33: 0 | C33: 0 | D33: 0 | E33: 0 | F33: 0 | G33: 0 | H33: 0 | I33: 0 | J33: 0 | K33: 0 | L33: 0 | M33: 0 | N33: =SUM(B33:M33) | O33: 0 | P33: 0 | Q33: 0 | R33: 0 | S33: 0 | T33: 0 | U33: 1267.25 | AA33: =SUM(O33:U33) | AB33: =SUM(O33:Z33) | AC33: 0 | AD33: 0 | AE33: 0 | AF33: 0 | AG33: 0 | AH33: 0 | AI33: =SUM(AC33:AH33) | AJ33: =SUM(AC33:AH33)+AI33 | AK33: =IF(N33<>0,(AB33-N33)/ABS(N33),0) | AL33: =IF(AB33<>0,(AJ33-AB33)/ABS(AB33),0)
