Workbook

Sheet Budget V Actuals
A1: Budget Analysis
A3: 2026 Budget (Ops FinPlan) | B3: Q1 | T3: Q2 | AL3: Q3 | BD3: Q4
B4: Abacus | C4: Bees Knees | D4: Bramleywood | E4: Cedars | F4: Hazebrouck | G4: Kingsclere | H4: Merrydale | I4: Stepping Stones | J4: Happitots | K4: Northumberland | L4: Smart Tots | M4: Lower Earley | N4: Woosehill | O4: Our Den | P4: Finchampstead | Q4: Boot Farm | R4: Saltway | S4: Quarter Total | T4: Abacus | U4: Bees Knees | V4: Bramleywood | W4: Cedars | X4: Hazebrouck | Y4: Kingsclere | Z4: Merrydale | AA4: Stepping Stones | AB4: Happitots | AC4: Northumberland | AD4: Smart Tots | AE4: Lower Earley | AF4: Woosehill | AG4: Our Den | AH4: Finchampstead | AI4: Boot Farm | AJ4: Saltway | AK4: Quarter Total | AL4: Abacus | AM4: Bees Knees | AN4: Bramleywood | AO4: Cedars | AP4: Hazebrouck | AQ4: Kingsclere | AR4: Merrydale | AS4: Stepping Stones | AT4: Happitots | AU4: Northumberland | AV4: Smart Tots | AW4: Lower Earley | AX4: Woosehill | AY4: Our Den | AZ4: Finchampstead | BA4: Boot Farm | BB4: Saltway | BC4: Quarter Total | BD4: Abacus | BE4: Bees Knees | BF4: Bramleywood | BG4: Cedars | BH4: Hazebrouck | BI4: Kingsclere | BJ4: Merrydale | BK4: Stepping Stones | BL4: Happitots | BM4: Northumberland | BN4: Smart Tots | BO4: Lower Earley | BP4: Woosehill | BQ4: Our Den | BR4: Finchampstead | BS4: Boot Farm | BT4: Saltway | BU4: Quarter Total | BV4: Year Total
A5: Total Income | B5: 260830 | C5: 125630 | D5: 563670 | E5: 106810 | F5: 196490 | G5: 91990 | H5: 291750 | I5: 199710 | J5: 192250 | K5: 67480 | L5: 149900 | M5: 112690 | N5: 115620 | O5: 33250 | P5: 39450 | Q5: 157130 | R5: 269610 | S5: =SUM(B5:R5) | T5: 289080 | U5: 136960 | V5: 602667 | W5: 115829 | X5: 216765 | Y5: 100403 | Z5: 308563 | AA5: 209965 | AB5: 213061 | AC5: 77021 | AD5: 161488 | AE5: 123501 | AF5: 128445 | AG5: 41028 | AH5: 50569 | AI5: 166369 | AJ5: 293768 | AK5: =SUM(T5:AJ5) | AL5: 270220 | AM5: 122044 | AN5: 546014 | AO5: 119279 | AP5: 193416 | AQ5: 90431 | AR5: 319479 | AS5: 211677 | AT5: 219255 | AU5: 83356 | AV5: 151026 | AW5: 99904 | AX5: 117375 | AY5: 25707 | AZ5: 60559 | BA5: 141201 | BB5: 272107 | BC5: =SUM(AL5:BB5) | BD5: 294034 | BE5: 125569 | BF5: 585332 | BG5: 126433 | BH5: 212338 | BI5: 95981 | BJ5: 330732 | BK5: 198993 | BL5: 239586 | BM5: 100916 | BN5: 161717 | BO5: 111841 | BP5: 131477 | BQ5: 31543 | BR5: 92357 | BS5: 162850 | BT5: 311515 | BU5: =SUM(BD5:BT5) | BV5: =BU5+BC5+AK5+S5
A6: Total Personnel | B6: 126099 | C6: 65767 | D6: 244486 | E6: 60422 | F6: 85681 | G6: 61987 | H6: 109560 | I6: 98915 | J6: 127573 | K6: 53861 | L6: 92441 | M6: 70972 | N6: 84600 | O6: 20939 | P6: 57407 | Q6: 79138 | R6: 127724 | S6: =SUM(B6:R6) | T6: 132075 | U6: 68350 | V6: 254017 | W6: 62673 | X6: 89313 | Y6: 64380 | Z6: 114145 | AA6: 104283 | AB6: 132338 | AC6: 56614 | AD6: 97542 | AE6: 73628 | AF6: 87870 | AG6: 21772 | AH6: 59738 | AI6: 82603 | AJ6: 133213 | AK6: =SUM(T6:AJ6) | AL6: 132075 | AM6: 68350 | AN6: 254026 | AO6: 62673 | AP6: 89313 | AQ6: 64389 | AR6: 114154 | AS6: 104283 | AT6: 132338 | AU6: 56614 | AV6: 97542 | AW6: 73628 | AX6: 87870 | AY6: 21772 | AZ6: 59738 | BA6: 82603 | BB6: 133213 | BC6: =SUM(AL6:BB6) | BD6: 132075 | BE6: 68350 | BF6: 254035 | BG6: 62673 | BH6: 89331 | BI6: 64398 | BJ6: 114163 | BK6: 104283 | BL6: 132338 | BM6: 56614 | BN6: 97542 | BO6: 73628 | BP6: 87933 | BQ6: 21772 | BR6: 59738 | BS6: 82603 | BT6: 133213 | BU6: =SUM(BD6:BT6) | BV6: =BU6+BC6+AK6+S6
A7: Total Childcare Costs | B7: 10736 | C7: 5074 | D7: 20598 | E7: 4659 | F7: 7380 | G7: 3980 | H7: 11678 | I7: 7490 | J7: 7906 | K7: 2729 | L7: 5849 | M7: 4363 | N7: 4584 | O7: 1503 | P7: 1726 | Q7: 6571 | R7: 10845 | S7: =SUM(B7:R7) | T7: 11875 | U7: 5504 | V7: 22020 | W7: 5001 | X7: 8128 | Y7: 4316 | Z7: 12340 | AA7: 7859 | AB7: 8696 | AC7: 3073 | AD7: 6287 | AE7: 4770 | AF7: 5076 | AG7: 1801 | AH7: 2144 | AI7: 6922 | AJ7: 11763 | AK7: =SUM(T7:AJ7) | AL7: 11130 | AM7: 4938 | AN7: 19998 | AO7: 5133 | AP7: 7305 | AQ7: 3917 | AR7: 12784 | AS7: 7920 | AT7: 8932 | AU7: 3301 | AV7: 5909 | AW7: 3939 | AX7: 4685 | AY7: 1267 | AZ7: 2522 | BA7: 5966 | BB7: 10940 | BC7: =SUM(AL7:BB7) | BD7: 12091 | BE7: 5072 | BF7: 21432 | BG7: 5404 | BH7: 8004 | BI7: 4139 | BJ7: 13241 | BK7: 7464 | BL7: 9704 | BM7: 3933 | BN7: 6314 | BO7: 4386 | BP7: 5225 | BQ7: 1496 | BR7: 3685 | BS7: 6788 | BT7: 12438 | BU7: =SUM(BD7:BT7) | BV7: =BU7+BC7+AK7+S7
A8: Total Premises & Admin | B8: 16555 | C8: 9048 | D8: 38163 | E8: 15032 | F8: 31746 | G8: 11268 | H8: 23828 | I8: 9723 | J8: 19906 | K8: 10561 | L8: 10295 | M8: 10912 | N8: 17759 | O8: 5127 | P8: 13215 | Q8: 22364 | R8: 13615 | S8: =SUM(B8:R8) | T8: 18536 | U8: 14116 | V8: 47366 | W8: 5634 | X8: 29332 | Y8: 11109 | Z8: 24523 | AA8: 9726 | AB8: 16905 | AC8: 11811 | AD8: 17824 | AE8: 14396 | AF8: 20628 | AG8: 4849 | AH8: 13078 | AI8: 19316 | AJ8: 13436 | AK8: =SUM(T8:AJ8) | AL8: 15036 | AM8: 9116 | AN8: 36366 | AO8: 5634 | AP8: 33082 | AQ8: 6609 | AR8: 16023 | AS8: 14726 | AT8: 15405 | AU8: 13811 | AV8: 19074 | AW8: 14896 | AX8: 15628 | AY8: 4849 | AZ8: 11778 | BA8: 21616 | BB8: 14936 | BC8: =SUM(AL8:BB8) | BD8: 15036 | BE8: 9116 | BF8: 34866 | BG8: 5634 | BH8: 29082 | BI8: 6609 | BJ8: 16023 | BK8: 9726 | BL8: 15405 | BM8: 11811 | BN8: 15324 | BO8: 13896 | BP8: 15628 | BQ8: 4849 | BR8: 11778 | BS8: 17316 | BT8: 13436 | BU8: =SUM(BD8:BT8) | BV8: =BU8+BC8+AK8+S8
A9: Total Direct Costs | B9: =SUM(B6:B8) | C9: =SUM(C6:C8) | D9: =SUM(D6:D8) | E9: =SUM(E6:E8) | F9: =SUM(F6:F8) | G9: =SUM(G6:G8) | H9: =SUM(H6:H8) | I9: =SUM(I6:I8) | ... R9: =SUM(R6:R8) | S9: =SUM(B9:R9) | T9: =SUM(T6:T8) | U9: =SUM(U6:U8) | V9: =SUM(V6:V8) | W9: =SUM(W6:W8) | X9: =SUM(X6:X8) | Y9: =SUM(Y6:Y8) | Z9: =SUM(Z6:Z8) | AA9: =SUM(AA6:AA8) | ... AJ9: =SUM(AJ6:AJ8) | AK9: =SUM(T9:AJ9) | AL9: =SUM(AL6:AL8) | AM9: =SUM(AM6:AM8) | AN9: =SUM(AN6:AN8) | AO9: =SUM(AO6:AO8) | AP9: =SUM(AP6:AP8) | AQ9: =SUM(AQ6:AQ8) | AR9: =SUM(AR6:AR8) | AS9: =SUM(AS6:AS8) | ... BB9: =SUM(BB6:BB8) | BC9: =SUM(AL9:BB9) | BD9: =SUM(BD6:BD8) | BE9: =SUM(BE6:BE8) | BF9: =SUM(BF6:BF8) | BG9: =SUM(BG6:BG8) | BH9: =SUM(BH6:BH8) | BI9: =SUM(BI6:BI8) | BJ9: =SUM(BJ6:BJ8) | BK9: =SUM(BK6:BK8) | ... BT9: =SUM(BT6:BT8) | BU9: =SUM(BD9:BT9) | BV9: =BU9+BC9+AK9+S9
A11: CONTRIBUTION | B11: =B5-B9 | C11: =C5-C9 | D11: =D5-D9 | E11: =E5-E9 | F11: =F5-F9 | G11: =G5-G9 | H11: =H5-H9 | I11: =I5-I9 | ... R11: =R5-R9 | S11: =SUM(B11:R11) | T11: =T5-T9 | U11: =U5-U9 | V11: =V5-V9 | W11: =W5-W9 | X11: =X5-X9 | Y11: =Y5-Y9 | Z11: =Z5-Z9 | AA11: =AA5-AA9 | ... AJ11: =AJ5-AJ9 | AK11: =SUM(T11:AJ11) | AL11: =AL5-AL9 | AM11: =AM5-AM9 | AN11: =AN5-AN9 | AO11: =AO5-AO9 | AP11: =AP5-AP9 | AQ11: =AQ5-AQ9 | AR11: =AR5-AR9 | AS11: =AS5-AS9 | ... BB11: =BB5-BB9 | BC11: =SUM(AL11:BB11) | BD11: =BD5-BD9 | BE11: =BE5-BE9 | BF11: =BF5-BF9 | BG11: =BG5-BG9 | BH11: =BH5-BH9 | BI11: =BI5-BI9 | BJ11: =BJ5-BJ9 | BK11: =BK5-BK9 | ... BT11: =BT5-BT9 | BU11: =SUM(BD11:BT11) | BV11: =BU11+BC11+AK11+S11
B12: =B11/B9 | C12: =C11/C9 | D12: =D11/D9 | E12: =E11/E9 | F12: =F11/F9 | G12: =G11/G9 | H12: =H11/H9 | I12: =I11/I9 | ... BV12: =BV11/BV9
A14: 2026 Actuals | B14: Q1 | T14: Q2 | U14: FORECAST DATA | AL14: Q3 | AM14: FORECAST DATA | BD14: Q4 | BE14: FORECAST DATA
B15: Abacus | C15: Bees Knees | D15: Bramleywood | E15: Cedars | F15: Hazebrouck | G15: Kingsclere | H15: Merrydale | I15: Stepping Stones | J15: Happitots | K15: Northumberland | L15: Smart Tots | M15: Lower Earley | N15: Woosehill | O15: Our Den | P15: Finchampstead | Q15: Boot Farm | R15: Saltway | S15: Totals | T15: Abacus | U15: Bees Knees | V15: Bramleywood | W15: Cedars | X15: Hazebrouck | Y15: Kingsclere | Z15: Merrydale | AA15: Stepping Stones | AB15: Happitots | AC15: Northumberland | AD15: Smart Tots | AE15: Lower Earley | AF15: Woosehill | AG15: Our Den | AH15: Finchampstead | AI15: Boot Farm | AJ15: Saltway | AK15: Totals | AL15: Abacus | AM15: Bees Knees | AN15: Bramleywood | AO15: Cedars | AP15: Hazebrouck | AQ15: Kingsclere | AR15: Merrydale | AS15: Stepping Stones | AT15: Happitots | AU15: Northumberland | AV15: Smart Tots | AW15: Lower Earley | AX15: Woosehill | AY15: Our Den | AZ15: Finchampstead | BA15: Boot Farm | BB15: Saltway | BC15: Totals | BD15: Abacus | BE15: Bees Knees | BF15: Bramleywood | BG15: Cedars | BH15: Hazebrouck | BI15: Kingsclere | BJ15: Merrydale | BK15: Stepping Stones | BL15: Happitots | BM15: Northumberland | BN15: Smart Tots | BO15: Lower Earley | BP15: Woosehill | BQ15: Our Den | BR15: Finchampstead | BS15: Boot Farm | BT15: Saltway | BU15: Totals | BV15: Year Total
A16: Total Income | B16: =SUM('[1]ABA P&L'!$O11:$Q11) | C16: =SUM('[1]BK P&L'!$O11:$Q11) | D16: =SUM('[1]BW P&L'!$O11:$Q11) | E16: =SUM('[1]CED P&L'!$O11:$Q11) | F16: =SUM('[1]HB P&L'!$O11:$Q11) | G16: =SUM('[1]KIN P&L'!$O11:$Q11) | H16: =SUM('[1]MER P&L'!$O11:$Q11) | I16: =SUM('[1]SST P&L'!$O11:$Q11) | J16: =SUM('[1]HDN P&L'!$O11:$Q11) | K16: =SUM('[1]NDN P&L'!$O11:$Q11) | L16: =SUM('[1]SDN P&L'!$O11:$Q11) | M16: =SUM('[1]LE P&L'!$O11:$Q11) | N16: =SUM('[1]WH P&L'!$O11:$Q11) | O16: =SUM('[1]HS P&L'!$O11:$Q11) | P16: =SUM('[1]FH P&L'!$O11:$Q11) | Q16: =SUM('[1]HAB P&L'!$O11:$Q11) | R16: =SUM('[1]SALT P&L'!$O11:$Q11) | S16: =SUM(B16:R16) | T16: =SUM('[1]ABA P&L'!$R11:$T11) | U16: =SUM('[1]BK P&L'!$R11:$T11) | V16: =SUM('[1]BW P&L'!$R11:$T11) | W16: =SUM('[1]CED P&L'!$R11:$T11) | X16: =SUM('[1]HB P&L'!$R11:$T11) | Y16: =SUM('[1]KIN P&L'!$R11:$T11) | Z16: =SUM('[1]MER P&L'!$R11:$T11) | AA16: =SUM('[1]SST P&L'!$R11:$T11) | AB16: =SUM('[1]HDN P&L'!$R11:$T11) | AC16: =SUM('[1]NDN P&L'!$R11:$T11) | AD16: =SUM('[1]SDN P&L'!$R11:$T11) | AE16: =SUM('[1]LE P&L'!$R11:$T11) | AF16: =SUM('[1]WH P&L'!$R11:$T11) | AG16: =SUM('[1]HS P&L'!$R11:$T11) | AH16: =SUM('[1]FH P&L'!$R11:$T11) | AI16: =SUM('[1]HAB P&L'!$R11:$T11) | AJ16: =SUM('[1]SALT P&L'!$R11:$T11) | AK16: =SUM(T16:AJ16) | AL16: =SUM('[1]ABA P&L'!$U11:$W11) | AM16: =SUM('[1]BK P&L'!$U11:$W11) | AN16: =SUM('[1]BW P&L'!$U11:$W11) | AO16: =SUM('[1]CED P&L'!$U11:$W11) | AP16: =SUM('[1]HB P&L'!$U11:$W11) | AQ16: =SUM('[1]KIN P&L'!$U11:$W11) | AR16: =SUM('[1]MER P&L'!$U11:$W11) | AS16: =SUM('[1]SST P&L'!$U11:$W11) | AT16: =SUM('[1]HDN P&L'!$U11:$W11) | AU16: =SUM('[1]NDN P&L'!$U11:$W11) | AV16: =SUM('[1]SDN P&L'!$U11:$W11) | AW16: =SUM('[1]LE P&L'!$U11:$W11) | AX16: =SUM('[1]WH P&L'!$U11:$W11) | AY16: =SUM('[1]HS P&L'!$U11:$W11) | AZ16: =SUM('[1]FH P&L'!$U11:$W11) | BA16: =SUM('[1]HAB P&L'!$U11:$W11) | BB16: =SUM('[1]SALT P&L'!$U11:$W11) | BC16: =SUM(AL16:BB16) | BD16: =SUM('[1]ABA P&L'!$X11:$Z11) | BE16: =SUM('[1]BK P&L'!$X11:$Z11) | BF16: =SUM('[1]BW P&L'!$X11:$Z11) | BG16: =SUM('[1]CED P&L'!$X11:$Z11) | BH16: =SUM('[1]HB P&L'!$X11:$Z11) | BI16: =SUM('[1]KIN P&L'!$X11:$Z11) | BJ16: =SUM('[1]MER P&L'!$X11:$Z11) | BK16: =SUM('[1]SST P&L'!$X11:$Z11) | BL16: =SUM('[1]HDN P&L'!$X11:$Z11) | BM16: =SUM('[1]NDN P&L'!$X11:$Z11) | BN16: =SUM('[1]SDN P&L'!$X11:$Z11) | BO16: =SUM('[1]LE P&L'!$X11:$Z11) | BP16: =SUM('[1]WH P&L'!$X11:$Z11) | BQ16: =SUM('[1]HS P&L'!$X11:$Z11) | BR16: =SUM('[1]FH P&L'!$X11:$Z11) | BS16: =SUM('[1]HAB P&L'!$X11:$Z11) | BT16: =SUM('[1]SALT P&L'!$X11:$Z11) | BU16: =SUM(BD16:BT16) | BV16: =BU16+BC16+AK16+S16
A17: Total Personnel | B17: =SUM('[1]ABA P&L'!$O23:$Q23) | C17: =SUM('[1]BK P&L'!$O23:$Q23) | D17: =SUM('[1]BW P&L'!$O23:$Q23) | E17: =SUM('[1]CED P&L'!$O23:$Q23) | F17: =SUM('[1]HB P&L'!$O23:$Q23) | G17: =SUM('[1]KIN P&L'!$O23:$Q23) | H17: =SUM('[1]MER P&L'!$O23:$Q23) | I17: =SUM('[1]SST P&L'!$O23:$Q23) | J17: =SUM('[1]HDN P&L'!$O23:$Q23) | K17: =SUM('[1]NDN P&L'!$O23:$Q23) | L17: =SUM('[1]SDN P&L'!$O23:$Q23) | M17: =SUM('[1]LE P&L'!$O23:$Q23) | N17: =SUM('[1]WH P&L'!$O23:$Q23) | O17: =SUM('[1]HS P&L'!$O23:$Q23) | P17: =SUM('[1]FH P&L'!$O23:$Q23) | Q17: =SUM('[1]HAB P&L'!$O23:$Q23) | R17: =SUM('[1]SALT P&L'!$O23:$Q23) | S17: =SUM(B17:R17) | T17: =SUM('[1]ABA P&L'!$R23:$T23) | U17: =SUM('[1]BK P&L'!$R23:$T23) | V17: =SUM('[1]BW P&L'!$R23:$T23) | W17: =SUM('[1]CED P&L'!$R23:$T23) | X17: =SUM('[1]HB P&L'!$R23:$T23) | Y17: =SUM('[1]KIN P&L'!$R23:$T23) | Z17: =SUM('[1]MER P&L'!$R23:$T23) | AA17: =SUM('[1]SST P&L'!$R23:$T23) | AB17: =SUM('[1]HDN P&L'!$R23:$T23) | AC17: =SUM('[1]NDN P&L'!$R23:$T23) | AD17: =SUM('[1]SDN P&L'!$R23:$T23) | AE17: =SUM('[1]LE P&L'!$R23:$T23) | AF17: =SUM('[1]WH P&L'!$R23:$T23) | AG17: =SUM('[1]HS P&L'!$R23:$T23) | AH17: =SUM('[1]FH P&L'!$R23:$T23) | AI17: =SUM('[1]HAB P&L'!$R23:$T23) | AJ17: =SUM('[1]SALT P&L'!$R23:$T23) | AK17: =SUM(T17:AJ17) | AL17: =SUM('[1]ABA P&L'!$U23:$W23) | AM17: =SUM('[1]BK P&L'!$U23:$W23) | AN17: =SUM('[1]BW P&L'!$U23:$W23) | AO17: =SUM('[1]CED P&L'!$U23:$W23) | AP17: =SUM('[1]HB P&L'!$U23:$W23) | AQ17: =SUM('[1]KIN P&L'!$U23:$W23) | AR17: =SUM('[1]MER P&L'!$U23:$W23) | AS17: =SUM('[1]SST P&L'!$U23:$W23) | AT17: =SUM('[1]HDN P&L'!$U23:$W23) | AU17: =SUM('[1]NDN P&L'!$U23:$W23) | AV17: =SUM('[1]SDN P&L'!$U23:$W23) | AW17: =SUM('[1]LE P&L'!$U23:$W23) | AX17: =SUM('[1]WH P&L'!$U23:$W23) | AY17: =SUM('[1]HS P&L'!$U23:$W23) | AZ17: =SUM('[1]FH P&L'!$U23:$W23) | BA17: =SUM('[1]HAB P&L'!$U23:$W23) | BB17: =SUM('[1]SALT P&L'!$U23:$W23) | BC17: =SUM(AL17:BB17) | BD17: =SUM('[1]ABA P&L'!$X23:$Z23) | BE17: =SUM('[1]BK P&L'!$X23:$Z23) | BF17: =SUM('[1]BW P&L'!$X23:$Z23) | BG17: =SUM('[1]CED P&L'!$X23:$Z23) | BH17: =SUM('[1]HB P&L'!$X23:$Z23) | BI17: =SUM('[1]KIN P&L'!$X23:$Z23) | BJ17: =SUM('[1]MER P&L'!$X23:$Z23) | BK17: =SUM('[1]SST P&L'!$X23:$Z23) | BL17: =SUM('[1]HDN P&L'!$X23:$Z23) | BM17: =SUM('[1]NDN P&L'!$X23:$Z23) | BN17: =SUM('[1]SDN P&L'!$X23:$Z23) | BO17: =SUM('[1]LE P&L'!$X23:$Z23) | BP17: =SUM('[1]WH P&L'!$X23:$Z23) | BQ17: =SUM('[1]HS P&L'!$X23:$Z23) | BR17: =SUM('[1]FH P&L'!$X23:$Z23) | BS17: =SUM('[1]HAB P&L'!$X23:$Z23) | BT17: =SUM('[1]SALT P&L'!$X23:$Z23) | BU17: =SUM(BD17:BT17) | BV17: =BU17+BC17+AK17+S17
A18: Total Childcare Costs | B18: =SUM('[1]ABA P&L'!$O32:$Q32) | C18: =SUM('[1]BK P&L'!$O32:$Q32) | D18: =SUM('[1]BW P&L'!$O32:$Q32) | E18: =SUM('[1]CED P&L'!$O32:$Q32) | F18: =SUM('[1]HB P&L'!$O32:$Q32) | G18: =SUM('[1]KIN P&L'!$O32:$Q32) | H18: =SUM('[1]MER P&L'!$O32:$Q32) | I18: =SUM('[1]SST P&L'!$O32:$Q32) | J18: =SUM('[1]HDN P&L'!$O32:$Q32) | K18: =SUM('[1]NDN P&L'!$O32:$Q32) | L18: =SUM('[1]SDN P&L'!$O32:$Q32) | M18: =SUM('[1]LE P&L'!$O32:$Q32) | N18: =SUM('[1]WH P&L'!$O32:$Q32) | O18: =SUM('[1]HS P&L'!$O32:$Q32) | P18: =SUM('[1]FH P&L'!$O32:$Q32) | Q18: =SUM('[1]HAB P&L'!$O32:$Q32) | R18: =SUM('[1]SALT P&L'!$O32:$Q32) | S18: =SUM(B18:R18) | T18: =SUM('[1]ABA P&L'!$R32:$T32) | U18: =SUM('[1]BK P&L'!$R32:$T32) | V18: =SUM('[1]BW P&L'!$R32:$T32) | W18: =SUM('[1]CED P&L'!$R32:$T32) | X18: =SUM('[1]HB P&L'!$R32:$T32) | Y18: =SUM('[1]KIN P&L'!$R32:$T32) | Z18: =SUM('[1]MER P&L'!$R32:$T32) | AA18: =SUM('[1]SST P&L'!$R32:$T32) | AB18: =SUM('[1]HDN P&L'!$R32:$T32) | AC18: =SUM('[1]NDN P&L'!$R32:$T32) | AD18: =SUM('[1]SDN P&L'!$R32:$T32) | AE18: =SUM('[1]LE P&L'!$R32:$T32) | AF18: =SUM('[1]WH P&L'!$R32:$T32) | AG18: =SUM('[1]HS P&L'!$R32:$T32) | AH18: =SUM('[1]FH P&L'!$R32:$T32) | AI18: =SUM('[1]HAB P&L'!$R32:$T32) | AJ18: =SUM('[1]SALT P&L'!$R32:$T32) | AK18: =SUM(T18:AJ18) | AL18: =SUM('[1]ABA P&L'!$U32:$W32) | AM18: =SUM('[1]BK P&L'!$U32:$W32) | AN18: =SUM('[1]BW P&L'!$U32:$W32) | AO18: =SUM('[1]CED P&L'!$U32:$W32) | AP18: =SUM('[1]HB P&L'!$U32:$W32) | AQ18: =SUM('[1]KIN P&L'!$U32:$W32) | AR18: =SUM('[1]MER P&L'!$U32:$W32) | AS18: =SUM('[1]SST P&L'!$U32:$W32) | AT18: =SUM('[1]HDN P&L'!$U32:$W32) | AU18: =SUM('[1]NDN P&L'!$U32:$W32) | AV18: =SUM('[1]SDN P&L'!$U32:$W32) | AW18: =SUM('[1]LE P&L'!$U32:$W32) | AX18: =SUM('[1]WH P&L'!$U32:$W32) | AY18: =SUM('[1]HS P&L'!$U32:$W32) | AZ18: =SUM('[1]FH P&L'!$U32:$W32) | BA18: =SUM('[1]HAB P&L'!$U32:$W32) | BB18: =SUM('[1]SALT P&L'!$U32:$W32) | BC18: =SUM(AL18:BB18) | BD18: =SUM('[1]ABA P&L'!$X32:$Z32) | BE18: =SUM('[1]BK P&L'!$X32:$Z32) | BF18: =SUM('[1]BW P&L'!$X32:$Z32) | BG18: =SUM('[1]CED P&L'!$X32:$Z32) | BH18: =SUM('[1]HB P&L'!$X32:$Z32) | BI18: =SUM('[1]KIN P&L'!$X32:$Z32) | BJ18: =SUM('[1]MER P&L'!$X32:$Z32) | BK18: =SUM('[1]SST P&L'!$X32:$Z32) | BL18: =SUM('[1]HDN P&L'!$X32:$Z32) | BM18: =SUM('[1]NDN P&L'!$X32:$Z32) | BN18: =SUM('[1]SDN P&L'!$X32:$Z32) | BO18: =SUM('[1]LE P&L'!$X32:$Z32) | BP18: =SUM('[1]WH P&L'!$X32:$Z32) | BQ18: =SUM('[1]HS P&L'!$X32:$Z32) | BR18: =SUM('[1]FH P&L'!$X32:$Z32) | BS18: =SUM('[1]HAB P&L'!$X32:$Z32) | BT18: =SUM('[1]SALT P&L'!$X32:$Z32) | BU18: =SUM(BD18:BT18) | BV18: =BU18+BC18+AK18+S18
A19: Total Premises & Admin | B19: =SUM('[1]ABA P&L'!$O45:$Q45) | C19: =SUM('[1]BK P&L'!$O45:$Q45) | D19: =SUM('[1]BW P&L'!$O45:$Q45) | E19: =SUM('[1]CED P&L'!$O45:$Q45) | F19: =SUM('[1]HB P&L'!$O45:$Q45) | G19: =SUM('[1]KIN P&L'!$O45:$Q45) | H19: =SUM('[1]MER P&L'!$O45:$Q45) | I19: =SUM('[1]SST P&L'!$O45:$Q45) | J19: =SUM('[1]HDN P&L'!$O45:$Q45) | K19: =SUM('[1]NDN P&L'!$O45:$Q45) | L19: =SUM('[1]SDN P&L'!$O45:$Q45) | M19: =SUM('[1]LE P&L'!$O45:$Q45) | N19: =SUM('[1]WH P&L'!$O45:$Q45) | O19: =SUM('[1]HS P&L'!$O45:$Q45) | P19: =SUM('[1]FH P&L'!$O45:$Q45) | Q19: =SUM('[1]HAB P&L'!$O45:$Q45) | R19: =SUM('[1]SALT P&L'!$O45:$Q45) | S19: =SUM(B19:R19) | T19: =SUM('[1]ABA P&L'!$R45:$T45) | U19: =SUM('[1]BK P&L'!$R45:$T45) | V19: =SUM('[1]BW P&L'!$R45:$T45) | W19: =SUM('[1]CED P&L'!$R45:$T45) | X19: =SUM('[1]HB P&L'!$R45:$T45) | Y19: =SUM('[1]KIN P&L'!$R45:$T45) | Z19: =SUM('[1]MER P&L'!$R45:$T45) | AA19: =SUM('[1]SST P&L'!$R45:$T45) | AB19: =SUM('[1]HDN P&L'!$R45:$T45) | AC19: =SUM('[1]NDN P&L'!$R45:$T45) | AD19: =SUM('[1]SDN P&L'!$R45:$T45) | AE19: =SUM('[1]LE P&L'!$R45:$T45) | AF19: =SUM('[1]WH P&L'!$R45:$T45) | AG19: =SUM('[1]HS P&L'!$R45:$T45) | AH19: =SUM('[1]FH P&L'!$R45:$T45) | AI19: =SUM('[1]HAB P&L'!$R45:$T45) | AJ19: =SUM('[1]SALT P&L'!$R45:$T45) | AK19: =SUM(T19:AJ19) | AL19: =SUM('[1]ABA P&L'!$U45:$W45) | AM19: =SUM('[1]BK P&L'!$U45:$W45) | AN19: =SUM('[1]BW P&L'!$U45:$W45) | AO19: =SUM('[1]CED P&L'!$U45:$W45) | AP19: =SUM('[1]HB P&L'!$U45:$W45) | AQ19: =SUM('[1]KIN P&L'!$U45:$W45) | AR19: =SUM('[1]MER P&L'!$U45:$W45) | AS19: =SUM('[1]SST P&L'!$U45:$W45) | AT19: =SUM('[1]HDN P&L'!$U45:$W45) | AU19: =SUM('[1]NDN P&L'!$U45:$W45) | AV19: =SUM('[1]SDN P&L'!$U45:$W45) | AW19: =SUM('[1]LE P&L'!$U45:$W45) | AX19: =SUM('[1]WH P&L'!$U45:$W45) | AY19: =SUM('[1]HS P&L'!$U45:$W45) | AZ19: =SUM('[1]FH P&L'!$U45:$W45) | BA19: =SUM('[1]HAB P&L'!$U45:$W45) | BB19: =SUM('[1]SALT P&L'!$U45:$W45) | BC19: =SUM(AL19:BB19) | BD19: =SUM('[1]ABA P&L'!$X45:$Z45) | BE19: =SUM('[1]BK P&L'!$X45:$Z45) | BF19: =SUM('[1]BW P&L'!$X45:$Z45) | BG19: =SUM('[1]CED P&L'!$X45:$Z45) | BH19: =SUM('[1]HB P&L'!$X45:$Z45) | BI19: =SUM('[1]KIN P&L'!$X45:$Z45) | BJ19: =SUM('[1]MER P&L'!$X45:$Z45) | BK19: =SUM('[1]SST P&L'!$X45:$Z45) | BL19: =SUM('[1]HDN P&L'!$X45:$Z45) | BM19: =SUM('[1]NDN P&L'!$X45:$Z45) | BN19: =SUM('[1]SDN P&L'!$X45:$Z45) | BO19: =SUM('[1]LE P&L'!$X45:$Z45) | BP19: =SUM('[1]WH P&L'!$X45:$Z45) | BQ19: =SUM('[1]HS P&L'!$X45:$Z45) | BR19: =SUM('[1]FH P&L'!$X45:$Z45) | BS19: =SUM('[1]HAB P&L'!$X45:$Z45) | BT19: =SUM('[1]SALT P&L'!$X45:$Z45) | BU19: =SUM(BD19:BT19) | BV19: =BU19+BC19+AK19+S19
A20: Total Direct Costs | B20: =SUM('[1]ABA P&L'!$O46:$Q46) | C20: =SUM('[1]BK P&L'!$O46:$Q46) | D20: =SUM('[1]BW P&L'!$O46:$Q46) | E20: =SUM('[1]CED P&L'!$O46:$Q46) | F20: =SUM('[1]HB P&L'!$O46:$Q46) | G20: =SUM('[1]KIN P&L'!$O46:$Q46) | H20: =SUM('[1]MER P&L'!$O46:$Q46) | I20: =SUM('[1]SST P&L'!$O46:$Q46) | J20: =SUM('[1]HDN P&L'!$O46:$Q46) | K20: =SUM('[1]NDN P&L'!$O46:$Q46) | L20: =SUM('[1]SDN P&L'!$O46:$Q46) | M20: =SUM('[1]LE P&L'!$O46:$Q46) | N20: =SUM('[1]WH P&L'!$O46:$Q46) | O20: =SUM('[1]HS P&L'!$O46:$Q46) | P20: =SUM('[1]FH P&L'!$O46:$Q46) | Q20: =SUM('[1]HAB P&L'!$O46:$Q46) | R20: =SUM('[1]SALT P&L'!$O46:$Q46) | S20: =SUM(B20:R20) | T20: =SUM('[1]ABA P&L'!$R46:$T46) | U20: =SUM('[1]BK P&L'!$R46:$T46) | V20: =SUM('[1]BW P&L'!$R46:$T46) | W20: =SUM('[1]CED P&L'!$R46:$T46) | X20: =SUM('[1]HB P&L'!$R46:$T46) | Y20: =SUM('[1]KIN P&L'!$R46:$T46) | Z20: =SUM('[1]MER P&L'!$R46:$T46) | AA20: =SUM('[1]SST P&L'!$R46:$T46) | AB20: =SUM('[1]HDN P&L'!$R46:$T46) | AC20: =SUM('[1]NDN P&L'!$R46:$T46) | AD20: =SUM('[1]SDN P&L'!$R46:$T46) | AE20: =SUM('[1]LE P&L'!$R46:$T46) | AF20: =SUM('[1]WH P&L'!$R46:$T46) | AG20: =SUM('[1]HS P&L'!$R46:$T46) | AH20: =SUM('[1]FH P&L'!$R46:$T46) | AI20: =SUM('[1]HAB P&L'!$R46:$T46) | AJ20: =SUM('[1]SALT P&L'!$R46:$T46) | AK20: =SUM(T20:AJ20) | AL20: =SUM('[1]ABA P&L'!$U46:$W46) | AM20: =SUM('[1]BK P&L'!$U46:$W46) | AN20: =SUM('[1]BW P&L'!$U46:$W46) | AO20: =SUM('[1]CED P&L'!$U46:$W46) | AP20: =SUM('[1]HB P&L'!$U46:$W46) | AQ20: =SUM('[1]KIN P&L'!$U46:$W46) | AR20: =SUM('[1]MER P&L'!$U46:$W46) | AS20: =SUM('[1]SST P&L'!$U46:$W46) | AT20: =SUM('[1]HDN P&L'!$U46:$W46) | AU20: =SUM('[1]NDN P&L'!$U46:$W46) | AV20: =SUM('[1]SDN P&L'!$U46:$W46) | AW20: =SUM('[1]LE P&L'!$U46:$W46) | AX20: =SUM('[1]WH P&L'!$U46:$W46) | AY20: =SUM('[1]HS P&L'!$U46:$W46) | AZ20: =SUM('[1]FH P&L'!$U46:$W46) | BA20: =SUM('[1]HAB P&L'!$U46:$W46) | BB20: =SUM('[1]SALT P&L'!$U46:$W46) | BC20: =SUM(AL20:BB20) | BD20: =SUM('[1]ABA P&L'!$X46:$Z46) | BE20: =SUM('[1]BK P&L'!$X46:$Z46) | BF20: =SUM('[1]BW P&L'!$X46:$Z46) | BG20: =SUM('[1]CED P&L'!$X46:$Z46) | BH20: =SUM('[1]HB P&L'!$X46:$Z46) | BI20: =SUM('[1]KIN P&L'!$X46:$Z46) | BJ20: =SUM('[1]MER P&L'!$X46:$Z46) | BK20: =SUM('[1]SST P&L'!$X46:$Z46) | BL20: =SUM('[1]HDN P&L'!$X46:$Z46) | BM20: =SUM('[1]NDN P&L'!$X46:$Z46) | BN20: =SUM('[1]SDN P&L'!$X46:$Z46) | BO20: =SUM('[1]LE P&L'!$X46:$Z46) | BP20: =SUM('[1]WH P&L'!$X46:$Z46) | BQ20: =SUM('[1]HS P&L'!$X46:$Z46) | BR20: =SUM('[1]FH P&L'!$X46:$Z46) | BS20: =SUM('[1]HAB P&L'!$X46:$Z46) | BT20: =SUM('[1]SALT P&L'!$X46:$Z46) | BU20: =SUM(BD20:BT20) | BV20: =BU20+BC20+AK20+S20
A22: CONTRIBUTION | B22: =B16-B20 | C22: =C16-C20 | D22: =D16-D20 | E22: =E16-E20 | F22: =F16-F20 | G22: =G16-G20 | H22: =H16-H20 | I22: =I16-I20 | ... R22: =R16-R20 | S22: =SUM(B22:R22) | T22: =T16-T20 | U22: =U16-U20 | V22: =V16-V20 | W22: =W16-W20 | X22: =X16-X20 | Y22: =Y16-Y20 | Z22: =Z16-Z20 | AA22: =AA16-AA20 | ... AJ22: =AJ16-AJ20 | AK22: =SUM(T22:AJ22) | AL22: =AL16-AL20 | AM22: =AM16-AM20 | AN22: =AN16-AN20 | AO22: =AO16-AO20 | AP22: =AP16-AP20 | AQ22: =AQ16-AQ20 | AR22: =AR16-AR20 | AS22: =AS16-AS20 | ... BB22: =BB16-BB20 | BC22: =SUM(AL22:BB22) | BD22: =BD16-BD20 | BE22: =BE16-BE20 | BF22: =BF16-BF20 | BG22: =BG16-BG20 | BH22: =BH16-BH20 | BI22: =BI16-BI20 | BJ22: =BJ16-BJ20 | BK22: =BK16-BK20 | ... BT22: =BT16-BT20 | BU22: =SUM(BD22:BT22) | BV22: =BU22+BC22+AK22+S22
B23: =B22/B20 | C23: =C22/C20 | D23: =D22/D20 | E23: =E22/E20 | F23: =F22/F20 | G23: =G22/G20 | H23: =H22/H20 | I23: =I22/I20 | ... BV23: =BV22/BV20
A25: Budegt V Actuals | B25: Q1 | T25: Q2 | U25: FORECAST DATA | AL25: Q3 | AM25: FORECAST DATA | BD25: Q4 | BE25: FORECAST DATA
B26: Abacus | C26: Bees Knees | D26: Bramleywood | E26: Cedars | F26: Hazebrouck | G26: Kingsclere | H26: Merrydale | I26: Stepping Stones | J26: Happitots | K26: Northumberland | L26: Smart Tots | M26: Lower Earley | N26: Woosehill | O26: Our Den | P26: Finchampstead | Q26: Boot Farm | R26: Saltway | S26: Totals | T26: Abacus | U26: Bees Knees | V26: Bramleywood | W26: Cedars | X26: Hazebrouck | Y26: Kingsclere | Z26: Merrydale | AA26: Stepping Stones | AB26: Happitots | AC26: Northumberland | AD26: Smart Tots | AE26: Lower Earley | AF26: Woosehill | AG26: Our Den | AH26: Finchampstead | AI26: Boot Farm | AJ26: Saltway | AK26: Totals | AL26: Abacus | AM26: Bees Knees | AN26: Bramleywood | AO26: Cedars | AP26: Hazebrouck | AQ26: Kingsclere | AR26: Merrydale | AS26: Stepping Stones | AT26: Happitots | AU26: Northumberland | AV26: Smart Tots | AW26: Lower Earley | AX26: Woosehill | AY26: Our Den | AZ26: Finchampstead | BA26: Boot Farm | BB26: Saltway | BC26: Totals | BD26: Abacus | BE26: Bees Knees | BF26: Bramleywood | BG26: Cedars | BH26: Hazebrouck | BI26: Kingsclere | BJ26: Merrydale | BK26: Stepping Stones | BL26: Happitots | BM26: Northumberland | BN26: Smart Tots | BO26: Lower Earley | BP26: Woosehill | BQ26: Our Den | BR26: Finchampstead | BS26: Boot Farm | BT26: Saltway | BU26: Totals | BV26: Year Total
A27: Income | B27: =B16-B5 | C27: =C16-C5 | D27: =D16-D5 | E27: =E16-E5 | F27: =F16-F5 | G27: =G16-G5 | H27: =H16-H5 | I27: =I16-I5 | ... BV27: =BV16-BV5
A28: Income % | B28: =B27/B5 | C28: =C27/C5 | D28: =D27/D5 | E28: =E27/E5 | F28: =F27/F5 | G28: =G27/G5 | H28: =H27/H5 | I28: =I27/I5 | ... N28: =N27/N5 | P28: =P27/P5 | Q28: =Q27/Q5 | R28: =R27/R5 | S28: =S27/S5 | T28: =T27/T5 | U28: =U27/U5 | V28: =V27/V5 | W28: =W27/W5 | ... BV28: =BV27/BV5
A30: Personnel Costs (negative = increase in cost) | B30: =B6-B17 | C30: =C6-C17 | D30: =D6-D17 | E30: =E6-E17 | F30: =F6-F17 | G30: =G6-G17 | H30: =H6-H17 | I30: =I6-I17 | ... BV30: =BV6-BV17
A31: Personnel Cost change as % | B31: =-B30/B6 | C31: =-C30/C6 | D31: =-D30/D6 | E31: =-E30/E6 | F31: =-F30/F6 | G31: =-G30/G6 | H31: =-H30/H6 | I31: =-I30/I6 | ... N31: =-N30/N6 | P31: =-P30/P6 | Q31: =-Q30/Q6 | R31: =-R30/R6 | S31: =-S30/S6 | T31: =-T30/T6 | U31: =-U30/U6 | V31: =-V30/V6 | W31: =-W30/W6 | ... BV31: =-BV30/BV6
A33: Sal:Rev Budegt
A34: Sal:Rev Actual | B34: =B17/B16 | C34: =C17/C16 | D34: =D17/D16 | E34: =E17/E16 | F34: =F17/F16 | G34: =G17/G16 | H34: =H17/H16 | I34: =I17/I16 | ... N34: =N17/N16 | P34: =P17/P16 | Q34: =Q17/Q16 | R34: =R17/R16 | S34: =S17/S16 | T34: =T17/T16 | U34: =U17/U16 | V34: =V17/V16 | W34: =W17/W16 | ... BV34: =BV17/BV16
A36: Childcare Costs (negative = increase in cost) | B36: =B7-B18 | C36: =C7-C18 | D36: =D7-D18 | E36: =E7-E18 | F36: =F7-F18 | G36: =G7-G18 | H36: =H7-H18 | I36: =I7-I18 | ... BV36: =BV7-BV18
A37: Childcare Cost Change % | B37: =-B36/B7 | C37: =-C36/C7 | D37: =-D36/D7 | E37: =-E36/E7 | F37: =-F36/F7 | G37: =-G36/G7 | H37: =-H36/H7 | I37: =-I36/I7 | ... N37: =-N36/N7 | P37: =-P36/P7 | Q37: =-Q36/Q7 | R37: =-R36/R7 | S37: =-S36/S7 | T37: =-T36/T7 | U37: =-U36/U7 | V37: =-V36/V7 | W37: =-W36/W7 | ... BV37: =-BV36/BV7
A39: Contribution | B39: =B22-B11 | C39: =C22-C11 | D39: =D22-D11 | E39: =E22-E11 | F39: =F22-F11 | G39: =G22-G11 | H39: =H22-H11 | I39: =I22-I11 | ... BV39: =BV22-BV11
A40: Contribution Change % | B40: =B39/B11 | C40: =C39/C11 | D40: =D39/D11 | E40: =E39/E11 | F40: =F39/F11 | G40: =G39/G11 | H40: =H39/H11 | I40: =I39/I11 | ... N40: =N39/N11 | P40: =P39/P11 | Q40: =Q39/Q11 | R40: =R39/R11 | S40: =S39/S11 | T40: =T39/T11 | U40: =U39/U11 | V40: =V39/V11 | W40: =W39/W11 | ... BV40: =BV39/BV11
A43: Comment

Sheet Year On Year Analysis
A1: Year on Year Analysis
A3: 2025 | B3: Q1 | U3: Q2 | AN3: Q3 | BG3: Q4
B4: Abacus | C4: Bees Knees | D4: Bramleywood | E4: Cedars | F4: Hazebrouck | G4: Kingsclere | H4: Merrydale | I4: Stepping Stones | J4: Happitots | K4: Northumberland | L4: Smart Tots | M4: Lower Earley | N4: Woosehill | O4: Our Den | P4: Finchampstead | Q4: Boot Farm | R4: Saltway | S4: Head Office & Misc | T4: Quarter Total | U4: Abacus | V4: Bees Knees | W4: Bramleywood | X4: Cedars | Y4: Hazebrouck | Z4: Kingsclere | AA4: Merrydale | AB4: Stepping Stones | AC4: Happitots | AD4: Northumberland | AE4: Smart Tots | AF4: Lower Earley | AG4: Woosehill | AH4: Our Den | AI4: Finchampstead | AJ4: Boot Farm | AK4: Saltway | AL4: Head Office & Misc | AM4: Quarter Total | AN4: Abacus | AO4: Bees Knees | AP4: Bramleywood | AQ4: Cedars | AR4: Hazebrouck | AS4: Kingsclere | AT4: Merrydale | AU4: Stepping Stones | AV4: Happitots | AW4: Northumberland | AX4: Smart Tots | AY4: Lower Earley | AZ4: Woosehill | BA4: Our Den | BB4: Finchampstead | BC4: Boot Farm | BD4: Saltway | BE4: Head Office & Misc | BF4: Quarter Total | BG4: Abacus | BH4: Bees Knees | BI4: Bramleywood | BJ4: Cedars | BK4: Hazebrouck | BL4: Kingsclere | BM4: Merrydale | BN4: Stepping Stones | BO4: Happitots | BP4: Northumberland | BQ4: Smart Tots | BR4: Lower Earley | BS4: Woosehill | BT4: Our Den | BU4: Finchampstead | BV4: Boot Farm | BW4: Saltway | BX4: Head Office & Misc | BY4: Quarter Total | BZ4: Year Total
A5: INCOME
A7: Fee Income Regular | B7: =SUM('ABA P&L'!$B8:$D8) | C7: =SUM('BK P&L'!$B8:$D8) | D7: =SUM('BW P&L'!$B8:$D8) | E7: =SUM('CED P&L'!$B8:$D8) | F7: =SUM('HB P&L'!$B8:$D8) | G7: =SUM('KIN P&L'!$B8:$D8) | H7: =SUM('MER P&L'!$B8:$D8) | I7: =SUM('SST P&L'!$B8:$D8) | J7: =SUM('HDN P&L'!$B8:$D8) | K7: =SUM('NDN P&L'!$B8:$D8) | L7: =SUM('SDN P&L'!$B8:$D8) | M7: =SUM('LE P&L'!$B8:$D8) | N7: =SUM('WH P&L'!$B8:$D8) | O7: =SUM('HS P&L'!$B8:$D8) | P7: =SUM('FH P&L'!$B8:$D8) | Q7: =SUM('HAB P&L'!$B8:$D8) | R7: =SUM('SALT P&L'!$B8:$D8) | S7: =SUM('KNL HO P&L'!$B8:$D8)+SUM('CCL HO P&L'!$B8:$D8)+SUM('YBHN HO P&L'!$B8:$D8)+SUM('YBN HO P&L'!$B8:$D8)+SUM('Moe2 P&L'!$B8:$D8) | T7: =SUM(B7:S7) | U7: =SUM('ABA P&L'!$E8:$G8) | V7: =SUM('BK P&L'!$E8:$G8) | W7: =SUM('BW P&L'!$E8:$G8) | X7: =SUM('CED P&L'!$E8:$G8) | Y7: =SUM('HB P&L'!$E8:$G8) | Z7: =SUM('KIN P&L'!$E8:$G8) | AA7: =SUM('MER P&L'!$E8:$G8) | AB7: =SUM('SST P&L'!$E8:$G8) | AC7: =SUM('HDN P&L'!$E8:$G8) | AD7: =SUM('NDN P&L'!$E8:$G8) | AE7: =SUM('SDN P&L'!$E8:$G8) | AF7: =SUM('LE P&L'!$E8:$G8) | AG7: =SUM('WH P&L'!$E8:$G8) | AH7: =SUM('HS P&L'!$E8:$G8) | AI7: =SUM('FH P&L'!$E8:$G8) | AJ7: =SUM('HAB P&L'!$E8:$G8) | AK7: =SUM('SALT P&L'!$E8:$G8) | AL7: =SUM('KNL HO P&L'!$E8:$G8)+SUM('CCL HO P&L'!$E8:$G8)+SUM('YBHN HO P&L'!$E8:$G8)+SUM('YBN HO P&L'!$E8:$G8)+SUM('Moe2 P&L'!$E8:$G8) | AM7: =SUM(U7:AL7) | AN7: =SUM('ABA P&L'!$H8:$J8) | AO7: =SUM('BK P&L'!$H8:$J8) | AP7: =SUM('BW P&L'!$H8:$J8) | AQ7: =SUM('CED P&L'!$H8:$J8) | AR7: =SUM('HB P&L'!$H8:$J8) | AS7: =SUM('KIN P&L'!$H8:$J8) | AT7: =SUM('MER P&L'!$H8:$J8) | AU7: =SUM('SST P&L'!$H8:$J8) | AV7: =SUM('HDN P&L'!$H8:$J8) | AW7: =SUM('NDN P&L'!$H8:$J8) | AX7: =SUM('SDN P&L'!$H8:$J8) | AY7: =SUM('LE P&L'!$H8:$J8) | AZ7: =SUM('WH P&L'!$H8:$J8) | BA7: =SUM('HS P&L'!$H8:$J8) | BB7: =SUM('FH P&L'!$H8:$J8) | BC7: =SUM('HAB P&L'!$H8:$J8) | BD7: =SUM('SALT P&L'!$H8:$J8) | BE7: =SUM('KNL HO P&L'!$H8:$J8)+SUM('CCL HO P&L'!$H8:$J8)+SUM('YBHN HO P&L'!$H8:$J8)+SUM('YBN HO P&L'!$H8:$J8)+SUM('Moe2 P&L'!$H8:$J8) | BF7: =SUM(AN7:BE7) | BG7: =SUM('ABA P&L'!$K8:$M8) | BH7: =SUM('BK P&L'!$K8:$M8) | BI7: =SUM('BW P&L'!$K8:$M8) | BJ7: =SUM('CED P&L'!$K8:$M8) | BK7: =SUM('HB P&L'!$K8:$M8) | BL7: =SUM('KIN P&L'!$K8:$M8) | BM7: =SUM('MER P&L'!$K8:$M8) | BN7: =SUM('SST P&L'!$K8:$M8) | BO7: =SUM('HDN P&L'!$K8:$M8) | BP7: =SUM('NDN P&L'!$K8:$M8) | BQ7: =SUM('SDN P&L'!$K8:$M8) | BR7: =SUM('LE P&L'!$K8:$M8) | BS7: =SUM('WH P&L'!$K8:$M8) | BT7: =SUM('HS P&L'!$K8:$M8) | BU7: =SUM('FH P&L'!$K8:$M8) | BV7: =SUM('HAB P&L'!$K8:$M8) | BW7: =SUM('SALT P&L'!$K8:$M8) | BX7: =SUM('KNL HO P&L'!$K8:$M8)+SUM('CCL HO P&L'!$K8:$M8)+SUM('YBHN HO P&L'!$K8:$M8)+SUM('YBN HO P&L'!$K8:$M8)+SUM('Moe2 P&L'!$K8:$M8) | BY7: =SUM(BG7:BX7) | BZ7: =BY7+BF7+AM7+T7
A8: EEEF Embeded | B8: =SUM('ABA P&L'!$B9:$D9) | C8: =SUM('BK P&L'!$B9:$D9) | D8: =SUM('BW P&L'!$B9:$D9) | E8: =SUM('CED P&L'!$B9:$D9) | F8: =SUM('HB P&L'!$B9:$D9) | G8: =SUM('KIN P&L'!$B9:$D9) | H8: =SUM('MER P&L'!$B9:$D9) | I8: =SUM('SST P&L'!$B9:$D9) | J8: =SUM('HDN P&L'!$B9:$D9) | K8: =SUM('NDN P&L'!$B9:$D9) | L8: =SUM('SDN P&L'!$B9:$D9) | M8: =SUM('LE P&L'!$B9:$D9) | N8: =SUM('WH P&L'!$B9:$D9) | O8: =SUM('HS P&L'!$B9:$D9) | P8: =SUM('FH P&L'!$B9:$D9) | Q8: =SUM('HAB P&L'!$B9:$D9) | R8: =SUM('SALT P&L'!$B9:$D9) | S8: =SUM('KNL HO P&L'!$B9:$D9)+SUM('CCL HO P&L'!$B9:$D9)+SUM('YBHN HO P&L'!$B9:$D9)+SUM('YBN HO P&L'!$B9:$D9)+SUM('Moe2 P&L'!$B9:$D9) | T8: =SUM(B8:S8) | U8: =SUM('ABA P&L'!$E9:$G9) | V8: =SUM('BK P&L'!$E9:$G9) | W8: =SUM('BW P&L'!$E9:$G9) | X8: =SUM('CED P&L'!$E9:$G9) | Y8: =SUM('HB P&L'!$E9:$G9) | Z8: =SUM('KIN P&L'!$E9:$G9) | AA8: =SUM('MER P&L'!$E9:$G9) | AB8: =SUM('SST P&L'!$E9:$G9) | AC8: =SUM('HDN P&L'!$E9:$G9) | AD8: =SUM('NDN P&L'!$E9:$G9) | AE8: =SUM('SDN P&L'!$E9:$G9) | AF8: =SUM('LE P&L'!$E9:$G9) | AG8: =SUM('WH P&L'!$E9:$G9) | AH8: =SUM('HS P&L'!$E9:$G9) | AI8: =SUM('FH P&L'!$E9:$G9) | AJ8: =SUM('HAB P&L'!$E9:$G9) | AK8: =SUM('SALT P&L'!$E9:$G9) | AL8: =SUM('KNL HO P&L'!$E9:$G9)+SUM('CCL HO P&L'!$E9:$G9)+SUM('YBHN HO P&L'!$E9:$G9)+SUM('YBN HO P&L'!$E9:$G9)+SUM('Moe2 P&L'!$E9:$G9) | AM8: =SUM(U8:AL8) | AN8: =SUM('ABA P&L'!$H9:$J9) | AO8: =SUM('BK P&L'!$H9:$J9) | AP8: =SUM('BW P&L'!$H9:$J9) | AQ8: =SUM('CED P&L'!$H9:$J9) | AR8: =SUM('HB P&L'!$H9:$J9) | AS8: =SUM('KIN P&L'!$H9:$J9) | AT8: =SUM('MER P&L'!$H9:$J9) | AU8: =SUM('SST P&L'!$H9:$J9) | AV8: =SUM('HDN P&L'!$H9:$J9) | AW8: =SUM('NDN P&L'!$H9:$J9) | AX8: =SUM('SDN P&L'!$H9:$J9) | AY8: =SUM('LE P&L'!$H9:$J9) | AZ8: =SUM('WH P&L'!$H9:$J9) | BA8: =SUM('HS P&L'!$H9:$J9) | BB8: =SUM('FH P&L'!$H9:$J9) | BC8: =SUM('HAB P&L'!$H9:$J9) | BD8: =SUM('SALT P&L'!$H9:$J9) | BE8: =SUM('KNL HO P&L'!$H9:$J9)+SUM('CCL HO P&L'!$H9:$J9)+SUM('YBHN HO P&L'!$H9:$J9)+SUM('YBN HO P&L'!$H9:$J9)+SUM('Moe2 P&L'!$H9:$J9) | BF8: =SUM(AN8:BE8) | BG8: =SUM('ABA P&L'!$K9:$M9) | BH8: =SUM('BK P&L'!$K9:$M9) | BI8: =SUM('BW P&L'!$K9:$M9) | BJ8: =SUM('CED P&L'!$K9:$M9) | BK8: =SUM('HB P&L'!$K9:$M9) | BL8: =SUM('KIN P&L'!$K9:$M9) | BM8: =SUM('MER P&L'!$K9:$M9) | BN8: =SUM('SST P&L'!$K9:$M9) | BO8: =SUM('HDN P&L'!$K9:$M9) | BP8: =SUM('NDN P&L'!$K9:$M9) | BQ8: =SUM('SDN P&L'!$K9:$M9) | BR8: =SUM('LE P&L'!$K9:$M9) | BS8: =SUM('WH P&L'!$K9:$M9) | BT8: =SUM('HS P&L'!$K9:$M9) | BU8: =SUM('FH P&L'!$K9:$M9) | BV8: =SUM('HAB P&L'!$K9:$M9) | BW8: =SUM('SALT P&L'!$K9:$M9) | BX8: =SUM('KNL HO P&L'!$K9:$M9)+SUM('CCL HO P&L'!$K9:$M9)+SUM('YBHN HO P&L'!$K9:$M9)+SUM('YBN HO P&L'!$K9:$M9)+SUM('Moe2 P&L'!$K9:$M9) | BY8: =SUM(BG8:BX8) | BZ8: =BY8+BF8+AM8+T8
A9: Other Income | B9: =SUM('ABA P&L'!$B10:$D10) | C9: =SUM('BK P&L'!$B10:$D10) | D9: =SUM('BW P&L'!$B10:$D10) | E9: =SUM('CED P&L'!$B10:$D10) | F9: =SUM('HB P&L'!$B10:$D10) | G9: =SUM('KIN P&L'!$B10:$D10) | H9: =SUM('MER P&L'!$B10:$D10) | I9: =SUM('SST P&L'!$B10:$D10) | J9: =SUM('HDN P&L'!$B10:$D10) | K9: =SUM('NDN P&L'!$B10:$D10) | L9: =SUM('SDN P&L'!$B10:$D10) | M9: =SUM('LE P&L'!$B10:$D10) | N9: =SUM('WH P&L'!$B10:$D10) | O9: =SUM('HS P&L'!$B10:$D10) | P9: =SUM('FH P&L'!$B10:$D10) | Q9: =SUM('HAB P&L'!$B10:$D10) | R9: =SUM('SALT P&L'!$B10:$D10) | S9: =SUM('KNL HO P&L'!$B10:$D10)+SUM('CCL HO P&L'!$B10:$D10)+SUM('YBHN HO P&L'!$B10:$D10)+SUM('YBN HO P&L'!$B10:$D10)+SUM('Moe2 P&L'!$B10:$D10) | T9: =SUM(B9:S9) | U9: =SUM('ABA P&L'!$E10:$G10) | V9: =SUM('BK P&L'!$E10:$G10) | W9: =SUM('BW P&L'!$E10:$G10) | X9: =SUM('CED P&L'!$E10:$G10) | Y9: =SUM('HB P&L'!$E10:$G10) | Z9: =SUM('KIN P&L'!$E10:$G10) | AA9: =SUM('MER P&L'!$E10:$G10) | AB9: =SUM('SST P&L'!$E10:$G10) | AC9: =SUM('HDN P&L'!$E10:$G10) | AD9: =SUM('NDN P&L'!$E10:$G10) | AE9: =SUM('SDN P&L'!$E10:$G10) | AF9: =SUM('LE P&L'!$E10:$G10) | AG9: =SUM('WH P&L'!$E10:$G10) | AH9: =SUM('HS P&L'!$E10:$G10) | AI9: =SUM('FH P&L'!$E10:$G10) | AJ9: =SUM('HAB P&L'!$E10:$G10) | AK9: =SUM('SALT P&L'!$E10:$G10) | AL9: =SUM('KNL HO P&L'!$E10:$G10)+SUM('CCL HO P&L'!$E10:$G10)+SUM('YBHN HO P&L'!$E10:$G10)+SUM('YBN HO P&L'!$E10:$G10)+SUM('Moe2 P&L'!$E10:$G10) | AM9: =SUM(U9:AL9) | AN9: =SUM('ABA P&L'!$H10:$J10) | AO9: =SUM('BK P&L'!$H10:$J10) | AP9: =SUM('BW P&L'!$H10:$J10) | AQ9: =SUM('CED P&L'!$H10:$J10) | AR9: =SUM('HB P&L'!$H10:$J10) | AS9: =SUM('KIN P&L'!$H10:$J10) | AT9: =SUM('MER P&L'!$H10:$J10) | AU9: =SUM('SST P&L'!$H10:$J10) | AV9: =SUM('HDN P&L'!$H10:$J10) | AW9: =SUM('NDN P&L'!$H10:$J10) | AX9: =SUM('SDN P&L'!$H10:$J10) | AY9: =SUM('LE P&L'!$H10:$J10) | AZ9: =SUM('WH P&L'!$H10:$J10) | BA9: =SUM('HS P&L'!$H10:$J10) | BB9: =SUM('FH P&L'!$H10:$J10) | BC9: =SUM('HAB P&L'!$H10:$J10) | BD9: =SUM('SALT P&L'!$H10:$J10) | BE9: =SUM('KNL HO P&L'!$H10:$J10)+SUM('CCL HO P&L'!$H10:$J10)+SUM('YBHN HO P&L'!$H10:$J10)+SUM('YBN HO P&L'!$H10:$J10)+SUM('Moe2 P&L'!$H10:$J10) | BF9: =SUM(AN9:BE9) | BG9: =SUM('ABA P&L'!$K10:$M10) | BH9: =SUM('BK P&L'!$K10:$M10) | BI9: =SUM('BW P&L'!$K10:$M10) | BJ9: =SUM('CED P&L'!$K10:$M10) | BK9: =SUM('HB P&L'!$K10:$M10) | BL9: =SUM('KIN P&L'!$K10:$M10) | BM9: =SUM('MER P&L'!$K10:$M10) | BN9: =SUM('SST P&L'!$K10:$M10) | BO9: =SUM('HDN P&L'!$K10:$M10) | BP9: =SUM('NDN P&L'!$K10:$M10) | BQ9: =SUM('SDN P&L'!$K10:$M10) | BR9: =SUM('LE P&L'!$K10:$M10) | BS9: =SUM('WH P&L'!$K10:$M10) | BT9: =SUM('HS P&L'!$K10:$M10) | BU9: =SUM('FH P&L'!$K10:$M10) | BV9: =SUM('HAB P&L'!$K10:$M10) | BW9: =SUM('SALT P&L'!$K10:$M10) | BX9: =SUM('KNL HO P&L'!$K10:$M10)+SUM('CCL HO P&L'!$K10:$M10)+SUM('YBHN HO P&L'!$K10:$M10)+SUM('YBN HO P&L'!$K10:$M10)+SUM('Moe2 P&L'!$K10:$M10) | BY9: =SUM(BG9:BX9) | BZ9: =BY9+BF9+AM9+T9
A10: Total Income | B10: =SUM('ABA P&L'!$B11:$D11) | C10: =SUM('BK P&L'!$B11:$D11) | D10: =SUM('BW P&L'!$B11:$D11) | E10: =SUM('CED P&L'!$B11:$D11) | F10: =SUM('HB P&L'!$B11:$D11) | G10: =SUM('KIN P&L'!$B11:$D11) | H10: =SUM('MER P&L'!$B11:$D11) | I10: =SUM('SST P&L'!$B11:$D11) | J10: =SUM('HDN P&L'!$B11:$D11) | K10: =SUM('NDN P&L'!$B11:$D11) | L10: =SUM('SDN P&L'!$B11:$D11) | M10: =SUM('LE P&L'!$B11:$D11) | N10: =SUM('WH P&L'!$B11:$D11) | O10: =SUM('HS P&L'!$B11:$D11) | P10: =SUM('FH P&L'!$B11:$D11) | Q10: =SUM('HAB P&L'!$B11:$D11) | R10: =SUM('SALT P&L'!$B11:$D11) | S10: =SUM('KNL HO P&L'!$B11:$D11)+SUM('CCL HO P&L'!$B11:$D11)+SUM('YBHN HO P&L'!$B11:$D11)+SUM('YBN HO P&L'!$B11:$D11)+SUM('Moe2 P&L'!$B11:$D11) | T10: =SUM(B10:S10) | U10: =SUM('ABA P&L'!$E11:$G11) | V10: =SUM('BK P&L'!$E11:$G11) | W10: =SUM('BW P&L'!$E11:$G11) | X10: =SUM('CED P&L'!$E11:$G11) | Y10: =SUM('HB P&L'!$E11:$G11) | Z10: =SUM('KIN P&L'!$E11:$G11) | AA10: =SUM('MER P&L'!$E11:$G11) | AB10: =SUM('SST P&L'!$E11:$G11) | AC10: =SUM('HDN P&L'!$E11:$G11) | AD10: =SUM('NDN P&L'!$E11:$G11) | AE10: =SUM('SDN P&L'!$E11:$G11) | AF10: =SUM('LE P&L'!$E11:$G11) | AG10: =SUM('WH P&L'!$E11:$G11) | AH10: =SUM('HS P&L'!$E11:$G11) | AI10: =SUM('FH P&L'!$E11:$G11) | AJ10: =SUM('HAB P&L'!$E11:$G11) | AK10: =SUM('SALT P&L'!$E11:$G11) | AL10: =SUM('KNL HO P&L'!$E11:$G11)+SUM('CCL HO P&L'!$E11:$G11)+SUM('YBHN HO P&L'!$E11:$G11)+SUM('YBN HO P&L'!$E11:$G11)+SUM('Moe2 P&L'!$E11:$G11) | AM10: =SUM(U10:AL10) | AN10: =SUM('ABA P&L'!$H11:$J11) | AO10: =SUM('BK P&L'!$H11:$J11) | AP10: =SUM('BW P&L'!$H11:$J11) | AQ10: =SUM('CED P&L'!$H11:$J11) | AR10: =SUM('HB P&L'!$H11:$J11) | AS10: =SUM('KIN P&L'!$H11:$J11) | AT10: =SUM('MER P&L'!$H11:$J11) | AU10: =SUM('SST P&L'!$H11:$J11) | AV10: =SUM('HDN P&L'!$H11:$J11) | AW10: =SUM('NDN P&L'!$H11:$J11) | AX10: =SUM('SDN P&L'!$H11:$J11) | AY10: =SUM('LE P&L'!$H11:$J11) | AZ10: =SUM('WH P&L'!$H11:$J11) | BA10: =SUM('HS P&L'!$H11:$J11) | BB10: =SUM('FH P&L'!$H11:$J11) | BC10: =SUM('HAB P&L'!$H11:$J11) | BD10: =SUM('SALT P&L'!$H11:$J11) | BE10: =SUM('KNL HO P&L'!$H11:$J11)+SUM('CCL HO P&L'!$H11:$J11)+SUM('YBHN HO P&L'!$H11:$J11)+SUM('YBN HO P&L'!$H11:$J11)+SUM('Moe2 P&L'!$H11:$J11) | BF10: =SUM(AN10:BE10) | BG10: =SUM('ABA P&L'!$K11:$M11) | BH10: =SUM('BK P&L'!$K11:$M11) | BI10: =SUM('BW P&L'!$K11:$M11) | BJ10: =SUM('CED P&L'!$K11:$M11) | BK10: =SUM('HB P&L'!$K11:$M11) | BL10: =SUM('KIN P&L'!$K11:$M11) | BM10: =SUM('MER P&L'!$K11:$M11) | BN10: =SUM('SST P&L'!$K11:$M11) | BO10: =SUM('HDN P&L'!$K11:$M11) | BP10: =SUM('NDN P&L'!$K11:$M11) | BQ10: =SUM('SDN P&L'!$K11:$M11) | BR10: =SUM('LE P&L'!$K11:$M11) | BS10: =SUM('WH P&L'!$K11:$M11) | BT10: =SUM('HS P&L'!$K11:$M11) | BU10: =SUM('FH P&L'!$K11:$M11) | BV10: =SUM('HAB P&L'!$K11:$M11) | BW10: =SUM('SALT P&L'!$K11:$M11) | BX10: =SUM('KNL HO P&L'!$K11:$M11)+SUM('CCL HO P&L'!$K11:$M11)+SUM('YBHN HO P&L'!$K11:$M11)+SUM('YBN HO P&L'!$K11:$M11)+SUM('Moe2 P&L'!$K11:$M11) | BY10: =SUM(BG10:BX10) | BZ10: =BY10+BF10+AM10+T10
A11: DIRECTCOSTS | B11: =SUM('ABA P&L'!$B12:$D12) | C11: =SUM('BK P&L'!$B12:$D12) | D11: =SUM('BW P&L'!$B12:$D12) | E11: =SUM('CED P&L'!$B12:$D12) | F11: =SUM('HB P&L'!$B12:$D12) | G11: =SUM('KIN P&L'!$B12:$D12) | H11: =SUM('MER P&L'!$B12:$D12) | I11: =SUM('SST P&L'!$B12:$D12) | J11: =SUM('HDN P&L'!$B12:$D12) | K11: =SUM('NDN P&L'!$B12:$D12) | L11: =SUM('SDN P&L'!$B12:$D12) | M11: =SUM('LE P&L'!$B12:$D12) | N11: =SUM('WH P&L'!$B12:$D12) | O11: =SUM('HS P&L'!$B12:$D12) | P11: =SUM('FH P&L'!$B12:$D12) | Q11: =SUM('HAB P&L'!$B12:$D12) | R11: =SUM('SALT P&L'!$B12:$D12) | S11: =SUM('KNL HO P&L'!$B12:$D12)+SUM('CCL HO P&L'!$B12:$D12)+SUM('YBHN HO P&L'!$B12:$D12)+SUM('YBN HO P&L'!$B12:$D12)+SUM('Moe2 P&L'!$B12:$D12) | T11: =SUM(B11:S11) | U11: =SUM('ABA P&L'!$E12:$G12) | V11: =SUM('BK P&L'!$E12:$G12) | W11: =SUM('BW P&L'!$E12:$G12) | X11: =SUM('CED P&L'!$E12:$G12) | Y11: =SUM('HB P&L'!$E12:$G12) | Z11: =SUM('KIN P&L'!$E12:$G12) | AA11: =SUM('MER P&L'!$E12:$G12) | AB11: =SUM('SST P&L'!$E12:$G12) | AC11: =SUM('HDN P&L'!$E12:$G12) | AD11: =SUM('NDN P&L'!$E12:$G12) | AE11: =SUM('SDN P&L'!$E12:$G12) | AF11: =SUM('LE P&L'!$E12:$G12) | AG11: =SUM('WH P&L'!$E12:$G12) | AH11: =SUM('HS P&L'!$E12:$G12) | AI11: =SUM('FH P&L'!$E12:$G12) | AJ11: =SUM('HAB P&L'!$E12:$G12) | AK11: =SUM('SALT P&L'!$E12:$G12) | AL11: =SUM('KNL HO P&L'!$E12:$G12)+SUM('CCL HO P&L'!$E12:$G12)+SUM('YBHN HO P&L'!$E12:$G12)+SUM('YBN HO P&L'!$E12:$G12)+SUM('Moe2 P&L'!$E12:$G12) | AM11: =SUM(U11:AL11) | AN11: =SUM('ABA P&L'!$H12:$J12) | AO11: =SUM('BK P&L'!$H12:$J12) | AP11: =SUM('BW P&L'!$H12:$J12) | AQ11: =SUM('CED P&L'!$H12:$J12) | AR11: =SUM('HB P&L'!$H12:$J12) | AS11: =SUM('KIN P&L'!$H12:$J12) | AT11: =SUM('MER P&L'!$H12:$J12) | AU11: =SUM('SST P&L'!$H12:$J12) | AV11: =SUM('HDN P&L'!$H12:$J12) | AW11: =SUM('NDN P&L'!$H12:$J12) | AX11: =SUM('SDN P&L'!$H12:$J12) | AY11: =SUM('LE P&L'!$H12:$J12) | AZ11: =SUM('WH P&L'!$H12:$J12) | BA11: =SUM('HS P&L'!$H12:$J12) | BB11: =SUM('FH P&L'!$H12:$J12) | BC11: =SUM('HAB P&L'!$H12:$J12) | BD11: =SUM('SALT P&L'!$H12:$J12) | BE11: =SUM('KNL HO P&L'!$H12:$J12)+SUM('CCL HO P&L'!$H12:$J12)+SUM('YBHN HO P&L'!$H12:$J12)+SUM('YBN HO P&L'!$H12:$J12)+SUM('Moe2 P&L'!$H12:$J12) | BF11: =SUM(AN11:BE11) | BG11: =SUM('ABA P&L'!$K12:$M12) | BH11: =SUM('BK P&L'!$K12:$M12) | BI11: =SUM('BW P&L'!$K12:$M12) | BJ11: =SUM('CED P&L'!$K12:$M12) | BK11: =SUM('HB P&L'!$K12:$M12) | BL11: =SUM('KIN P&L'!$K12:$M12) | BM11: =SUM('MER P&L'!$K12:$M12) | BN11: =SUM('SST P&L'!$K12:$M12) | BO11: =SUM('HDN P&L'!$K12:$M12) | BP11: =SUM('NDN P&L'!$K12:$M12) | BQ11: =SUM('SDN P&L'!$K12:$M12) | BR11: =SUM('LE P&L'!$K12:$M12) | BS11: =SUM('WH P&L'!$K12:$M12) | BT11: =SUM('HS P&L'!$K12:$M12) | BU11: =SUM('FH P&L'!$K12:$M12) | BV11: =SUM('HAB P&L'!$K12:$M12) | BW11: =SUM('SALT P&L'!$K12:$M12) | BX11: =SUM('KNL HO P&L'!$K12:$M12)+SUM('CCL HO P&L'!$K12:$M12)+SUM('YBHN HO P&L'!$K12:$M12)+SUM('YBN HO P&L'!$K12:$M12)+SUM('Moe2 P&L'!$K12:$M12) | BY11: =SUM(BG11:BX11) | BZ11: =BY11+BF11+AM11+T11
A12: Personnel | B12: =SUM('ABA P&L'!$B15:$D15) | C12: =SUM('BK P&L'!$B15:$D15) | D12: =SUM('BW P&L'!$B15:$D15) | E12: =SUM('CED P&L'!$B15:$D15) | F12: =SUM('HB P&L'!$B15:$D15) | G12: =SUM('KIN P&L'!$B15:$D15) | H12: =SUM('MER P&L'!$B15:$D15) | I12: =SUM('SST P&L'!$B15:$D15) | J12: =SUM('HDN P&L'!$B15:$D15) | K12: =SUM('NDN P&L'!$B15:$D15) | L12: =SUM('SDN P&L'!$B15:$D15) | M12: =SUM('LE P&L'!$B15:$D15) | N12: =SUM('WH P&L'!$B15:$D15) | O12: =SUM('HS P&L'!$B15:$D15) | P12: =SUM('FH P&L'!$B15:$D15) | Q12: =SUM('HAB P&L'!$B15:$D15) | R12: =SUM('SALT P&L'!$B15:$D15) | S12: =SUM('KNL HO P&L'!$B15:$D15)+SUM('CCL HO P&L'!$B15:$D15)+SUM('YBHN HO P&L'!$B15:$D15)+SUM('YBN HO P&L'!$B15:$D15)+SUM('Moe2 P&L'!$B15:$D15) | T12: =SUM(B12:S12) | U12: =SUM('ABA P&L'!$E15:$G15) | V12: =SUM('BK P&L'!$E15:$G15) | W12: =SUM('BW P&L'!$E15:$G15) | X12: =SUM('CED P&L'!$E15:$G15) | Y12: =SUM('HB P&L'!$E15:$G15) | Z12: =SUM('KIN P&L'!$E15:$G15) | AA12: =SUM('MER P&L'!$E15:$G15) | AB12: =SUM('SST P&L'!$E15:$G15) | AC12: =SUM('HDN P&L'!$E15:$G15) | AD12: =SUM('NDN P&L'!$E15:$G15) | AE12: =SUM('SDN P&L'!$E15:$G15) | AF12: =SUM('LE P&L'!$E15:$G15) | AG12: =SUM('WH P&L'!$E15:$G15) | AH12: =SUM('HS P&L'!$E15:$G15) | AI12: =SUM('FH P&L'!$E15:$G15) | AJ12: =SUM('HAB P&L'!$E15:$G15) | AK12: =SUM('SALT P&L'!$E15:$G15) | AL12: =SUM('KNL HO P&L'!$E15:$G15)+SUM('CCL HO P&L'!$E15:$G15)+SUM('YBHN HO P&L'!$E15:$G15)+SUM('YBN HO P&L'!$E15:$G15)+SUM('Moe2 P&L'!$E15:$G15) | AM12: =SUM(U12:AL12) | AN12: =SUM('ABA P&L'!$H15:$J15) | AO12: =SUM('BK P&L'!$H15:$J15) | AP12: =SUM('BW P&L'!$H15:$J15) | AQ12: =SUM('CED P&L'!$H15:$J15) | AR12: =SUM('HB P&L'!$H15:$J15) | AS12: =SUM('KIN P&L'!$H15:$J15) | AT12: =SUM('MER P&L'!$H15:$J15) | AU12: =SUM('SST P&L'!$H15:$J15) | AV12: =SUM('HDN P&L'!$H15:$J15) | AW12: =SUM('NDN P&L'!$H15:$J15) | AX12: =SUM('SDN P&L'!$H15:$J15) | AY12: =SUM('LE P&L'!$H15:$J15) | AZ12: =SUM('WH P&L'!$H15:$J15) | BA12: =SUM('HS P&L'!$H15:$J15) | BB12: =SUM('FH P&L'!$H15:$J15) | BC12: =SUM('HAB P&L'!$H15:$J15) | BD12: =SUM('SALT P&L'!$H15:$J15) | BE12: =SUM('KNL HO P&L'!$H15:$J15)+SUM('CCL HO P&L'!$H15:$J15)+SUM('YBHN HO P&L'!$H15:$J15)+SUM('YBN HO P&L'!$H15:$J15)+SUM('Moe2 P&L'!$H15:$J15) | BF12: =SUM(AN12:BE12) | BG12: =SUM('ABA P&L'!$K15:$M15) | BH12: =SUM('BK P&L'!$K15:$M15) | BI12: =SUM('BW P&L'!$K15:$M15) | BJ12: =SUM('CED P&L'!$K15:$M15) | BK12: =SUM('HB P&L'!$K15:$M15) | BL12: =SUM('KIN P&L'!$K15:$M15) | BM12: =SUM('MER P&L'!$K15:$M15) | BN12: =SUM('SST P&L'!$K15:$M15) | BO12: =SUM('HDN P&L'!$K15:$M15) | BP12: =SUM('NDN P&L'!$K15:$M15) | BQ12: =SUM('SDN P&L'!$K15:$M15) | BR12: =SUM('LE P&L'!$K15:$M15) | BS12: =SUM('WH P&L'!$K15:$M15) | BT12: =SUM('HS P&L'!$K15:$M15) | BU12: =SUM('FH P&L'!$K15:$M15) | BV12: =SUM('HAB P&L'!$K15:$M15) | BW12: =SUM('SALT P&L'!$K15:$M15) | BX12: =SUM('KNL HO P&L'!$K15:$M15)+SUM('CCL HO P&L'!$K15:$M15)+SUM('YBHN HO P&L'!$K15:$M15)+SUM('YBN HO P&L'!$K15:$M15)+SUM('Moe2 P&L'!$K15:$M15) | BY12: =SUM(BG12:BX12) | BZ12: =BY12+BF12+AM12+T12
A13: Nursery Salaries | B13: =SUM('ABA P&L'!$B16:$D16) | C13: =SUM('BK P&L'!$B16:$D16) | D13: =SUM('BW P&L'!$B16:$D16) | E13: =SUM('CED P&L'!$B16:$D16) | F13: =SUM('HB P&L'!$B16:$D16) | G13: =SUM('KIN P&L'!$B16:$D16) | H13: =SUM('MER P&L'!$B16:$D16) | I13: =SUM('SST P&L'!$B16:$D16) | J13: =SUM('HDN P&L'!$B16:$D16) | K13: =SUM('NDN P&L'!$B16:$D16) | L13: =SUM('SDN P&L'!$B16:$D16) | M13: =SUM('LE P&L'!$B16:$D16) | N13: =SUM('WH P&L'!$B16:$D16) | O13: =SUM('HS P&L'!$B16:$D16) | P13: =SUM('FH P&L'!$B16:$D16) | Q13: =SUM('HAB P&L'!$B16:$D16) | R13: =SUM('SALT P&L'!$B16:$D16) | S13: =SUM('KNL HO P&L'!$B16:$D16)+SUM('CCL HO P&L'!$B16:$D16)+SUM('YBHN HO P&L'!$B16:$D16)+SUM('YBN HO P&L'!$B16:$D16)+SUM('Moe2 P&L'!$B16:$D16) | T13: =SUM(B13:S13) | U13: =SUM('ABA P&L'!$E16:$G16) | V13: =SUM('BK P&L'!$E16:$G16) | W13: =SUM('BW P&L'!$E16:$G16) | X13: =SUM('CED P&L'!$E16:$G16) | Y13: =SUM('HB P&L'!$E16:$G16) | Z13: =SUM('KIN P&L'!$E16:$G16) | AA13: =SUM('MER P&L'!$E16:$G16) | AB13: =SUM('SST P&L'!$E16:$G16) | AC13: =SUM('HDN P&L'!$E16:$G16) | AD13: =SUM('NDN P&L'!$E16:$G16) | AE13: =SUM('SDN P&L'!$E16:$G16) | AF13: =SUM('LE P&L'!$E16:$G16) | AG13: =SUM('WH P&L'!$E16:$G16) | AH13: =SUM('HS P&L'!$E16:$G16) | AI13: =SUM('FH P&L'!$E16:$G16) | AJ13: =SUM('HAB P&L'!$E16:$G16) | AK13: =SUM('SALT P&L'!$E16:$G16) | AL13: =SUM('KNL HO P&L'!$E16:$G16)+SUM('CCL HO P&L'!$E16:$G16)+SUM('YBHN HO P&L'!$E16:$G16)+SUM('YBN HO P&L'!$E16:$G16)+SUM('Moe2 P&L'!$E16:$G16) | AM13: =SUM(U13:AL13) | AN13: =SUM('ABA P&L'!$H16:$J16) | AO13: =SUM('BK P&L'!$H16:$J16) | AP13: =SUM('BW P&L'!$H16:$J16) | AQ13: =SUM('CED P&L'!$H16:$J16) | AR13: =SUM('HB P&L'!$H16:$J16) | AS13: =SUM('KIN P&L'!$H16:$J16) | AT13: =SUM('MER P&L'!$H16:$J16) | AU13: =SUM('SST P&L'!$H16:$J16) | AV13: =SUM('HDN P&L'!$H16:$J16) | AW13: =SUM('NDN P&L'!$H16:$J16) | AX13: =SUM('SDN P&L'!$H16:$J16) | AY13: =SUM('LE P&L'!$H16:$J16) | AZ13: =SUM('WH P&L'!$H16:$J16) | BA13: =SUM('HS P&L'!$H16:$J16) | BB13: =SUM('FH P&L'!$H16:$J16) | BC13: =SUM('HAB P&L'!$H16:$J16) | BD13: =SUM('SALT P&L'!$H16:$J16) | BE13: =SUM('KNL HO P&L'!$H16:$J16)+SUM('CCL HO P&L'!$H16:$J16)+SUM('YBHN HO P&L'!$H16:$J16)+SUM('YBN HO P&L'!$H16:$J16)+SUM('Moe2 P&L'!$H16:$J16) | BF13: =SUM(AN13:BE13) | BG13: =SUM('ABA P&L'!$K16:$M16) | BH13: =SUM('BK P&L'!$K16:$M16) | BI13: =SUM('BW P&L'!$K16:$M16) | BJ13: =SUM('CED P&L'!$K16:$M16) | BK13: =SUM('HB P&L'!$K16:$M16) | BL13: =SUM('KIN P&L'!$K16:$M16) | BM13: =SUM('MER P&L'!$K16:$M16) | BN13: =SUM('SST P&L'!$K16:$M16) | BO13: =SUM('HDN P&L'!$K16:$M16) | BP13: =SUM('NDN P&L'!$K16:$M16) | BQ13: =SUM('SDN P&L'!$K16:$M16) | BR13: =SUM('LE P&L'!$K16:$M16) | BS13: =SUM('WH P&L'!$K16:$M16) | BT13: =SUM('HS P&L'!$K16:$M16) | BU13: =SUM('FH P&L'!$K16:$M16) | BV13: =SUM('HAB P&L'!$K16:$M16) | BW13: =SUM('SALT P&L'!$K16:$M16) | BX13: =SUM('KNL HO P&L'!$K16:$M16)+SUM('CCL HO P&L'!$K16:$M16)+SUM('YBHN HO P&L'!$K16:$M16)+SUM('YBN HO P&L'!$K16:$M16)+SUM('Moe2 P&L'!$K16:$M16) | BY13: =SUM(BG13:BX13) | BZ13: =BY13+BF13+AM13+T13
A14: Nursery NI | B14: =SUM('ABA P&L'!$B17:$D17) | C14: =SUM('BK P&L'!$B17:$D17) | D14: =SUM('BW P&L'!$B17:$D17) | E14: =SUM('CED P&L'!$B17:$D17) | F14: =SUM('HB P&L'!$B17:$D17) | G14: =SUM('KIN P&L'!$B17:$D17) | H14: =SUM('MER P&L'!$B17:$D17) | I14: =SUM('SST P&L'!$B17:$D17) | J14: =SUM('HDN P&L'!$B17:$D17) | K14: =SUM('NDN P&L'!$B17:$D17) | L14: =SUM('SDN P&L'!$B17:$D17) | M14: =SUM('LE P&L'!$B17:$D17) | N14: =SUM('WH P&L'!$B17:$D17) | O14: =SUM('HS P&L'!$B17:$D17) | P14: =SUM('FH P&L'!$B17:$D17) | Q14: =SUM('HAB P&L'!$B17:$D17) | R14: =SUM('SALT P&L'!$B17:$D17) | S14: =SUM('KNL HO P&L'!$B17:$D17)+SUM('CCL HO P&L'!$B17:$D17)+SUM('YBHN HO P&L'!$B17:$D17)+SUM('YBN HO P&L'!$B17:$D17)+SUM('Moe2 P&L'!$B17:$D17) | T14: =SUM(B14:S14) | U14: =SUM('ABA P&L'!$E17:$G17) | V14: =SUM('BK P&L'!$E17:$G17) | W14: =SUM('BW P&L'!$E17:$G17) | X14: =SUM('CED P&L'!$E17:$G17) | Y14: =SUM('HB P&L'!$E17:$G17) | Z14: =SUM('KIN P&L'!$E17:$G17) | AA14: =SUM('MER P&L'!$E17:$G17) | AB14: =SUM('SST P&L'!$E17:$G17) | AC14: =SUM('HDN P&L'!$E17:$G17) | AD14: =SUM('NDN P&L'!$E17:$G17) | AE14: =SUM('SDN P&L'!$E17:$G17) | AF14: =SUM('LE P&L'!$E17:$G17) | AG14: =SUM('WH P&L'!$E17:$G17) | AH14: =SUM('HS P&L'!$E17:$G17) | AI14: =SUM('FH P&L'!$E17:$G17) | AJ14: =SUM('HAB P&L'!$E17:$G17) | AK14: =SUM('SALT P&L'!$E17:$G17) | AL14: =SUM('KNL HO P&L'!$E17:$G17)+SUM('CCL HO P&L'!$E17:$G17)+SUM('YBHN HO P&L'!$E17:$G17)+SUM('YBN HO P&L'!$E17:$G17)+SUM('Moe2 P&L'!$E17:$G17) | AM14: =SUM(U14:AL14) | AN14: =SUM('ABA P&L'!$H17:$J17) | AO14: =SUM('BK P&L'!$H17:$J17) | AP14: =SUM('BW P&L'!$H17:$J17) | AQ14: =SUM('CED P&L'!$H17:$J17) | AR14: =SUM('HB P&L'!$H17:$J17) | AS14: =SUM('KIN P&L'!$H17:$J17) | AT14: =SUM('MER P&L'!$H17:$J17) | AU14: =SUM('SST P&L'!$H17:$J17) | AV14: =SUM('HDN P&L'!$H17:$J17) | AW14: =SUM('NDN P&L'!$H17:$J17) | AX14: =SUM('SDN P&L'!$H17:$J17) | AY14: =SUM('LE P&L'!$H17:$J17) | AZ14: =SUM('WH P&L'!$H17:$J17) | BA14: =SUM('HS P&L'!$H17:$J17) | BB14: =SUM('FH P&L'!$H17:$J17) | BC14: =SUM('HAB P&L'!$H17:$J17) | BD14: =SUM('SALT P&L'!$H17:$J17) | BE14: =SUM('KNL HO P&L'!$H17:$J17)+SUM('CCL HO P&L'!$H17:$J17)+SUM('YBHN HO P&L'!$H17:$J17)+SUM('YBN HO P&L'!$H17:$J17)+SUM('Moe2 P&L'!$H17:$J17) | BF14: =SUM(AN14:BE14) | BG14: =SUM('ABA P&L'!$K17:$M17) | BH14: =SUM('BK P&L'!$K17:$M17) | BI14: =SUM('BW P&L'!$K17:$M17) | BJ14: =SUM('CED P&L'!$K17:$M17) | BK14: =SUM('HB P&L'!$K17:$M17) | BL14: =SUM('KIN P&L'!$K17:$M17) | BM14: =SUM('MER P&L'!$K17:$M17) | BN14: =SUM('SST P&L'!$K17:$M17) | BO14: =SUM('HDN P&L'!$K17:$M17) | BP14: =SUM('NDN P&L'!$K17:$M17) | BQ14: =SUM('SDN P&L'!$K17:$M17) | BR14: =SUM('LE P&L'!$K17:$M17) | BS14: =SUM('WH P&L'!$K17:$M17) | BT14: =SUM('HS P&L'!$K17:$M17) | BU14: =SUM('FH P&L'!$K17:$M17) | BV14: =SUM('HAB P&L'!$K17:$M17) | BW14: =SUM('SALT P&L'!$K17:$M17) | BX14: =SUM('KNL HO P&L'!$K17:$M17)+SUM('CCL HO P&L'!$K17:$M17)+SUM('YBHN HO P&L'!$K17:$M17)+SUM('YBN HO P&L'!$K17:$M17)+SUM('Moe2 P&L'!$K17:$M17) | BY14: =SUM(BG14:BX14) | BZ14: =BY14+BF14+AM14+T14
A15: Nursery Pension | B15: =SUM('ABA P&L'!$B18:$D18) | C15: =SUM('BK P&L'!$B18:$D18) | D15: =SUM('BW P&L'!$B18:$D18) | E15: =SUM('CED P&L'!$B18:$D18) | F15: =SUM('HB P&L'!$B18:$D18) | G15: =SUM('KIN P&L'!$B18:$D18) | H15: =SUM('MER P&L'!$B18:$D18) | I15: =SUM('SST P&L'!$B18:$D18) | J15: =SUM('HDN P&L'!$B18:$D18) | K15: =SUM('NDN P&L'!$B18:$D18) | L15: =SUM('SDN P&L'!$B18:$D18) | M15: =SUM('LE P&L'!$B18:$D18) | N15: =SUM('WH P&L'!$B18:$D18) | O15: =SUM('HS P&L'!$B18:$D18) | P15: =SUM('FH P&L'!$B18:$D18) | Q15: =SUM('HAB P&L'!$B18:$D18) | R15: =SUM('SALT P&L'!$B18:$D18) | S15: =SUM('KNL HO P&L'!$B18:$D18)+SUM('CCL HO P&L'!$B18:$D18)+SUM('YBHN HO P&L'!$B18:$D18)+SUM('YBN HO P&L'!$B18:$D18)+SUM('Moe2 P&L'!$B18:$D18) | T15: =SUM(B15:S15) | U15: =SUM('ABA P&L'!$E18:$G18) | V15: =SUM('BK P&L'!$E18:$G18) | W15: =SUM('BW P&L'!$E18:$G18) | X15: =SUM('CED P&L'!$E18:$G18) | Y15: =SUM('HB P&L'!$E18:$G18) | Z15: =SUM('KIN P&L'!$E18:$G18) | AA15: =SUM('MER P&L'!$E18:$G18) | AB15: =SUM('SST P&L'!$E18:$G18) | AC15: =SUM('HDN P&L'!$E18:$G18) | AD15: =SUM('NDN P&L'!$E18:$G18) | AE15: =SUM('SDN P&L'!$E18:$G18) | AF15: =SUM('LE P&L'!$E18:$G18) | AG15: =SUM('WH P&L'!$E18:$G18) | AH15: =SUM('HS P&L'!$E18:$G18) | AI15: =SUM('FH P&L'!$E18:$G18) | AJ15: =SUM('HAB P&L'!$E18:$G18) | AK15: =SUM('SALT P&L'!$E18:$G18) | AL15: =SUM('KNL HO P&L'!$E18:$G18)+SUM('CCL HO P&L'!$E18:$G18)+SUM('YBHN HO P&L'!$E18:$G18)+SUM('YBN HO P&L'!$E18:$G18)+SUM('Moe2 P&L'!$E18:$G18) | AM15: =SUM(U15:AL15) | AN15: =SUM('ABA P&L'!$H18:$J18) | AO15: =SUM('BK P&L'!$H18:$J18) | AP15: =SUM('BW P&L'!$H18:$J18) | AQ15: =SUM('CED P&L'!$H18:$J18) | AR15: =SUM('HB P&L'!$H18:$J18) | AS15: =SUM('KIN P&L'!$H18:$J18) | AT15: =SUM('MER P&L'!$H18:$J18) | AU15: =SUM('SST P&L'!$H18:$J18) | AV15: =SUM('HDN P&L'!$H18:$J18) | AW15: =SUM('NDN P&L'!$H18:$J18) | AX15: =SUM('SDN P&L'!$H18:$J18) | AY15: =SUM('LE P&L'!$H18:$J18) | AZ15: =SUM('WH P&L'!$H18:$J18) | BA15: =SUM('HS P&L'!$H18:$J18) | BB15: =SUM('FH P&L'!$H18:$J18) | BC15: =SUM('HAB P&L'!$H18:$J18) | BD15: =SUM('SALT P&L'!$H18:$J18) | BE15: =SUM('KNL HO P&L'!$H18:$J18)+SUM('CCL HO P&L'!$H18:$J18)+SUM('YBHN HO P&L'!$H18:$J18)+SUM('YBN HO P&L'!$H18:$J18)+SUM('Moe2 P&L'!$H18:$J18) | BF15: =SUM(AN15:BE15) | BG15: =SUM('ABA P&L'!$K18:$M18) | BH15: =SUM('BK P&L'!$K18:$M18) | BI15: =SUM('BW P&L'!$K18:$M18) | BJ15: =SUM('CED P&L'!$K18:$M18) | BK15: =SUM('HB P&L'!$K18:$M18) | BL15: =SUM('KIN P&L'!$K18:$M18) | BM15: =SUM('MER P&L'!$K18:$M18) | BN15: =SUM('SST P&L'!$K18:$M18) | BO15: =SUM('HDN P&L'!$K18:$M18) | BP15: =SUM('NDN P&L'!$K18:$M18) | BQ15: =SUM('SDN P&L'!$K18:$M18) | BR15: =SUM('LE P&L'!$K18:$M18) | BS15: =SUM('WH P&L'!$K18:$M18) | BT15: =SUM('HS P&L'!$K18:$M18) | BU15: =SUM('FH P&L'!$K18:$M18) | BV15: =SUM('HAB P&L'!$K18:$M18) | BW15: =SUM('SALT P&L'!$K18:$M18) | BX15: =SUM('KNL HO P&L'!$K18:$M18)+SUM('CCL HO P&L'!$K18:$M18)+SUM('YBHN HO P&L'!$K18:$M18)+SUM('YBN HO P&L'!$K18:$M18)+SUM('Moe2 P&L'!$K18:$M18) | BY15: =SUM(BG15:BX15) | BZ15: =BY15+BF15+AM15+T15
A16: Uniform | B16: =SUM('ABA P&L'!$B19:$D19) | C16: =SUM('BK P&L'!$B19:$D19) | D16: =SUM('BW P&L'!$B19:$D19) | E16: =SUM('CED P&L'!$B19:$D19) | F16: =SUM('HB P&L'!$B19:$D19) | G16: =SUM('KIN P&L'!$B19:$D19) | H16: =SUM('MER P&L'!$B19:$D19) | I16: =SUM('SST P&L'!$B19:$D19) | J16: =SUM('HDN P&L'!$B19:$D19) | K16: =SUM('NDN P&L'!$B19:$D19) | L16: =SUM('SDN P&L'!$B19:$D19) | M16: =SUM('LE P&L'!$B19:$D19) | N16: =SUM('WH P&L'!$B19:$D19) | O16: =SUM('HS P&L'!$B19:$D19) | P16: =SUM('FH P&L'!$B19:$D19) | Q16: =SUM('HAB P&L'!$B19:$D19) | R16: =SUM('SALT P&L'!$B19:$D19) | S16: =SUM('KNL HO P&L'!$B19:$D19)+SUM('CCL HO P&L'!$B19:$D19)+SUM('YBHN HO P&L'!$B19:$D19)+SUM('YBN HO P&L'!$B19:$D19)+SUM('Moe2 P&L'!$B19:$D19) | T16: =SUM(B16:S16) | U16: =SUM('ABA P&L'!$E19:$G19) | V16: =SUM('BK P&L'!$E19:$G19) | W16: =SUM('BW P&L'!$E19:$G19) | X16: =SUM('CED P&L'!$E19:$G19) | Y16: =SUM('HB P&L'!$E19:$G19) | Z16: =SUM('KIN P&L'!$E19:$G19) | AA16: =SUM('MER P&L'!$E19:$G19) | AB16: =SUM('SST P&L'!$E19:$G19) | AC16: =SUM('HDN P&L'!$E19:$G19) | AD16: =SUM('NDN P&L'!$E19:$G19) | AE16: =SUM('SDN P&L'!$E19:$G19) | AF16: =SUM('LE P&L'!$E19:$G19) | AG16: =SUM('WH P&L'!$E19:$G19) | AH16: =SUM('HS P&L'!$E19:$G19) | AI16: =SUM('FH P&L'!$E19:$G19) | AJ16: =SUM('HAB P&L'!$E19:$G19) | AK16: =SUM('SALT P&L'!$E19:$G19) | AL16: =SUM('KNL HO P&L'!$E19:$G19)+SUM('CCL HO P&L'!$E19:$G19)+SUM('YBHN HO P&L'!$E19:$G19)+SUM('YBN HO P&L'!$E19:$G19)+SUM('Moe2 P&L'!$E19:$G19) | AM16: =SUM(U16:AL16) | AN16: =SUM('ABA P&L'!$H19:$J19) | AO16: =SUM('BK P&L'!$H19:$J19) | AP16: =SUM('BW P&L'!$H19:$J19) | AQ16: =SUM('CED P&L'!$H19:$J19) | AR16: =SUM('HB P&L'!$H19:$J19) | AS16: =SUM('KIN P&L'!$H19:$J19) | AT16: =SUM('MER P&L'!$H19:$J19) | AU16: =SUM('SST P&L'!$H19:$J19) | AV16: =SUM('HDN P&L'!$H19:$J19) | AW16: =SUM('NDN P&L'!$H19:$J19) | AX16: =SUM('SDN P&L'!$H19:$J19) | AY16: =SUM('LE P&L'!$H19:$J19) | AZ16: =SUM('WH P&L'!$H19:$J19) | BA16: =SUM('HS P&L'!$H19:$J19) | BB16: =SUM('FH P&L'!$H19:$J19) | BC16: =SUM('HAB P&L'!$H19:$J19) | BD16: =SUM('SALT P&L'!$H19:$J19) | BE16: =SUM('KNL HO P&L'!$H19:$J19)+SUM('CCL HO P&L'!$H19:$J19)+SUM('YBHN HO P&L'!$H19:$J19)+SUM('YBN HO P&L'!$H19:$J19)+SUM('Moe2 P&L'!$H19:$J19) | BF16: =SUM(AN16:BE16) | BG16: =SUM('ABA P&L'!$K19:$M19) | BH16: =SUM('BK P&L'!$K19:$M19) | BI16: =SUM('BW P&L'!$K19:$M19) | BJ16: =SUM('CED P&L'!$K19:$M19) | BK16: =SUM('HB P&L'!$K19:$M19) | BL16: =SUM('KIN P&L'!$K19:$M19) | BM16: =SUM('MER P&L'!$K19:$M19) | BN16: =SUM('SST P&L'!$K19:$M19) | BO16: =SUM('HDN P&L'!$K19:$M19) | BP16: =SUM('NDN P&L'!$K19:$M19) | BQ16: =SUM('SDN P&L'!$K19:$M19) | BR16: =SUM('LE P&L'!$K19:$M19) | BS16: =SUM('WH P&L'!$K19:$M19) | BT16: =SUM('HS P&L'!$K19:$M19) | BU16: =SUM('FH P&L'!$K19:$M19) | BV16: =SUM('HAB P&L'!$K19:$M19) | BW16: =SUM('SALT P&L'!$K19:$M19) | BX16: =SUM('KNL HO P&L'!$K19:$M19)+SUM('CCL HO P&L'!$K19:$M19)+SUM('YBHN HO P&L'!$K19:$M19)+SUM('YBN HO P&L'!$K19:$M19)+SUM('Moe2 P&L'!$K19:$M19) | BY16: =SUM(BG16:BX16) | BZ16: =BY16+BF16+AM16+T16
A17: Training | B17: =SUM('ABA P&L'!$B20:$D20) | C17: =SUM('BK P&L'!$B20:$D20) | D17: =SUM('BW P&L'!$B20:$D20) | E17: =SUM('CED P&L'!$B20:$D20) | F17: =SUM('HB P&L'!$B20:$D20) | G17: =SUM('KIN P&L'!$B20:$D20) | H17: =SUM('MER P&L'!$B20:$D20) | I17: =SUM('SST P&L'!$B20:$D20) | J17: =SUM('HDN P&L'!$B20:$D20) | K17: =SUM('NDN P&L'!$B20:$D20) | L17: =SUM('SDN P&L'!$B20:$D20) | M17: =SUM('LE P&L'!$B20:$D20) | N17: =SUM('WH P&L'!$B20:$D20) | O17: =SUM('HS P&L'!$B20:$D20) | P17: =SUM('FH P&L'!$B20:$D20) | Q17: =SUM('HAB P&L'!$B20:$D20) | R17: =SUM('SALT P&L'!$B20:$D20) | S17: =SUM('KNL HO P&L'!$B20:$D20)+SUM('CCL HO P&L'!$B20:$D20)+SUM('YBHN HO P&L'!$B20:$D20)+SUM('YBN HO P&L'!$B20:$D20)+SUM('Moe2 P&L'!$B20:$D20) | T17: =SUM(B17:S17) | U17: =SUM('ABA P&L'!$E20:$G20) | V17: =SUM('BK P&L'!$E20:$G20) | W17: =SUM('BW P&L'!$E20:$G20) | X17: =SUM('CED P&L'!$E20:$G20) | Y17: =SUM('HB P&L'!$E20:$G20) | Z17: =SUM('KIN P&L'!$E20:$G20) | AA17: =SUM('MER P&L'!$E20:$G20) | AB17: =SUM('SST P&L'!$E20:$G20) | AC17: =SUM('HDN P&L'!$E20:$G20) | AD17: =SUM('NDN P&L'!$E20:$G20) | AE17: =SUM('SDN P&L'!$E20:$G20) | AF17: =SUM('LE P&L'!$E20:$G20) | AG17: =SUM('WH P&L'!$E20:$G20) | AH17: =SUM('HS P&L'!$E20:$G20) | AI17: =SUM('FH P&L'!$E20:$G20) | AJ17: =SUM('HAB P&L'!$E20:$G20) | AK17: =SUM('SALT P&L'!$E20:$G20) | AL17: =SUM('KNL HO P&L'!$E20:$G20)+SUM('CCL HO P&L'!$E20:$G20)+SUM('YBHN HO P&L'!$E20:$G20)+SUM('YBN HO P&L'!$E20:$G20)+SUM('Moe2 P&L'!$E20:$G20) | AM17: =SUM(U17:AL17) | AN17: =SUM('ABA P&L'!$H20:$J20) | AO17: =SUM('BK P&L'!$H20:$J20) | AP17: =SUM('BW P&L'!$H20:$J20) | AQ17: =SUM('CED P&L'!$H20:$J20) | AR17: =SUM('HB P&L'!$H20:$J20) | AS17: =SUM('KIN P&L'!$H20:$J20) | AT17: =SUM('MER P&L'!$H20:$J20) | AU17: =SUM('SST P&L'!$H20:$J20) | AV17: =SUM('HDN P&L'!$H20:$J20) | AW17: =SUM('NDN P&L'!$H20:$J20) | AX17: =SUM('SDN P&L'!$H20:$J20) | AY17: =SUM('LE P&L'!$H20:$J20) | AZ17: =SUM('WH P&L'!$H20:$J20) | BA17: =SUM('HS P&L'!$H20:$J20) | BB17: =SUM('FH P&L'!$H20:$J20) | BC17: =SUM('HAB P&L'!$H20:$J20) | BD17: =SUM('SALT P&L'!$H20:$J20) | BE17: =SUM('KNL HO P&L'!$H20:$J20)+SUM('CCL HO P&L'!$H20:$J20)+SUM('YBHN HO P&L'!$H20:$J20)+SUM('YBN HO P&L'!$H20:$J20)+SUM('Moe2 P&L'!$H20:$J20) | BF17: =SUM(AN17:BE17) | BG17: =SUM('ABA P&L'!$K20:$M20) | BH17: =SUM('BK P&L'!$K20:$M20) | BI17: =SUM('BW P&L'!$K20:$M20) | BJ17: =SUM('CED P&L'!$K20:$M20) | BK17: =SUM('HB P&L'!$K20:$M20) | BL17: =SUM('KIN P&L'!$K20:$M20) | BM17: =SUM('MER P&L'!$K20:$M20) | BN17: =SUM('SST P&L'!$K20:$M20) | BO17: =SUM('HDN P&L'!$K20:$M20) | BP17: =SUM('NDN P&L'!$K20:$M20) | BQ17: =SUM('SDN P&L'!$K20:$M20) | BR17: =SUM('LE P&L'!$K20:$M20) | BS17: =SUM('WH P&L'!$K20:$M20) | BT17: =SUM('HS P&L'!$K20:$M20) | BU17: =SUM('FH P&L'!$K20:$M20) | BV17: =SUM('HAB P&L'!$K20:$M20) | BW17: =SUM('SALT P&L'!$K20:$M20) | BX17: =SUM('KNL HO P&L'!$K20:$M20)+SUM('CCL HO P&L'!$K20:$M20)+SUM('YBHN HO P&L'!$K20:$M20)+SUM('YBN HO P&L'!$K20:$M20)+SUM('Moe2 P&L'!$K20:$M20) | BY17: =SUM(BG17:BX17) | BZ17: =BY17+BF17+AM17+T17
A18: Staff Welfare | B18: =SUM('ABA P&L'!$B21:$D21) | C18: =SUM('BK P&L'!$B21:$D21) | D18: =SUM('BW P&L'!$B21:$D21) | E18: =SUM('CED P&L'!$B21:$D21) | F18: =SUM('HB P&L'!$B21:$D21) | G18: =SUM('KIN P&L'!$B21:$D21) | H18: =SUM('MER P&L'!$B21:$D21) | I18: =SUM('SST P&L'!$B21:$D21) | J18: =SUM('HDN P&L'!$B21:$D21) | K18: =SUM('NDN P&L'!$B21:$D21) | L18: =SUM('SDN P&L'!$B21:$D21) | M18: =SUM('LE P&L'!$B21:$D21) | N18: =SUM('WH P&L'!$B21:$D21) | O18: =SUM('HS P&L'!$B21:$D21) | P18: =SUM('FH P&L'!$B21:$D21) | Q18: =SUM('HAB P&L'!$B21:$D21) | R18: =SUM('SALT P&L'!$B21:$D21) | S18: =SUM('KNL HO P&L'!$B21:$D21)+SUM('CCL HO P&L'!$B21:$D21)+SUM('YBHN HO P&L'!$B21:$D21)+SUM('YBN HO P&L'!$B21:$D21)+SUM('Moe2 P&L'!$B21:$D21) | T18: =SUM(B18:S18) | U18: =SUM('ABA P&L'!$E21:$G21) | V18: =SUM('BK P&L'!$E21:$G21) | W18: =SUM('BW P&L'!$E21:$G21) | X18: =SUM('CED P&L'!$E21:$G21) | Y18: =SUM('HB P&L'!$E21:$G21) | Z18: =SUM('KIN P&L'!$E21:$G21) | AA18: =SUM('MER P&L'!$E21:$G21) | AB18: =SUM('SST P&L'!$E21:$G21) | AC18: =SUM('HDN P&L'!$E21:$G21) | AD18: =SUM('NDN P&L'!$E21:$G21) | AE18: =SUM('SDN P&L'!$E21:$G21) | AF18: =SUM('LE P&L'!$E21:$G21) | AG18: =SUM('WH P&L'!$E21:$G21) | AH18: =SUM('HS P&L'!$E21:$G21) | AI18: =SUM('FH P&L'!$E21:$G21) | AJ18: =SUM('HAB P&L'!$E21:$G21) | AK18: =SUM('SALT P&L'!$E21:$G21) | AL18: =SUM('KNL HO P&L'!$E21:$G21)+SUM('CCL HO P&L'!$E21:$G21)+SUM('YBHN HO P&L'!$E21:$G21)+SUM('YBN HO P&L'!$E21:$G21)+SUM('Moe2 P&L'!$E21:$G21) | AM18: =SUM(U18:AL18) | AN18: =SUM('ABA P&L'!$H21:$J21) | AO18: =SUM('BK P&L'!$H21:$J21) | AP18: =SUM('BW P&L'!$H21:$J21) | AQ18: =SUM('CED P&L'!$H21:$J21) | AR18: =SUM('HB P&L'!$H21:$J21) | AS18: =SUM('KIN P&L'!$H21:$J21) | AT18: =SUM('MER P&L'!$H21:$J21) | AU18: =SUM('SST P&L'!$H21:$J21) | AV18: =SUM('HDN P&L'!$H21:$J21) | AW18: =SUM('NDN P&L'!$H21:$J21) | AX18: =SUM('SDN P&L'!$H21:$J21) | AY18: =SUM('LE P&L'!$H21:$J21) | AZ18: =SUM('WH P&L'!$H21:$J21) | BA18: =SUM('HS P&L'!$H21:$J21) | BB18: =SUM('FH P&L'!$H21:$J21) | BC18: =SUM('HAB P&L'!$H21:$J21) | BD18: =SUM('SALT P&L'!$H21:$J21) | BE18: =SUM('KNL HO P&L'!$H21:$J21)+SUM('CCL HO P&L'!$H21:$J21)+SUM('YBHN HO P&L'!$H21:$J21)+SUM('YBN HO P&L'!$H21:$J21)+SUM('Moe2 P&L'!$H21:$J21) | BF18: =SUM(AN18:BE18) | BG18: =SUM('ABA P&L'!$K21:$M21) | BH18: =SUM('BK P&L'!$K21:$M21) | BI18: =SUM('BW P&L'!$K21:$M21) | BJ18: =SUM('CED P&L'!$K21:$M21) | BK18: =SUM('HB P&L'!$K21:$M21) | BL18: =SUM('KIN P&L'!$K21:$M21) | BM18: =SUM('MER P&L'!$K21:$M21) | BN18: =SUM('SST P&L'!$K21:$M21) | BO18: =SUM('HDN P&L'!$K21:$M21) | BP18: =SUM('NDN P&L'!$K21:$M21) | BQ18: =SUM('SDN P&L'!$K21:$M21) | BR18: =SUM('LE P&L'!$K21:$M21) | BS18: =SUM('WH P&L'!$K21:$M21) | BT18: =SUM('HS P&L'!$K21:$M21) | BU18: =SUM('FH P&L'!$K21:$M21) | BV18: =SUM('HAB P&L'!$K21:$M21) | BW18: =SUM('SALT P&L'!$K21:$M21) | BX18: =SUM('KNL HO P&L'!$K21:$M21)+SUM('CCL HO P&L'!$K21:$M21)+SUM('YBHN HO P&L'!$K21:$M21)+SUM('YBN HO P&L'!$K21:$M21)+SUM('Moe2 P&L'!$K21:$M21) | BY18: =SUM(BG18:BX18) | BZ18: =BY18+BF18+AM18+T18
A19: Recruitment | B19: =SUM('ABA P&L'!$B22:$D22) | C19: =SUM('BK P&L'!$B22:$D22) | D19: =SUM('BW P&L'!$B22:$D22) | E19: =SUM('CED P&L'!$B22:$D22) | F19: =SUM('HB P&L'!$B22:$D22) | G19: =SUM('KIN P&L'!$B22:$D22) | H19: =SUM('MER P&L'!$B22:$D22) | I19: =SUM('SST P&L'!$B22:$D22) | J19: =SUM('HDN P&L'!$B22:$D22) | K19: =SUM('NDN P&L'!$B22:$D22) | L19: =SUM('SDN P&L'!$B22:$D22) | M19: =SUM('LE P&L'!$B22:$D22) | N19: =SUM('WH P&L'!$B22:$D22) | O19: =SUM('HS P&L'!$B22:$D22) | P19: =SUM('FH P&L'!$B22:$D22) | Q19: =SUM('HAB P&L'!$B22:$D22) | R19: =SUM('SALT P&L'!$B22:$D22) | S19: =SUM('KNL HO P&L'!$B22:$D22)+SUM('CCL HO P&L'!$B22:$D22)+SUM('YBHN HO P&L'!$B22:$D22)+SUM('YBN HO P&L'!$B22:$D22)+SUM('Moe2 P&L'!$B22:$D22) | T19: =SUM(B19:S19) | U19: =SUM('ABA P&L'!$E22:$G22) | V19: =SUM('BK P&L'!$E22:$G22) | W19: =SUM('BW P&L'!$E22:$G22) | X19: =SUM('CED P&L'!$E22:$G22) | Y19: =SUM('HB P&L'!$E22:$G22) | Z19: =SUM('KIN P&L'!$E22:$G22) | AA19: =SUM('MER P&L'!$E22:$G22) | AB19: =SUM('SST P&L'!$E22:$G22) | AC19: =SUM('HDN P&L'!$E22:$G22) | AD19: =SUM('NDN P&L'!$E22:$G22) | AE19: =SUM('SDN P&L'!$E22:$G22) | AF19: =SUM('LE P&L'!$E22:$G22) | AG19: =SUM('WH P&L'!$E22:$G22) | AH19: =SUM('HS P&L'!$E22:$G22) | AI19: =SUM('FH P&L'!$E22:$G22) | AJ19: =SUM('HAB P&L'!$E22:$G22) | AK19: =SUM('SALT P&L'!$E22:$G22) | AL19: =SUM('KNL HO P&L'!$E22:$G22)+SUM('CCL HO P&L'!$E22:$G22)+SUM('YBHN HO P&L'!$E22:$G22)+SUM('YBN HO P&L'!$E22:$G22)+SUM('Moe2 P&L'!$E22:$G22) | AM19: =SUM(U19:AL19) | AN19: =SUM('ABA P&L'!$H22:$J22) | AO19: =SUM('BK P&L'!$H22:$J22) | AP19: =SUM('BW P&L'!$H22:$J22) | AQ19: =SUM('CED P&L'!$H22:$J22) | AR19: =SUM('HB P&L'!$H22:$J22) | AS19: =SUM('KIN P&L'!$H22:$J22) | AT19: =SUM('MER P&L'!$H22:$J22) | AU19: =SUM('SST P&L'!$H22:$J22) | AV19: =SUM('HDN P&L'!$H22:$J22) | AW19: =SUM('NDN P&L'!$H22:$J22) | AX19: =SUM('SDN P&L'!$H22:$J22) | AY19: =SUM('LE P&L'!$H22:$J22) | AZ19: =SUM('WH P&L'!$H22:$J22) | BA19: =SUM('HS P&L'!$H22:$J22) | BB19: =SUM('FH P&L'!$H22:$J22) | BC19: =SUM('HAB P&L'!$H22:$J22) | BD19: =SUM('SALT P&L'!$H22:$J22) | BE19: =SUM('KNL HO P&L'!$H22:$J22)+SUM('CCL HO P&L'!$H22:$J22)+SUM('YBHN HO P&L'!$H22:$J22)+SUM('YBN HO P&L'!$H22:$J22)+SUM('Moe2 P&L'!$H22:$J22) | BF19: =SUM(AN19:BE19) | BG19: =SUM('ABA P&L'!$K22:$M22) | BH19: =SUM('BK P&L'!$K22:$M22) | BI19: =SUM('BW P&L'!$K22:$M22) | BJ19: =SUM('CED P&L'!$K22:$M22) | BK19: =SUM('HB P&L'!$K22:$M22) | BL19: =SUM('KIN P&L'!$K22:$M22) | BM19: =SUM('MER P&L'!$K22:$M22) | BN19: =SUM('SST P&L'!$K22:$M22) | BO19: =SUM('HDN P&L'!$K22:$M22) | BP19: =SUM('NDN P&L'!$K22:$M22) | BQ19: =SUM('SDN P&L'!$K22:$M22) | BR19: =SUM('LE P&L'!$K22:$M22) | BS19: =SUM('WH P&L'!$K22:$M22) | BT19: =SUM('HS P&L'!$K22:$M22) | BU19: =SUM('FH P&L'!$K22:$M22) | BV19: =SUM('HAB P&L'!$K22:$M22) | BW19: =SUM('SALT P&L'!$K22:$M22) | BX19: =SUM('KNL HO P&L'!$K22:$M22)+SUM('CCL HO P&L'!$K22:$M22)+SUM('YBHN HO P&L'!$K22:$M22)+SUM('YBN HO P&L'!$K22:$M22)+SUM('Moe2 P&L'!$K22:$M22) | BY19: =SUM(BG19:BX19) | BZ19: =BY19+BF19+AM19+T19
A20: Rewards & Recognition | B20: =SUM('ABA P&L'!$B23:$D23) | C20: =SUM('BK P&L'!$B23:$D23) | D20: =SUM('BW P&L'!$B23:$D23) | E20: =SUM('CED P&L'!$B23:$D23) | F20: =SUM('HB P&L'!$B23:$D23) | G20: =SUM('KIN P&L'!$B23:$D23) | H20: =SUM('MER P&L'!$B23:$D23) | I20: =SUM('SST P&L'!$B23:$D23) | J20: =SUM('HDN P&L'!$B23:$D23) | K20: =SUM('NDN P&L'!$B23:$D23) | L20: =SUM('SDN P&L'!$B23:$D23) | M20: =SUM('LE P&L'!$B23:$D23) | N20: =SUM('WH P&L'!$B23:$D23) | O20: =SUM('HS P&L'!$B23:$D23) | P20: =SUM('FH P&L'!$B23:$D23) | Q20: =SUM('HAB P&L'!$B23:$D23) | R20: =SUM('SALT P&L'!$B23:$D23) | S20: =SUM('KNL HO P&L'!$B23:$D23)+SUM('CCL HO P&L'!$B23:$D23)+SUM('YBHN HO P&L'!$B23:$D23)+SUM('YBN HO P&L'!$B23:$D23)+SUM('Moe2 P&L'!$B23:$D23) | T20: =SUM(B20:S20) | U20: =SUM('ABA P&L'!$E23:$G23) | V20: =SUM('BK P&L'!$E23:$G23) | W20: =SUM('BW P&L'!$E23:$G23) | X20: =SUM('CED P&L'!$E23:$G23) | Y20: =SUM('HB P&L'!$E23:$G23) | Z20: =SUM('KIN P&L'!$E23:$G23) | AA20: =SUM('MER P&L'!$E23:$G23) | AB20: =SUM('SST P&L'!$E23:$G23) | AC20: =SUM('HDN P&L'!$E23:$G23) | AD20: =SUM('NDN P&L'!$E23:$G23) | AE20: =SUM('SDN P&L'!$E23:$G23) | AF20: =SUM('LE P&L'!$E23:$G23) | AG20: =SUM('WH P&L'!$E23:$G23) | AH20: =SUM('HS P&L'!$E23:$G23) | AI20: =SUM('FH P&L'!$E23:$G23) | AJ20: =SUM('HAB P&L'!$E23:$G23) | AK20: =SUM('SALT P&L'!$E23:$G23) | AL20: =SUM('KNL HO P&L'!$E23:$G23)+SUM('CCL HO P&L'!$E23:$G23)+SUM('YBHN HO P&L'!$E23:$G23)+SUM('YBN HO P&L'!$E23:$G23)+SUM('Moe2 P&L'!$E23:$G23) | AM20: =SUM(U20:AL20) | AN20: =SUM('ABA P&L'!$H23:$J23) | AO20: =SUM('BK P&L'!$H23:$J23) | AP20: =SUM('BW P&L'!$H23:$J23) | AQ20: =SUM('CED P&L'!$H23:$J23) | AR20: =SUM('HB P&L'!$H23:$J23) | AS20: =SUM('KIN P&L'!$H23:$J23) | AT20: =SUM('MER P&L'!$H23:$J23) | AU20: =SUM('SST P&L'!$H23:$J23) | AV20: =SUM('HDN P&L'!$H23:$J23) | AW20: =SUM('NDN P&L'!$H23:$J23) | AX20: =SUM('SDN P&L'!$H23:$J23) | AY20: =SUM('LE P&L'!$H23:$J23) | AZ20: =SUM('WH P&L'!$H23:$J23) | BA20: =SUM('HS P&L'!$H23:$J23) | BB20: =SUM('FH P&L'!$H23:$J23) | BC20: =SUM('HAB P&L'!$H23:$J23) | BD20: =SUM('SALT P&L'!$H23:$J23) | BE20: =SUM('KNL HO P&L'!$H23:$J23)+SUM('CCL HO P&L'!$H23:$J23)+SUM('YBHN HO P&L'!$H23:$J23)+SUM('YBN HO P&L'!$H23:$J23)+SUM('Moe2 P&L'!$H23:$J23) | BF20: =SUM(AN20:BE20) | BG20: =SUM('ABA P&L'!$K23:$M23) | BH20: =SUM('BK P&L'!$K23:$M23) | BI20: =SUM('BW P&L'!$K23:$M23) | BJ20: =SUM('CED P&L'!$K23:$M23) | BK20: =SUM('HB P&L'!$K23:$M23) | BL20: =SUM('KIN P&L'!$K23:$M23) | BM20: =SUM('MER P&L'!$K23:$M23) | BN20: =SUM('SST P&L'!$K23:$M23) | BO20: =SUM('HDN P&L'!$K23:$M23) | BP20: =SUM('NDN P&L'!$K23:$M23) | BQ20: =SUM('SDN P&L'!$K23:$M23) | BR20: =SUM('LE P&L'!$K23:$M23) | BS20: =SUM('WH P&L'!$K23:$M23) | BT20: =SUM('HS P&L'!$K23:$M23) | BU20: =SUM('FH P&L'!$K23:$M23) | BV20: =SUM('HAB P&L'!$K23:$M23) | BW20: =SUM('SALT P&L'!$K23:$M23) | BX20: =SUM('KNL HO P&L'!$K23:$M23)+SUM('CCL HO P&L'!$K23:$M23)+SUM('YBHN HO P&L'!$K23:$M23)+SUM('YBN HO P&L'!$K23:$M23)+SUM('Moe2 P&L'!$K23:$M23) | BY20: =SUM(BG20:BX20) | BZ20: =BY20+BF20+AM20+T20
A21: Temps | B21: =SUM('ABA P&L'!$B24:$D24) | C21: =SUM('BK P&L'!$B24:$D24) | D21: =SUM('BW P&L'!$B24:$D24) | E21: =SUM('CED P&L'!$B24:$D24) | F21: =SUM('HB P&L'!$B24:$D24) | G21: =SUM('KIN P&L'!$B24:$D24) | H21: =SUM('MER P&L'!$B24:$D24) | I21: =SUM('SST P&L'!$B24:$D24) | J21: =SUM('HDN P&L'!$B24:$D24) | K21: =SUM('NDN P&L'!$B24:$D24) | L21: =SUM('SDN P&L'!$B24:$D24) | M21: =SUM('LE P&L'!$B24:$D24) | N21: =SUM('WH P&L'!$B24:$D24) | O21: =SUM('HS P&L'!$B24:$D24) | P21: =SUM('FH P&L'!$B24:$D24) | Q21: =SUM('HAB P&L'!$B24:$D24) | R21: =SUM('SALT P&L'!$B24:$D24) | S21: =SUM('KNL HO P&L'!$B24:$D24)+SUM('CCL HO P&L'!$B24:$D24)+SUM('YBHN HO P&L'!$B24:$D24)+SUM('YBN HO P&L'!$B24:$D24)+SUM('Moe2 P&L'!$B24:$D24) | T21: =SUM(B21:S21) | U21: =SUM('ABA P&L'!$E24:$G24) | V21: =SUM('BK P&L'!$E24:$G24) | W21: =SUM('BW P&L'!$E24:$G24) | X21: =SUM('CED P&L'!$E24:$G24) | Y21: =SUM('HB P&L'!$E24:$G24) | Z21: =SUM('KIN P&L'!$E24:$G24) | AA21: =SUM('MER P&L'!$E24:$G24) | AB21: =SUM('SST P&L'!$E24:$G24) | AC21: =SUM('HDN P&L'!$E24:$G24) | AD21: =SUM('NDN P&L'!$E24:$G24) | AE21: =SUM('SDN P&L'!$E24:$G24) | AF21: =SUM('LE P&L'!$E24:$G24) | AG21: =SUM('WH P&L'!$E24:$G24) | AH21: =SUM('HS P&L'!$E24:$G24) | AI21: =SUM('FH P&L'!$E24:$G24) | AJ21: =SUM('HAB P&L'!$E24:$G24) | AK21: =SUM('SALT P&L'!$E24:$G24) | AL21: =SUM('KNL HO P&L'!$E24:$G24)+SUM('CCL HO P&L'!$E24:$G24)+SUM('YBHN HO P&L'!$E24:$G24)+SUM('YBN HO P&L'!$E24:$G24)+SUM('Moe2 P&L'!$E24:$G24) | AM21: =SUM(U21:AL21) | AN21: =SUM('ABA P&L'!$H24:$J24) | AO21: =SUM('BK P&L'!$H24:$J24) | AP21: =SUM('BW P&L'!$H24:$J24) | AQ21: =SUM('CED P&L'!$H24:$J24) | AR21: =SUM('HB P&L'!$H24:$J24) | AS21: =SUM('KIN P&L'!$H24:$J24) | AT21: =SUM('MER P&L'!$H24:$J24) | AU21: =SUM('SST P&L'!$H24:$J24) | AV21: =SUM('HDN P&L'!$H24:$J24) | AW21: =SUM('NDN P&L'!$H24:$J24) | AX21: =SUM('SDN P&L'!$H24:$J24) | AY21: =SUM('LE P&L'!$H24:$J24) | AZ21: =SUM('WH P&L'!$H24:$J24) | BA21: =SUM('HS P&L'!$H24:$J24) | BB21: =SUM('FH P&L'!$H24:$J24) | BC21: =SUM('HAB P&L'!$H24:$J24) | BD21: =SUM('SALT P&L'!$H24:$J24) | BE21: =SUM('KNL HO P&L'!$H24:$J24)+SUM('CCL HO P&L'!$H24:$J24)+SUM('YBHN HO P&L'!$H24:$J24)+SUM('YBN HO P&L'!$H24:$J24)+SUM('Moe2 P&L'!$H24:$J24) | BF21: =SUM(AN21:BE21) | BG21: =SUM('ABA P&L'!$K24:$M24) | BH21: =SUM('BK P&L'!$K24:$M24) | BI21: =SUM('BW P&L'!$K24:$M24) | BJ21: =SUM('CED P&L'!$K24:$M24) | BK21: =SUM('HB P&L'!$K24:$M24) | BL21: =SUM('KIN P&L'!$K24:$M24) | BM21: =SUM('MER P&L'!$K24:$M24) | BN21: =SUM('SST P&L'!$K24:$M24) | BO21: =SUM('HDN P&L'!$K24:$M24) | BP21: =SUM('NDN P&L'!$K24:$M24) | BQ21: =SUM('SDN P&L'!$K24:$M24) | BR21: =SUM('LE P&L'!$K24:$M24) | BS21: =SUM('WH P&L'!$K24:$M24) | BT21: =SUM('HS P&L'!$K24:$M24) | BU21: =SUM('FH P&L'!$K24:$M24) | BV21: =SUM('HAB P&L'!$K24:$M24) | BW21: =SUM('SALT P&L'!$K24:$M24) | BX21: =SUM('KNL HO P&L'!$K24:$M24)+SUM('CCL HO P&L'!$K24:$M24)+SUM('YBHN HO P&L'!$K24:$M24)+SUM('YBN HO P&L'!$K24:$M24)+SUM('Moe2 P&L'!$K24:$M24) | BY21: =SUM(BG21:BX21) | BZ21: =BY21+BF21+AM21+T21
A22: Total Personnel | B22: =SUM('ABA P&L'!$B25:$D25) | C22: =SUM('BK P&L'!$B25:$D25) | D22: =SUM('BW P&L'!$B25:$D25) | E22: =SUM('CED P&L'!$B25:$D25) | F22: =SUM('HB P&L'!$B25:$D25) | G22: =SUM('KIN P&L'!$B25:$D25) | H22: =SUM('MER P&L'!$B25:$D25) | I22: =SUM('SST P&L'!$B25:$D25) | J22: =SUM('HDN P&L'!$B25:$D25) | K22: =SUM('NDN P&L'!$B25:$D25) | L22: =SUM('SDN P&L'!$B25:$D25) | M22: =SUM('LE P&L'!$B25:$D25) | N22: =SUM('WH P&L'!$B25:$D25) | O22: =SUM('HS P&L'!$B25:$D25) | P22: =SUM('FH P&L'!$B25:$D25) | Q22: =SUM('HAB P&L'!$B25:$D25) | R22: =SUM('SALT P&L'!$B25:$D25) | S22: =SUM('KNL HO P&L'!$B25:$D25)+SUM('CCL HO P&L'!$B25:$D25)+SUM('YBHN HO P&L'!$B25:$D25)+SUM('YBN HO P&L'!$B25:$D25)+SUM('Moe2 P&L'!$B25:$D25) | T22: =SUM(B22:S22) | U22: =SUM('ABA P&L'!$E25:$G25) | V22: =SUM('BK P&L'!$E25:$G25) | W22: =SUM('BW P&L'!$E25:$G25) | X22: =SUM('CED P&L'!$E25:$G25) | Y22: =SUM('HB P&L'!$E25:$G25) | Z22: =SUM('KIN P&L'!$E25:$G25) | AA22: =SUM('MER P&L'!$E25:$G25) | AB22: =SUM('SST P&L'!$E25:$G25) | AC22: =SUM('HDN P&L'!$E25:$G25) | AD22: =SUM('NDN P&L'!$E25:$G25) | AE22: =SUM('SDN P&L'!$E25:$G25) | AF22: =SUM('LE P&L'!$E25:$G25) | AG22: =SUM('WH P&L'!$E25:$G25) | AH22: =SUM('HS P&L'!$E25:$G25) | AI22: =SUM('FH P&L'!$E25:$G25) | AJ22: =SUM('HAB P&L'!$E25:$G25) | AK22: =SUM('SALT P&L'!$E25:$G25) | AL22: =SUM('KNL HO P&L'!$E25:$G25)+SUM('CCL HO P&L'!$E25:$G25)+SUM('YBHN HO P&L'!$E25:$G25)+SUM('YBN HO P&L'!$E25:$G25)+SUM('Moe2 P&L'!$E25:$G25) | AM22: =SUM(U22:AL22) | AN22: =SUM('ABA P&L'!$H25:$J25) | AO22: =SUM('BK P&L'!$H25:$J25) | AP22: =SUM('BW P&L'!$H25:$J25) | AQ22: =SUM('CED P&L'!$H25:$J25) | AR22: =SUM('HB P&L'!$H25:$J25) | AS22: =SUM('KIN P&L'!$H25:$J25) | AT22: =SUM('MER P&L'!$H25:$J25) | AU22: =SUM('SST P&L'!$H25:$J25) | AV22: =SUM('HDN P&L'!$H25:$J25) | AW22: =SUM('NDN P&L'!$H25:$J25) | AX22: =SUM('SDN P&L'!$H25:$J25) | AY22: =SUM('LE P&L'!$H25:$J25) | AZ22: =SUM('WH P&L'!$H25:$J25) | BA22: =SUM('HS P&L'!$H25:$J25) | BB22: =SUM('FH P&L'!$H25:$J25) | BC22: =SUM('HAB P&L'!$H25:$J25) | BD22: =SUM('SALT P&L'!$H25:$J25) | BE22: =SUM('KNL HO P&L'!$H25:$J25)+SUM('CCL HO P&L'!$H25:$J25)+SUM('YBHN HO P&L'!$H25:$J25)+SUM('YBN HO P&L'!$H25:$J25)+SUM('Moe2 P&L'!$H25:$J25) | BF22: =SUM(AN22:BE22) | BG22: =SUM('ABA P&L'!$K25:$M25) | BH22: =SUM('BK P&L'!$K25:$M25) | BI22: =SUM('BW P&L'!$K25:$M25) | BJ22: =SUM('CED P&L'!$K25:$M25) | BK22: =SUM('HB P&L'!$K25:$M25) | BL22: =SUM('KIN P&L'!$K25:$M25) | BM22: =SUM('MER P&L'!$K25:$M25) | BN22: =SUM('SST P&L'!$K25:$M25) | BO22: =SUM('HDN P&L'!$K25:$M25) | BP22: =SUM('NDN P&L'!$K25:$M25) | BQ22: =SUM('SDN P&L'!$K25:$M25) | BR22: =SUM('LE P&L'!$K25:$M25) | BS22: =SUM('WH P&L'!$K25:$M25) | BT22: =SUM('HS P&L'!$K25:$M25) | BU22: =SUM('FH P&L'!$K25:$M25) | BV22: =SUM('HAB P&L'!$K25:$M25) | BW22: =SUM('SALT P&L'!$K25:$M25) | BX22: =SUM('KNL HO P&L'!$K25:$M25)+SUM('CCL HO P&L'!$K25:$M25)+SUM('YBHN HO P&L'!$K25:$M25)+SUM('YBN HO P&L'!$K25:$M25)+SUM('Moe2 P&L'!$K25:$M25) | BY22: =SUM(BG22:BX22) | BZ22: =BY22+BF22+AM22+T22
A23: Childcare | B23: =SUM('ABA P&L'!$B26:$D26) | C23: =SUM('BK P&L'!$B26:$D26) | D23: =SUM('BW P&L'!$B26:$D26) | E23: =SUM('CED P&L'!$B26:$D26) | F23: =SUM('HB P&L'!$B26:$D26) | G23: =SUM('KIN P&L'!$B26:$D26) | H23: =SUM('MER P&L'!$B26:$D26) | I23: =SUM('SST P&L'!$B26:$D26) | J23: =SUM('HDN P&L'!$B26:$D26) | K23: =SUM('NDN P&L'!$B26:$D26) | L23: =SUM('SDN P&L'!$B26:$D26) | M23: =SUM('LE P&L'!$B26:$D26) | N23: =SUM('WH P&L'!$B26:$D26) | O23: =SUM('HS P&L'!$B26:$D26) | P23: =SUM('FH P&L'!$B26:$D26) | Q23: =SUM('HAB P&L'!$B26:$D26) | R23: =SUM('SALT P&L'!$B26:$D26) | S23: =SUM('KNL HO P&L'!$B26:$D26)+SUM('CCL HO P&L'!$B26:$D26)+SUM('YBHN HO P&L'!$B26:$D26)+SUM('YBN HO P&L'!$B26:$D26)+SUM('Moe2 P&L'!$B26:$D26) | T23: =SUM(B23:S23) | U23: =SUM('ABA P&L'!$E26:$G26) | V23: =SUM('BK P&L'!$E26:$G26) | W23: =SUM('BW P&L'!$E26:$G26) | X23: =SUM('CED P&L'!$E26:$G26) | Y23: =SUM('HB P&L'!$E26:$G26) | Z23: =SUM('KIN P&L'!$E26:$G26) | AA23: =SUM('MER P&L'!$E26:$G26) | AB23: =SUM('SST P&L'!$E26:$G26) | AC23: =SUM('HDN P&L'!$E26:$G26) | AD23: =SUM('NDN P&L'!$E26:$G26) | AE23: =SUM('SDN P&L'!$E26:$G26) | AF23: =SUM('LE P&L'!$E26:$G26) | AG23: =SUM('WH P&L'!$E26:$G26) | AH23: =SUM('HS P&L'!$E26:$G26) | AI23: =SUM('FH P&L'!$E26:$G26) | AJ23: =SUM('HAB P&L'!$E26:$G26) | AK23: =SUM('SALT P&L'!$E26:$G26) | AL23: =SUM('KNL HO P&L'!$E26:$G26)+SUM('CCL HO P&L'!$E26:$G26)+SUM('YBHN HO P&L'!$E26:$G26)+SUM('YBN HO P&L'!$E26:$G26)+SUM('Moe2 P&L'!$E26:$G26) | AM23: =SUM(U23:AL23) | AN23: =SUM('ABA P&L'!$H26:$J26) | AO23: =SUM('BK P&L'!$H26:$J26) | AP23: =SUM('BW P&L'!$H26:$J26) | AQ23: =SUM('CED P&L'!$H26:$J26) | AR23: =SUM('HB P&L'!$H26:$J26) | AS23: =SUM('KIN P&L'!$H26:$J26) | AT23: =SUM('MER P&L'!$H26:$J26) | AU23: =SUM('SST P&L'!$H26:$J26) | AV23: =SUM('HDN P&L'!$H26:$J26) | AW23: =SUM('NDN P&L'!$H26:$J26) | AX23: =SUM('SDN P&L'!$H26:$J26) | AY23: =SUM('LE P&L'!$H26:$J26) | AZ23: =SUM('WH P&L'!$H26:$J26) | BA23: =SUM('HS P&L'!$H26:$J26) | BB23: =SUM('FH P&L'!$H26:$J26) | BC23: =SUM('HAB P&L'!$H26:$J26) | BD23: =SUM('SALT P&L'!$H26:$J26) | BE23: =SUM('KNL HO P&L'!$H26:$J26)+SUM('CCL HO P&L'!$H26:$J26)+SUM('YBHN HO P&L'!$H26:$J26)+SUM('YBN HO P&L'!$H26:$J26)+SUM('Moe2 P&L'!$H26:$J26) | BF23: =SUM(AN23:BE23) | BG23: =SUM('ABA P&L'!$K26:$M26) | BH23: =SUM('BK P&L'!$K26:$M26) | BI23: =SUM('BW P&L'!$K26:$M26) | BJ23: =SUM('CED P&L'!$K26:$M26) | BK23: =SUM('HB P&L'!$K26:$M26) | BL23: =SUM('KIN P&L'!$K26:$M26) | BM23: =SUM('MER P&L'!$K26:$M26) | BN23: =SUM('SST P&L'!$K26:$M26) | BO23: =SUM('HDN P&L'!$K26:$M26) | BP23: =SUM('NDN P&L'!$K26:$M26) | BQ23: =SUM('SDN P&L'!$K26:$M26) | BR23: =SUM('LE P&L'!$K26:$M26) | BS23: =SUM('WH P&L'!$K26:$M26) | BT23: =SUM('HS P&L'!$K26:$M26) | BU23: =SUM('FH P&L'!$K26:$M26) | BV23: =SUM('HAB P&L'!$K26:$M26) | BW23: =SUM('SALT P&L'!$K26:$M26) | BX23: =SUM('KNL HO P&L'!$K26:$M26)+SUM('CCL HO P&L'!$K26:$M26)+SUM('YBHN HO P&L'!$K26:$M26)+SUM('YBN HO P&L'!$K26:$M26)+SUM('Moe2 P&L'!$K26:$M26) | BY23: =SUM(BG23:BX23) | BZ23: =BY23+BF23+AM23+T23
... A45: Total Direct Costs | B45: =SUM('ABA P&L'!$B48:$D48) | C45: =SUM('BK P&L'!$B48:$D48) | D45: =SUM('BW P&L'!$B48:$D48) | E45: =SUM('CED P&L'!$B48:$D48) | F45: =SUM('HB P&L'!$B48:$D48) | G45: =SUM('KIN P&L'!$B48:$D48) | H45: =SUM('MER P&L'!$B48:$D48) | I45: =SUM('SST P&L'!$B48:$D48) | J45: =SUM('HDN P&L'!$B48:$D48) | K45: =SUM('NDN P&L'!$B48:$D48) | L45: =SUM('SDN P&L'!$B48:$D48) | M45: =SUM('LE P&L'!$B48:$D48) | N45: =SUM('WH P&L'!$B48:$D48) | O45: =SUM('HS P&L'!$B48:$D48) | P45: =SUM('FH P&L'!$B48:$D48) | Q45: =SUM('HAB P&L'!$B48:$D48) | R45: =SUM('SALT P&L'!$B48:$D48) | S45: =SUM('KNL HO P&L'!$B48:$D48)+SUM('CCL HO P&L'!$B48:$D48)+SUM('YBHN HO P&L'!$B48:$D48)+SUM('YBN HO P&L'!$B48:$D48)+SUM('Moe2 P&L'!$B48:$D48) | T45: =SUM(B45:S45) | U45: =SUM('ABA P&L'!$E48:$G48) | V45: =SUM('BK P&L'!$E48:$G48) | W45: =SUM('BW P&L'!$E48:$G48) | X45: =SUM('CED P&L'!$E48:$G48) | Y45: =SUM('HB P&L'!$E48:$G48) | Z45: =SUM('KIN P&L'!$E48:$G48) | AA45: =SUM('MER P&L'!$E48:$G48) | AB45: =SUM('SST P&L'!$E48:$G48) | AC45: =SUM('HDN P&L'!$E48:$G48) | AD45: =SUM('NDN P&L'!$E48:$G48) | AE45: =SUM('SDN P&L'!$E48:$G48) | AF45: =SUM('LE P&L'!$E48:$G48) | AG45: =SUM('WH P&L'!$E48:$G48) | AH45: =SUM('HS P&L'!$E48:$G48) | AI45: =SUM('FH P&L'!$E48:$G48) | AJ45: =SUM('HAB P&L'!$E48:$G48) | AK45: =SUM('SALT P&L'!$E48:$G48) | AL45: =SUM('KNL HO P&L'!$E48:$G48)+SUM('CCL HO P&L'!$E48:$G48)+SUM('YBHN HO P&L'!$E48:$G48)+SUM('YBN HO P&L'!$E48:$G48)+SUM('Moe2 P&L'!$E48:$G48) | AM45: =SUM(U45:AL45) | AN45: =SUM('ABA P&L'!$H48:$J48) | AO45: =SUM('BK P&L'!$H48:$J48) | AP45: =SUM('BW P&L'!$H48:$J48) | AQ45: =SUM('CED P&L'!$H48:$J48) | AR45: =SUM('HB P&L'!$H48:$J48) | AS45: =SUM('KIN P&L'!$H48:$J48) | AT45: =SUM('MER P&L'!$H48:$J48) | AU45: =SUM('SST P&L'!$H48:$J48) | AV45: =SUM('HDN P&L'!$H48:$J48) | AW45: =SUM('NDN P&L'!$H48:$J48) | AX45: =SUM('SDN P&L'!$H48:$J48) | AY45: =SUM('LE P&L'!$H48:$J48) | AZ45: =SUM('WH P&L'!$H48:$J48) | BA45: =SUM('HS P&L'!$H48:$J48) | BB45: =SUM('FH P&L'!$H48:$J48) | BC45: =SUM('HAB P&L'!$H48:$J48) | BD45: =SUM('SALT P&L'!$H48:$J48) | BE45: =SUM('KNL HO P&L'!$H48:$J48)+SUM('CCL HO P&L'!$H48:$J48)+SUM('YBHN HO P&L'!$H48:$J48)+SUM('YBN HO P&L'!$H48:$J48)+SUM('Moe2 P&L'!$H48:$J48) | BF45: =SUM(AN45:BE45) | BG45: =SUM('ABA P&L'!$K48:$M48) | BH45: =SUM('BK P&L'!$K48:$M48) | BI45: =SUM('BW P&L'!$K48:$M48) | BJ45: =SUM('CED P&L'!$K48:$M48) | BK45: =SUM('HB P&L'!$K48:$M48) | BL45: =SUM('KIN P&L'!$K48:$M48) | BM45: =SUM('MER P&L'!$K48:$M48) | BN45: =SUM('SST P&L'!$K48:$M48) | BO45: =SUM('HDN P&L'!$K48:$M48) | BP45: =SUM('NDN P&L'!$K48:$M48) | BQ45: =SUM('SDN P&L'!$K48:$M48) | BR45: =SUM('LE P&L'!$K48:$M48) | BS45: =SUM('WH P&L'!$K48:$M48) | BT45: =SUM('HS P&L'!$K48:$M48) | BU45: =SUM('FH P&L'!$K48:$M48) | BV45: =SUM('HAB P&L'!$K48:$M48) | BW45: =SUM('SALT P&L'!$K48:$M48) | BX45: =SUM('KNL HO P&L'!$K48:$M48)+SUM('CCL HO P&L'!$K48:$M48)+SUM('YBHN HO P&L'!$K48:$M48)+SUM('YBN HO P&L'!$K48:$M48)+SUM('Moe2 P&L'!$K48:$M48) | BY45: =SUM(BG45:BX45) | BZ45: =BY45+BF45+AM45+T45
A47: CONTRIBUTION | B47: =B10-B45 | C47: =C10-C45 | D47: =D10-D45 | E47: =E10-E45 | F47: =F10-F45 | G47: =G10-G45 | H47: =H10-H45 | I47: =I10-I45 | ... S47: =S10-S45 | T47: =SUM(B47:S47) | U47: =U10-U45 | V47: =V10-V45 | W47: =W10-W45 | X47: =X10-X45 | Y47: =Y10-Y45 | Z47: =Z10-Z45 | AA47: =AA10-AA45 | AB47: =AB10-AB45 | ... AL47: =AL10-AL45 | AM47: =SUM(U47:AL47) | AN47: =AN10-AN45 | AO47: =AO10-AO45 | AP47: =AP10-AP45 | AQ47: =AQ10-AQ45 | AR47: =AR10-AR45 | AS47: =AS10-AS45 | AT47: =AT10-AT45 | AU47: =AU10-AU45 | ... BE47: =BE10-BE45 | BF47: =SUM(AN47:BE47) | BG47: =BG10-BG45 | BH47: =BH10-BH45 | BI47: =BI10-BI45 | BJ47: =BJ10-BJ45 | BK47: =BK10-BK45 | BL47: =BL10-BL45 | BM47: =BM10-BM45 | BN47: =BN10-BN45 | ... BX47: =BX10-BX45 | BY47: =SUM(BG47:BX47) | BZ47: =BY47+BF47+AM47+T47
B48: =B47/B45 | C48: =C47/C45 | D48: =D47/D45 | E48: =E47/E45 | F48: =F47/F45 | G48: =G47/G45 | H48: =H47/H45 | I48: =I47/I45 | ... S48: =S47/S45
A49: OVERHEADS | B49: =SUM('ABA P&L'!$B52:$D52) | C49: =SUM('BK P&L'!$B52:$D52) | D49: =SUM('BW P&L'!$B52:$D52) | E49: =SUM('CED P&L'!$B52:$D52) | F49: =SUM('HB P&L'!$B52:$D52) | G49: =SUM('KIN P&L'!$B52:$D52) | H49: =SUM('MER P&L'!$B52:$D52) | I49: =SUM('SST P&L'!$B52:$D52) | J49: =SUM('HDN P&L'!$B52:$D52) | K49: =SUM('NDN P&L'!$B52:$D52) | L49: =SUM('SDN P&L'!$B52:$D52) | M49: =SUM('LE P&L'!$B52:$D52) | N49: =SUM('WH P&L'!$B52:$D52) | O49: =SUM('HS P&L'!$B52:$D52) | P49: =SUM('FH P&L'!$B52:$D52) | Q49: =SUM('HAB P&L'!$B52:$D52) | R49: =SUM('SALT P&L'!$B52:$D52) | S49: =SUM('KNL HO P&L'!$B52:$D52)+SUM('CCL HO P&L'!$B52:$D52)+SUM('YBHN HO P&L'!$B52:$D52)+SUM('YBN HO P&L'!$B52:$D52)+SUM('Moe2 P&L'!$B52:$D52) | T49: =SUM(B49:S49) | U49: =SUM('ABA P&L'!$E52:$G52) | V49: =SUM('BK P&L'!$E52:$G52) | W49: =SUM('BW P&L'!$E52:$G52) | X49: =SUM('CED P&L'!$E52:$G52) | Y49: =SUM('HB P&L'!$E52:$G52) | Z49: =SUM('KIN P&L'!$E52:$G52) | AA49: =SUM('MER P&L'!$E52:$G52) | AB49: =SUM('SST P&L'!$E52:$G52) | AC49: =SUM('HDN P&L'!$E52:$G52) | AD49: =SUM('NDN P&L'!$E52:$G52) | AE49: =SUM('SDN P&L'!$E52:$G52) | AF49: =SUM('LE P&L'!$E52:$G52) | AG49: =SUM('WH P&L'!$E52:$G52) | AH49: =SUM('HS P&L'!$E52:$G52) | AI49: =SUM('FH P&L'!$E52:$G52) | AJ49: =SUM('HAB P&L'!$E52:$G52) | AK49: =SUM('SALT P&L'!$E52:$G52) | AL49: =SUM('KNL HO P&L'!$E52:$G52)+SUM('CCL HO P&L'!$E52:$G52)+SUM('YBHN HO P&L'!$E52:$G52)+SUM('YBN HO P&L'!$E52:$G52)+SUM('Moe2 P&L'!$E52:$G52) | AM49: =SUM(U49:AL49) | AN49: =SUM('ABA P&L'!$H52:$J52) | AO49: =SUM('BK P&L'!$H52:$J52) | AP49: =SUM('BW P&L'!$H52:$J52) | AQ49: =SUM('CED P&L'!$H52:$J52) | AR49: =SUM('HB P&L'!$H52:$J52) | AS49: =SUM('KIN P&L'!$H52:$J52) | AT49: =SUM('MER P&L'!$H52:$J52) | AU49: =SUM('SST P&L'!$H52:$J52) | AV49: =SUM('HDN P&L'!$H52:$J52) | AW49: =SUM('NDN P&L'!$H52:$J52) | AX49: =SUM('SDN P&L'!$H52:$J52) | AY49: =SUM('LE P&L'!$H52:$J52) | AZ49: =SUM('WH P&L'!$H52:$J52) | BA49: =SUM('HS P&L'!$H52:$J52) | BB49: =SUM('FH P&L'!$H52:$J52) | BC49: =SUM('HAB P&L'!$H52:$J52) | BD49: =SUM('SALT P&L'!$H52:$J52) | BE49: =SUM('KNL HO P&L'!$H52:$J52)+SUM('CCL HO P&L'!$H52:$J52)+SUM('YBHN HO P&L'!$H52:$J52)+SUM('YBN HO P&L'!$H52:$J52)+SUM('Moe2 P&L'!$H52:$J52) | BF49: =SUM(AN49:BE49) | BG49: =SUM('ABA P&L'!$K52:$M52) | BH49: =SUM('BK P&L'!$K52:$M52) | BI49: =SUM('BW P&L'!$K52:$M52) | BJ49: =SUM('CED P&L'!$K52:$M52) | BK49: =SUM('HB P&L'!$K52:$M52) | BL49: =SUM('KIN P&L'!$K52:$M52) | BM49: =SUM('MER P&L'!$K52:$M52) | BN49: =SUM('SST P&L'!$K52:$M52) | BO49: =SUM('HDN P&L'!$K52:$M52) | BP49: =SUM('NDN P&L'!$K52:$M52) | BQ49: =SUM('SDN P&L'!$K52:$M52) | BR49: =SUM('LE P&L'!$K52:$M52) | BS49: =SUM('WH P&L'!$K52:$M52) | BT49: =SUM('HS P&L'!$K52:$M52) | BU49: =SUM('FH P&L'!$K52:$M52) | BV49: =SUM('HAB P&L'!$K52:$M52) | BW49: =SUM('SALT P&L'!$K52:$M52) | BX49: =SUM('KNL HO P&L'!$K52:$M52)+SUM('CCL HO P&L'!$K52:$M52)+SUM('YBHN HO P&L'!$K52:$M52)+SUM('YBN HO P&L'!$K52:$M52)+SUM('Moe2 P&L'!$K52:$M52) | BY49: =SUM(BG49:BX49) | BZ49: =BY49+BF49+AM49+T49
A50: HO Salaries | B50: =SUM('ABA P&L'!$B53:$D53) | C50: =SUM('BK P&L'!$B53:$D53) | D50: =SUM('BW P&L'!$B53:$D53) | E50: =SUM('CED P&L'!$B53:$D53) | F50: =SUM('HB P&L'!$B53:$D53) | G50: =SUM('KIN P&L'!$B53:$D53) | H50: =SUM('MER P&L'!$B53:$D53) | I50: =SUM('SST P&L'!$B53:$D53) | J50: =SUM('HDN P&L'!$B53:$D53) | K50: =SUM('NDN P&L'!$B53:$D53) | L50: =SUM('SDN P&L'!$B53:$D53) | M50: =SUM('LE P&L'!$B53:$D53) | N50: =SUM('WH P&L'!$B53:$D53) | O50: =SUM('HS P&L'!$B53:$D53) | P50: =SUM('FH P&L'!$B53:$D53) | Q50: =SUM('HAB P&L'!$B53:$D53) | R50: =SUM('SALT P&L'!$B53:$D53) | S50: =SUM('KNL HO P&L'!$B53:$D53)+SUM('CCL HO P&L'!$B53:$D53)+SUM('YBHN HO P&L'!$B53:$D53)+SUM('YBN HO P&L'!$B53:$D53)+SUM('Moe2 P&L'!$B53:$D53) | T50: =SUM(B50:S50) | U50: =SUM('ABA P&L'!$E53:$G53) | V50: =SUM('BK P&L'!$E53:$G53) | W50: =SUM('BW P&L'!$E53:$G53) | X50: =SUM('CED P&L'!$E53:$G53) | Y50: =SUM('HB P&L'!$E53:$G53) | Z50: =SUM('KIN P&L'!$E53:$G53) | AA50: =SUM('MER P&L'!$E53:$G53) | AB50: =SUM('SST P&L'!$E53:$G53) | AC50: =SUM('HDN P&L'!$E53:$G53) | AD50: =SUM('NDN P&L'!$E53:$G53) | AE50: =SUM('SDN P&L'!$E53:$G53) | AF50: =SUM('LE P&L'!$E53:$G53) | AG50: =SUM('WH P&L'!$E53:$G53) | AH50: =SUM('HS P&L'!$E53:$G53) | AI50: =SUM('FH P&L'!$E53:$G53) | AJ50: =SUM('HAB P&L'!$E53:$G53) | AK50: =SUM('SALT P&L'!$E53:$G53) | AL50: =SUM('KNL HO P&L'!$E53:$G53)+SUM('CCL HO P&L'!$E53:$G53)+SUM('YBHN HO P&L'!$E53:$G53)+SUM('YBN HO P&L'!$E53:$G53)+SUM('Moe2 P&L'!$E53:$G53) | AM50: =SUM(U50:AL50) | AN50: =SUM('ABA P&L'!$H53:$J53) | AO50: =SUM('BK P&L'!$H53:$J53) | AP50: =SUM('BW P&L'!$H53:$J53) | AQ50: =SUM('CED P&L'!$H53:$J53) | AR50: =SUM('HB P&L'!$H53:$J53) | AS50: =SUM('KIN P&L'!$H53:$J53) | AT50: =SUM('MER P&L'!$H53:$J53) | AU50: =SUM('SST P&L'!$H53:$J53) | AV50: =SUM('HDN P&L'!$H53:$J53) | AW50: =SUM('NDN P&L'!$H53:$J53) | AX50: =SUM('SDN P&L'!$H53:$J53) | AY50: =SUM('LE P&L'!$H53:$J53) | AZ50: =SUM('WH P&L'!$H53:$J53) | BA50: =SUM('HS P&L'!$H53:$J53) | BB50: =SUM('FH P&L'!$H53:$J53) | BC50: =SUM('HAB P&L'!$H53:$J53) | BD50: =SUM('SALT P&L'!$H53:$J53) | BE50: =SUM('KNL HO P&L'!$H53:$J53)+SUM('CCL HO P&L'!$H53:$J53)+SUM('YBHN HO P&L'!$H53:$J53)+SUM('YBN HO P&L'!$H53:$J53)+SUM('Moe2 P&L'!$H53:$J53) | BF50: =SUM(AN50:BE50) | BG50: =SUM('ABA P&L'!$K53:$M53) | BH50: =SUM('BK P&L'!$K53:$M53) | BI50: =SUM('BW P&L'!$K53:$M53) | BJ50: =SUM('CED P&L'!$K53:$M53) | BK50: =SUM('HB P&L'!$K53:$M53) | BL50: =SUM('KIN P&L'!$K53:$M53) | BM50: =SUM('MER P&L'!$K53:$M53) | BN50: =SUM('SST P&L'!$K53:$M53) | BO50: =SUM('HDN P&L'!$K53:$M53) | BP50: =SUM('NDN P&L'!$K53:$M53) | BQ50: =SUM('SDN P&L'!$K53:$M53) | BR50: =SUM('LE P&L'!$K53:$M53) | BS50: =SUM('WH P&L'!$K53:$M53) | BT50: =SUM('HS P&L'!$K53:$M53) | BU50: =SUM('FH P&L'!$K53:$M53) | BV50: =SUM('HAB P&L'!$K53:$M53) | BW50: =SUM('SALT P&L'!$K53:$M53) | BX50: =SUM('KNL HO P&L'!$K53:$M53)+SUM('CCL HO P&L'!$K53:$M53)+SUM('YBHN HO P&L'!$K53:$M53)+SUM('YBN HO P&L'!$K53:$M53)+SUM('Moe2 P&L'!$K53:$M53) | BY50: =SUM(BG50:BX50) | BZ50: =BY50+BF50+AM50+T50
A51: HO NI | B51: =SUM('ABA P&L'!$B54:$D54) | C51: =SUM('BK P&L'!$B54:$D54) | D51: =SUM('BW P&L'!$B54:$D54) | E51: =SUM('CED P&L'!$B54:$D54) | F51: =SUM('HB P&L'!$B54:$D54) | G51: =SUM('KIN P&L'!$B54:$D54) | H51: =SUM('MER P&L'!$B54:$D54) | I51: =SUM('SST P&L'!$B54:$D54) | J51: =SUM('HDN P&L'!$B54:$D54) | K51: =SUM('NDN P&L'!$B54:$D54) | L51: =SUM('SDN P&L'!$B54:$D54) | M51: =SUM('LE P&L'!$B54:$D54) | N51: =SUM('WH P&L'!$B54:$D54) | O51: =SUM('HS P&L'!$B54:$D54) | P51: =SUM('FH P&L'!$B54:$D54) | Q51: =SUM('HAB P&L'!$B54:$D54) | R51: =SUM('SALT P&L'!$B54:$D54) | S51: =SUM('KNL HO P&L'!$B54:$D54)+SUM('CCL HO P&L'!$B54:$D54)+SUM('YBHN HO P&L'!$B54:$D54)+SUM('YBN HO P&L'!$B54:$D54)+SUM('Moe2 P&L'!$B54:$D54) | T51: =SUM(B51:S51) | U51: =SUM('ABA P&L'!$E54:$G54) | V51: =SUM('BK P&L'!$E54:$G54) | W51: =SUM('BW P&L'!$E54:$G54) | X51: =SUM('CED P&L'!$E54:$G54) | Y51: =SUM('HB P&L'!$E54:$G54) | Z51: =SUM('KIN P&L'!$E54:$G54) | AA51: =SUM('MER P&L'!$E54:$G54) | AB51: =SUM('SST P&L'!$E54:$G54) | AC51: =SUM('HDN P&L'!$E54:$G54) | AD51: =SUM('NDN P&L'!$E54:$G54) | AE51: =SUM('SDN P&L'!$E54:$G54) | AF51: =SUM('LE P&L'!$E54:$G54) | AG51: =SUM('WH P&L'!$E54:$G54) | AH51: =SUM('HS P&L'!$E54:$G54) | AI51: =SUM('FH P&L'!$E54:$G54) | AJ51: =SUM('HAB P&L'!$E54:$G54) | AK51: =SUM('SALT P&L'!$E54:$G54) | AL51: =SUM('KNL HO P&L'!$E54:$G54)+SUM('CCL HO P&L'!$E54:$G54)+SUM('YBHN HO P&L'!$E54:$G54)+SUM('YBN HO P&L'!$E54:$G54)+SUM('Moe2 P&L'!$E54:$G54) | AM51: =SUM(U51:AL51) | AN51: =SUM('ABA P&L'!$H54:$J54) | AO51: =SUM('BK P&L'!$H54:$J54) | AP51: =SUM('BW P&L'!$H54:$J54) | AQ51: =SUM('CED P&L'!$H54:$J54) | AR51: =SUM('HB P&L'!$H54:$J54) | AS51: =SUM('KIN P&L'!$H54:$J54) | AT51: =SUM('MER P&L'!$H54:$J54) | AU51: =SUM('SST P&L'!$H54:$J54) | AV51: =SUM('HDN P&L'!$H54:$J54) | AW51: =SUM('NDN P&L'!$H54:$J54) | AX51: =SUM('SDN P&L'!$H54:$J54) | AY51: =SUM('LE P&L'!$H54:$J54) | AZ51: =SUM('WH P&L'!$H54:$J54) | BA51: =SUM('HS P&L'!$H54:$J54) | BB51: =SUM('FH P&L'!$H54:$J54) | BC51: =SUM('HAB P&L'!$H54:$J54) | BD51: =SUM('SALT P&L'!$H54:$J54) | BE51: =SUM('KNL HO P&L'!$H54:$J54)+SUM('CCL HO P&L'!$H54:$J54)+SUM('YBHN HO P&L'!$H54:$J54)+SUM('YBN HO P&L'!$H54:$J54)+SUM('Moe2 P&L'!$H54:$J54) | BF51: =SUM(AN51:BE51) | BG51: =SUM('ABA P&L'!$K54:$M54) | BH51: =SUM('BK P&L'!$K54:$M54) | BI51: =SUM('BW P&L'!$K54:$M54) | BJ51: =SUM('CED P&L'!$K54:$M54) | BK51: =SUM('HB P&L'!$K54:$M54) | BL51: =SUM('KIN P&L'!$K54:$M54) | BM51: =SUM('MER P&L'!$K54:$M54) | BN51: =SUM('SST P&L'!$K54:$M54) | BO51: =SUM('HDN P&L'!$K54:$M54) | BP51: =SUM('NDN P&L'!$K54:$M54) | BQ51: =SUM('SDN P&L'!$K54:$M54) | BR51: =SUM('LE P&L'!$K54:$M54) | BS51: =SUM('WH P&L'!$K54:$M54) | BT51: =SUM('HS P&L'!$K54:$M54) | BU51: =SUM('FH P&L'!$K54:$M54) | BV51: =SUM('HAB P&L'!$K54:$M54) | BW51: =SUM('SALT P&L'!$K54:$M54) | BX51: =SUM('KNL HO P&L'!$K54:$M54)+SUM('CCL HO P&L'!$K54:$M54)+SUM('YBHN HO P&L'!$K54:$M54)+SUM('YBN HO P&L'!$K54:$M54)+SUM('Moe2 P&L'!$K54:$M54) | BY51: =SUM(BG51:BX51) | BZ51: =BY51+BF51+AM51+T51
A52: HO Health Care | B52: =SUM('ABA P&L'!$B55:$D55) | C52: =SUM('BK P&L'!$B55:$D55) | D52: =SUM('BW P&L'!$B55:$D55) | E52: =SUM('CED P&L'!$B55:$D55) | F52: =SUM('HB P&L'!$B55:$D55) | G52: =SUM('KIN P&L'!$B55:$D55) | H52: =SUM('MER P&L'!$B55:$D55) | I52: =SUM('SST P&L'!$B55:$D55) | J52: =SUM('HDN P&L'!$B55:$D55) | K52: =SUM('NDN P&L'!$B55:$D55) | L52: =SUM('SDN P&L'!$B55:$D55) | M52: =SUM('LE P&L'!$B55:$D55) | N52: =SUM('WH P&L'!$B55:$D55) | O52: =SUM('HS P&L'!$B55:$D55) | P52: =SUM('FH P&L'!$B55:$D55) | Q52: =SUM('HAB P&L'!$B55:$D55) | R52: =SUM('SALT P&L'!$B55:$D55) | S52: =SUM('KNL HO P&L'!$B55:$D55)+SUM('CCL HO P&L'!$B55:$D55)+SUM('YBHN HO P&L'!$B55:$D55)+SUM('YBN HO P&L'!$B55:$D55)+SUM('Moe2 P&L'!$B55:$D55) | T52: =SUM(B52:S52) | U52: =SUM('ABA P&L'!$E55:$G55) | V52: =SUM('BK P&L'!$E55:$G55) | W52: =SUM('BW P&L'!$E55:$G55) | X52: =SUM('CED P&L'!$E55:$G55) | Y52: =SUM('HB P&L'!$E55:$G55) | Z52: =SUM('KIN P&L'!$E55:$G55) | AA52: =SUM('MER P&L'!$E55:$G55) | AB52: =SUM('SST P&L'!$E55:$G55) | AC52: =SUM('HDN P&L'!$E55:$G55) | AD52: =SUM('NDN P&L'!$E55:$G55) | AE52: =SUM('SDN P&L'!$E55:$G55) | AF52: =SUM('LE P&L'!$E55:$G55) | AG52: =SUM('WH P&L'!$E55:$G55) | AH52: =SUM('HS P&L'!$E55:$G55) | AI52: =SUM('FH P&L'!$E55:$G55) | AJ52: =SUM('HAB P&L'!$E55:$G55) | AK52: =SUM('SALT P&L'!$E55:$G55) | AL52: =SUM('KNL HO P&L'!$E55:$G55)+SUM('CCL HO P&L'!$E55:$G55)+SUM('YBHN HO P&L'!$E55:$G55)+SUM('YBN HO P&L'!$E55:$G55)+SUM('Moe2 P&L'!$E55:$G55) | AM52: =SUM(U52:AL52) | AN52: =SUM('ABA P&L'!$H55:$J55) | AO52: =SUM('BK P&L'!$H55:$J55) | AP52: =SUM('BW P&L'!$H55:$J55) | AQ52: =SUM('CED P&L'!$H55:$J55) | AR52: =SUM('HB P&L'!$H55:$J55) | AS52: =SUM('KIN P&L'!$H55:$J55) | AT52: =SUM('MER P&L'!$H55:$J55) | AU52: =SUM('SST P&L'!$H55:$J55) | AV52: =SUM('HDN P&L'!$H55:$J55) | AW52: =SUM('NDN P&L'!$H55:$J55) | AX52: =SUM('SDN P&L'!$H55:$J55) | AY52: =SUM('LE P&L'!$H55:$J55) | AZ52: =SUM('WH P&L'!$H55:$J55) | BA52: =SUM('HS P&L'!$H55:$J55) | BB52: =SUM('FH P&L'!$H55:$J55) | BC52: =SUM('HAB P&L'!$H55:$J55) | BD52: =SUM('SALT P&L'!$H55:$J55) | BE52: =SUM('KNL HO P&L'!$H55:$J55)+SUM('CCL HO P&L'!$H55:$J55)+SUM('YBHN HO P&L'!$H55:$J55)+SUM('YBN HO P&L'!$H55:$J55)+SUM('Moe2 P&L'!$H55:$J55) | BF52: =SUM(AN52:BE52) | BG52: =SUM('ABA P&L'!$K55:$M55) | BH52: =SUM('BK P&L'!$K55:$M55) | BI52: =SUM('BW P&L'!$K55:$M55) | BJ52: =SUM('CED P&L'!$K55:$M55) | BK52: =SUM('HB P&L'!$K55:$M55) | BL52: =SUM('KIN P&L'!$K55:$M55) | BM52: =SUM('MER P&L'!$K55:$M55) | BN52: =SUM('SST P&L'!$K55:$M55) | BO52: =SUM('HDN P&L'!$K55:$M55) | BP52: =SUM('NDN P&L'!$K55:$M55) | BQ52: =SUM('SDN P&L'!$K55:$M55) | BR52: =SUM('LE P&L'!$K55:$M55) | BS52: =SUM('WH P&L'!$K55:$M55) | BT52: =SUM('HS P&L'!$K55:$M55) | BU52: =SUM('FH P&L'!$K55:$M55) | BV52: =SUM('HAB P&L'!$K55:$M55) | BW52: =SUM('SALT P&L'!$K55:$M55) | BX52: =SUM('KNL HO P&L'!$K55:$M55)+SUM('CCL HO P&L'!$K55:$M55)+SUM('YBHN HO P&L'!$K55:$M55)+SUM('YBN HO P&L'!$K55:$M55)+SUM('Moe2 P&L'!$K55:$M55) | BY52: =SUM(BG52:BX52) | BZ52: =BY52+BF52+AM52+T52
A53: HO Pension | B53: =SUM('ABA P&L'!$B56:$D56) | C53: =SUM('BK P&L'!$B56:$D56) | D53: =SUM('BW P&L'!$B56:$D56) | E53: =SUM('CED P&L'!$B56:$D56) | F53: =SUM('HB P&L'!$B56:$D56) | G53: =SUM('KIN P&L'!$B56:$D56) | H53: =SUM('MER P&L'!$B56:$D56) | I53: =SUM('SST P&L'!$B56:$D56) | J53: =SUM('HDN P&L'!$B56:$D56) | K53: =SUM('NDN P&L'!$B56:$D56) | L53: =SUM('SDN P&L'!$B56:$D56) | M53: =SUM('LE P&L'!$B56:$D56) | N53: =SUM('WH P&L'!$B56:$D56) | O53: =SUM('HS P&L'!$B56:$D56) | P53: =SUM('FH P&L'!$B56:$D56) | Q53: =SUM('HAB P&L'!$B56:$D56) | R53: =SUM('SALT P&L'!$B56:$D56) | S53: =SUM('KNL HO P&L'!$B56:$D56)+SUM('CCL HO P&L'!$B56:$D56)+SUM('YBHN HO P&L'!$B56:$D56)+SUM('YBN HO P&L'!$B56:$D56)+SUM('Moe2 P&L'!$B56:$D56) | T53: =SUM(B53:S53) | U53: =SUM('ABA P&L'!$E56:$G56) | V53: =SUM('BK P&L'!$E56:$G56) | W53: =SUM('BW P&L'!$E56:$G56) | X53: =SUM('CED P&L'!$E56:$G56) | Y53: =SUM('HB P&L'!$E56:$G56) | Z53: =SUM('KIN P&L'!$E56:$G56) | AA53: =SUM('MER P&L'!$E56:$G56) | AB53: =SUM('SST P&L'!$E56:$G56) | AC53: =SUM('HDN P&L'!$E56:$G56) | AD53: =SUM('NDN P&L'!$E56:$G56) | AE53: =SUM('SDN P&L'!$E56:$G56) | AF53: =SUM('LE P&L'!$E56:$G56) | AG53: =SUM('WH P&L'!$E56:$G56) | AH53: =SUM('HS P&L'!$E56:$G56) | AI53: =SUM('FH P&L'!$E56:$G56) | AJ53: =SUM('HAB P&L'!$E56:$G56) | AK53: =SUM('SALT P&L'!$E56:$G56) | AL53: =SUM('KNL HO P&L'!$E56:$G56)+SUM('CCL HO P&L'!$E56:$G56)+SUM('YBHN HO P&L'!$E56:$G56)+SUM('YBN HO P&L'!$E56:$G56)+SUM('Moe2 P&L'!$E56:$G56) | AM53: =SUM(U53:AL53) | AN53: =SUM('ABA P&L'!$H56:$J56) | AO53: =SUM('BK P&L'!$H56:$J56) | AP53: =SUM('BW P&L'!$H56:$J56) | AQ53: =SUM('CED P&L'!$H56:$J56) | AR53: =SUM('HB P&L'!$H56:$J56) | AS53: =SUM('KIN P&L'!$H56:$J56) | AT53: =SUM('MER P&L'!$H56:$J56) | AU53: =SUM('SST P&L'!$H56:$J56) | AV53: =SUM('HDN P&L'!$H56:$J56) | AW53: =SUM('NDN P&L'!$H56:$J56) | AX53: =SUM('SDN P&L'!$H56:$J56) | AY53: =SUM('LE P&L'!$H56:$J56) | AZ53: =SUM('WH P&L'!$H56:$J56) | BA53: =SUM('HS P&L'!$H56:$J56) | BB53: =SUM('FH P&L'!$H56:$J56) | BC53: =SUM('HAB P&L'!$H56:$J56) | BD53: =SUM('SALT P&L'!$H56:$J56) | BE53: =SUM('KNL HO P&L'!$H56:$J56)+SUM('CCL HO P&L'!$H56:$J56)+SUM('YBHN HO P&L'!$H56:$J56)+SUM('YBN HO P&L'!$H56:$J56)+SUM('Moe2 P&L'!$H56:$J56) | BF53: =SUM(AN53:BE53) | BG53: =SUM('ABA P&L'!$K56:$M56) | BH53: =SUM('BK P&L'!$K56:$M56) | BI53: =SUM('BW P&L'!$K56:$M56) | BJ53: =SUM('CED P&L'!$K56:$M56) | BK53: =SUM('HB P&L'!$K56:$M56) | BL53: =SUM('KIN P&L'!$K56:$M56) | BM53: =SUM('MER P&L'!$K56:$M56) | BN53: =SUM('SST P&L'!$K56:$M56) | BO53: =SUM('HDN P&L'!$K56:$M56) | BP53: =SUM('NDN P&L'!$K56:$M56) | BQ53: =SUM('SDN P&L'!$K56:$M56) | BR53: =SUM('LE P&L'!$K56:$M56) | BS53: =SUM('WH P&L'!$K56:$M56) | BT53: =SUM('HS P&L'!$K56:$M56) | BU53: =SUM('FH P&L'!$K56:$M56) | BV53: =SUM('HAB P&L'!$K56:$M56) | BW53: =SUM('SALT P&L'!$K56:$M56) | BX53: =SUM('KNL HO P&L'!$K56:$M56)+SUM('CCL HO P&L'!$K56:$M56)+SUM('YBHN HO P&L'!$K56:$M56)+SUM('YBN HO P&L'!$K56:$M56)+SUM('Moe2 P&L'!$K56:$M56) | BY53: =SUM(BG53:BX53) | BZ53: =BY53+BF53+AM53+T53
A54: Staff Entertaining | B54: =SUM('ABA P&L'!$B57:$D57) | C54: =SUM('BK P&L'!$B57:$D57) | D54: =SUM('BW P&L'!$B57:$D57) | E54: =SUM('CED P&L'!$B57:$D57) | F54: =SUM('HB P&L'!$B57:$D57) | G54: =SUM('KIN P&L'!$B57:$D57) | H54: =SUM('MER P&L'!$B57:$D57) | I54: =SUM('SST P&L'!$B57:$D57) | J54: =SUM('HDN P&L'!$B57:$D57) | K54: =SUM('NDN P&L'!$B57:$D57) | L54: =SUM('SDN P&L'!$B57:$D57) | M54: =SUM('LE P&L'!$B57:$D57) | N54: =SUM('WH P&L'!$B57:$D57) | O54: =SUM('HS P&L'!$B57:$D57) | P54: =SUM('FH P&L'!$B57:$D57) | Q54: =SUM('HAB P&L'!$B57:$D57) | R54: =SUM('SALT P&L'!$B57:$D57) | S54: =SUM('KNL HO P&L'!$B57:$D57)+SUM('CCL HO P&L'!$B57:$D57)+SUM('YBHN HO P&L'!$B57:$D57)+SUM('YBN HO P&L'!$B57:$D57)+SUM('Moe2 P&L'!$B57:$D57) | T54: =SUM(B54:S54) | U54: =SUM('ABA P&L'!$E57:$G57) | V54: =SUM('BK P&L'!$E57:$G57) | W54: =SUM('BW P&L'!$E57:$G57) | X54: =SUM('CED P&L'!$E57:$G57) | Y54: =SUM('HB P&L'!$E57:$G57) | Z54: =SUM('KIN P&L'!$E57:$G57) | AA54: =SUM('MER P&L'!$E57:$G57) | AB54: =SUM('SST P&L'!$E57:$G57) | AC54: =SUM('HDN P&L'!$E57:$G57) | AD54: =SUM('NDN P&L'!$E57:$G57) | AE54: =SUM('SDN P&L'!$E57:$G57) | AF54: =SUM('LE P&L'!$E57:$G57) | AG54: =SUM('WH P&L'!$E57:$G57) | AH54: =SUM('HS P&L'!$E57:$G57) | AI54: =SUM('FH P&L'!$E57:$G57) | AJ54: =SUM('HAB P&L'!$E57:$G57) | AK54: =SUM('SALT P&L'!$E57:$G57) | AL54: =SUM('KNL HO P&L'!$E57:$G57)+SUM('CCL HO P&L'!$E57:$G57)+SUM('YBHN HO P&L'!$E57:$G57)+SUM('YBN HO P&L'!$E57:$G57)+SUM('Moe2 P&L'!$E57:$G57) | AM54: =SUM(U54:AL54) | AN54: =SUM('ABA P&L'!$H57:$J57) | AO54: =SUM('BK P&L'!$H57:$J57) | AP54: =SUM('BW P&L'!$H57:$J57) | AQ54: =SUM('CED P&L'!$H57:$J57) | AR54: =SUM('HB P&L'!$H57:$J57) | AS54: =SUM('KIN P&L'!$H57:$J57) | AT54: =SUM('MER P&L'!$H57:$J57) | AU54: =SUM('SST P&L'!$H57:$J57) | AV54: =SUM('HDN P&L'!$H57:$J57) | AW54: =SUM('NDN P&L'!$H57:$J57) | AX54: =SUM('SDN P&L'!$H57:$J57) | AY54: =SUM('LE P&L'!$H57:$J57) | AZ54: =SUM('WH P&L'!$H57:$J57) | BA54: =SUM('HS P&L'!$H57:$J57) | BB54: =SUM('FH P&L'!$H57:$J57) | BC54: =SUM('HAB P&L'!$H57:$J57) | BD54: =SUM('SALT P&L'!$H57:$J57) | BE54: =SUM('KNL HO P&L'!$H57:$J57)+SUM('CCL HO P&L'!$H57:$J57)+SUM('YBHN HO P&L'!$H57:$J57)+SUM('YBN HO P&L'!$H57:$J57)+SUM('Moe2 P&L'!$H57:$J57) | BF54: =SUM(AN54:BE54) | BG54: =SUM('ABA P&L'!$K57:$M57) | BH54: =SUM('BK P&L'!$K57:$M57) | BI54: =SUM('BW P&L'!$K57:$M57) | BJ54: =SUM('CED P&L'!$K57:$M57) | BK54: =SUM('HB P&L'!$K57:$M57) | BL54: =SUM('KIN P&L'!$K57:$M57) | BM54: =SUM('MER P&L'!$K57:$M57) | BN54: =SUM('SST P&L'!$K57:$M57) | BO54: =SUM('HDN P&L'!$K57:$M57) | BP54: =SUM('NDN P&L'!$K57:$M57) | BQ54: =SUM('SDN P&L'!$K57:$M57) | BR54: =SUM('LE P&L'!$K57:$M57) | BS54: =SUM('WH P&L'!$K57:$M57) | BT54: =SUM('HS P&L'!$K57:$M57) | BU54: =SUM('FH P&L'!$K57:$M57) | BV54: =SUM('HAB P&L'!$K57:$M57) | BW54: =SUM('SALT P&L'!$K57:$M57) | BX54: =SUM('KNL HO P&L'!$K57:$M57)+SUM('CCL HO P&L'!$K57:$M57)+SUM('YBHN HO P&L'!$K57:$M57)+SUM('YBN HO P&L'!$K57:$M57)+SUM('Moe2 P&L'!$K57:$M57) | BY54: =SUM(BG54:BX54) | BZ54: =BY54+BF54+AM54+T54
A55: Business Insurance | B55: =SUM('ABA P&L'!$B58:$D58) | C55: =SUM('BK P&L'!$B58:$D58) | D55: =SUM('BW P&L'!$B58:$D58) | E55: =SUM('CED P&L'!$B58:$D58) | F55: =SUM('HB P&L'!$B58:$D58) | G55: =SUM('KIN P&L'!$B58:$D58) | H55: =SUM('MER P&L'!$B58:$D58) | I55: =SUM('SST P&L'!$B58:$D58) | J55: =SUM('HDN P&L'!$B58:$D58) | K55: =SUM('NDN P&L'!$B58:$D58) | L55: =SUM('SDN P&L'!$B58:$D58) | M55: =SUM('LE P&L'!$B58:$D58) | N55: =SUM('WH P&L'!$B58:$D58) | O55: =SUM('HS P&L'!$B58:$D58) | P55: =SUM('FH P&L'!$B58:$D58) | Q55: =SUM('HAB P&L'!$B58:$D58) | R55: =SUM('SALT P&L'!$B58:$D58) | S55: =SUM('KNL HO P&L'!$B58:$D58)+SUM('CCL HO P&L'!$B58:$D58)+SUM('YBHN HO P&L'!$B58:$D58)+SUM('YBN HO P&L'!$B58:$D58)+SUM('Moe2 P&L'!$B58:$D58) | T55: =SUM(B55:S55) | U55: =SUM('ABA P&L'!$E58:$G58) | V55: =SUM('BK P&L'!$E58:$G58) | W55: =SUM('BW P&L'!$E58:$G58) | X55: =SUM('CED P&L'!$E58:$G58) | Y55: =SUM('HB P&L'!$E58:$G58) | Z55: =SUM('KIN P&L'!$E58:$G58) | AA55: =SUM('MER P&L'!$E58:$G58) | AB55: =SUM('SST P&L'!$E58:$G58) | AC55: =SUM('HDN P&L'!$E58:$G58) | AD55: =SUM('NDN P&L'!$E58:$G58) | AE55: =SUM('SDN P&L'!$E58:$G58) | AF55: =SUM('LE P&L'!$E58:$G58) | AG55: =SUM('WH P&L'!$E58:$G58) | AH55: =SUM('HS P&L'!$E58:$G58) | AI55: =SUM('FH P&L'!$E58:$G58) | AJ55: =SUM('HAB P&L'!$E58:$G58) | AK55: =SUM('SALT P&L'!$E58:$G58) | AL55: =SUM('KNL HO P&L'!$E58:$G58)+SUM('CCL HO P&L'!$E58:$G58)+SUM('YBHN HO P&L'!$E58:$G58)+SUM('YBN HO P&L'!$E58:$G58)+SUM('Moe2 P&L'!$E58:$G58) | AM55: =SUM(U55:AL55) | AN55: =SUM('ABA P&L'!$H58:$J58) | AO55: =SUM('BK P&L'!$H58:$J58) | AP55: =SUM('BW P&L'!$H58:$J58) | AQ55: =SUM('CED P&L'!$H58:$J58) | AR55: =SUM('HB P&L'!$H58:$J58) | AS55: =SUM('KIN P&L'!$H58:$J58) | AT55: =SUM('MER P&L'!$H58:$J58) | AU55: =SUM('SST P&L'!$H58:$J58) | AV55: =SUM('HDN P&L'!$H58:$J58) | AW55: =SUM('NDN P&L'!$H58:$J58) | AX55: =SUM('SDN P&L'!$H58:$J58) | AY55: =SUM('LE P&L'!$H58:$J58) | AZ55: =SUM('WH P&L'!$H58:$J58) | BA55: =SUM('HS P&L'!$H58:$J58) | BB55: =SUM('FH P&L'!$H58:$J58) | BC55: =SUM('HAB P&L'!$H58:$J58) | BD55: =SUM('SALT P&L'!$H58:$J58) | BE55: =SUM('KNL HO P&L'!$H58:$J58)+SUM('CCL HO P&L'!$H58:$J58)+SUM('YBHN HO P&L'!$H58:$J58)+SUM('YBN HO P&L'!$H58:$J58)+SUM('Moe2 P&L'!$H58:$J58) | BF55: =SUM(AN55:BE55) | BG55: =SUM('ABA P&L'!$K58:$M58) | BH55: =SUM('BK P&L'!$K58:$M58) | BI55: =SUM('BW P&L'!$K58:$M58) | BJ55: =SUM('CED P&L'!$K58:$M58) | BK55: =SUM('HB P&L'!$K58:$M58) | BL55: =SUM('KIN P&L'!$K58:$M58) | BM55: =SUM('MER P&L'!$K58:$M58) | BN55: =SUM('SST P&L'!$K58:$M58) | BO55: =SUM('HDN P&L'!$K58:$M58) | BP55: =SUM('NDN P&L'!$K58:$M58) | BQ55: =SUM('SDN P&L'!$K58:$M58) | BR55: =SUM('LE P&L'!$K58:$M58) | BS55: =SUM('WH P&L'!$K58:$M58) | BT55: =SUM('HS P&L'!$K58:$M58) | BU55: =SUM('FH P&L'!$K58:$M58) | BV55: =SUM('HAB P&L'!$K58:$M58) | BW55: =SUM('SALT P&L'!$K58:$M58) | BX55: =SUM('KNL HO P&L'!$K58:$M58)+SUM('CCL HO P&L'!$K58:$M58)+SUM('YBHN HO P&L'!$K58:$M58)+SUM('YBN HO P&L'!$K58:$M58)+SUM('Moe2 P&L'!$K58:$M58) | BY55: =SUM(BG55:BX55) | BZ55: =BY55+BF55+AM55+T55
A56: IT Support | B56: =SUM('ABA P&L'!$B59:$D59) | C56: =SUM('BK P&L'!$B59:$D59) | D56: =SUM('BW P&L'!$B59:$D59) | E56: =SUM('CED P&L'!$B59:$D59) | F56: =SUM('HB P&L'!$B59:$D59) | G56: =SUM('KIN P&L'!$B59:$D59) | H56: =SUM('MER P&L'!$B59:$D59) | I56: =SUM('SST P&L'!$B59:$D59) | J56: =SUM('HDN P&L'!$B59:$D59) | K56: =SUM('NDN P&L'!$B59:$D59) | L56: =SUM('SDN P&L'!$B59:$D59) | M56: =SUM('LE P&L'!$B59:$D59) | N56: =SUM('WH P&L'!$B59:$D59) | O56: =SUM('HS P&L'!$B59:$D59) | P56: =SUM('FH P&L'!$B59:$D59) | Q56: =SUM('HAB P&L'!$B59:$D59) | R56: =SUM('SALT P&L'!$B59:$D59) | S56: =SUM('KNL HO P&L'!$B59:$D59)+SUM('CCL HO P&L'!$B59:$D59)+SUM('YBHN HO P&L'!$B59:$D59)+SUM('YBN HO P&L'!$B59:$D59)+SUM('Moe2 P&L'!$B59:$D59) | T56: =SUM(B56:S56) | U56: =SUM('ABA P&L'!$E59:$G59) | V56: =SUM('BK P&L'!$E59:$G59) | W56: =SUM('BW P&L'!$E59:$G59) | X56: =SUM('CED P&L'!$E59:$G59) | Y56: =SUM('HB P&L'!$E59:$G59) | Z56: =SUM('KIN P&L'!$E59:$G59) | AA56: =SUM('MER P&L'!$E59:$G59) | AB56: =SUM('SST P&L'!$E59:$G59) | AC56: =SUM('HDN P&L'!$E59:$G59) | AD56: =SUM('NDN P&L'!$E59:$G59) | AE56: =SUM('SDN P&L'!$E59:$G59) | AF56: =SUM('LE P&L'!$E59:$G59) | AG56: =SUM('WH P&L'!$E59:$G59) | AH56: =SUM('HS P&L'!$E59:$G59) | AI56: =SUM('FH P&L'!$E59:$G59) | AJ56: =SUM('HAB P&L'!$E59:$G59) | AK56: =SUM('SALT P&L'!$E59:$G59) | AL56: =SUM('KNL HO P&L'!$E59:$G59)+SUM('CCL HO P&L'!$E59:$G59)+SUM('YBHN HO P&L'!$E59:$G59)+SUM('YBN HO P&L'!$E59:$G59)+SUM('Moe2 P&L'!$E59:$G59) | AM56: =SUM(U56:AL56) | AN56: =SUM('ABA P&L'!$H59:$J59) | AO56: =SUM('BK P&L'!$H59:$J59) | AP56: =SUM('BW P&L'!$H59:$J59) | AQ56: =SUM('CED P&L'!$H59:$J59) | AR56: =SUM('HB P&L'!$H59:$J59) | AS56: =SUM('KIN P&L'!$H59:$J59) | AT56: =SUM('MER P&L'!$H59:$J59) | AU56: =SUM('SST P&L'!$H59:$J59) | AV56: =SUM('HDN P&L'!$H59:$J59) | AW56: =SUM('NDN P&L'!$H59:$J59) | AX56: =SUM('SDN P&L'!$H59:$J59) | AY56: =SUM('LE P&L'!$H59:$J59) | AZ56: =SUM('WH P&L'!$H59:$J59) | BA56: =SUM('HS P&L'!$H59:$J59) | BB56: =SUM('FH P&L'!$H59:$J59) | BC56: =SUM('HAB P&L'!$H59:$J59) | BD56: =SUM('SALT P&L'!$H59:$J59) | BE56: =SUM('KNL HO P&L'!$H59:$J59)+SUM('CCL HO P&L'!$H59:$J59)+SUM('YBHN HO P&L'!$H59:$J59)+SUM('YBN HO P&L'!$H59:$J59)+SUM('Moe2 P&L'!$H59:$J59) | BF56: =SUM(AN56:BE56) | BG56: =SUM('ABA P&L'!$K59:$M59) | BH56: =SUM('BK P&L'!$K59:$M59) | BI56: =SUM('BW P&L'!$K59:$M59) | BJ56: =SUM('CED P&L'!$K59:$M59) | BK56: =SUM('HB P&L'!$K59:$M59) | BL56: =SUM('KIN P&L'!$K59:$M59) | BM56: =SUM('MER P&L'!$K59:$M59) | BN56: =SUM('SST P&L'!$K59:$M59) | BO56: =SUM('HDN P&L'!$K59:$M59) | BP56: =SUM('NDN P&L'!$K59:$M59) | BQ56: =SUM('SDN P&L'!$K59:$M59) | BR56: =SUM('LE P&L'!$K59:$M59) | BS56: =SUM('WH P&L'!$K59:$M59) | BT56: =SUM('HS P&L'!$K59:$M59) | BU56: =SUM('FH P&L'!$K59:$M59) | BV56: =SUM('HAB P&L'!$K59:$M59) | BW56: =SUM('SALT P&L'!$K59:$M59) | BX56: =SUM('KNL HO P&L'!$K59:$M59)+SUM('CCL HO P&L'!$K59:$M59)+SUM('YBHN HO P&L'!$K59:$M59)+SUM('YBN HO P&L'!$K59:$M59)+SUM('Moe2 P&L'!$K59:$M59) | BY56: =SUM(BG56:BX56) | BZ56: =BY56+BF56+AM56+T56
A57: Fees & Subscriptions | B57: =SUM('ABA P&L'!$B60:$D60) | C57: =SUM('BK P&L'!$B60:$D60) | D57: =SUM('BW P&L'!$B60:$D60) | E57: =SUM('CED P&L'!$B60:$D60) | F57: =SUM('HB P&L'!$B60:$D60) | G57: =SUM('KIN P&L'!$B60:$D60) | H57: =SUM('MER P&L'!$B60:$D60) | I57: =SUM('SST P&L'!$B60:$D60) | J57: =SUM('HDN P&L'!$B60:$D60) | K57: =SUM('NDN P&L'!$B60:$D60) | L57: =SUM('SDN P&L'!$B60:$D60) | M57: =SUM('LE P&L'!$B60:$D60) | N57: =SUM('WH P&L'!$B60:$D60) | O57: =SUM('HS P&L'!$B60:$D60) | P57: =SUM('FH P&L'!$B60:$D60) | Q57: =SUM('HAB P&L'!$B60:$D60) | R57: =SUM('SALT P&L'!$B60:$D60) | S57: =SUM('KNL HO P&L'!$B60:$D60)+SUM('CCL HO P&L'!$B60:$D60)+SUM('YBHN HO P&L'!$B60:$D60)+SUM('YBN HO P&L'!$B60:$D60)+SUM('Moe2 P&L'!$B60:$D60) | T57: =SUM(B57:S57) | U57: =SUM('ABA P&L'!$E60:$G60) | V57: =SUM('BK P&L'!$E60:$G60) | W57: =SUM('BW P&L'!$E60:$G60) | X57: =SUM('CED P&L'!$E60:$G60) | Y57: =SUM('HB P&L'!$E60:$G60) | Z57: =SUM('KIN P&L'!$E60:$G60) | AA57: =SUM('MER P&L'!$E60:$G60) | AB57: =SUM('SST P&L'!$E60:$G60) | AC57: =SUM('HDN P&L'!$E60:$G60) | AD57: =SUM('NDN P&L'!$E60:$G60) | AE57: =SUM('SDN P&L'!$E60:$G60) | AF57: =SUM('LE P&L'!$E60:$G60) | AG57: =SUM('WH P&L'!$E60:$G60) | AH57: =SUM('HS P&L'!$E60:$G60) | AI57: =SUM('FH P&L'!$E60:$G60) | AJ57: =SUM('HAB P&L'!$E60:$G60) | AK57: =SUM('SALT P&L'!$E60:$G60) | AL57: =SUM('KNL HO P&L'!$E60:$G60)+SUM('CCL HO P&L'!$E60:$G60)+SUM('YBHN HO P&L'!$E60:$G60)+SUM('YBN HO P&L'!$E60:$G60)+SUM('Moe2 P&L'!$E60:$G60) | AM57: =SUM(U57:AL57) | AN57: =SUM('ABA P&L'!$H60:$J60) | AO57: =SUM('BK P&L'!$H60:$J60) | AP57: =SUM('BW P&L'!$H60:$J60) | AQ57: =SUM('CED P&L'!$H60:$J60) | AR57: =SUM('HB P&L'!$H60:$J60) | AS57: =SUM('KIN P&L'!$H60:$J60) | AT57: =SUM('MER P&L'!$H60:$J60) | AU57: =SUM('SST P&L'!$H60:$J60) | AV57: =SUM('HDN P&L'!$H60:$J60) | AW57: =SUM('NDN P&L'!$H60:$J60) | AX57: =SUM('SDN P&L'!$H60:$J60) | AY57: =SUM('LE P&L'!$H60:$J60) | AZ57: =SUM('WH P&L'!$H60:$J60) | BA57: =SUM('HS P&L'!$H60:$J60) | BB57: =SUM('FH P&L'!$H60:$J60) | BC57: =SUM('HAB P&L'!$H60:$J60) | BD57: =SUM('SALT P&L'!$H60:$J60) | BE57: =SUM('KNL HO P&L'!$H60:$J60)+SUM('CCL HO P&L'!$H60:$J60)+SUM('YBHN HO P&L'!$H60:$J60)+SUM('YBN HO P&L'!$H60:$J60)+SUM('Moe2 P&L'!$H60:$J60) | BF57: =SUM(AN57:BE57) | BG57: =SUM('ABA P&L'!$K60:$M60) | BH57: =SUM('BK P&L'!$K60:$M60) | BI57: =SUM('BW P&L'!$K60:$M60) | BJ57: =SUM('CED P&L'!$K60:$M60) | BK57: =SUM('HB P&L'!$K60:$M60) | BL57: =SUM('KIN P&L'!$K60:$M60) | BM57: =SUM('MER P&L'!$K60:$M60) | BN57: =SUM('SST P&L'!$K60:$M60) | BO57: =SUM('HDN P&L'!$K60:$M60) | BP57: =SUM('NDN P&L'!$K60:$M60) | BQ57: =SUM('SDN P&L'!$K60:$M60) | BR57: =SUM('LE P&L'!$K60:$M60) | BS57: =SUM('WH P&L'!$K60:$M60) | BT57: =SUM('HS P&L'!$K60:$M60) | BU57: =SUM('FH P&L'!$K60:$M60) | BV57: =SUM('HAB P&L'!$K60:$M60) | BW57: =SUM('SALT P&L'!$K60:$M60) | BX57: =SUM('KNL HO P&L'!$K60:$M60)+SUM('CCL HO P&L'!$K60:$M60)+SUM('YBHN HO P&L'!$K60:$M60)+SUM('YBN HO P&L'!$K60:$M60)+SUM('Moe2 P&L'!$K60:$M60) | BY57: =SUM(BG57:BX57) | BZ57: =BY57+BF57+AM57+T57
A58: Miscellaneous | B58: =SUM('ABA P&L'!$B61:$D61) | C58: =SUM('BK P&L'!$B61:$D61) | D58: =SUM('BW P&L'!$B61:$D61) | E58: =SUM('CED P&L'!$B61:$D61) | F58: =SUM('HB P&L'!$B61:$D61) | G58: =SUM('KIN P&L'!$B61:$D61) | H58: =SUM('MER P&L'!$B61:$D61) | I58: =SUM('SST P&L'!$B61:$D61) | J58: =SUM('HDN P&L'!$B61:$D61) | K58: =SUM('NDN P&L'!$B61:$D61) | L58: =SUM('SDN P&L'!$B61:$D61) | M58: =SUM('LE P&L'!$B61:$D61) | N58: =SUM('WH P&L'!$B61:$D61) | O58: =SUM('HS P&L'!$B61:$D61) | P58: =SUM('FH P&L'!$B61:$D61) | Q58: =SUM('HAB P&L'!$B61:$D61) | R58: =SUM('SALT P&L'!$B61:$D61) | S58: =SUM('KNL HO P&L'!$B61:$D61)+SUM('CCL HO P&L'!$B61:$D61)+SUM('YBHN HO P&L'!$B61:$D61)+SUM('YBN HO P&L'!$B61:$D61)+SUM('Moe2 P&L'!$B61:$D61) | T58: =SUM(B58:S58) | U58: =SUM('ABA P&L'!$E61:$G61) | V58: =SUM('BK P&L'!$E61:$G61) | W58: =SUM('BW P&L'!$E61:$G61) | X58: =SUM('CED P&L'!$E61:$G61) | Y58: =SUM('HB P&L'!$E61:$G61) | Z58: =SUM('KIN P&L'!$E61:$G61) | AA58: =SUM('MER P&L'!$E61:$G61) | AB58: =SUM('SST P&L'!$E61:$G61) | AC58: =SUM('HDN P&L'!$E61:$G61) | AD58: =SUM('NDN P&L'!$E61:$G61) | AE58: =SUM('SDN P&L'!$E61:$G61) | AF58: =SUM('LE P&L'!$E61:$G61) | AG58: =SUM('WH P&L'!$E61:$G61) | AH58: =SUM('HS P&L'!$E61:$G61) | AI58: =SUM('FH P&L'!$E61:$G61) | AJ58: =SUM('HAB P&L'!$E61:$G61) | AK58: =SUM('SALT P&L'!$E61:$G61) | AL58: =SUM('KNL HO P&L'!$E61:$G61)+SUM('CCL HO P&L'!$E61:$G61)+SUM('YBHN HO P&L'!$E61:$G61)+SUM('YBN HO P&L'!$E61:$G61)+SUM('Moe2 P&L'!$E61:$G61) | AM58: =SUM(U58:AL58) | AN58: =SUM('ABA P&L'!$H61:$J61) | AO58: =SUM('BK P&L'!$H61:$J61) | AP58: =SUM('BW P&L'!$H61:$J61) | AQ58: =SUM('CED P&L'!$H61:$J61) | AR58: =SUM('HB P&L'!$H61:$J61) | AS58: =SUM('KIN P&L'!$H61:$J61) | AT58: =SUM('MER P&L'!$H61:$J61) | AU58: =SUM('SST P&L'!$H61:$J61) | AV58: =SUM('HDN P&L'!$H61:$J61) | AW58: =SUM('NDN P&L'!$H61:$J61) | AX58: =SUM('SDN P&L'!$H61:$J61) | AY58: =SUM('LE P&L'!$H61:$J61) | AZ58: =SUM('WH P&L'!$H61:$J61) | BA58: =SUM('HS P&L'!$H61:$J61) | BB58: =SUM('FH P&L'!$H61:$J61) | BC58: =SUM('HAB P&L'!$H61:$J61) | BD58: =SUM('SALT P&L'!$H61:$J61) | BE58: =SUM('KNL HO P&L'!$H61:$J61)+SUM('CCL HO P&L'!$H61:$J61)+SUM('YBHN HO P&L'!$H61:$J61)+SUM('YBN HO P&L'!$H61:$J61)+SUM('Moe2 P&L'!$H61:$J61) | BF58: =SUM(AN58:BE58) | BG58: =SUM('ABA P&L'!$K61:$M61) | BH58: =SUM('BK P&L'!$K61:$M61) | BI58: =SUM('BW P&L'!$K61:$M61) | BJ58: =SUM('CED P&L'!$K61:$M61) | BK58: =SUM('HB P&L'!$K61:$M61) | BL58: =SUM('KIN P&L'!$K61:$M61) | BM58: =SUM('MER P&L'!$K61:$M61) | BN58: =SUM('SST P&L'!$K61:$M61) | BO58: =SUM('HDN P&L'!$K61:$M61) | BP58: =SUM('NDN P&L'!$K61:$M61) | BQ58: =SUM('SDN P&L'!$K61:$M61) | BR58: =SUM('LE P&L'!$K61:$M61) | BS58: =SUM('WH P&L'!$K61:$M61) | BT58: =SUM('HS P&L'!$K61:$M61) | BU58: =SUM('FH P&L'!$K61:$M61) | BV58: =SUM('HAB P&L'!$K61:$M61) | BW58: =SUM('SALT P&L'!$K61:$M61) | BX58: =SUM('KNL HO P&L'!$K61:$M61)+SUM('CCL HO P&L'!$K61:$M61)+SUM('YBHN HO P&L'!$K61:$M61)+SUM('YBN HO P&L'!$K61:$M61)+SUM('Moe2 P&L'!$K61:$M61) | BY58: =SUM(BG58:BX58) | BZ58: =BY58+BF58+AM58+T58
A59: Motor & Travel | B59: =SUM('ABA P&L'!$B62:$D62) | C59: =SUM('BK P&L'!$B62:$D62) | D59: =SUM('BW P&L'!$B62:$D62) | E59: =SUM('CED P&L'!$B62:$D62) | F59: =SUM('HB P&L'!$B62:$D62) | G59: =SUM('KIN P&L'!$B62:$D62) | H59: =SUM('MER P&L'!$B62:$D62) | I59: =SUM('SST P&L'!$B62:$D62) | J59: =SUM('HDN P&L'!$B62:$D62) | K59: =SUM('NDN P&L'!$B62:$D62) | L59: =SUM('SDN P&L'!$B62:$D62) | M59: =SUM('LE P&L'!$B62:$D62) | N59: =SUM('WH P&L'!$B62:$D62) | O59: =SUM('HS P&L'!$B62:$D62) | P59: =SUM('FH P&L'!$B62:$D62) | Q59: =SUM('HAB P&L'!$B62:$D62) | R59: =SUM('SALT P&L'!$B62:$D62) | S59: =SUM('KNL HO P&L'!$B62:$D62)+SUM('CCL HO P&L'!$B62:$D62)+SUM('YBHN HO P&L'!$B62:$D62)+SUM('YBN HO P&L'!$B62:$D62)+SUM('Moe2 P&L'!$B62:$D62) | T59: =SUM(B59:S59) | U59: =SUM('ABA P&L'!$E62:$G62) | V59: =SUM('BK P&L'!$E62:$G62) | W59: =SUM('BW P&L'!$E62:$G62) | X59: =SUM('CED P&L'!$E62:$G62) | Y59: =SUM('HB P&L'!$E62:$G62) | Z59: =SUM('KIN P&L'!$E62:$G62) | AA59: =SUM('MER P&L'!$E62:$G62) | AB59: =SUM('SST P&L'!$E62:$G62) | AC59: =SUM('HDN P&L'!$E62:$G62) | AD59: =SUM('NDN P&L'!$E62:$G62) | AE59: =SUM('SDN P&L'!$E62:$G62) | AF59: =SUM('LE P&L'!$E62:$G62) | AG59: =SUM('WH P&L'!$E62:$G62) | AH59: =SUM('HS P&L'!$E62:$G62) | AI59: =SUM('FH P&L'!$E62:$G62) | AJ59: =SUM('HAB P&L'!$E62:$G62) | AK59: =SUM('SALT P&L'!$E62:$G62) | AL59: =SUM('KNL HO P&L'!$E62:$G62)+SUM('CCL HO P&L'!$E62:$G62)+SUM('YBHN HO P&L'!$E62:$G62)+SUM('YBN HO P&L'!$E62:$G62)+SUM('Moe2 P&L'!$E62:$G62) | AM59: =SUM(U59:AL59) | AN59: =SUM('ABA P&L'!$H62:$J62) | AO59: =SUM('BK P&L'!$H62:$J62) | AP59: =SUM('BW P&L'!$H62:$J62) | AQ59: =SUM('CED P&L'!$H62:$J62) | AR59: =SUM('HB P&L'!$H62:$J62) | AS59: =SUM('KIN P&L'!$H62:$J62) | AT59: =SUM('MER P&L'!$H62:$J62) | AU59: =SUM('SST P&L'!$H62:$J62) | AV59: =SUM('HDN P&L'!$H62:$J62) | AW59: =SUM('NDN P&L'!$H62:$J62) | AX59: =SUM('SDN P&L'!$H62:$J62) | AY59: =SUM('LE P&L'!$H62:$J62) | AZ59: =SUM('WH P&L'!$H62:$J62) | BA59: =SUM('HS P&L'!$H62:$J62) | BB59: =SUM('FH P&L'!$H62:$J62) | BC59: =SUM('HAB P&L'!$H62:$J62) | BD59: =SUM('SALT P&L'!$H62:$J62) | BE59: =SUM('KNL HO P&L'!$H62:$J62)+SUM('CCL HO P&L'!$H62:$J62)+SUM('YBHN HO P&L'!$H62:$J62)+SUM('YBN HO P&L'!$H62:$J62)+SUM('Moe2 P&L'!$H62:$J62) | BF59: =SUM(AN59:BE59) | BG59: =SUM('ABA P&L'!$K62:$M62) | BH59: =SUM('BK P&L'!$K62:$M62) | BI59: =SUM('BW P&L'!$K62:$M62) | BJ59: =SUM('CED P&L'!$K62:$M62) | BK59: =SUM('HB P&L'!$K62:$M62) | BL59: =SUM('KIN P&L'!$K62:$M62) | BM59: =SUM('MER P&L'!$K62:$M62) | BN59: =SUM('SST P&L'!$K62:$M62) | BO59: =SUM('HDN P&L'!$K62:$M62) | BP59: =SUM('NDN P&L'!$K62:$M62) | BQ59: =SUM('SDN P&L'!$K62:$M62) | BR59: =SUM('LE P&L'!$K62:$M62) | BS59: =SUM('WH P&L'!$K62:$M62) | BT59: =SUM('HS P&L'!$K62:$M62) | BU59: =SUM('FH P&L'!$K62:$M62) | BV59: =SUM('HAB P&L'!$K62:$M62) | BW59: =SUM('SALT P&L'!$K62:$M62) | BX59: =SUM('KNL HO P&L'!$K62:$M62)+SUM('CCL HO P&L'!$K62:$M62)+SUM('YBHN HO P&L'!$K62:$M62)+SUM('YBN HO P&L'!$K62:$M62)+SUM('Moe2 P&L'!$K62:$M62) | BY59: =SUM(BG59:BX59) | BZ59: =BY59+BF59+AM59+T59
A60: Motor Insurance | B60: =SUM('ABA P&L'!$B63:$D63) | C60: =SUM('BK P&L'!$B63:$D63) | D60: =SUM('BW P&L'!$B63:$D63) | E60: =SUM('CED P&L'!$B63:$D63) | F60: =SUM('HB P&L'!$B63:$D63) | G60: =SUM('KIN P&L'!$B63:$D63) | H60: =SUM('MER P&L'!$B63:$D63) | I60: =SUM('SST P&L'!$B63:$D63) | J60: =SUM('HDN P&L'!$B63:$D63) | K60: =SUM('NDN P&L'!$B63:$D63) | L60: =SUM('SDN P&L'!$B63:$D63) | M60: =SUM('LE P&L'!$B63:$D63) | N60: =SUM('WH P&L'!$B63:$D63) | O60: =SUM('HS P&L'!$B63:$D63) | P60: =SUM('FH P&L'!$B63:$D63) | Q60: =SUM('HAB P&L'!$B63:$D63) | R60: =SUM('SALT P&L'!$B63:$D63) | S60: =SUM('KNL HO P&L'!$B63:$D63)+SUM('CCL HO P&L'!$B63:$D63)+SUM('YBHN HO P&L'!$B63:$D63)+SUM('YBN HO P&L'!$B63:$D63)+SUM('Moe2 P&L'!$B63:$D63) | T60: =SUM(B60:S60) | U60: =SUM('ABA P&L'!$E63:$G63) | V60: =SUM('BK P&L'!$E63:$G63) | W60: =SUM('BW P&L'!$E63:$G63) | X60: =SUM('CED P&L'!$E63:$G63) | Y60: =SUM('HB P&L'!$E63:$G63) | Z60: =SUM('KIN P&L'!$E63:$G63) | AA60: =SUM('MER P&L'!$E63:$G63) | AB60: =SUM('SST P&L'!$E63:$G63) | AC60: =SUM('HDN P&L'!$E63:$G63) | AD60: =SUM('NDN P&L'!$E63:$G63) | AE60: =SUM('SDN P&L'!$E63:$G63) | AF60: =SUM('LE P&L'!$E63:$G63) | AG60: =SUM('WH P&L'!$E63:$G63) | AH60: =SUM('HS P&L'!$E63:$G63) | AI60: =SUM('FH P&L'!$E63:$G63) | AJ60: =SUM('HAB P&L'!$E63:$G63) | AK60: =SUM('SALT P&L'!$E63:$G63) | AL60: =SUM('KNL HO P&L'!$E63:$G63)+SUM('CCL HO P&L'!$E63:$G63)+SUM('YBHN HO P&L'!$E63:$G63)+SUM('YBN HO P&L'!$E63:$G63)+SUM('Moe2 P&L'!$E63:$G63) | AM60: =SUM(U60:AL60) | AN60: =SUM('ABA P&L'!$H63:$J63) | AO60: =SUM('BK P&L'!$H63:$J63) | AP60: =SUM('BW P&L'!$H63:$J63) | AQ60: =SUM('CED P&L'!$H63:$J63) | AR60: =SUM('HB P&L'!$H63:$J63) | AS60: =SUM('KIN P&L'!$H63:$J63) | AT60: =SUM('MER P&L'!$H63:$J63) | AU60: =SUM('SST P&L'!$H63:$J63) | AV60: =SUM('HDN P&L'!$H63:$J63) | AW60: =SUM('NDN P&L'!$H63:$J63) | AX60: =SUM('SDN P&L'!$H63:$J63) | AY60: =SUM('LE P&L'!$H63:$J63) | AZ60: =SUM('WH P&L'!$H63:$J63) | BA60: =SUM('HS P&L'!$H63:$J63) | BB60: =SUM('FH P&L'!$H63:$J63) | BC60: =SUM('HAB P&L'!$H63:$J63) | BD60: =SUM('SALT P&L'!$H63:$J63) | BE60: =SUM('KNL HO P&L'!$H63:$J63)+SUM('CCL HO P&L'!$H63:$J63)+SUM('YBHN HO P&L'!$H63:$J63)+SUM('YBN HO P&L'!$H63:$J63)+SUM('Moe2 P&L'!$H63:$J63) | BF60: =SUM(AN60:BE60) | BG60: =SUM('ABA P&L'!$K63:$M63) | BH60: =SUM('BK P&L'!$K63:$M63) | BI60: =SUM('BW P&L'!$K63:$M63) | BJ60: =SUM('CED P&L'!$K63:$M63) | BK60: =SUM('HB P&L'!$K63:$M63) | BL60: =SUM('KIN P&L'!$K63:$M63) | BM60: =SUM('MER P&L'!$K63:$M63) | BN60: =SUM('SST P&L'!$K63:$M63) | BO60: =SUM('HDN P&L'!$K63:$M63) | BP60: =SUM('NDN P&L'!$K63:$M63) | BQ60: =SUM('SDN P&L'!$K63:$M63) | BR60: =SUM('LE P&L'!$K63:$M63) | BS60: =SUM('WH P&L'!$K63:$M63) | BT60: =SUM('HS P&L'!$K63:$M63) | BU60: =SUM('FH P&L'!$K63:$M63) | BV60: =SUM('HAB P&L'!$K63:$M63) | BW60: =SUM('SALT P&L'!$K63:$M63) | BX60: =SUM('KNL HO P&L'!$K63:$M63)+SUM('CCL HO P&L'!$K63:$M63)+SUM('YBHN HO P&L'!$K63:$M63)+SUM('YBN HO P&L'!$K63:$M63)+SUM('Moe2 P&L'!$K63:$M63) | BY60: =SUM(BG60:BX60) | BZ60: =BY60+BF60+AM60+T60
... A66: Total Overheads | B66: =SUM('ABA P&L'!$B69:$D69) | C66: =SUM('BK P&L'!$B69:$D69) | D66: =SUM('BW P&L'!$B69:$D69) | E66: =SUM('CED P&L'!$B69:$D69) | F66: =SUM('HB P&L'!$B69:$D69) | G66: =SUM('KIN P&L'!$B69:$D69) | H66: =SUM('MER P&L'!$B69:$D69) | I66: =SUM('SST P&L'!$B69:$D69) | J66: =SUM('HDN P&L'!$B69:$D69) | K66: =SUM('NDN P&L'!$B69:$D69) | L66: =SUM('SDN P&L'!$B69:$D69) | M66: =SUM('LE P&L'!$B69:$D69) | N66: =SUM('WH P&L'!$B69:$D69) | O66: =SUM('HS P&L'!$B69:$D69) | P66: =SUM('FH P&L'!$B69:$D69) | Q66: =SUM('HAB P&L'!$B69:$D69) | R66: =SUM('SALT P&L'!$B69:$D69) | S66: =SUM('KNL HO P&L'!$B69:$D69)+SUM('CCL HO P&L'!$B69:$D69)+SUM('YBHN HO P&L'!$B69:$D69)+SUM('YBN HO P&L'!$B69:$D69)+SUM('Moe2 P&L'!$B69:$D69) | T66: =SUM(B66:S66) | U66: =SUM('ABA P&L'!$E69:$G69) | V66: =SUM('BK P&L'!$E69:$G69) | W66: =SUM('BW P&L'!$E69:$G69) | X66: =SUM('CED P&L'!$E69:$G69) | Y66: =SUM('HB P&L'!$E69:$G69) | Z66: =SUM('KIN P&L'!$E69:$G69) | AA66: =SUM('MER P&L'!$E69:$G69) | AB66: =SUM('SST P&L'!$E69:$G69) | AC66: =SUM('HDN P&L'!$E69:$G69) | AD66: =SUM('NDN P&L'!$E69:$G69) | AE66: =SUM('SDN P&L'!$E69:$G69) | AF66: =SUM('LE P&L'!$E69:$G69) | AG66: =SUM('WH P&L'!$E69:$G69) | AH66: =SUM('HS P&L'!$E69:$G69) | AI66: =SUM('FH P&L'!$E69:$G69) | AJ66: =SUM('HAB P&L'!$E69:$G69) | AK66: =SUM('SALT P&L'!$E69:$G69) | AL66: =SUM('KNL HO P&L'!$E69:$G69)+SUM('CCL HO P&L'!$E69:$G69)+SUM('YBHN HO P&L'!$E69:$G69)+SUM('YBN HO P&L'!$E69:$G69)+SUM('Moe2 P&L'!$E69:$G69) | AM66: =SUM(U66:AL66) | AN66: =SUM('ABA P&L'!$H69:$J69) | AO66: =SUM('BK P&L'!$H69:$J69) | AP66: =SUM('BW P&L'!$H69:$J69) | AQ66: =SUM('CED P&L'!$H69:$J69) | AR66: =SUM('HB P&L'!$H69:$J69) | AS66: =SUM('KIN P&L'!$H69:$J69) | AT66: =SUM('MER P&L'!$H69:$J69) | AU66: =SUM('SST P&L'!$H69:$J69) | AV66: =SUM('HDN P&L'!$H69:$J69) | AW66: =SUM('NDN P&L'!$H69:$J69) | AX66: =SUM('SDN P&L'!$H69:$J69) | AY66: =SUM('LE P&L'!$H69:$J69) | AZ66: =SUM('WH P&L'!$H69:$J69) | BA66: =SUM('HS P&L'!$H69:$J69) | BB66: =SUM('FH P&L'!$H69:$J69) | BC66: =SUM('HAB P&L'!$H69:$J69) | BD66: =SUM('SALT P&L'!$H69:$J69) | BE66: =SUM('KNL HO P&L'!$H69:$J69)+SUM('CCL HO P&L'!$H69:$J69)+SUM('YBHN HO P&L'!$H69:$J69)+SUM('YBN HO P&L'!$H69:$J69)+SUM('Moe2 P&L'!$H69:$J69) | BF66: =SUM(AN66:BE66) | BG66: =SUM('ABA P&L'!$K69:$M69) | BH66: =SUM('BK P&L'!$K69:$M69) | BI66: =SUM('BW P&L'!$K69:$M69) | BJ66: =SUM('CED P&L'!$K69:$M69) | BK66: =SUM('HB P&L'!$K69:$M69) | BL66: =SUM('KIN P&L'!$K69:$M69) | BM66: =SUM('MER P&L'!$K69:$M69) | BN66: =SUM('SST P&L'!$K69:$M69) | BO66: =SUM('HDN P&L'!$K69:$M69) | BP66: =SUM('NDN P&L'!$K69:$M69) | BQ66: =SUM('SDN P&L'!$K69:$M69) | BR66: =SUM('LE P&L'!$K69:$M69) | BS66: =SUM('WH P&L'!$K69:$M69) | BT66: =SUM('HS P&L'!$K69:$M69) | BU66: =SUM('FH P&L'!$K69:$M69) | BV66: =SUM('HAB P&L'!$K69:$M69) | BW66: =SUM('SALT P&L'!$K69:$M69) | BX66: =SUM('KNL HO P&L'!$K69:$M69)+SUM('CCL HO P&L'!$K69:$M69)+SUM('YBHN HO P&L'!$K69:$M69)+SUM('YBN HO P&L'!$K69:$M69)+SUM('Moe2 P&L'!$K69:$M69) | BY66: =SUM(BG66:BX66) | BZ66: =BY66+BF66+AM66+T66
A67: EBITDA | B67: =B47-B66 | C67: =C47-C66 | D67: =D47-D66 | E67: =E47-E66 | F67: =F47-F66 | G67: =G47-G66 | H67: =H47-H66 | I67: =I47-I66 | ... S67: =S47-S66 | T67: =SUM(B67:S67) | U67: =U47-U66 | V67: =V47-V66 | W67: =W47-W66 | X67: =X47-X66 | Y67: =Y47-Y66 | Z67: =Z47-Z66 | AA67: =AA47-AA66 | AB67: =AB47-AB66 | ... AL67: =AL47-AL66 | AM67: =SUM(U67:AL67) | AN67: =AN47-AN66 | AO67: =AO47-AO66 | AP67: =AP47-AP66 | AQ67: =AQ47-AQ66 | AR67: =AR47-AR66 | AS67: =AS47-AS66 | AT67: =AT47-AT66 | AU67: =AU47-AU66 | ... BE67: =BE47-BE66 | BF67: =SUM(AN67:BE67) | BG67: =BG47-BG66 | BH67: =BH47-BH66 | BI67: =BI47-BI66 | BJ67: =BJ47-BJ66 | BK67: =BK47-BK66 | BL67: =BL47-BL66 | BM67: =BM47-BM66 | BN67: =BN47-BN66 | ... BX67: =BX47-BX66 | BY67: =SUM(BG67:BX67) | BZ67: =BY67+BF67+AM67+T67
A69: 2026 | B69: Q1 | U69: Q2 | V69: FORECAST DATA | AN69: Q3 | AO69: FORECAST DATA | BG69: Q4 | BH69: FORECAST DATA
B70: Abacus | C70: Bees Knees | D70: Bramleywood | E70: Cedars | F70: Hazebrouck | G70: Kingsclere | H70: Merrydale | I70: Stepping Stones | J70: Happitots | K70: Northumberland | L70: Smart Tots | M70: Lower Earley | N70: Woosehill | O70: Our Den | P70: Finchampstead | Q70: Boot Farm | R70: Saltway | S70: Head Office & Misc | T70: Totals | U70: Abacus | V70: Bees Knees | W70: Bramleywood | X70: Cedars | Y70: Hazebrouck | Z70: Kingsclere | AA70: Merrydale | AB70: Stepping Stones | AC70: Happitots | AD70: Northumberland | AE70: Smart Tots | AF70: Lower Earley | AG70: Woosehill | AH70: Our Den | AI70: Finchampstead | AJ70: Boot Farm | AK70: Saltway | AL70: Head Office & Misc | AM70: Totals | AN70: Abacus | AO70: Bees Knees | AP70: Bramleywood | AQ70: Cedars | AR70: Hazebrouck | AS70: Kingsclere | AT70: Merrydale | AU70: Stepping Stones | AV70: Happitots | AW70: Northumberland | AX70: Smart Tots | AY70: Lower Earley | AZ70: Woosehill | BA70: Our Den | BB70: Finchampstead | BC70: Boot Farm | BD70: Saltway | BE70: Head Office & Misc | BF70: Totals | BG70: Abacus | BH70: Bees Knees | BI70: Bramleywood | BJ70: Cedars | BK70: Hazebrouck | BL70: Kingsclere | BM70: Merrydale | BN70: Stepping Stones | BO70: Happitots | BP70: Northumberland | BQ70: Smart Tots | BR70: Lower Earley | BS70: Woosehill | BT70: Our Den | BU70: Finchampstead | BV70: Boot Farm | BW70: Saltway | BX70: Head Office & Misc | BY70: Totals | BZ70: Year Total | CB70: Checks
A71: INCOME
A73: Fee Income Regular | B73: =SUM('ABA P&L'!$O8:$Q8) | C73: =SUM('BK P&L'!$O8:$Q8) | D73: =SUM('BW P&L'!$O8:$Q8) | E73: =SUM('CED P&L'!$O8:$Q8) | F73: =SUM('HB P&L'!$O8:$Q8) | G73: =SUM('KIN P&L'!$O8:$Q8) | H73: =SUM('MER P&L'!$O8:$Q8) | I73: =SUM('SST P&L'!$O8:$Q8) | J73: =SUM('HDN P&L'!$O8:$Q8) | K73: =SUM('NDN P&L'!$O8:$Q8) | L73: =SUM('SDN P&L'!$O8:$Q8) | M73: =SUM('LE P&L'!$O8:$Q8) | N73: =SUM('WH P&L'!$O8:$Q8) | O73: =SUM('HS P&L'!$O8:$Q8) | P73: =SUM('FH P&L'!$O8:$Q8) | Q73: =SUM('HAB P&L'!$O8:$Q8) | R73: =SUM('SALT P&L'!$O8:$Q8) | S73: =SUM('KNL HO P&L'!$O8:$Q8)+SUM('CCL HO P&L'!$O8:$Q8)+SUM('YBHN HO P&L'!$O8:$Q8)+SUM('YBN HO P&L'!$O8:$Q8)+SUM('Moe2 P&L'!$O8:$Q8) | T73: =SUM(B73:S73) | U73: =SUM('ABA P&L'!$R8:$T8) | V73: =SUM('BK P&L'!$R8:$T8) | W73: =SUM('BW P&L'!$R8:$T8) | X73: =SUM('CED P&L'!$R8:$T8) | Y73: =SUM('HB P&L'!$R8:$T8) | Z73: =SUM('KIN P&L'!$R8:$T8) | AA73: =SUM('MER P&L'!$R8:$T8) | AB73: =SUM('SST P&L'!$R8:$T8) | AC73: =SUM('HDN P&L'!$R8:$T8) | AD73: =SUM('NDN P&L'!$R8:$T8) | AE73: =SUM('SDN P&L'!$R8:$T8) | AF73: =SUM('LE P&L'!$R8:$T8) | AG73: =SUM('WH P&L'!$R8:$T8) | AH73: =SUM('HS P&L'!$R8:$T8) | AI73: =SUM('FH P&L'!$R8:$T8) | AJ73: =SUM('HAB P&L'!$R8:$T8) | AK73: =SUM('SALT P&L'!$R8:$T8) | AL73: =SUM('KNL HO P&L'!$R8:$T8)+SUM('CCL HO P&L'!$R8:$T8)+SUM('YBHN HO P&L'!$R8:$T8)+SUM('YBN HO P&L'!$R8:$T8)+SUM('Moe2 P&L'!$R8:$T8) | AM73: =SUM(U73:AL73) | AN73: =SUM('ABA P&L'!$U8:$W8) | AO73: =SUM('BK P&L'!$U8:$W8) | AP73: =SUM('BW P&L'!$U8:$W8) | AQ73: =SUM('CED P&L'!$U8:$W8) | AR73: =SUM('HB P&L'!$U8:$W8) | AS73: =SUM('KIN P&L'!$U8:$W8) | AT73: =SUM('MER P&L'!$U8:$W8) | AU73: =SUM('SST P&L'!$U8:$W8) | AV73: =SUM('HDN P&L'!$U8:$W8) | AW73: =SUM('NDN P&L'!$U8:$W8) | AX73: =SUM('SDN P&L'!$U8:$W8) | AY73: =SUM('LE P&L'!$U8:$W8) | AZ73: =SUM('WH P&L'!$U8:$W8) | BA73: =SUM('HS P&L'!$U8:$W8) | BB73: =SUM('FH P&L'!$U8:$W8) | BC73: =SUM('HAB P&L'!$U8:$W8) | BD73: =SUM('SALT P&L'!$U8:$W8) | BE73: =SUM('KNL HO P&L'!$U8:$W8)+SUM('CCL HO P&L'!$U8:$W8)+SUM('YBHN HO P&L'!$U8:$W8)+SUM('YBN HO P&L'!$U8:$W8)+SUM('Moe2 P&L'!$U8:$W8) | BF73: =SUM(AN73:BE73) | BG73: =SUM('ABA P&L'!$X8:$Z8) | BH73: =SUM('BK P&L'!$X8:$Z8) | BI73: =SUM('BW P&L'!$X8:$Z8) | BJ73: =SUM('CED P&L'!$X8:$Z8) | BK73: =SUM('HB P&L'!$X8:$Z8) | BL73: =SUM('KIN P&L'!$X8:$Z8) | BM73: =SUM('MER P&L'!$X8:$Z8) | BN73: =SUM('SST P&L'!$X8:$Z8) | BO73: =SUM('HDN P&L'!$X8:$Z8) | BP73: =SUM('NDN P&L'!$X8:$Z8) | BQ73: =SUM('SDN P&L'!$X8:$Z8) | BR73: =SUM('LE P&L'!$X8:$Z8) | BS73: =SUM('WH P&L'!$X8:$Z8) | BT73: =SUM('HS P&L'!$X8:$Z8) | BU73: =SUM('FH P&L'!$X8:$Z8) | BV73: =SUM('HAB P&L'!$X8:$Z8) | BW73: =SUM('SALT P&L'!$X8:$Z8) | BX73: =SUM('KNL HO P&L'!$X8:$Z8)+SUM('CCL HO P&L'!$X8:$Z8)+SUM('YBHN HO P&L'!$X8:$Z8)+SUM('YBN HO P&L'!$X8:$Z8)+SUM('Moe2 P&L'!$X8:$Z8) | BY73: =SUM(BG73:BX73) | BZ73: =BY73+BF73+AM73+T73 | CA73: ='GROUP TOTALS MONTHLY P&L'!AB8 | CB73: =BZ73-CA73
A74: EEEF Embeded | B74: =SUM('ABA P&L'!$O9:$Q9) | C74: =SUM('BK P&L'!$O9:$Q9) | D74: =SUM('BW P&L'!$O9:$Q9) | E74: =SUM('CED P&L'!$O9:$Q9) | F74: =SUM('HB P&L'!$O9:$Q9) | G74: =SUM('KIN P&L'!$O9:$Q9) | H74: =SUM('MER P&L'!$O9:$Q9) | I74: =SUM('SST P&L'!$O9:$Q9) | J74: =SUM('HDN P&L'!$O9:$Q9) | K74: =SUM('NDN P&L'!$O9:$Q9) | L74: =SUM('SDN P&L'!$O9:$Q9) | M74: =SUM('LE P&L'!$O9:$Q9) | N74: =SUM('WH P&L'!$O9:$Q9) | O74: =SUM('HS P&L'!$O9:$Q9) | P74: =SUM('FH P&L'!$O9:$Q9) | Q74: =SUM('HAB P&L'!$O9:$Q9) | R74: =SUM('SALT P&L'!$O9:$Q9) | S74: =SUM('KNL HO P&L'!$O9:$Q9)+SUM('CCL HO P&L'!$O9:$Q9)+SUM('YBHN HO P&L'!$O9:$Q9)+SUM('YBN HO P&L'!$O9:$Q9)+SUM('Moe2 P&L'!$O9:$Q9) | T74: =SUM(B74:S74) | U74: =SUM('ABA P&L'!$R9:$T9) | V74: =SUM('BK P&L'!$R9:$T9) | W74: =SUM('BW P&L'!$R9:$T9) | X74: =SUM('CED P&L'!$R9:$T9) | Y74: =SUM('HB P&L'!$R9:$T9) | Z74: =SUM('KIN P&L'!$R9:$T9) | AA74: =SUM('MER P&L'!$R9:$T9) | AB74: =SUM('SST P&L'!$R9:$T9) | AC74: =SUM('HDN P&L'!$R9:$T9) | AD74: =SUM('NDN P&L'!$R9:$T9) | AE74: =SUM('SDN P&L'!$R9:$T9) | AF74: =SUM('LE P&L'!$R9:$T9) | AG74: =SUM('WH P&L'!$R9:$T9) | AH74: =SUM('HS P&L'!$R9:$T9) | AI74: =SUM('FH P&L'!$R9:$T9) | AJ74: =SUM('HAB P&L'!$R9:$T9) | AK74: =SUM('SALT P&L'!$R9:$T9) | AL74: =SUM('KNL HO P&L'!$R9:$T9)+SUM('CCL HO P&L'!$R9:$T9)+SUM('YBHN HO P&L'!$R9:$T9)+SUM('YBN HO P&L'!$R9:$T9)+SUM('Moe2 P&L'!$R9:$T9) | AM74: =SUM(U74:AL74) | AN74: =SUM('ABA P&L'!$U9:$W9) | AO74: =SUM('BK P&L'!$U9:$W9) | AP74: =SUM('BW P&L'!$U9:$W9) | AQ74: =SUM('CED P&L'!$U9:$W9) | AR74: =SUM('HB P&L'!$U9:$W9) | AS74: =SUM('KIN P&L'!$U9:$W9) | AT74: =SUM('MER P&L'!$U9:$W9) | AU74: =SUM('SST P&L'!$U9:$W9) | AV74: =SUM('HDN P&L'!$U9:$W9) | AW74: =SUM('NDN P&L'!$U9:$W9) | AX74: =SUM('SDN P&L'!$U9:$W9) | AY74: =SUM('LE P&L'!$U9:$W9) | AZ74: =SUM('WH P&L'!$U9:$W9) | BA74: =SUM('HS P&L'!$U9:$W9) | BB74: =SUM('FH P&L'!$U9:$W9) | BC74: =SUM('HAB P&L'!$U9:$W9) | BD74: =SUM('SALT P&L'!$U9:$W9) | BE74: =SUM('KNL HO P&L'!$U9:$W9)+SUM('CCL HO P&L'!$U9:$W9)+SUM('YBHN HO P&L'!$U9:$W9)+SUM('YBN HO P&L'!$U9:$W9)+SUM('Moe2 P&L'!$U9:$W9) | BF74: =SUM(AN74:BE74) | BG74: =SUM('ABA P&L'!$X9:$Z9) | BH74: =SUM('BK P&L'!$X9:$Z9) | BI74: =SUM('BW P&L'!$X9:$Z9) | BJ74: =SUM('CED P&L'!$X9:$Z9) | BK74: =SUM('HB P&L'!$X9:$Z9) | BL74: =SUM('KIN P&L'!$X9:$Z9) | BM74: =SUM('MER P&L'!$X9:$Z9) | BN74: =SUM('SST P&L'!$X9:$Z9) | BO74: =SUM('HDN P&L'!$X9:$Z9) | BP74: =SUM('NDN P&L'!$X9:$Z9) | BQ74: =SUM('SDN P&L'!$X9:$Z9) | BR74: =SUM('LE P&L'!$X9:$Z9) | BS74: =SUM('WH P&L'!$X9:$Z9) | BT74: =SUM('HS P&L'!$X9:$Z9) | BU74: =SUM('FH P&L'!$X9:$Z9) | BV74: =SUM('HAB P&L'!$X9:$Z9) | BW74: =SUM('SALT P&L'!$X9:$Z9) | BX74: =SUM('KNL HO P&L'!$X9:$Z9)+SUM('CCL HO P&L'!$X9:$Z9)+SUM('YBHN HO P&L'!$X9:$Z9)+SUM('YBN HO P&L'!$X9:$Z9)+SUM('Moe2 P&L'!$X9:$Z9) | BY74: =SUM(BG74:BX74) | BZ74: =BY74+BF74+AM74+T74 | CA74: ='GROUP TOTALS MONTHLY P&L'!AB9 | CB74: =BZ74-CA74
A75: Other Income | B75: =SUM('ABA P&L'!$O10:$Q10) | C75: =SUM('BK P&L'!$O10:$Q10) | D75: =SUM('BW P&L'!$O10:$Q10) | E75: =SUM('CED P&L'!$O10:$Q10) | F75: =SUM('HB P&L'!$O10:$Q10) | G75: =SUM('KIN P&L'!$O10:$Q10) | H75: =SUM('MER P&L'!$O10:$Q10) | I75: =SUM('SST P&L'!$O10:$Q10) | J75: =SUM('HDN P&L'!$O10:$Q10) | K75: =SUM('NDN P&L'!$O10:$Q10) | L75: =SUM('SDN P&L'!$O10:$Q10) | M75: =SUM('LE P&L'!$O10:$Q10) | N75: =SUM('WH P&L'!$O10:$Q10) | O75: =SUM('HS P&L'!$O10:$Q10) | P75: =SUM('FH P&L'!$O10:$Q10) | Q75: =SUM('HAB P&L'!$O10:$Q10) | R75: =SUM('SALT P&L'!$O10:$Q10) | S75: =SUM('KNL HO P&L'!$O10:$Q10)+SUM('CCL HO P&L'!$O10:$Q10)+SUM('YBHN HO P&L'!$O10:$Q10)+SUM('YBN HO P&L'!$O10:$Q10)+SUM('Moe2 P&L'!$O10:$Q10) | T75: =SUM(B75:S75) | U75: =SUM('ABA P&L'!$R10:$T10) | V75: =SUM('BK P&L'!$R10:$T10) | W75: =SUM('BW P&L'!$R10:$T10) | X75: =SUM('CED P&L'!$R10:$T10) | Y75: =SUM('HB P&L'!$R10:$T10) | Z75: =SUM('KIN P&L'!$R10:$T10) | AA75: =SUM('MER P&L'!$R10:$T10) | AB75: =SUM('SST P&L'!$R10:$T10) | AC75: =SUM('HDN P&L'!$R10:$T10) | AD75: =SUM('NDN P&L'!$R10:$T10) | AE75: =SUM('SDN P&L'!$R10:$T10) | AF75: =SUM('LE P&L'!$R10:$T10) | AG75: =SUM('WH P&L'!$R10:$T10) | AH75: =SUM('HS P&L'!$R10:$T10) | AI75: =SUM('FH P&L'!$R10:$T10) | AJ75: =SUM('HAB P&L'!$R10:$T10) | AK75: =SUM('SALT P&L'!$R10:$T10) | AL75: =SUM('KNL HO P&L'!$R10:$T10)+SUM('CCL HO P&L'!$R10:$T10)+SUM('YBHN HO P&L'!$R10:$T10)+SUM('YBN HO P&L'!$R10:$T10)+SUM('Moe2 P&L'!$R10:$T10) | AM75: =SUM(U75:AL75) | AN75: =SUM('ABA P&L'!$U10:$W10) | AO75: =SUM('BK P&L'!$U10:$W10) | AP75: =SUM('BW P&L'!$U10:$W10) | AQ75: =SUM('CED P&L'!$U10:$W10) | AR75: =SUM('HB P&L'!$U10:$W10) | AS75: =SUM('KIN P&L'!$U10:$W10) | AT75: =SUM('MER P&L'!$U10:$W10) | AU75: =SUM('SST P&L'!$U10:$W10) | AV75: =SUM('HDN P&L'!$U10:$W10) | AW75: =SUM('NDN P&L'!$U10:$W10) | AX75: =SUM('SDN P&L'!$U10:$W10) | AY75: =SUM('LE P&L'!$U10:$W10) | AZ75: =SUM('WH P&L'!$U10:$W10) | BA75: =SUM('HS P&L'!$U10:$W10) | BB75: =SUM('FH P&L'!$U10:$W10) | BC75: =SUM('HAB P&L'!$U10:$W10) | BD75: =SUM('SALT P&L'!$U10:$W10) | BE75: =SUM('KNL HO P&L'!$U10:$W10)+SUM('CCL HO P&L'!$U10:$W10)+SUM('YBHN HO P&L'!$U10:$W10)+SUM('YBN HO P&L'!$U10:$W10)+SUM('Moe2 P&L'!$U10:$W10) | BF75: =SUM(AN75:BE75) | BG75: =SUM('ABA P&L'!$X10:$Z10) | BH75: =SUM('BK P&L'!$X10:$Z10) | BI75: =SUM('BW P&L'!$X10:$Z10) | BJ75: =SUM('CED P&L'!$X10:$Z10) | BK75: =SUM('HB P&L'!$X10:$Z10) | BL75: =SUM('KIN P&L'!$X10:$Z10) | BM75: =SUM('MER P&L'!$X10:$Z10) | BN75: =SUM('SST P&L'!$X10:$Z10) | BO75: =SUM('HDN P&L'!$X10:$Z10) | BP75: =SUM('NDN P&L'!$X10:$Z10) | BQ75: =SUM('SDN P&L'!$X10:$Z10) | BR75: =SUM('LE P&L'!$X10:$Z10) | BS75: =SUM('WH P&L'!$X10:$Z10) | BT75: =SUM('HS P&L'!$X10:$Z10) | BU75: =SUM('FH P&L'!$X10:$Z10) | BV75: =SUM('HAB P&L'!$X10:$Z10) | BW75: =SUM('SALT P&L'!$X10:$Z10) | BX75: =SUM('KNL HO P&L'!$X10:$Z10)+SUM('CCL HO P&L'!$X10:$Z10)+SUM('YBHN HO P&L'!$X10:$Z10)+SUM('YBN HO P&L'!$X10:$Z10)+SUM('Moe2 P&L'!$X10:$Z10) | BY75: =SUM(BG75:BX75) | BZ75: =BY75+BF75+AM75+T75 | CA75: ='GROUP TOTALS MONTHLY P&L'!AB10 | CB75: =BZ75-CA75
A76: Total Income | B76: =SUM('ABA P&L'!$O11:$Q11) | C76: =SUM('BK P&L'!$O11:$Q11) | D76: =SUM('BW P&L'!$O11:$Q11) | E76: =SUM('CED P&L'!$O11:$Q11) | F76: =SUM('HB P&L'!$O11:$Q11) | G76: =SUM('KIN P&L'!$O11:$Q11) | H76: =SUM('MER P&L'!$O11:$Q11) | I76: =SUM('SST P&L'!$O11:$Q11) | J76: =SUM('HDN P&L'!$O11:$Q11) | K76: =SUM('NDN P&L'!$O11:$Q11) | L76: =SUM('SDN P&L'!$O11:$Q11) | M76: =SUM('LE P&L'!$O11:$Q11) | N76: =SUM('WH P&L'!$O11:$Q11) | O76: =SUM('HS P&L'!$O11:$Q11) | P76: =SUM('FH P&L'!$O11:$Q11) | Q76: =SUM('HAB P&L'!$O11:$Q11) | R76: =SUM('SALT P&L'!$O11:$Q11) | S76: =SUM('KNL HO P&L'!$O11:$Q11)+SUM('CCL HO P&L'!$O11:$Q11)+SUM('YBHN HO P&L'!$O11:$Q11)+SUM('YBN HO P&L'!$O11:$Q11)+SUM('Moe2 P&L'!$O11:$Q11) | T76: =SUM(B76:S76) | U76: =SUM('ABA P&L'!$R11:$T11) | V76: =SUM('BK P&L'!$R11:$T11) | W76: =SUM('BW P&L'!$R11:$T11) | X76: =SUM('CED P&L'!$R11:$T11) | Y76: =SUM('HB P&L'!$R11:$T11) | Z76: =SUM('KIN P&L'!$R11:$T11) | AA76: =SUM('MER P&L'!$R11:$T11) | AB76: =SUM('SST P&L'!$R11:$T11) | AC76: =SUM('HDN P&L'!$R11:$T11) | AD76: =SUM('NDN P&L'!$R11:$T11) | AE76: =SUM('SDN P&L'!$R11:$T11) | AF76: =SUM('LE P&L'!$R11:$T11) | AG76: =SUM('WH P&L'!$R11:$T11) | AH76: =SUM('HS P&L'!$R11:$T11) | AI76: =SUM('FH P&L'!$R11:$T11) | AJ76: =SUM('HAB P&L'!$R11:$T11) | AK76: =SUM('SALT P&L'!$R11:$T11) | AL76: =SUM('KNL HO P&L'!$R11:$T11)+SUM('CCL HO P&L'!$R11:$T11)+SUM('YBHN HO P&L'!$R11:$T11)+SUM('YBN HO P&L'!$R11:$T11)+SUM('Moe2 P&L'!$R11:$T11) | AM76: =SUM(U76:AL76) | AN76: =SUM('ABA P&L'!$U11:$W11) | AO76: =SUM('BK P&L'!$U11:$W11) | AP76: =SUM('BW P&L'!$U11:$W11) | AQ76: =SUM('CED P&L'!$U11:$W11) | AR76: =SUM('HB P&L'!$U11:$W11) | AS76: =SUM('KIN P&L'!$U11:$W11) | AT76: =SUM('MER P&L'!$U11:$W11) | AU76: =SUM('SST P&L'!$U11:$W11) | AV76: =SUM('HDN P&L'!$U11:$W11) | AW76: =SUM('NDN P&L'!$U11:$W11) | AX76: =SUM('SDN P&L'!$U11:$W11) | AY76: =SUM('LE P&L'!$U11:$W11) | AZ76: =SUM('WH P&L'!$U11:$W11) | BA76: =SUM('HS P&L'!$U11:$W11) | BB76: =SUM('FH P&L'!$U11:$W11) | BC76: =SUM('HAB P&L'!$U11:$W11) | BD76: =SUM('SALT P&L'!$U11:$W11) | BE76: =SUM('KNL HO P&L'!$U11:$W11)+SUM('CCL HO P&L'!$U11:$W11)+SUM('YBHN HO P&L'!$U11:$W11)+SUM('YBN HO P&L'!$U11:$W11)+SUM('Moe2 P&L'!$U11:$W11) | BF76: =SUM(AN76:BE76) | BG76: =SUM('ABA P&L'!$X11:$Z11) | BH76: =SUM('BK P&L'!$X11:$Z11) | BI76: =SUM('BW P&L'!$X11:$Z11) | BJ76: =SUM('CED P&L'!$X11:$Z11) | BK76: =SUM('HB P&L'!$X11:$Z11) | BL76: =SUM('KIN P&L'!$X11:$Z11) | BM76: =SUM('MER P&L'!$X11:$Z11) | BN76: =SUM('SST P&L'!$X11:$Z11) | BO76: =SUM('HDN P&L'!$X11:$Z11) | BP76: =SUM('NDN P&L'!$X11:$Z11) | BQ76: =SUM('SDN P&L'!$X11:$Z11) | BR76: =SUM('LE P&L'!$X11:$Z11) | BS76: =SUM('WH P&L'!$X11:$Z11) | BT76: =SUM('HS P&L'!$X11:$Z11) | BU76: =SUM('FH P&L'!$X11:$Z11) | BV76: =SUM('HAB P&L'!$X11:$Z11) | BW76: =SUM('SALT P&L'!$X11:$Z11) | BX76: =SUM('KNL HO P&L'!$X11:$Z11)+SUM('CCL HO P&L'!$X11:$Z11)+SUM('YBHN HO P&L'!$X11:$Z11)+SUM('YBN HO P&L'!$X11:$Z11)+SUM('Moe2 P&L'!$X11:$Z11) | BY76: =SUM(BG76:BX76) | BZ76: =BY76+BF76+AM76+T76 | CA76: ='GROUP TOTALS MONTHLY P&L'!AB11 | CB76: =BZ76-CA76
A77: DIRECTCOSTS | B77: =SUM('ABA P&L'!$O12:$Q12) | C77: =SUM('BK P&L'!$O12:$Q12) | D77: =SUM('BW P&L'!$O12:$Q12) | E77: =SUM('CED P&L'!$O12:$Q12) | F77: =SUM('HB P&L'!$O12:$Q12) | G77: =SUM('KIN P&L'!$O12:$Q12) | H77: =SUM('MER P&L'!$O12:$Q12) | I77: =SUM('SST P&L'!$O12:$Q12) | J77: =SUM('HDN P&L'!$O12:$Q12) | K77: =SUM('NDN P&L'!$O12:$Q12) | L77: =SUM('SDN P&L'!$O12:$Q12) | M77: =SUM('LE P&L'!$O12:$Q12) | N77: =SUM('WH P&L'!$O12:$Q12) | O77: =SUM('HS P&L'!$O12:$Q12) | P77: =SUM('FH P&L'!$O12:$Q12) | Q77: =SUM('HAB P&L'!$O12:$Q12) | R77: =SUM('SALT P&L'!$O12:$Q12) | S77: =SUM('KNL HO P&L'!$O12:$Q12)+SUM('CCL HO P&L'!$O12:$Q12)+SUM('YBHN HO P&L'!$O12:$Q12)+SUM('YBN HO P&L'!$O12:$Q12)+SUM('Moe2 P&L'!$O12:$Q12) | T77: =SUM(B77:S77) | U77: =SUM('ABA P&L'!$R12:$T12) | V77: =SUM('BK P&L'!$R12:$T12) | W77: =SUM('BW P&L'!$R12:$T12) | X77: =SUM('CED P&L'!$R12:$T12) | Y77: =SUM('HB P&L'!$R12:$T12) | Z77: =SUM('KIN P&L'!$R12:$T12) | AA77: =SUM('MER P&L'!$R12:$T12) | AB77: =SUM('SST P&L'!$R12:$T12) | AC77: =SUM('HDN P&L'!$R12:$T12) | AD77: =SUM('NDN P&L'!$R12:$T12) | AE77: =SUM('SDN P&L'!$R12:$T12) | AF77: =SUM('LE P&L'!$R12:$T12) | AG77: =SUM('WH P&L'!$R12:$T12) | AH77: =SUM('HS P&L'!$R12:$T12) | AI77: =SUM('FH P&L'!$R12:$T12) | AJ77: =SUM('HAB P&L'!$R12:$T12) | AK77: =SUM('SALT P&L'!$R12:$T12) | AL77: =SUM('KNL HO P&L'!$R12:$T12)+SUM('CCL HO P&L'!$R12:$T12)+SUM('YBHN HO P&L'!$R12:$T12)+SUM('YBN HO P&L'!$R12:$T12)+SUM('Moe2 P&L'!$R12:$T12) | AM77: =SUM(U77:AL77) | AN77: =SUM('ABA P&L'!$U12:$W12) | AO77: =SUM('BK P&L'!$U12:$W12) | AP77: =SUM('BW P&L'!$U12:$W12) | AQ77: =SUM('CED P&L'!$U12:$W12) | AR77: =SUM('HB P&L'!$U12:$W12) | AS77: =SUM('KIN P&L'!$U12:$W12) | AT77: =SUM('MER P&L'!$U12:$W12) | AU77: =SUM('SST P&L'!$U12:$W12) | AV77: =SUM('HDN P&L'!$U12:$W12) | AW77: =SUM('NDN P&L'!$U12:$W12) | AX77: =SUM('SDN P&L'!$U12:$W12) | AY77: =SUM('LE P&L'!$U12:$W12) | AZ77: =SUM('WH P&L'!$U12:$W12) | BA77: =SUM('HS P&L'!$U12:$W12) | BB77: =SUM('FH P&L'!$U12:$W12) | BC77: =SUM('HAB P&L'!$U12:$W12) | BD77: =SUM('SALT P&L'!$U12:$W12) | BE77: =SUM('KNL HO P&L'!$U12:$W12)+SUM('CCL HO P&L'!$U12:$W12)+SUM('YBHN HO P&L'!$U12:$W12)+SUM('YBN HO P&L'!$U12:$W12)+SUM('Moe2 P&L'!$U12:$W12) | BF77: =SUM(AN77:BE77) | BG77: =SUM('ABA P&L'!$X12:$Z12) | BH77: =SUM('BK P&L'!$X12:$Z12) | BI77: =SUM('BW P&L'!$X12:$Z12) | BJ77: =SUM('CED P&L'!$X12:$Z12) | BK77: =SUM('HB P&L'!$X12:$Z12) | BL77: =SUM('KIN P&L'!$X12:$Z12) | BM77: =SUM('MER P&L'!$X12:$Z12) | BN77: =SUM('SST P&L'!$X12:$Z12) | BO77: =SUM('HDN P&L'!$X12:$Z12) | BP77: =SUM('NDN P&L'!$X12:$Z12) | BQ77: =SUM('SDN P&L'!$X12:$Z12) | BR77: =SUM('LE P&L'!$X12:$Z12) | BS77: =SUM('WH P&L'!$X12:$Z12) | BT77: =SUM('HS P&L'!$X12:$Z12) | BU77: =SUM('FH P&L'!$X12:$Z12) | BV77: =SUM('HAB P&L'!$X12:$Z12) | BW77: =SUM('SALT P&L'!$X12:$Z12) | BX77: =SUM('KNL HO P&L'!$X12:$Z12)+SUM('CCL HO P&L'!$X12:$Z12)+SUM('YBHN HO P&L'!$X12:$Z12)+SUM('YBN HO P&L'!$X12:$Z12)+SUM('Moe2 P&L'!$X12:$Z12) | BY77: =SUM(BG77:BX77) | BZ77: =BY77+BF77+AM77+T77 | CA77: ='GROUP TOTALS MONTHLY P&L'!AB12 | CB77: =BZ77-CA77
A78: Personnel | B78: =SUM('ABA P&L'!$O15:$Q15) | C78: =SUM('BK P&L'!$O15:$Q15) | D78: =SUM('BW P&L'!$O15:$Q15) | E78: =SUM('CED P&L'!$O15:$Q15) | F78: =SUM('HB P&L'!$O15:$Q15) | G78: =SUM('KIN P&L'!$O15:$Q15) | H78: =SUM('MER P&L'!$O15:$Q15) | I78: =SUM('SST P&L'!$O15:$Q15) | J78: =SUM('HDN P&L'!$O15:$Q15) | K78: =SUM('NDN P&L'!$O15:$Q15) | L78: =SUM('SDN P&L'!$O15:$Q15) | M78: =SUM('LE P&L'!$O15:$Q15) | N78: =SUM('WH P&L'!$O15:$Q15) | O78: =SUM('HS P&L'!$O15:$Q15) | P78: =SUM('FH P&L'!$O15:$Q15) | Q78: =SUM('HAB P&L'!$O15:$Q15) | R78: =SUM('SALT P&L'!$O15:$Q15) | S78: =SUM('KNL HO P&L'!$O15:$Q15)+SUM('CCL HO P&L'!$O15:$Q15)+SUM('YBHN HO P&L'!$O15:$Q15)+SUM('YBN HO P&L'!$O15:$Q15)+SUM('Moe2 P&L'!$O15:$Q15) | T78: =SUM(B78:S78) | U78: =SUM('ABA P&L'!$R15:$T15) | V78: =SUM('BK P&L'!$R15:$T15) | W78: =SUM('BW P&L'!$R15:$T15) | X78: =SUM('CED P&L'!$R15:$T15) | Y78: =SUM('HB P&L'!$R15:$T15) | Z78: =SUM('KIN P&L'!$R15:$T15) | AA78: =SUM('MER P&L'!$R15:$T15) | AB78: =SUM('SST P&L'!$R15:$T15) | AC78: =SUM('HDN P&L'!$R15:$T15) | AD78: =SUM('NDN P&L'!$R15:$T15) | AE78: =SUM('SDN P&L'!$R15:$T15) | AF78: =SUM('LE P&L'!$R15:$T15) | AG78: =SUM('WH P&L'!$R15:$T15) | AH78: =SUM('HS P&L'!$R15:$T15) | AI78: =SUM('FH P&L'!$R15:$T15) | AJ78: =SUM('HAB P&L'!$R15:$T15) | AK78: =SUM('SALT P&L'!$R15:$T15) | AL78: =SUM('KNL HO P&L'!$R15:$T15)+SUM('CCL HO P&L'!$R15:$T15)+SUM('YBHN HO P&L'!$R15:$T15)+SUM('YBN HO P&L'!$R15:$T15)+SUM('Moe2 P&L'!$R15:$T15) | AM78: =SUM(U78:AL78) | AN78: =SUM('ABA P&L'!$U15:$W15) | AO78: =SUM('BK P&L'!$U15:$W15) | AP78: =SUM('BW P&L'!$U15:$W15) | AQ78: =SUM('CED P&L'!$U15:$W15) | AR78: =SUM('HB P&L'!$U15:$W15) | AS78: =SUM('KIN P&L'!$U15:$W15) | AT78: =SUM('MER P&L'!$U15:$W15) | AU78: =SUM('SST P&L'!$U15:$W15) | AV78: =SUM('HDN P&L'!$U15:$W15) | AW78: =SUM('NDN P&L'!$U15:$W15) | AX78: =SUM('SDN P&L'!$U15:$W15) | AY78: =SUM('LE P&L'!$U15:$W15) | AZ78: =SUM('WH P&L'!$U15:$W15) | BA78: =SUM('HS P&L'!$U15:$W15) | BB78: =SUM('FH P&L'!$U15:$W15) | BC78: =SUM('HAB P&L'!$U15:$W15) | BD78: =SUM('SALT P&L'!$U15:$W15) | BE78: =SUM('KNL HO P&L'!$U15:$W15)+SUM('CCL HO P&L'!$U15:$W15)+SUM('YBHN HO P&L'!$U15:$W15)+SUM('YBN HO P&L'!$U15:$W15)+SUM('Moe2 P&L'!$U15:$W15) | BF78: =SUM(AN78:BE78) | BG78: =SUM('ABA P&L'!$X15:$Z15) | BH78: =SUM('BK P&L'!$X15:$Z15) | BI78: =SUM('BW P&L'!$X15:$Z15) | BJ78: =SUM('CED P&L'!$X15:$Z15) | BK78: =SUM('HB P&L'!$X15:$Z15) | BL78: =SUM('KIN P&L'!$X15:$Z15) | BM78: =SUM('MER P&L'!$X15:$Z15) | BN78: =SUM('SST P&L'!$X15:$Z15) | BO78: =SUM('HDN P&L'!$X15:$Z15) | BP78: =SUM('NDN P&L'!$X15:$Z15) | BQ78: =SUM('SDN P&L'!$X15:$Z15) | BR78: =SUM('LE P&L'!$X15:$Z15) | BS78: =SUM('WH P&L'!$X15:$Z15) | BT78: =SUM('HS P&L'!$X15:$Z15) | BU78: =SUM('FH P&L'!$X15:$Z15) | BV78: =SUM('HAB P&L'!$X15:$Z15) | BW78: =SUM('SALT P&L'!$X15:$Z15) | BX78: =SUM('KNL HO P&L'!$X15:$Z15)+SUM('CCL HO P&L'!$X15:$Z15)+SUM('YBHN HO P&L'!$X15:$Z15)+SUM('YBN HO P&L'!$X15:$Z15)+SUM('Moe2 P&L'!$X15:$Z15) | BY78: =SUM(BG78:BX78) | BZ78: =BY78+BF78+AM78+T78 | CA78: ='GROUP TOTALS MONTHLY P&L'!AB15 | CB78: =BZ78-CA78
A79: Nursery Salaries | B79: =SUM('ABA P&L'!$O16:$Q16) | C79: =SUM('BK P&L'!$O16:$Q16) | D79: =SUM('BW P&L'!$O16:$Q16) | E79: =SUM('CED P&L'!$O16:$Q16) | F79: =SUM('HB P&L'!$O16:$Q16) | G79: =SUM('KIN P&L'!$O16:$Q16) | H79: =SUM('MER P&L'!$O16:$Q16) | I79: =SUM('SST P&L'!$O16:$Q16) | J79: =SUM('HDN P&L'!$O16:$Q16) | K79: =SUM('NDN P&L'!$O16:$Q16) | L79: =SUM('SDN P&L'!$O16:$Q16) | M79: =SUM('LE P&L'!$O16:$Q16) | N79: =SUM('WH P&L'!$O16:$Q16) | O79: =SUM('HS P&L'!$O16:$Q16) | P79: =SUM('FH P&L'!$O16:$Q16) | Q79: =SUM('HAB P&L'!$O16:$Q16) | R79: =SUM('SALT P&L'!$O16:$Q16) | S79: =SUM('KNL HO P&L'!$O16:$Q16)+SUM('CCL HO P&L'!$O16:$Q16)+SUM('YBHN HO P&L'!$O16:$Q16)+SUM('YBN HO P&L'!$O16:$Q16)+SUM('Moe2 P&L'!$O16:$Q16) | T79: =SUM(B79:S79) | U79: =SUM('ABA P&L'!$R16:$T16) | V79: =SUM('BK P&L'!$R16:$T16) | W79: =SUM('BW P&L'!$R16:$T16) | X79: =SUM('CED P&L'!$R16:$T16) | Y79: =SUM('HB P&L'!$R16:$T16) | Z79: =SUM('KIN P&L'!$R16:$T16) | AA79: =SUM('MER P&L'!$R16:$T16) | AB79: =SUM('SST P&L'!$R16:$T16) | AC79: =SUM('HDN P&L'!$R16:$T16) | AD79: =SUM('NDN P&L'!$R16:$T16) | AE79: =SUM('SDN P&L'!$R16:$T16) | AF79: =SUM('LE P&L'!$R16:$T16) | AG79: =SUM('WH P&L'!$R16:$T16) | AH79: =SUM('HS P&L'!$R16:$T16) | AI79: =SUM('FH P&L'!$R16:$T16) | AJ79: =SUM('HAB P&L'!$R16:$T16) | AK79: =SUM('SALT P&L'!$R16:$T16) | AL79: =SUM('KNL HO P&L'!$R16:$T16)+SUM('CCL HO P&L'!$R16:$T16)+SUM('YBHN HO P&L'!$R16:$T16)+SUM('YBN HO P&L'!$R16:$T16)+SUM('Moe2 P&L'!$R16:$T16) | AM79: =SUM(U79:AL79) | AN79: =SUM('ABA P&L'!$U16:$W16) | AO79: =SUM('BK P&L'!$U16:$W16) | AP79: =SUM('BW P&L'!$U16:$W16) | AQ79: =SUM('CED P&L'!$U16:$W16) | AR79: =SUM('HB P&L'!$U16:$W16) | AS79: =SUM('KIN P&L'!$U16:$W16) | AT79: =SUM('MER P&L'!$U16:$W16) | AU79: =SUM('SST P&L'!$U16:$W16) | AV79: =SUM('HDN P&L'!$U16:$W16) | AW79: =SUM('NDN P&L'!$U16:$W16) | AX79: =SUM('SDN P&L'!$U16:$W16) | AY79: =SUM('LE P&L'!$U16:$W16) | AZ79: =SUM('WH P&L'!$U16:$W16) | BA79: =SUM('HS P&L'!$U16:$W16) | BB79: =SUM('FH P&L'!$U16:$W16) | BC79: =SUM('HAB P&L'!$U16:$W16) | BD79: =SUM('SALT P&L'!$U16:$W16) | BE79: =SUM('KNL HO P&L'!$U16:$W16)+SUM('CCL HO P&L'!$U16:$W16)+SUM('YBHN HO P&L'!$U16:$W16)+SUM('YBN HO P&L'!$U16:$W16)+SUM('Moe2 P&L'!$U16:$W16) | BF79: =SUM(AN79:BE79) | BG79: =SUM('ABA P&L'!$X16:$Z16) | BH79: =SUM('BK P&L'!$X16:$Z16) | BI79: =SUM('BW P&L'!$X16:$Z16) | BJ79: =SUM('CED P&L'!$X16:$Z16) | BK79: =SUM('HB P&L'!$X16:$Z16) | BL79: =SUM('KIN P&L'!$X16:$Z16) | BM79: =SUM('MER P&L'!$X16:$Z16) | BN79: =SUM('SST P&L'!$X16:$Z16) | BO79: =SUM('HDN P&L'!$X16:$Z16) | BP79: =SUM('NDN P&L'!$X16:$Z16) | BQ79: =SUM('SDN P&L'!$X16:$Z16) | BR79: =SUM('LE P&L'!$X16:$Z16) | BS79: =SUM('WH P&L'!$X16:$Z16) | BT79: =SUM('HS P&L'!$X16:$Z16) | BU79: =SUM('FH P&L'!$X16:$Z16) | BV79: =SUM('HAB P&L'!$X16:$Z16) | BW79: =SUM('SALT P&L'!$X16:$Z16) | BX79: =SUM('KNL HO P&L'!$X16:$Z16)+SUM('CCL HO P&L'!$X16:$Z16)+SUM('YBHN HO P&L'!$X16:$Z16)+SUM('YBN HO P&L'!$X16:$Z16)+SUM('Moe2 P&L'!$X16:$Z16) | BY79: =SUM(BG79:BX79) | BZ79: =BY79+BF79+AM79+T79 | CA79: ='GROUP TOTALS MONTHLY P&L'!AB16 | CB79: =BZ79-CA79
A80: Nursery NI | B80: =SUM('ABA P&L'!$O17:$Q17) | C80: =SUM('BK P&L'!$O17:$Q17) | D80: =SUM('BW P&L'!$O17:$Q17) | E80: =SUM('CED P&L'!$O17:$Q17) | F80: =SUM('HB P&L'!$O17:$Q17) | G80: =SUM('KIN P&L'!$O17:$Q17) | H80: =SUM('MER P&L'!$O17:$Q17) | I80: =SUM('SST P&L'!$O17:$Q17) | J80: =SUM('HDN P&L'!$O17:$Q17) | K80: =SUM('NDN P&L'!$O17:$Q17) | L80: =SUM('SDN P&L'!$O17:$Q17) | M80: =SUM('LE P&L'!$O17:$Q17) | N80: =SUM('WH P&L'!$O17:$Q17) | O80: =SUM('HS P&L'!$O17:$Q17) | P80: =SUM('FH P&L'!$O17:$Q17) | Q80: =SUM('HAB P&L'!$O17:$Q17) | R80: =SUM('SALT P&L'!$O17:$Q17) | S80: =SUM('KNL HO P&L'!$O17:$Q17)+SUM('CCL HO P&L'!$O17:$Q17)+SUM('YBHN HO P&L'!$O17:$Q17)+SUM('YBN HO P&L'!$O17:$Q17)+SUM('Moe2 P&L'!$O17:$Q17) | T80: =SUM(B80:S80) | U80: =SUM('ABA P&L'!$R17:$T17) | V80: =SUM('BK P&L'!$R17:$T17) | W80: =SUM('BW P&L'!$R17:$T17) | X80: =SUM('CED P&L'!$R17:$T17) | Y80: =SUM('HB P&L'!$R17:$T17) | Z80: =SUM('KIN P&L'!$R17:$T17) | AA80: =SUM('MER P&L'!$R17:$T17) | AB80: =SUM('SST P&L'!$R17:$T17) | AC80: =SUM('HDN P&L'!$R17:$T17) | AD80: =SUM('NDN P&L'!$R17:$T17) | AE80: =SUM('SDN P&L'!$R17:$T17) | AF80: =SUM('LE P&L'!$R17:$T17) | AG80: =SUM('WH P&L'!$R17:$T17) | AH80: =SUM('HS P&L'!$R17:$T17) | AI80: =SUM('FH P&L'!$R17:$T17) | AJ80: =SUM('HAB P&L'!$R17:$T17) | AK80: =SUM('SALT P&L'!$R17:$T17) | AL80: =SUM('KNL HO P&L'!$R17:$T17)+SUM('CCL HO P&L'!$R17:$T17)+SUM('YBHN HO P&L'!$R17:$T17)+SUM('YBN HO P&L'!$R17:$T17)+SUM('Moe2 P&L'!$R17:$T17) | AM80: =SUM(U80:AL80) | AN80: =SUM('ABA P&L'!$U17:$W17) | AO80: =SUM('BK P&L'!$U17:$W17) | AP80: =SUM('BW P&L'!$U17:$W17) | AQ80: =SUM('CED P&L'!$U17:$W17) | AR80: =SUM('HB P&L'!$U17:$W17) | AS80: =SUM('KIN P&L'!$U17:$W17) | AT80: =SUM('MER P&L'!$U17:$W17) | AU80: =SUM('SST P&L'!$U17:$W17) | AV80: =SUM('HDN P&L'!$U17:$W17) | AW80: =SUM('NDN P&L'!$U17:$W17) | AX80: =SUM('SDN P&L'!$U17:$W17) | AY80: =SUM('LE P&L'!$U17:$W17) | AZ80: =SUM('WH P&L'!$U17:$W17) | BA80: =SUM('HS P&L'!$U17:$W17) | BB80: =SUM('FH P&L'!$U17:$W17) | BC80: =SUM('HAB P&L'!$U17:$W17) | BD80: =SUM('SALT P&L'!$U17:$W17) | BE80: =SUM('KNL HO P&L'!$U17:$W17)+SUM('CCL HO P&L'!$U17:$W17)+SUM('YBHN HO P&L'!$U17:$W17)+SUM('YBN HO P&L'!$U17:$W17)+SUM('Moe2 P&L'!$U17:$W17) | BF80: =SUM(AN80:BE80) | BG80: =SUM('ABA P&L'!$X17:$Z17) | BH80: =SUM('BK P&L'!$X17:$Z17) | BI80: =SUM('BW P&L'!$X17:$Z17) | BJ80: =SUM('CED P&L'!$X17:$Z17) | BK80: =SUM('HB P&L'!$X17:$Z17) | BL80: =SUM('KIN P&L'!$X17:$Z17) | BM80: =SUM('MER P&L'!$X17:$Z17) | BN80: =SUM('SST P&L'!$X17:$Z17) | BO80: =SUM('HDN P&L'!$X17:$Z17) | BP80: =SUM('NDN P&L'!$X17:$Z17) | BQ80: =SUM('SDN P&L'!$X17:$Z17) | BR80: =SUM('LE P&L'!$X17:$Z17) | BS80: =SUM('WH P&L'!$X17:$Z17) | BT80: =SUM('HS P&L'!$X17:$Z17) | BU80: =SUM('FH P&L'!$X17:$Z17) | BV80: =SUM('HAB P&L'!$X17:$Z17) | BW80: =SUM('SALT P&L'!$X17:$Z17) | BX80: =SUM('KNL HO P&L'!$X17:$Z17)+SUM('CCL HO P&L'!$X17:$Z17)+SUM('YBHN HO P&L'!$X17:$Z17)+SUM('YBN HO P&L'!$X17:$Z17)+SUM('Moe2 P&L'!$X17:$Z17) | BY80: =SUM(BG80:BX80) | BZ80: =BY80+BF80+AM80+T80 | CA80: ='GROUP TOTALS MONTHLY P&L'!AB17 | CB80: =BZ80-CA80
A81: Nursery Pension | B81: =SUM('ABA P&L'!$O18:$Q18) | C81: =SUM('BK P&L'!$O18:$Q18) | D81: =SUM('BW P&L'!$O18:$Q18) | E81: =SUM('CED P&L'!$O18:$Q18) | F81: =SUM('HB P&L'!$O18:$Q18) | G81: =SUM('KIN P&L'!$O18:$Q18) | H81: =SUM('MER P&L'!$O18:$Q18) | I81: =SUM('SST P&L'!$O18:$Q18) | J81: =SUM('HDN P&L'!$O18:$Q18) | K81: =SUM('NDN P&L'!$O18:$Q18) | L81: =SUM('SDN P&L'!$O18:$Q18) | M81: =SUM('LE P&L'!$O18:$Q18) | N81: =SUM('WH P&L'!$O18:$Q18) | O81: =SUM('HS P&L'!$O18:$Q18) | P81: =SUM('FH P&L'!$O18:$Q18) | Q81: =SUM('HAB P&L'!$O18:$Q18) | R81: =SUM('SALT P&L'!$O18:$Q18) | S81: =SUM('KNL HO P&L'!$O18:$Q18)+SUM('CCL HO P&L'!$O18:$Q18)+SUM('YBHN HO P&L'!$O18:$Q18)+SUM('YBN HO P&L'!$O18:$Q18)+SUM('Moe2 P&L'!$O18:$Q18) | T81: =SUM(B81:S81) | U81: =SUM('ABA P&L'!$R18:$T18) | V81: =SUM('BK P&L'!$R18:$T18) | W81: =SUM('BW P&L'!$R18:$T18) | X81: =SUM('CED P&L'!$R18:$T18) | Y81: =SUM('HB P&L'!$R18:$T18) | Z81: =SUM('KIN P&L'!$R18:$T18) | AA81: =SUM('MER P&L'!$R18:$T18) | AB81: =SUM('SST P&L'!$R18:$T18) | AC81: =SUM('HDN P&L'!$R18:$T18) | AD81: =SUM('NDN P&L'!$R18:$T18) | AE81: =SUM('SDN P&L'!$R18:$T18) | AF81: =SUM('LE P&L'!$R18:$T18) | AG81: =SUM('WH P&L'!$R18:$T18) | AH81: =SUM('HS P&L'!$R18:$T18) | AI81: =SUM('FH P&L'!$R18:$T18) | AJ81: =SUM('HAB P&L'!$R18:$T18) | AK81: =SUM('SALT P&L'!$R18:$T18) | AL81: =SUM('KNL HO P&L'!$R18:$T18)+SUM('CCL HO P&L'!$R18:$T18)+SUM('YBHN HO P&L'!$R18:$T18)+SUM('YBN HO P&L'!$R18:$T18)+SUM('Moe2 P&L'!$R18:$T18) | AM81: =SUM(U81:AL81) | AN81: =SUM('ABA P&L'!$U18:$W18) | AO81: =SUM('BK P&L'!$U18:$W18) | AP81: =SUM('BW P&L'!$U18:$W18) | AQ81: =SUM('CED P&L'!$U18:$W18) | AR81: =SUM('HB P&L'!$U18:$W18) | AS81: =SUM('KIN P&L'!$U18:$W18) | AT81: =SUM('MER P&L'!$U18:$W18) | AU81: =SUM('SST P&L'!$U18:$W18) | AV81: =SUM('HDN P&L'!$U18:$W18) | AW81: =SUM('NDN P&L'!$U18:$W18) | AX81: =SUM('SDN P&L'!$U18:$W18) | AY81: =SUM('LE P&L'!$U18:$W18) | AZ81: =SUM('WH P&L'!$U18:$W18) | BA81: =SUM('HS P&L'!$U18:$W18) | BB81: =SUM('FH P&L'!$U18:$W18) | BC81: =SUM('HAB P&L'!$U18:$W18) | BD81: =SUM('SALT P&L'!$U18:$W18) | BE81: =SUM('KNL HO P&L'!$U18:$W18)+SUM('CCL HO P&L'!$U18:$W18)+SUM('YBHN HO P&L'!$U18:$W18)+SUM('YBN HO P&L'!$U18:$W18)+SUM('Moe2 P&L'!$U18:$W18) | BF81: =SUM(AN81:BE81) | BG81: =SUM('ABA P&L'!$X18:$Z18) | BH81: =SUM('BK P&L'!$X18:$Z18) | BI81: =SUM('BW P&L'!$X18:$Z18) | BJ81: =SUM('CED P&L'!$X18:$Z18) | BK81: =SUM('HB P&L'!$X18:$Z18) | BL81: =SUM('KIN P&L'!$X18:$Z18) | BM81: =SUM('MER P&L'!$X18:$Z18) | BN81: =SUM('SST P&L'!$X18:$Z18) | BO81: =SUM('HDN P&L'!$X18:$Z18) | BP81: =SUM('NDN P&L'!$X18:$Z18) | BQ81: =SUM('SDN P&L'!$X18:$Z18) | BR81: =SUM('LE P&L'!$X18:$Z18) | BS81: =SUM('WH P&L'!$X18:$Z18) | BT81: =SUM('HS P&L'!$X18:$Z18) | BU81: =SUM('FH P&L'!$X18:$Z18) | BV81: =SUM('HAB P&L'!$X18:$Z18) | BW81: =SUM('SALT P&L'!$X18:$Z18) | BX81: =SUM('KNL HO P&L'!$X18:$Z18)+SUM('CCL HO P&L'!$X18:$Z18)+SUM('YBHN HO P&L'!$X18:$Z18)+SUM('YBN HO P&L'!$X18:$Z18)+SUM('Moe2 P&L'!$X18:$Z18) | BY81: =SUM(BG81:BX81) | BZ81: =BY81+BF81+AM81+T81 | CA81: ='GROUP TOTALS MONTHLY P&L'!AB18 | CB81: =BZ81-CA81
A82: Uniform | B82: =SUM('ABA P&L'!$O19:$Q19) | C82: =SUM('BK P&L'!$O19:$Q19) | D82: =SUM('BW P&L'!$O19:$Q19) | E82: =SUM('CED P&L'!$O19:$Q19) | F82: =SUM('HB P&L'!$O19:$Q19) | G82: =SUM('KIN P&L'!$O19:$Q19) | H82: =SUM('MER P&L'!$O19:$Q19) | I82: =SUM('SST P&L'!$O19:$Q19) | J82: =SUM('HDN P&L'!$O19:$Q19) | K82: =SUM('NDN P&L'!$O19:$Q19) | L82: =SUM('SDN P&L'!$O19:$Q19) | M82: =SUM('LE P&L'!$O19:$Q19) | N82: =SUM('WH P&L'!$O19:$Q19) | O82: =SUM('HS P&L'!$O19:$Q19) | P82: =SUM('FH P&L'!$O19:$Q19) | Q82: =SUM('HAB P&L'!$O19:$Q19) | R82: =SUM('SALT P&L'!$O19:$Q19) | S82: =SUM('KNL HO P&L'!$O19:$Q19)+SUM('CCL HO P&L'!$O19:$Q19)+SUM('YBHN HO P&L'!$O19:$Q19)+SUM('YBN HO P&L'!$O19:$Q19)+SUM('Moe2 P&L'!$O19:$Q19) | T82: =SUM(B82:S82) | U82: =SUM('ABA P&L'!$R19:$T19) | V82: =SUM('BK P&L'!$R19:$T19) | W82: =SUM('BW P&L'!$R19:$T19) | X82: =SUM('CED P&L'!$R19:$T19) | Y82: =SUM('HB P&L'!$R19:$T19) | Z82: =SUM('KIN P&L'!$R19:$T19) | AA82: =SUM('MER P&L'!$R19:$T19) | AB82: =SUM('SST P&L'!$R19:$T19) | AC82: =SUM('HDN P&L'!$R19:$T19) | AD82: =SUM('NDN P&L'!$R19:$T19) | AE82: =SUM('SDN P&L'!$R19:$T19) | AF82: =SUM('LE P&L'!$R19:$T19) | AG82: =SUM('WH P&L'!$R19:$T19) | AH82: =SUM('HS P&L'!$R19:$T19) | AI82: =SUM('FH P&L'!$R19:$T19) | AJ82: =SUM('HAB P&L'!$R19:$T19) | AK82: =SUM('SALT P&L'!$R19:$T19) | AL82: =SUM('KNL HO P&L'!$R19:$T19)+SUM('CCL HO P&L'!$R19:$T19)+SUM('YBHN HO P&L'!$R19:$T19)+SUM('YBN HO P&L'!$R19:$T19)+SUM('Moe2 P&L'!$R19:$T19) | AM82: =SUM(U82:AL82) | AN82: =SUM('ABA P&L'!$U19:$W19) | AO82: =SUM('BK P&L'!$U19:$W19) | AP82: =SUM('BW P&L'!$U19:$W19) | AQ82: =SUM('CED P&L'!$U19:$W19) | AR82: =SUM('HB P&L'!$U19:$W19) | AS82: =SUM('KIN P&L'!$U19:$W19) | AT82: =SUM('MER P&L'!$U19:$W19) | AU82: =SUM('SST P&L'!$U19:$W19) | AV82: =SUM('HDN P&L'!$U19:$W19) | AW82: =SUM('NDN P&L'!$U19:$W19) | AX82: =SUM('SDN P&L'!$U19:$W19) | AY82: =SUM('LE P&L'!$U19:$W19) | AZ82: =SUM('WH P&L'!$U19:$W19) | BA82: =SUM('HS P&L'!$U19:$W19) | BB82: =SUM('FH P&L'!$U19:$W19) | BC82: =SUM('HAB P&L'!$U19:$W19) | BD82: =SUM('SALT P&L'!$U19:$W19) | BE82: =SUM('KNL HO P&L'!$U19:$W19)+SUM('CCL HO P&L'!$U19:$W19)+SUM('YBHN HO P&L'!$U19:$W19)+SUM('YBN HO P&L'!$U19:$W19)+SUM('Moe2 P&L'!$U19:$W19) | BF82: =SUM(AN82:BE82) | BG82: =SUM('ABA P&L'!$X19:$Z19) | BH82: =SUM('BK P&L'!$X19:$Z19) | BI82: =SUM('BW P&L'!$X19:$Z19) | BJ82: =SUM('CED P&L'!$X19:$Z19) | BK82: =SUM('HB P&L'!$X19:$Z19) | BL82: =SUM('KIN P&L'!$X19:$Z19) | BM82: =SUM('MER P&L'!$X19:$Z19) | BN82: =SUM('SST P&L'!$X19:$Z19) | BO82: =SUM('HDN P&L'!$X19:$Z19) | BP82: =SUM('NDN P&L'!$X19:$Z19) | BQ82: =SUM('SDN P&L'!$X19:$Z19) | BR82: =SUM('LE P&L'!$X19:$Z19) | BS82: =SUM('WH P&L'!$X19:$Z19) | BT82: =SUM('HS P&L'!$X19:$Z19) | BU82: =SUM('FH P&L'!$X19:$Z19) | BV82: =SUM('HAB P&L'!$X19:$Z19) | BW82: =SUM('SALT P&L'!$X19:$Z19) | BX82: =SUM('KNL HO P&L'!$X19:$Z19)+SUM('CCL HO P&L'!$X19:$Z19)+SUM('YBHN HO P&L'!$X19:$Z19)+SUM('YBN HO P&L'!$X19:$Z19)+SUM('Moe2 P&L'!$X19:$Z19) | BY82: =SUM(BG82:BX82) | BZ82: =BY82+BF82+AM82+T82 | CA82: ='GROUP TOTALS MONTHLY P&L'!AB19 | CB82: =BZ82-CA82
A83: Training | B83: =SUM('ABA P&L'!$O20:$Q20) | C83: =SUM('BK P&L'!$O20:$Q20) | D83: =SUM('BW P&L'!$O20:$Q20) | E83: =SUM('CED P&L'!$O20:$Q20) | F83: =SUM('HB P&L'!$O20:$Q20) | G83: =SUM('KIN P&L'!$O20:$Q20) | H83: =SUM('MER P&L'!$O20:$Q20) | I83: =SUM('SST P&L'!$O20:$Q20) | J83: =SUM('HDN P&L'!$O20:$Q20) | K83: =SUM('NDN P&L'!$O20:$Q20) | L83: =SUM('SDN P&L'!$O20:$Q20) | M83: =SUM('LE P&L'!$O20:$Q20) | N83: =SUM('WH P&L'!$O20:$Q20) | O83: =SUM('HS P&L'!$O20:$Q20) | P83: =SUM('FH P&L'!$O20:$Q20) | Q83: =SUM('HAB P&L'!$O20:$Q20) | R83: =SUM('SALT P&L'!$O20:$Q20) | S83: =SUM('KNL HO P&L'!$O20:$Q20)+SUM('CCL HO P&L'!$O20:$Q20)+SUM('YBHN HO P&L'!$O20:$Q20)+SUM('YBN HO P&L'!$O20:$Q20)+SUM('Moe2 P&L'!$O20:$Q20) | T83: =SUM(B83:S83) | U83: =SUM('ABA P&L'!$R20:$T20) | V83: =SUM('BK P&L'!$R20:$T20) | W83: =SUM('BW P&L'!$R20:$T20) | X83: =SUM('CED P&L'!$R20:$T20) | Y83: =SUM('HB P&L'!$R20:$T20) | Z83: =SUM('KIN P&L'!$R20:$T20) | AA83: =SUM('MER P&L'!$R20:$T20) | AB83: =SUM('SST P&L'!$R20:$T20) | AC83: =SUM('HDN P&L'!$R20:$T20) | AD83: =SUM('NDN P&L'!$R20:$T20) | AE83: =SUM('SDN P&L'!$R20:$T20) | AF83: =SUM('LE P&L'!$R20:$T20) | AG83: =SUM('WH P&L'!$R20:$T20) | AH83: =SUM('HS P&L'!$R20:$T20) | AI83: =SUM('FH P&L'!$R20:$T20) | AJ83: =SUM('HAB P&L'!$R20:$T20) | AK83: =SUM('SALT P&L'!$R20:$T20) | AL83: =SUM('KNL HO P&L'!$R20:$T20)+SUM('CCL HO P&L'!$R20:$T20)+SUM('YBHN HO P&L'!$R20:$T20)+SUM('YBN HO P&L'!$R20:$T20)+SUM('Moe2 P&L'!$R20:$T20) | AM83: =SUM(U83:AL83) | AN83: =SUM('ABA P&L'!$U20:$W20) | AO83: =SUM('BK P&L'!$U20:$W20) | AP83: =SUM('BW P&L'!$U20:$W20) | AQ83: =SUM('CED P&L'!$U20:$W20) | AR83: =SUM('HB P&L'!$U20:$W20) | AS83: =SUM('KIN P&L'!$U20:$W20) | AT83: =SUM('MER P&L'!$U20:$W20) | AU83: =SUM('SST P&L'!$U20:$W20) | AV83: =SUM('HDN P&L'!$U20:$W20) | AW83: =SUM('NDN P&L'!$U20:$W20) | AX83: =SUM('SDN P&L'!$U20:$W20) | AY83: =SUM('LE P&L'!$U20:$W20) | AZ83: =SUM('WH P&L'!$U20:$W20) | BA83: =SUM('HS P&L'!$U20:$W20) | BB83: =SUM('FH P&L'!$U20:$W20) | BC83: =SUM('HAB P&L'!$U20:$W20) | BD83: =SUM('SALT P&L'!$U20:$W20) | BE83: =SUM('KNL HO P&L'!$U20:$W20)+SUM('CCL HO P&L'!$U20:$W20)+SUM('YBHN HO P&L'!$U20:$W20)+SUM('YBN HO P&L'!$U20:$W20)+SUM('Moe2 P&L'!$U20:$W20) | BF83: =SUM(AN83:BE83) | BG83: =SUM('ABA P&L'!$X20:$Z20) | BH83: =SUM('BK P&L'!$X20:$Z20) | BI83: =SUM('BW P&L'!$X20:$Z20) | BJ83: =SUM('CED P&L'!$X20:$Z20) | BK83: =SUM('HB P&L'!$X20:$Z20) | BL83: =SUM('KIN P&L'!$X20:$Z20) | BM83: =SUM('MER P&L'!$X20:$Z20) | BN83: =SUM('SST P&L'!$X20:$Z20) | BO83: =SUM('HDN P&L'!$X20:$Z20) | BP83: =SUM('NDN P&L'!$X20:$Z20) | BQ83: =SUM('SDN P&L'!$X20:$Z20) | BR83: =SUM('LE P&L'!$X20:$Z20) | BS83: =SUM('WH P&L'!$X20:$Z20) | BT83: =SUM('HS P&L'!$X20:$Z20) | BU83: =SUM('FH P&L'!$X20:$Z20) | BV83: =SUM('HAB P&L'!$X20:$Z20) | BW83: =SUM('SALT P&L'!$X20:$Z20) | BX83: =SUM('KNL HO P&L'!$X20:$Z20)+SUM('CCL HO P&L'!$X20:$Z20)+SUM('YBHN HO P&L'!$X20:$Z20)+SUM('YBN HO P&L'!$X20:$Z20)+SUM('Moe2 P&L'!$X20:$Z20) | BY83: =SUM(BG83:BX83) | BZ83: =BY83+BF83+AM83+T83 | CA83: ='GROUP TOTALS MONTHLY P&L'!AB20 | CB83: =BZ83-CA83
A84: Staff Welfare | B84: =SUM('ABA P&L'!$O21:$Q21) | C84: =SUM('BK P&L'!$O21:$Q21) | D84: =SUM('BW P&L'!$O21:$Q21) | E84: =SUM('CED P&L'!$O21:$Q21) | F84: =SUM('HB P&L'!$O21:$Q21) | G84: =SUM('KIN P&L'!$O21:$Q21) | H84: =SUM('MER P&L'!$O21:$Q21) | I84: =SUM('SST P&L'!$O21:$Q21) | J84: =SUM('HDN P&L'!$O21:$Q21) | K84: =SUM('NDN P&L'!$O21:$Q21) | L84: =SUM('SDN P&L'!$O21:$Q21) | M84: =SUM('LE P&L'!$O21:$Q21) | N84: =SUM('WH P&L'!$O21:$Q21) | O84: =SUM('HS P&L'!$O21:$Q21) | P84: =SUM('FH P&L'!$O21:$Q21) | Q84: =SUM('HAB P&L'!$O21:$Q21) | R84: =SUM('SALT P&L'!$O21:$Q21) | S84: =SUM('KNL HO P&L'!$O21:$Q21)+SUM('CCL HO P&L'!$O21:$Q21)+SUM('YBHN HO P&L'!$O21:$Q21)+SUM('YBN HO P&L'!$O21:$Q21)+SUM('Moe2 P&L'!$O21:$Q21) | T84: =SUM(B84:S84) | U84: =SUM('ABA P&L'!$R21:$T21) | V84: =SUM('BK P&L'!$R21:$T21) | W84: =SUM('BW P&L'!$R21:$T21) | X84: =SUM('CED P&L'!$R21:$T21) | Y84: =SUM('HB P&L'!$R21:$T21) | Z84: =SUM('KIN P&L'!$R21:$T21) | AA84: =SUM('MER P&L'!$R21:$T21) | AB84: =SUM('SST P&L'!$R21:$T21) | AC84: =SUM('HDN P&L'!$R21:$T21) | AD84: =SUM('NDN P&L'!$R21:$T21) | AE84: =SUM('SDN P&L'!$R21:$T21) | AF84: =SUM('LE P&L'!$R21:$T21) | AG84: =SUM('WH P&L'!$R21:$T21) | AH84: =SUM('HS P&L'!$R21:$T21) | AI84: =SUM('FH P&L'!$R21:$T21) | AJ84: =SUM('HAB P&L'!$R21:$T21) | AK84: =SUM('SALT P&L'!$R21:$T21) | AL84: =SUM('KNL HO P&L'!$R21:$T21)+SUM('CCL HO P&L'!$R21:$T21)+SUM('YBHN HO P&L'!$R21:$T21)+SUM('YBN HO P&L'!$R21:$T21)+SUM('Moe2 P&L'!$R21:$T21) | AM84: =SUM(U84:AL84) | AN84: =SUM('ABA P&L'!$U21:$W21) | AO84: =SUM('BK P&L'!$U21:$W21) | AP84: =SUM('BW P&L'!$U21:$W21) | AQ84: =SUM('CED P&L'!$U21:$W21) | AR84: =SUM('HB P&L'!$U21:$W21) | AS84: =SUM('KIN P&L'!$U21:$W21) | AT84: =SUM('MER P&L'!$U21:$W21) | AU84: =SUM('SST P&L'!$U21:$W21) | AV84: =SUM('HDN P&L'!$U21:$W21) | AW84: =SUM('NDN P&L'!$U21:$W21) | AX84: =SUM('SDN P&L'!$U21:$W21) | AY84: =SUM('LE P&L'!$U21:$W21) | AZ84: =SUM('WH P&L'!$U21:$W21) | BA84: =SUM('HS P&L'!$U21:$W21) | BB84: =SUM('FH P&L'!$U21:$W21) | BC84: =SUM('HAB P&L'!$U21:$W21) | BD84: =SUM('SALT P&L'!$U21:$W21) | BE84: =SUM('KNL HO P&L'!$U21:$W21)+SUM('CCL HO P&L'!$U21:$W21)+SUM('YBHN HO P&L'!$U21:$W21)+SUM('YBN HO P&L'!$U21:$W21)+SUM('Moe2 P&L'!$U21:$W21) | BF84: =SUM(AN84:BE84) | BG84: =SUM('ABA P&L'!$X21:$Z21) | BH84: =SUM('BK P&L'!$X21:$Z21) | BI84: =SUM('BW P&L'!$X21:$Z21) | BJ84: =SUM('CED P&L'!$X21:$Z21) | BK84: =SUM('HB P&L'!$X21:$Z21) | BL84: =SUM('KIN P&L'!$X21:$Z21) | BM84: =SUM('MER P&L'!$X21:$Z21) | BN84: =SUM('SST P&L'!$X21:$Z21) | BO84: =SUM('HDN P&L'!$X21:$Z21) | BP84: =SUM('NDN P&L'!$X21:$Z21) | BQ84: =SUM('SDN P&L'!$X21:$Z21) | BR84: =SUM('LE P&L'!$X21:$Z21) | BS84: =SUM('WH P&L'!$X21:$Z21) | BT84: =SUM('HS P&L'!$X21:$Z21) | BU84: =SUM('FH P&L'!$X21:$Z21) | BV84: =SUM('HAB P&L'!$X21:$Z21) | BW84: =SUM('SALT P&L'!$X21:$Z21) | BX84: =SUM('KNL HO P&L'!$X21:$Z21)+SUM('CCL HO P&L'!$X21:$Z21)+SUM('YBHN HO P&L'!$X21:$Z21)+SUM('YBN HO P&L'!$X21:$Z21)+SUM('Moe2 P&L'!$X21:$Z21) | BY84: =SUM(BG84:BX84) | BZ84: =BY84+BF84+AM84+T84 | CA84: ='GROUP TOTALS MONTHLY P&L'!AB21 | CB84: =BZ84-CA84
A85: Recruitment | B85: =SUM('ABA P&L'!$O22:$Q22) | C85: =SUM('BK P&L'!$O22:$Q22) | D85: =SUM('BW P&L'!$O22:$Q22) | E85: =SUM('CED P&L'!$O22:$Q22) | F85: =SUM('HB P&L'!$O22:$Q22) | G85: =SUM('KIN P&L'!$O22:$Q22) | H85: =SUM('MER P&L'!$O22:$Q22) | I85: =SUM('SST P&L'!$O22:$Q22) | J85: =SUM('HDN P&L'!$O22:$Q22) | K85: =SUM('NDN P&L'!$O22:$Q22) | L85: =SUM('SDN P&L'!$O22:$Q22) | M85: =SUM('LE P&L'!$O22:$Q22) | N85: =SUM('WH P&L'!$O22:$Q22) | O85: =SUM('HS P&L'!$O22:$Q22) | P85: =SUM('FH P&L'!$O22:$Q22) | Q85: =SUM('HAB P&L'!$O22:$Q22) | R85: =SUM('SALT P&L'!$O22:$Q22) | S85: =SUM('KNL HO P&L'!$O22:$Q22)+SUM('CCL HO P&L'!$O22:$Q22)+SUM('YBHN HO P&L'!$O22:$Q22)+SUM('YBN HO P&L'!$O22:$Q22)+SUM('Moe2 P&L'!$O22:$Q22) | T85: =SUM(B85:S85) | U85: =SUM('ABA P&L'!$R22:$T22) | V85: =SUM('BK P&L'!$R22:$T22) | W85: =SUM('BW P&L'!$R22:$T22) | X85: =SUM('CED P&L'!$R22:$T22) | Y85: =SUM('HB P&L'!$R22:$T22) | Z85: =SUM('KIN P&L'!$R22:$T22) | AA85: =SUM('MER P&L'!$R22:$T22) | AB85: =SUM('SST P&L'!$R22:$T22) | AC85: =SUM('HDN P&L'!$R22:$T22) | AD85: =SUM('NDN P&L'!$R22:$T22) | AE85: =SUM('SDN P&L'!$R22:$T22) | AF85: =SUM('LE P&L'!$R22:$T22) | AG85: =SUM('WH P&L'!$R22:$T22) | AH85: =SUM('HS P&L'!$R22:$T22) | AI85: =SUM('FH P&L'!$R22:$T22) | AJ85: =SUM('HAB P&L'!$R22:$T22) | AK85: =SUM('SALT P&L'!$R22:$T22) | AL85: =SUM('KNL HO P&L'!$R22:$T22)+SUM('CCL HO P&L'!$R22:$T22)+SUM('YBHN HO P&L'!$R22:$T22)+SUM('YBN HO P&L'!$R22:$T22)+SUM('Moe2 P&L'!$R22:$T22) | AM85: =SUM(U85:AL85) | AN85: =SUM('ABA P&L'!$U22:$W22) | AO85: =SUM('BK P&L'!$U22:$W22) | AP85: =SUM('BW P&L'!$U22:$W22) | AQ85: =SUM('CED P&L'!$U22:$W22) | AR85: =SUM('HB P&L'!$U22:$W22) | AS85: =SUM('KIN P&L'!$U22:$W22) | AT85: =SUM('MER P&L'!$U22:$W22) | AU85: =SUM('SST P&L'!$U22:$W22) | AV85: =SUM('HDN P&L'!$U22:$W22) | AW85: =SUM('NDN P&L'!$U22:$W22) | AX85: =SUM('SDN P&L'!$U22:$W22) | AY85: =SUM('LE P&L'!$U22:$W22) | AZ85: =SUM('WH P&L'!$U22:$W22) | BA85: =SUM('HS P&L'!$U22:$W22) | BB85: =SUM('FH P&L'!$U22:$W22) | BC85: =SUM('HAB P&L'!$U22:$W22) | BD85: =SUM('SALT P&L'!$U22:$W22) | BE85: =SUM('KNL HO P&L'!$U22:$W22)+SUM('CCL HO P&L'!$U22:$W22)+SUM('YBHN HO P&L'!$U22:$W22)+SUM('YBN HO P&L'!$U22:$W22)+SUM('Moe2 P&L'!$U22:$W22) | BF85: =SUM(AN85:BE85) | BG85: =SUM('ABA P&L'!$X22:$Z22) | BH85: =SUM('BK P&L'!$X22:$Z22) | BI85: =SUM('BW P&L'!$X22:$Z22) | BJ85: =SUM('CED P&L'!$X22:$Z22) | BK85: =SUM('HB P&L'!$X22:$Z22) | BL85: =SUM('KIN P&L'!$X22:$Z22) | BM85: =SUM('MER P&L'!$X22:$Z22) | BN85: =SUM('SST P&L'!$X22:$Z22) | BO85: =SUM('HDN P&L'!$X22:$Z22) | BP85: =SUM('NDN P&L'!$X22:$Z22) | BQ85: =SUM('SDN P&L'!$X22:$Z22) | BR85: =SUM('LE P&L'!$X22:$Z22) | BS85: =SUM('WH P&L'!$X22:$Z22) | BT85: =SUM('HS P&L'!$X22:$Z22) | BU85: =SUM('FH P&L'!$X22:$Z22) | BV85: =SUM('HAB P&L'!$X22:$Z22) | BW85: =SUM('SALT P&L'!$X22:$Z22) | BX85: =SUM('KNL HO P&L'!$X22:$Z22)+SUM('CCL HO P&L'!$X22:$Z22)+SUM('YBHN HO P&L'!$X22:$Z22)+SUM('YBN HO P&L'!$X22:$Z22)+SUM('Moe2 P&L'!$X22:$Z22) | BY85: =SUM(BG85:BX85) | BZ85: =BY85+BF85+AM85+T85 | CA85: ='GROUP TOTALS MONTHLY P&L'!AB22 | CB85: =BZ85-CA85
A86: Rewards & Recognition | B86: =SUM('ABA P&L'!$O23:$Q23) | C86: =SUM('BK P&L'!$O23:$Q23) | D86: =SUM('BW P&L'!$O23:$Q23) | E86: =SUM('CED P&L'!$O23:$Q23) | F86: =SUM('HB P&L'!$O23:$Q23) | G86: =SUM('KIN P&L'!$O23:$Q23) | H86: =SUM('MER P&L'!$O23:$Q23) | I86: =SUM('SST P&L'!$O23:$Q23) | J86: =SUM('HDN P&L'!$O23:$Q23) | K86: =SUM('NDN P&L'!$O23:$Q23) | L86: =SUM('SDN P&L'!$O23:$Q23) | M86: =SUM('LE P&L'!$O23:$Q23) | N86: =SUM('WH P&L'!$O23:$Q23) | O86: =SUM('HS P&L'!$O23:$Q23) | P86: =SUM('FH P&L'!$O23:$Q23) | Q86: =SUM('HAB P&L'!$O23:$Q23) | R86: =SUM('SALT P&L'!$O23:$Q23) | S86: =SUM('KNL HO P&L'!$O23:$Q23)+SUM('CCL HO P&L'!$O23:$Q23)+SUM('YBHN HO P&L'!$O23:$Q23)+SUM('YBN HO P&L'!$O23:$Q23)+SUM('Moe2 P&L'!$O23:$Q23) | T86: =SUM(B86:S86) | U86: =SUM('ABA P&L'!$R23:$T23) | V86: =SUM('BK P&L'!$R23:$T23) | W86: =SUM('BW P&L'!$R23:$T23) | X86: =SUM('CED P&L'!$R23:$T23) | Y86: =SUM('HB P&L'!$R23:$T23) | Z86: =SUM('KIN P&L'!$R23:$T23) | AA86: =SUM('MER P&L'!$R23:$T23) | AB86: =SUM('SST P&L'!$R23:$T23) | AC86: =SUM('HDN P&L'!$R23:$T23) | AD86: =SUM('NDN P&L'!$R23:$T23) | AE86: =SUM('SDN P&L'!$R23:$T23) | AF86: =SUM('LE P&L'!$R23:$T23) | AG86: =SUM('WH P&L'!$R23:$T23) | AH86: =SUM('HS P&L'!$R23:$T23) | AI86: =SUM('FH P&L'!$R23:$T23) | AJ86: =SUM('HAB P&L'!$R23:$T23) | AK86: =SUM('SALT P&L'!$R23:$T23) | AL86: =SUM('KNL HO P&L'!$R23:$T23)+SUM('CCL HO P&L'!$R23:$T23)+SUM('YBHN HO P&L'!$R23:$T23)+SUM('YBN HO P&L'!$R23:$T23)+SUM('Moe2 P&L'!$R23:$T23) | AM86: =SUM(U86:AL86) | AN86: =SUM('ABA P&L'!$U23:$W23) | AO86: =SUM('BK P&L'!$U23:$W23) | AP86: =SUM('BW P&L'!$U23:$W23) | AQ86: =SUM('CED P&L'!$U23:$W23) | AR86: =SUM('HB P&L'!$U23:$W23) | AS86: =SUM('KIN P&L'!$U23:$W23) | AT86: =SUM('MER P&L'!$U23:$W23) | AU86: =SUM('SST P&L'!$U23:$W23) | AV86: =SUM('HDN P&L'!$U23:$W23) | AW86: =SUM('NDN P&L'!$U23:$W23) | AX86: =SUM('SDN P&L'!$U23:$W23) | AY86: =SUM('LE P&L'!$U23:$W23) | AZ86: =SUM('WH P&L'!$U23:$W23) | BA86: =SUM('HS P&L'!$U23:$W23) | BB86: =SUM('FH P&L'!$U23:$W23) | BC86: =SUM('HAB P&L'!$U23:$W23) | BD86: =SUM('SALT P&L'!$U23:$W23) | BE86: =SUM('KNL HO P&L'!$U23:$W23)+SUM('CCL HO P&L'!$U23:$W23)+SUM('YBHN HO P&L'!$U23:$W23)+SUM('YBN HO P&L'!$U23:$W23)+SUM('Moe2 P&L'!$U23:$W23) | BF86: =SUM(AN86:BE86) | BG86: =SUM('ABA P&L'!$X23:$Z23) | BH86: =SUM('BK P&L'!$X23:$Z23) | BI86: =SUM('BW P&L'!$X23:$Z23) | BJ86: =SUM('CED P&L'!$X23:$Z23) | BK86: =SUM('HB P&L'!$X23:$Z23) | BL86: =SUM('KIN P&L'!$X23:$Z23) | BM86: =SUM('MER P&L'!$X23:$Z23) | BN86: =SUM('SST P&L'!$X23:$Z23) | BO86: =SUM('HDN P&L'!$X23:$Z23) | BP86: =SUM('NDN P&L'!$X23:$Z23) | BQ86: =SUM('SDN P&L'!$X23:$Z23) | BR86: =SUM('LE P&L'!$X23:$Z23) | BS86: =SUM('WH P&L'!$X23:$Z23) | BT86: =SUM('HS P&L'!$X23:$Z23) | BU86: =SUM('FH P&L'!$X23:$Z23) | BV86: =SUM('HAB P&L'!$X23:$Z23) | BW86: =SUM('SALT P&L'!$X23:$Z23) | BX86: =SUM('KNL HO P&L'!$X23:$Z23)+SUM('CCL HO P&L'!$X23:$Z23)+SUM('YBHN HO P&L'!$X23:$Z23)+SUM('YBN HO P&L'!$X23:$Z23)+SUM('Moe2 P&L'!$X23:$Z23) | BY86: =SUM(BG86:BX86) | BZ86: =BY86+BF86+AM86+T86 | CA86: ='GROUP TOTALS MONTHLY P&L'!AB23 | CB86: =BZ86-CA86
A87: Temps | B87: =SUM('ABA P&L'!$O24:$Q24) | C87: =SUM('BK P&L'!$O24:$Q24) | D87: =SUM('BW P&L'!$O24:$Q24) | E87: =SUM('CED P&L'!$O24:$Q24) | F87: =SUM('HB P&L'!$O24:$Q24) | G87: =SUM('KIN P&L'!$O24:$Q24) | H87: =SUM('MER P&L'!$O24:$Q24) | I87: =SUM('SST P&L'!$O24:$Q24) | J87: =SUM('HDN P&L'!$O24:$Q24) | K87: =SUM('NDN P&L'!$O24:$Q24) | L87: =SUM('SDN P&L'!$O24:$Q24) | M87: =SUM('LE P&L'!$O24:$Q24) | N87: =SUM('WH P&L'!$O24:$Q24) | O87: =SUM('HS P&L'!$O24:$Q24) | P87: =SUM('FH P&L'!$O24:$Q24) | Q87: =SUM('HAB P&L'!$O24:$Q24) | R87: =SUM('SALT P&L'!$O24:$Q24) | S87: =SUM('KNL HO P&L'!$O24:$Q24)+SUM('CCL HO P&L'!$O24:$Q24)+SUM('YBHN HO P&L'!$O24:$Q24)+SUM('YBN HO P&L'!$O24:$Q24)+SUM('Moe2 P&L'!$O24:$Q24) | T87: =SUM(B87:S87) | U87: =SUM('ABA P&L'!$R24:$T24) | V87: =SUM('BK P&L'!$R24:$T24) | W87: =SUM('BW P&L'!$R24:$T24) | X87: =SUM('CED P&L'!$R24:$T24) | Y87: =SUM('HB P&L'!$R24:$T24) | Z87: =SUM('KIN P&L'!$R24:$T24) | AA87: =SUM('MER P&L'!$R24:$T24) | AB87: =SUM('SST P&L'!$R24:$T24) | AC87: =SUM('HDN P&L'!$R24:$T24) | AD87: =SUM('NDN P&L'!$R24:$T24) | AE87: =SUM('SDN P&L'!$R24:$T24) | AF87: =SUM('LE P&L'!$R24:$T24) | AG87: =SUM('WH P&L'!$R24:$T24) | AH87: =SUM('HS P&L'!$R24:$T24) | AI87: =SUM('FH P&L'!$R24:$T24) | AJ87: =SUM('HAB P&L'!$R24:$T24) | AK87: =SUM('SALT P&L'!$R24:$T24) | AL87: =SUM('KNL HO P&L'!$R24:$T24)+SUM('CCL HO P&L'!$R24:$T24)+SUM('YBHN HO P&L'!$R24:$T24)+SUM('YBN HO P&L'!$R24:$T24)+SUM('Moe2 P&L'!$R24:$T24) | AM87: =SUM(U87:AL87) | AN87: =SUM('ABA P&L'!$U24:$W24) | AO87: =SUM('BK P&L'!$U24:$W24) | AP87: =SUM('BW P&L'!$U24:$W24) | AQ87: =SUM('CED P&L'!$U24:$W24) | AR87: =SUM('HB P&L'!$U24:$W24) | AS87: =SUM('KIN P&L'!$U24:$W24) | AT87: =SUM('MER P&L'!$U24:$W24) | AU87: =SUM('SST P&L'!$U24:$W24) | AV87: =SUM('HDN P&L'!$U24:$W24) | AW87: =SUM('NDN P&L'!$U24:$W24) | AX87: =SUM('SDN P&L'!$U24:$W24) | AY87: =SUM('LE P&L'!$U24:$W24) | AZ87: =SUM('WH P&L'!$U24:$W24) | BA87: =SUM('HS P&L'!$U24:$W24) | BB87: =SUM('FH P&L'!$U24:$W24) | BC87: =SUM('HAB P&L'!$U24:$W24) | BD87: =SUM('SALT P&L'!$U24:$W24) | BE87: =SUM('KNL HO P&L'!$U24:$W24)+SUM('CCL HO P&L'!$U24:$W24)+SUM('YBHN HO P&L'!$U24:$W24)+SUM('YBN HO P&L'!$U24:$W24)+SUM('Moe2 P&L'!$U24:$W24) | BF87: =SUM(AN87:BE87) | BG87: =SUM('ABA P&L'!$X24:$Z24) | BH87: =SUM('BK P&L'!$X24:$Z24) | BI87: =SUM('BW P&L'!$X24:$Z24) | BJ87: =SUM('CED P&L'!$X24:$Z24) | BK87: =SUM('HB P&L'!$X24:$Z24) | BL87: =SUM('KIN P&L'!$X24:$Z24) | BM87: =SUM('MER P&L'!$X24:$Z24) | BN87: =SUM('SST P&L'!$X24:$Z24) | BO87: =SUM('HDN P&L'!$X24:$Z24) | BP87: =SUM('NDN P&L'!$X24:$Z24) | BQ87: =SUM('SDN P&L'!$X24:$Z24) | BR87: =SUM('LE P&L'!$X24:$Z24) | BS87: =SUM('WH P&L'!$X24:$Z24) | BT87: =SUM('HS P&L'!$X24:$Z24) | BU87: =SUM('FH P&L'!$X24:$Z24) | BV87: =SUM('HAB P&L'!$X24:$Z24) | BW87: =SUM('SALT P&L'!$X24:$Z24) | BX87: =SUM('KNL HO P&L'!$X24:$Z24)+SUM('CCL HO P&L'!$X24:$Z24)+SUM('YBHN HO P&L'!$X24:$Z24)+SUM('YBN HO P&L'!$X24:$Z24)+SUM('Moe2 P&L'!$X24:$Z24) | BY87: =SUM(BG87:BX87) | BZ87: =BY87+BF87+AM87+T87 | CA87: ='GROUP TOTALS MONTHLY P&L'!AB24 | CB87: =BZ87-CA87
A88: Total Personnel | B88: =SUM('ABA P&L'!$O25:$Q25) | C88: =SUM('BK P&L'!$O25:$Q25) | D88: =SUM('BW P&L'!$O25:$Q25) | E88: =SUM('CED P&L'!$O25:$Q25) | F88: =SUM('HB P&L'!$O25:$Q25) | G88: =SUM('KIN P&L'!$O25:$Q25) | H88: =SUM('MER P&L'!$O25:$Q25) | I88: =SUM('SST P&L'!$O25:$Q25) | J88: =SUM('HDN P&L'!$O25:$Q25) | K88: =SUM('NDN P&L'!$O25:$Q25) | L88: =SUM('SDN P&L'!$O25:$Q25) | M88: =SUM('LE P&L'!$O25:$Q25) | N88: =SUM('WH P&L'!$O25:$Q25) | O88: =SUM('HS P&L'!$O25:$Q25) | P88: =SUM('FH P&L'!$O25:$Q25) | Q88: =SUM('HAB P&L'!$O25:$Q25) | R88: =SUM('SALT P&L'!$O25:$Q25) | S88: =SUM('KNL HO P&L'!$O25:$Q25)+SUM('CCL HO P&L'!$O25:$Q25)+SUM('YBHN HO P&L'!$O25:$Q25)+SUM('YBN HO P&L'!$O25:$Q25)+SUM('Moe2 P&L'!$O25:$Q25) | T88: =SUM(B88:S88) | U88: =SUM('ABA P&L'!$R25:$T25) | V88: =SUM('BK P&L'!$R25:$T25) | W88: =SUM('BW P&L'!$R25:$T25) | X88: =SUM('CED P&L'!$R25:$T25) | Y88: =SUM('HB P&L'!$R25:$T25) | Z88: =SUM('KIN P&L'!$R25:$T25) | AA88: =SUM('MER P&L'!$R25:$T25) | AB88: =SUM('SST P&L'!$R25:$T25) | AC88: =SUM('HDN P&L'!$R25:$T25) | AD88: =SUM('NDN P&L'!$R25:$T25) | AE88: =SUM('SDN P&L'!$R25:$T25) | AF88: =SUM('LE P&L'!$R25:$T25) | AG88: =SUM('WH P&L'!$R25:$T25) | AH88: =SUM('HS P&L'!$R25:$T25) | AI88: =SUM('FH P&L'!$R25:$T25) | AJ88: =SUM('HAB P&L'!$R25:$T25) | AK88: =SUM('SALT P&L'!$R25:$T25) | AL88: =SUM('KNL HO P&L'!$R25:$T25)+SUM('CCL HO P&L'!$R25:$T25)+SUM('YBHN HO P&L'!$R25:$T25)+SUM('YBN HO P&L'!$R25:$T25)+SUM('Moe2 P&L'!$R25:$T25) | AM88: =SUM(U88:AL88) | AN88: =SUM('ABA P&L'!$U25:$W25) | AO88: =SUM('BK P&L'!$U25:$W25) | AP88: =SUM('BW P&L'!$U25:$W25) | AQ88: =SUM('CED P&L'!$U25:$W25) | AR88: =SUM('HB P&L'!$U25:$W25) | AS88: =SUM('KIN P&L'!$U25:$W25) | AT88: =SUM('MER P&L'!$U25:$W25) | AU88: =SUM('SST P&L'!$U25:$W25) | AV88: =SUM('HDN P&L'!$U25:$W25) | AW88: =SUM('NDN P&L'!$U25:$W25) | AX88: =SUM('SDN P&L'!$U25:$W25) | AY88: =SUM('LE P&L'!$U25:$W25) | AZ88: =SUM('WH P&L'!$U25:$W25) | BA88: =SUM('HS P&L'!$U25:$W25) | BB88: =SUM('FH P&L'!$U25:$W25) | BC88: =SUM('HAB P&L'!$U25:$W25) | BD88: =SUM('SALT P&L'!$U25:$W25) | BE88: =SUM('KNL HO P&L'!$U25:$W25)+SUM('CCL HO P&L'!$U25:$W25)+SUM('YBHN HO P&L'!$U25:$W25)+SUM('YBN HO P&L'!$U25:$W25)+SUM('Moe2 P&L'!$U25:$W25) | BF88: =SUM(AN88:BE88) | BG88: =SUM('ABA P&L'!$X25:$Z25) | BH88: =SUM('BK P&L'!$X25:$Z25) | BI88: =SUM('BW P&L'!$X25:$Z25) | BJ88: =SUM('CED P&L'!$X25:$Z25) | BK88: =SUM('HB P&L'!$X25:$Z25) | BL88: =SUM('KIN P&L'!$X25:$Z25) | BM88: =SUM('MER P&L'!$X25:$Z25) | BN88: =SUM('SST P&L'!$X25:$Z25) | BO88: =SUM('HDN P&L'!$X25:$Z25) | BP88: =SUM('NDN P&L'!$X25:$Z25) | BQ88: =SUM('SDN P&L'!$X25:$Z25) | BR88: =SUM('LE P&L'!$X25:$Z25) | BS88: =SUM('WH P&L'!$X25:$Z25) | BT88: =SUM('HS P&L'!$X25:$Z25) | BU88: =SUM('FH P&L'!$X25:$Z25) | BV88: =SUM('HAB P&L'!$X25:$Z25) | BW88: =SUM('SALT P&L'!$X25:$Z25) | BX88: =SUM('KNL HO P&L'!$X25:$Z25)+SUM('CCL HO P&L'!$X25:$Z25)+SUM('YBHN HO P&L'!$X25:$Z25)+SUM('YBN HO P&L'!$X25:$Z25)+SUM('Moe2 P&L'!$X25:$Z25) | BY88: =SUM(BG88:BX88) | BZ88: =BY88+BF88+AM88+T88 | CA88: ='GROUP TOTALS MONTHLY P&L'!AB25 | CB88: =BZ88-CA88
A89: Childcare | B89: =SUM('ABA P&L'!$O26:$Q26) | C89: =SUM('BK P&L'!$O26:$Q26) | D89: =SUM('BW P&L'!$O26:$Q26) | E89: =SUM('CED P&L'!$O26:$Q26) | F89: =SUM('HB P&L'!$O26:$Q26) | G89: =SUM('KIN P&L'!$O26:$Q26) | H89: =SUM('MER P&L'!$O26:$Q26) | I89: =SUM('SST P&L'!$O26:$Q26) | J89: =SUM('HDN P&L'!$O26:$Q26) | K89: =SUM('NDN P&L'!$O26:$Q26) | L89: =SUM('SDN P&L'!$O26:$Q26) | M89: =SUM('LE P&L'!$O26:$Q26) | N89: =SUM('WH P&L'!$O26:$Q26) | O89: =SUM('HS P&L'!$O26:$Q26) | P89: =SUM('FH P&L'!$O26:$Q26) | Q89: =SUM('HAB P&L'!$O26:$Q26) | R89: =SUM('SALT P&L'!$O26:$Q26) | S89: =SUM('KNL HO P&L'!$O26:$Q26)+SUM('CCL HO P&L'!$O26:$Q26)+SUM('YBHN HO P&L'!$O26:$Q26)+SUM('YBN HO P&L'!$O26:$Q26)+SUM('Moe2 P&L'!$O26:$Q26) | T89: =SUM(B89:S89) | U89: =SUM('ABA P&L'!$R26:$T26) | V89: =SUM('BK P&L'!$R26:$T26) | W89: =SUM('BW P&L'!$R26:$T26) | X89: =SUM('CED P&L'!$R26:$T26) | Y89: =SUM('HB P&L'!$R26:$T26) | Z89: =SUM('KIN P&L'!$R26:$T26) | AA89: =SUM('MER P&L'!$R26:$T26) | AB89: =SUM('SST P&L'!$R26:$T26) | AC89: =SUM('HDN P&L'!$R26:$T26) | AD89: =SUM('NDN P&L'!$R26:$T26) | AE89: =SUM('SDN P&L'!$R26:$T26) | AF89: =SUM('LE P&L'!$R26:$T26) | AG89: =SUM('WH P&L'!$R26:$T26) | AH89: =SUM('HS P&L'!$R26:$T26) | AI89: =SUM('FH P&L'!$R26:$T26) | AJ89: =SUM('HAB P&L'!$R26:$T26) | AK89: =SUM('SALT P&L'!$R26:$T26) | AL89: =SUM('KNL HO P&L'!$R26:$T26)+SUM('CCL HO P&L'!$R26:$T26)+SUM('YBHN HO P&L'!$R26:$T26)+SUM('YBN HO P&L'!$R26:$T26)+SUM('Moe2 P&L'!$R26:$T26) | AM89: =SUM(U89:AL89) | AN89: =SUM('ABA P&L'!$U26:$W26) | AO89: =SUM('BK P&L'!$U26:$W26) | AP89: =SUM('BW P&L'!$U26:$W26) | AQ89: =SUM('CED P&L'!$U26:$W26) | AR89: =SUM('HB P&L'!$U26:$W26) | AS89: =SUM('KIN P&L'!$U26:$W26) | AT89: =SUM('MER P&L'!$U26:$W26) | AU89: =SUM('SST P&L'!$U26:$W26) | AV89: =SUM('HDN P&L'!$U26:$W26) | AW89: =SUM('NDN P&L'!$U26:$W26) | AX89: =SUM('SDN P&L'!$U26:$W26) | AY89: =SUM('LE P&L'!$U26:$W26) | AZ89: =SUM('WH P&L'!$U26:$W26) | BA89: =SUM('HS P&L'!$U26:$W26) | BB89: =SUM('FH P&L'!$U26:$W26) | BC89: =SUM('HAB P&L'!$U26:$W26) | BD89: =SUM('SALT P&L'!$U26:$W26) | BE89: =SUM('KNL HO P&L'!$U26:$W26)+SUM('CCL HO P&L'!$U26:$W26)+SUM('YBHN HO P&L'!$U26:$W26)+SUM('YBN HO P&L'!$U26:$W26)+SUM('Moe2 P&L'!$U26:$W26) | BF89: =SUM(AN89:BE89) | BG89: =SUM('ABA P&L'!$X26:$Z26) | BH89: =SUM('BK P&L'!$X26:$Z26) | BI89: =SUM('BW P&L'!$X26:$Z26) | BJ89: =SUM('CED P&L'!$X26:$Z26) | BK89: =SUM('HB P&L'!$X26:$Z26) | BL89: =SUM('KIN P&L'!$X26:$Z26) | BM89: =SUM('MER P&L'!$X26:$Z26) | BN89: =SUM('SST P&L'!$X26:$Z26) | BO89: =SUM('HDN P&L'!$X26:$Z26) | BP89: =SUM('NDN P&L'!$X26:$Z26) | BQ89: =SUM('SDN P&L'!$X26:$Z26) | BR89: =SUM('LE P&L'!$X26:$Z26) | BS89: =SUM('WH P&L'!$X26:$Z26) | BT89: =SUM('HS P&L'!$X26:$Z26) | BU89: =SUM('FH P&L'!$X26:$Z26) | BV89: =SUM('HAB P&L'!$X26:$Z26) | BW89: =SUM('SALT P&L'!$X26:$Z26) | BX89: =SUM('KNL HO P&L'!$X26:$Z26)+SUM('CCL HO P&L'!$X26:$Z26)+SUM('YBHN HO P&L'!$X26:$Z26)+SUM('YBN HO P&L'!$X26:$Z26)+SUM('Moe2 P&L'!$X26:$Z26) | BY89: =SUM(BG89:BX89) | BZ89: =BY89+BF89+AM89+T89 | CA89: ='GROUP TOTALS MONTHLY P&L'!AB26 | CB89: =BZ89-CA89
A90: Catering Costs | B90: =SUM('ABA P&L'!$O27:$Q27) | C90: =SUM('BK P&L'!$O27:$Q27) | D90: =SUM('BW P&L'!$O27:$Q27) | E90: =SUM('CED P&L'!$O27:$Q27) | F90: =SUM('HB P&L'!$O27:$Q27) | G90: =SUM('KIN P&L'!$O27:$Q27) | H90: =SUM('MER P&L'!$O27:$Q27) | I90: =SUM('SST P&L'!$O27:$Q27) | J90: =SUM('HDN P&L'!$O27:$Q27) | K90: =SUM('NDN P&L'!$O27:$Q27) | L90: =SUM('SDN P&L'!$O27:$Q27) | M90: =SUM('LE P&L'!$O27:$Q27) | N90: =SUM('WH P&L'!$O27:$Q27) | O90: =SUM('HS P&L'!$O27:$Q27) | P90: =SUM('FH P&L'!$O27:$Q27) | Q90: =SUM('HAB P&L'!$O27:$Q27) | R90: =SUM('SALT P&L'!$O27:$Q27) | S90: =SUM('KNL HO P&L'!$O27:$Q27)+SUM('CCL HO P&L'!$O27:$Q27)+SUM('YBHN HO P&L'!$O27:$Q27)+SUM('YBN HO P&L'!$O27:$Q27)+SUM('Moe2 P&L'!$O27:$Q27) | T90: =SUM(B90:S90) | U90: =SUM('ABA P&L'!$R27:$T27) | V90: =SUM('BK P&L'!$R27:$T27) | W90: =SUM('BW P&L'!$R27:$T27) | X90: =SUM('CED P&L'!$R27:$T27) | Y90: =SUM('HB P&L'!$R27:$T27) | Z90: =SUM('KIN P&L'!$R27:$T27) | AA90: =SUM('MER P&L'!$R27:$T27) | AB90: =SUM('SST P&L'!$R27:$T27) | AC90: =SUM('HDN P&L'!$R27:$T27) | AD90: =SUM('NDN P&L'!$R27:$T27) | AE90: =SUM('SDN P&L'!$R27:$T27) | AF90: =SUM('LE P&L'!$R27:$T27) | AG90: =SUM('WH P&L'!$R27:$T27) | AH90: =SUM('HS P&L'!$R27:$T27) | AI90: =SUM('FH P&L'!$R27:$T27) | AJ90: =SUM('HAB P&L'!$R27:$T27) | AK90: =SUM('SALT P&L'!$R27:$T27) | AL90: =SUM('KNL HO P&L'!$R27:$T27)+SUM('CCL HO P&L'!$R27:$T27)+SUM('YBHN HO P&L'!$R27:$T27)+SUM('YBN HO P&L'!$R27:$T27)+SUM('Moe2 P&L'!$R27:$T27) | AM90: =SUM(U90:AL90) | AN90: =SUM('ABA P&L'!$U27:$W27) | AO90: =SUM('BK P&L'!$U27:$W27) | AP90: =SUM('BW P&L'!$U27:$W27) | AQ90: =SUM('CED P&L'!$U27:$W27) | AR90: =SUM('HB P&L'!$U27:$W27) | AS90: =SUM('KIN P&L'!$U27:$W27) | AT90: =SUM('MER P&L'!$U27:$W27) | AU90: =SUM('SST P&L'!$U27:$W27) | AV90: =SUM('HDN P&L'!$U27:$W27) | AW90: =SUM('NDN P&L'!$U27:$W27) | AX90: =SUM('SDN P&L'!$U27:$W27) | AY90: =SUM('LE P&L'!$U27:$W27) | AZ90: =SUM('WH P&L'!$U27:$W27) | BA90: =SUM('HS P&L'!$U27:$W27) | BB90: =SUM('FH P&L'!$U27:$W27) | BC90: =SUM('HAB P&L'!$U27:$W27) | BD90: =SUM('SALT P&L'!$U27:$W27) | BE90: =SUM('KNL HO P&L'!$U27:$W27)+SUM('CCL HO P&L'!$U27:$W27)+SUM('YBHN HO P&L'!$U27:$W27)+SUM('YBN HO P&L'!$U27:$W27)+SUM('Moe2 P&L'!$U27:$W27) | BF90: =SUM(AN90:BE90) | BG90: =SUM('ABA P&L'!$X27:$Z27) | BH90: =SUM('BK P&L'!$X27:$Z27) | BI90: =SUM('BW P&L'!$X27:$Z27) | BJ90: =SUM('CED P&L'!$X27:$Z27) | BK90: =SUM('HB P&L'!$X27:$Z27) | BL90: =SUM('KIN P&L'!$X27:$Z27) | BM90: =SUM('MER P&L'!$X27:$Z27) | BN90: =SUM('SST P&L'!$X27:$Z27) | BO90: =SUM('HDN P&L'!$X27:$Z27) | BP90: =SUM('NDN P&L'!$X27:$Z27) | BQ90: =SUM('SDN P&L'!$X27:$Z27) | BR90: =SUM('LE P&L'!$X27:$Z27) | BS90: =SUM('WH P&L'!$X27:$Z27) | BT90: =SUM('HS P&L'!$X27:$Z27) | BU90: =SUM('FH P&L'!$X27:$Z27) | BV90: =SUM('HAB P&L'!$X27:$Z27) | BW90: =SUM('SALT P&L'!$X27:$Z27) | BX90: =SUM('KNL HO P&L'!$X27:$Z27)+SUM('CCL HO P&L'!$X27:$Z27)+SUM('YBHN HO P&L'!$X27:$Z27)+SUM('YBN HO P&L'!$X27:$Z27)+SUM('Moe2 P&L'!$X27:$Z27) | BY90: =SUM(BG90:BX90) | BZ90: =BY90+BF90+AM90+T90 | CA90: ='GROUP TOTALS MONTHLY P&L'!AB27 | CB90: =BZ90-CA90
A91: Toys and Games | B91: =SUM('ABA P&L'!$O28:$Q28) | C91: =SUM('BK P&L'!$O28:$Q28) | D91: =SUM('BW P&L'!$O28:$Q28) | E91: =SUM('CED P&L'!$O28:$Q28) | F91: =SUM('HB P&L'!$O28:$Q28) | G91: =SUM('KIN P&L'!$O28:$Q28) | H91: =SUM('MER P&L'!$O28:$Q28) | I91: =SUM('SST P&L'!$O28:$Q28) | J91: =SUM('HDN P&L'!$O28:$Q28) | K91: =SUM('NDN P&L'!$O28:$Q28) | L91: =SUM('SDN P&L'!$O28:$Q28) | M91: =SUM('LE P&L'!$O28:$Q28) | N91: =SUM('WH P&L'!$O28:$Q28) | O91: =SUM('HS P&L'!$O28:$Q28) | P91: =SUM('FH P&L'!$O28:$Q28) | Q91: =SUM('HAB P&L'!$O28:$Q28) | R91: =SUM('SALT P&L'!$O28:$Q28) | S91: =SUM('KNL HO P&L'!$O28:$Q28)+SUM('CCL HO P&L'!$O28:$Q28)+SUM('YBHN HO P&L'!$O28:$Q28)+SUM('YBN HO P&L'!$O28:$Q28)+SUM('Moe2 P&L'!$O28:$Q28) | T91: =SUM(B91:S91) | U91: =SUM('ABA P&L'!$R28:$T28) | V91: =SUM('BK P&L'!$R28:$T28) | W91: =SUM('BW P&L'!$R28:$T28) | X91: =SUM('CED P&L'!$R28:$T28) | Y91: =SUM('HB P&L'!$R28:$T28) | Z91: =SUM('KIN P&L'!$R28:$T28) | AA91: =SUM('MER P&L'!$R28:$T28) | AB91: =SUM('SST P&L'!$R28:$T28) | AC91: =SUM('HDN P&L'!$R28:$T28) | AD91: =SUM('NDN P&L'!$R28:$T28) | AE91: =SUM('SDN P&L'!$R28:$T28) | AF91: =SUM('LE P&L'!$R28:$T28) | AG91: =SUM('WH P&L'!$R28:$T28) | AH91: =SUM('HS P&L'!$R28:$T28) | AI91: =SUM('FH P&L'!$R28:$T28) | AJ91: =SUM('HAB P&L'!$R28:$T28) | AK91: =SUM('SALT P&L'!$R28:$T28) | AL91: =SUM('KNL HO P&L'!$R28:$T28)+SUM('CCL HO P&L'!$R28:$T28)+SUM('YBHN HO P&L'!$R28:$T28)+SUM('YBN HO P&L'!$R28:$T28)+SUM('Moe2 P&L'!$R28:$T28) | AM91: =SUM(U91:AL91) | AN91: =SUM('ABA P&L'!$U28:$W28) | AO91: =SUM('BK P&L'!$U28:$W28) | AP91: =SUM('BW P&L'!$U28:$W28) | AQ91: =SUM('CED P&L'!$U28:$W28) | AR91: =SUM('HB P&L'!$U28:$W28) | AS91: =SUM('KIN P&L'!$U28:$W28) | AT91: =SUM('MER P&L'!$U28:$W28) | AU91: =SUM('SST P&L'!$U28:$W28) | AV91: =SUM('HDN P&L'!$U28:$W28) | AW91: =SUM('NDN P&L'!$U28:$W28) | AX91: =SUM('SDN P&L'!$U28:$W28) | AY91: =SUM('LE P&L'!$U28:$W28) | AZ91: =SUM('WH P&L'!$U28:$W28) | BA91: =SUM('HS P&L'!$U28:$W28) | BB91: =SUM('FH P&L'!$U28:$W28) | BC91: =SUM('HAB P&L'!$U28:$W28) | BD91: =SUM('SALT P&L'!$U28:$W28) | BE91: =SUM('KNL HO P&L'!$U28:$W28)+SUM('CCL HO P&L'!$U28:$W28)+SUM('YBHN HO P&L'!$U28:$W28)+SUM('YBN HO P&L'!$U28:$W28)+SUM('Moe2 P&L'!$U28:$W28) | BF91: =SUM(AN91:BE91) | BG91: =SUM('ABA P&L'!$X28:$Z28) | BH91: =SUM('BK P&L'!$X28:$Z28) | BI91: =SUM('BW P&L'!$X28:$Z28) | BJ91: =SUM('CED P&L'!$X28:$Z28) | BK91: =SUM('HB P&L'!$X28:$Z28) | BL91: =SUM('KIN P&L'!$X28:$Z28) | BM91: =SUM('MER P&L'!$X28:$Z28) | BN91: =SUM('SST P&L'!$X28:$Z28) | BO91: =SUM('HDN P&L'!$X28:$Z28) | BP91: =SUM('NDN P&L'!$X28:$Z28) | BQ91: =SUM('SDN P&L'!$X28:$Z28) | BR91: =SUM('LE P&L'!$X28:$Z28) | BS91: =SUM('WH P&L'!$X28:$Z28) | BT91: =SUM('HS P&L'!$X28:$Z28) | BU91: =SUM('FH P&L'!$X28:$Z28) | BV91: =SUM('HAB P&L'!$X28:$Z28) | BW91: =SUM('SALT P&L'!$X28:$Z28) | BX91: =SUM('KNL HO P&L'!$X28:$Z28)+SUM('CCL HO P&L'!$X28:$Z28)+SUM('YBHN HO P&L'!$X28:$Z28)+SUM('YBN HO P&L'!$X28:$Z28)+SUM('Moe2 P&L'!$X28:$Z28) | BY91: =SUM(BG91:BX91) | BZ91: =BY91+BF91+AM91+T91 | CA91: ='GROUP TOTALS MONTHLY P&L'!AB28 | CB91: =BZ91-CA91 | CC91: Incorrect Setting codes
A92: Art Materials | B92: =SUM('ABA P&L'!$O29:$Q29) | C92: =SUM('BK P&L'!$O29:$Q29) | D92: =SUM('BW P&L'!$O29:$Q29) | E92: =SUM('CED P&L'!$O29:$Q29) | F92: =SUM('HB P&L'!$O29:$Q29) | G92: =SUM('KIN P&L'!$O29:$Q29) | H92: =SUM('MER P&L'!$O29:$Q29) | I92: =SUM('SST P&L'!$O29:$Q29) | J92: =SUM('HDN P&L'!$O29:$Q29) | K92: =SUM('NDN P&L'!$O29:$Q29) | L92: =SUM('SDN P&L'!$O29:$Q29) | M92: =SUM('LE P&L'!$O29:$Q29) | N92: =SUM('WH P&L'!$O29:$Q29) | O92: =SUM('HS P&L'!$O29:$Q29) | P92: =SUM('FH P&L'!$O29:$Q29) | Q92: =SUM('HAB P&L'!$O29:$Q29) | R92: =SUM('SALT P&L'!$O29:$Q29) | S92: =SUM('KNL HO P&L'!$O29:$Q29)+SUM('CCL HO P&L'!$O29:$Q29)+SUM('YBHN HO P&L'!$O29:$Q29)+SUM('YBN HO P&L'!$O29:$Q29)+SUM('Moe2 P&L'!$O29:$Q29) | T92: =SUM(B92:S92) | U92: =SUM('ABA P&L'!$R29:$T29) | V92: =SUM('BK P&L'!$R29:$T29) | W92: =SUM('BW P&L'!$R29:$T29) | X92: =SUM('CED P&L'!$R29:$T29) | Y92: =SUM('HB P&L'!$R29:$T29) | Z92: =SUM('KIN P&L'!$R29:$T29) | AA92: =SUM('MER P&L'!$R29:$T29) | AB92: =SUM('SST P&L'!$R29:$T29) | AC92: =SUM('HDN P&L'!$R29:$T29) | AD92: =SUM('NDN P&L'!$R29:$T29) | AE92: =SUM('SDN P&L'!$R29:$T29) | AF92: =SUM('LE P&L'!$R29:$T29) | AG92: =SUM('WH P&L'!$R29:$T29) | AH92: =SUM('HS P&L'!$R29:$T29) | AI92: =SUM('FH P&L'!$R29:$T29) | AJ92: =SUM('HAB P&L'!$R29:$T29) | AK92: =SUM('SALT P&L'!$R29:$T29) | AL92: =SUM('KNL HO P&L'!$R29:$T29)+SUM('CCL HO P&L'!$R29:$T29)+SUM('YBHN HO P&L'!$R29:$T29)+SUM('YBN HO P&L'!$R29:$T29)+SUM('Moe2 P&L'!$R29:$T29) | AM92: =SUM(U92:AL92) | AN92: =SUM('ABA P&L'!$U29:$W29) | AO92: =SUM('BK P&L'!$U29:$W29) | AP92: =SUM('BW P&L'!$U29:$W29) | AQ92: =SUM('CED P&L'!$U29:$W29) | AR92: =SUM('HB P&L'!$U29:$W29) | AS92: =SUM('KIN P&L'!$U29:$W29) | AT92: =SUM('MER P&L'!$U29:$W29) | AU92: =SUM('SST P&L'!$U29:$W29) | AV92: =SUM('HDN P&L'!$U29:$W29) | AW92: =SUM('NDN P&L'!$U29:$W29) | AX92: =SUM('SDN P&L'!$U29:$W29) | AY92: =SUM('LE P&L'!$U29:$W29) | AZ92: =SUM('WH P&L'!$U29:$W29) | BA92: =SUM('HS P&L'!$U29:$W29) | BB92: =SUM('FH P&L'!$U29:$W29) | BC92: =SUM('HAB P&L'!$U29:$W29) | BD92: =SUM('SALT P&L'!$U29:$W29) | BE92: =SUM('KNL HO P&L'!$U29:$W29)+SUM('CCL HO P&L'!$U29:$W29)+SUM('YBHN HO P&L'!$U29:$W29)+SUM('YBN HO P&L'!$U29:$W29)+SUM('Moe2 P&L'!$U29:$W29) | BF92: =SUM(AN92:BE92) | BG92: =SUM('ABA P&L'!$X29:$Z29) | BH92: =SUM('BK P&L'!$X29:$Z29) | BI92: =SUM('BW P&L'!$X29:$Z29) | BJ92: =SUM('CED P&L'!$X29:$Z29) | BK92: =SUM('HB P&L'!$X29:$Z29) | BL92: =SUM('KIN P&L'!$X29:$Z29) | BM92: =SUM('MER P&L'!$X29:$Z29) | BN92: =SUM('SST P&L'!$X29:$Z29) | BO92: =SUM('HDN P&L'!$X29:$Z29) | BP92: =SUM('NDN P&L'!$X29:$Z29) | BQ92: =SUM('SDN P&L'!$X29:$Z29) | BR92: =SUM('LE P&L'!$X29:$Z29) | BS92: =SUM('WH P&L'!$X29:$Z29) | BT92: =SUM('HS P&L'!$X29:$Z29) | BU92: =SUM('FH P&L'!$X29:$Z29) | BV92: =SUM('HAB P&L'!$X29:$Z29) | BW92: =SUM('SALT P&L'!$X29:$Z29) | BX92: =SUM('KNL HO P&L'!$X29:$Z29)+SUM('CCL HO P&L'!$X29:$Z29)+SUM('YBHN HO P&L'!$X29:$Z29)+SUM('YBN HO P&L'!$X29:$Z29)+SUM('Moe2 P&L'!$X29:$Z29) | BY92: =SUM(BG92:BX92) | BZ92: =BY92+BF92+AM92+T92 | CA92: ='GROUP TOTALS MONTHLY P&L'!AB29 | CB92: =BZ92-CA92 | CC92: Incorrect Setting codes
A93: Nursery Stationery | B93: =SUM('ABA P&L'!$O30:$Q30) | C93: =SUM('BK P&L'!$O30:$Q30) | D93: =SUM('BW P&L'!$O30:$Q30) | E93: =SUM('CED P&L'!$O30:$Q30) | F93: =SUM('HB P&L'!$O30:$Q30) | G93: =SUM('KIN P&L'!$O30:$Q30) | H93: =SUM('MER P&L'!$O30:$Q30) | I93: =SUM('SST P&L'!$O30:$Q30) | J93: =SUM('HDN P&L'!$O30:$Q30) | K93: =SUM('NDN P&L'!$O30:$Q30) | L93: =SUM('SDN P&L'!$O30:$Q30) | M93: =SUM('LE P&L'!$O30:$Q30) | N93: =SUM('WH P&L'!$O30:$Q30) | O93: =SUM('HS P&L'!$O30:$Q30) | P93: =SUM('FH P&L'!$O30:$Q30) | Q93: =SUM('HAB P&L'!$O30:$Q30) | R93: =SUM('SALT P&L'!$O30:$Q30) | S93: =SUM('KNL HO P&L'!$O30:$Q30)+SUM('CCL HO P&L'!$O30:$Q30)+SUM('YBHN HO P&L'!$O30:$Q30)+SUM('YBN HO P&L'!$O30:$Q30)+SUM('Moe2 P&L'!$O30:$Q30) | T93: =SUM(B93:S93) | U93: =SUM('ABA P&L'!$R30:$T30) | V93: =SUM('BK P&L'!$R30:$T30) | W93: =SUM('BW P&L'!$R30:$T30) | X93: =SUM('CED P&L'!$R30:$T30) | Y93: =SUM('HB P&L'!$R30:$T30) | Z93: =SUM('KIN P&L'!$R30:$T30) | AA93: =SUM('MER P&L'!$R30:$T30) | AB93: =SUM('SST P&L'!$R30:$T30) | AC93: =SUM('HDN P&L'!$R30:$T30) | AD93: =SUM('NDN P&L'!$R30:$T30) | AE93: =SUM('SDN P&L'!$R30:$T30) | AF93: =SUM('LE P&L'!$R30:$T30) | AG93: =SUM('WH P&L'!$R30:$T30) | AH93: =SUM('HS P&L'!$R30:$T30) | AI93: =SUM('FH P&L'!$R30:$T30) | AJ93: =SUM('HAB P&L'!$R30:$T30) | AK93: =SUM('SALT P&L'!$R30:$T30) | AL93: =SUM('KNL HO P&L'!$R30:$T30)+SUM('CCL HO P&L'!$R30:$T30)+SUM('YBHN HO P&L'!$R30:$T30)+SUM('YBN HO P&L'!$R30:$T30)+SUM('Moe2 P&L'!$R30:$T30) | AM93: =SUM(U93:AL93) | AN93: =SUM('ABA P&L'!$U30:$W30) | AO93: =SUM('BK P&L'!$U30:$W30) | AP93: =SUM('BW P&L'!$U30:$W30) | AQ93: =SUM('CED P&L'!$U30:$W30) | AR93: =SUM('HB P&L'!$U30:$W30) | AS93: =SUM('KIN P&L'!$U30:$W30) | AT93: =SUM('MER P&L'!$U30:$W30) | AU93: =SUM('SST P&L'!$U30:$W30) | AV93: =SUM('HDN P&L'!$U30:$W30) | AW93: =SUM('NDN P&L'!$U30:$W30) | AX93: =SUM('SDN P&L'!$U30:$W30) | AY93: =SUM('LE P&L'!$U30:$W30) | AZ93: =SUM('WH P&L'!$U30:$W30) | BA93: =SUM('HS P&L'!$U30:$W30) | BB93: =SUM('FH P&L'!$U30:$W30) | BC93: =SUM('HAB P&L'!$U30:$W30) | BD93: =SUM('SALT P&L'!$U30:$W30) | BE93: =SUM('KNL HO P&L'!$U30:$W30)+SUM('CCL HO P&L'!$U30:$W30)+SUM('YBHN HO P&L'!$U30:$W30)+SUM('YBN HO P&L'!$U30:$W30)+SUM('Moe2 P&L'!$U30:$W30) | BF93: =SUM(AN93:BE93) | BG93: =SUM('ABA P&L'!$X30:$Z30) | BH93: =SUM('BK P&L'!$X30:$Z30) | BI93: =SUM('BW P&L'!$X30:$Z30) | BJ93: =SUM('CED P&L'!$X30:$Z30) | BK93: =SUM('HB P&L'!$X30:$Z30) | BL93: =SUM('KIN P&L'!$X30:$Z30) | BM93: =SUM('MER P&L'!$X30:$Z30) | BN93: =SUM('SST P&L'!$X30:$Z30) | BO93: =SUM('HDN P&L'!$X30:$Z30) | BP93: =SUM('NDN P&L'!$X30:$Z30) | BQ93: =SUM('SDN P&L'!$X30:$Z30) | BR93: =SUM('LE P&L'!$X30:$Z30) | BS93: =SUM('WH P&L'!$X30:$Z30) | BT93: =SUM('HS P&L'!$X30:$Z30) | BU93: =SUM('FH P&L'!$X30:$Z30) | BV93: =SUM('HAB P&L'!$X30:$Z30) | BW93: =SUM('SALT P&L'!$X30:$Z30) | BX93: =SUM('KNL HO P&L'!$X30:$Z30)+SUM('CCL HO P&L'!$X30:$Z30)+SUM('YBHN HO P&L'!$X30:$Z30)+SUM('YBN HO P&L'!$X30:$Z30)+SUM('Moe2 P&L'!$X30:$Z30) | BY93: =SUM(BG93:BX93) | BZ93: =BY93+BF93+AM93+T93 | CA93: ='GROUP TOTALS MONTHLY P&L'!AB30 | CB93: =BZ93-CA93 | CC93: Incorrect Setting codes
A94: Nursery Equipment | B94: =SUM('ABA P&L'!$O31:$Q31) | C94: =SUM('BK P&L'!$O31:$Q31) | D94: =SUM('BW P&L'!$O31:$Q31) | E94: =SUM('CED P&L'!$O31:$Q31) | F94: =SUM('HB P&L'!$O31:$Q31) | G94: =SUM('KIN P&L'!$O31:$Q31) | H94: =SUM('MER P&L'!$O31:$Q31) | I94: =SUM('SST P&L'!$O31:$Q31) | J94: =SUM('HDN P&L'!$O31:$Q31) | K94: =SUM('NDN P&L'!$O31:$Q31) | L94: =SUM('SDN P&L'!$O31:$Q31) | M94: =SUM('LE P&L'!$O31:$Q31) | N94: =SUM('WH P&L'!$O31:$Q31) | O94: =SUM('HS P&L'!$O31:$Q31) | P94: =SUM('FH P&L'!$O31:$Q31) | Q94: =SUM('HAB P&L'!$O31:$Q31) | R94: =SUM('SALT P&L'!$O31:$Q31) | S94: =SUM('KNL HO P&L'!$O31:$Q31)+SUM('CCL HO P&L'!$O31:$Q31)+SUM('YBHN HO P&L'!$O31:$Q31)+SUM('YBN HO P&L'!$O31:$Q31)+SUM('Moe2 P&L'!$O31:$Q31) | T94: =SUM(B94:S94) | U94: =SUM('ABA P&L'!$R31:$T31) | V94: =SUM('BK P&L'!$R31:$T31) | W94: =SUM('BW P&L'!$R31:$T31) | X94: =SUM('CED P&L'!$R31:$T31) | Y94: =SUM('HB P&L'!$R31:$T31) | Z94: =SUM('KIN P&L'!$R31:$T31) | AA94: =SUM('MER P&L'!$R31:$T31) | AB94: =SUM('SST P&L'!$R31:$T31) | AC94: =SUM('HDN P&L'!$R31:$T31) | AD94: =SUM('NDN P&L'!$R31:$T31) | AE94: =SUM('SDN P&L'!$R31:$T31) | AF94: =SUM('LE P&L'!$R31:$T31) | AG94: =SUM('WH P&L'!$R31:$T31) | AH94: =SUM('HS P&L'!$R31:$T31) | AI94: =SUM('FH P&L'!$R31:$T31) | AJ94: =SUM('HAB P&L'!$R31:$T31) | AK94: =SUM('SALT P&L'!$R31:$T31) | AL94: =SUM('KNL HO P&L'!$R31:$T31)+SUM('CCL HO P&L'!$R31:$T31)+SUM('YBHN HO P&L'!$R31:$T31)+SUM('YBN HO P&L'!$R31:$T31)+SUM('Moe2 P&L'!$R31:$T31) | AM94: =SUM(U94:AL94) | AN94: =SUM('ABA P&L'!$U31:$W31) | AO94: =SUM('BK P&L'!$U31:$W31) | AP94: =SUM('BW P&L'!$U31:$W31) | AQ94: =SUM('CED P&L'!$U31:$W31) | AR94: =SUM('HB P&L'!$U31:$W31) | AS94: =SUM('KIN P&L'!$U31:$W31) | AT94: =SUM('MER P&L'!$U31:$W31) | AU94: =SUM('SST P&L'!$U31:$W31) | AV94: =SUM('HDN P&L'!$U31:$W31) | AW94: =SUM('NDN P&L'!$U31:$W31) | AX94: =SUM('SDN P&L'!$U31:$W31) | AY94: =SUM('LE P&L'!$U31:$W31) | AZ94: =SUM('WH P&L'!$U31:$W31) | BA94: =SUM('HS P&L'!$U31:$W31) | BB94: =SUM('FH P&L'!$U31:$W31) | BC94: =SUM('HAB P&L'!$U31:$W31) | BD94: =SUM('SALT P&L'!$U31:$W31) | BE94: =SUM('KNL HO P&L'!$U31:$W31)+SUM('CCL HO P&L'!$U31:$W31)+SUM('YBHN HO P&L'!$U31:$W31)+SUM('YBN HO P&L'!$U31:$W31)+SUM('Moe2 P&L'!$U31:$W31) | BF94: =SUM(AN94:BE94) | BG94: =SUM('ABA P&L'!$X31:$Z31) | BH94: =SUM('BK P&L'!$X31:$Z31) | BI94: =SUM('BW P&L'!$X31:$Z31) | BJ94: =SUM('CED P&L'!$X31:$Z31) | BK94: =SUM('HB P&L'!$X31:$Z31) | BL94: =SUM('KIN P&L'!$X31:$Z31) | BM94: =SUM('MER P&L'!$X31:$Z31) | BN94: =SUM('SST P&L'!$X31:$Z31) | BO94: =SUM('HDN P&L'!$X31:$Z31) | BP94: =SUM('NDN P&L'!$X31:$Z31) | BQ94: =SUM('SDN P&L'!$X31:$Z31) | BR94: =SUM('LE P&L'!$X31:$Z31) | BS94: =SUM('WH P&L'!$X31:$Z31) | BT94: =SUM('HS P&L'!$X31:$Z31) | BU94: =SUM('FH P&L'!$X31:$Z31) | BV94: =SUM('HAB P&L'!$X31:$Z31) | BW94: =SUM('SALT P&L'!$X31:$Z31) | BX94: =SUM('KNL HO P&L'!$X31:$Z31)+SUM('CCL HO P&L'!$X31:$Z31)+SUM('YBHN HO P&L'!$X31:$Z31)+SUM('YBN HO P&L'!$X31:$Z31)+SUM('Moe2 P&L'!$X31:$Z31) | BY94: =SUM(BG94:BX94) | BZ94: =BY94+BF94+AM94+T94 | CA94: ='GROUP TOTALS MONTHLY P&L'!AB31 | CB94: =BZ94-CA94
A95: Nursery Consumables | B95: =SUM('ABA P&L'!$O32:$Q32) | C95: =SUM('BK P&L'!$O32:$Q32) | D95: =SUM('BW P&L'!$O32:$Q32) | E95: =SUM('CED P&L'!$O32:$Q32) | F95: =SUM('HB P&L'!$O32:$Q32) | G95: =SUM('KIN P&L'!$O32:$Q32) | H95: =SUM('MER P&L'!$O32:$Q32) | I95: =SUM('SST P&L'!$O32:$Q32) | J95: =SUM('HDN P&L'!$O32:$Q32) | K95: =SUM('NDN P&L'!$O32:$Q32) | L95: =SUM('SDN P&L'!$O32:$Q32) | M95: =SUM('LE P&L'!$O32:$Q32) | N95: =SUM('WH P&L'!$O32:$Q32) | O95: =SUM('HS P&L'!$O32:$Q32) | P95: =SUM('FH P&L'!$O32:$Q32) | Q95: =SUM('HAB P&L'!$O32:$Q32) | R95: =SUM('SALT P&L'!$O32:$Q32) | S95: =SUM('KNL HO P&L'!$O32:$Q32)+SUM('CCL HO P&L'!$O32:$Q32)+SUM('YBHN HO P&L'!$O32:$Q32)+SUM('YBN HO P&L'!$O32:$Q32)+SUM('Moe2 P&L'!$O32:$Q32) | T95: =SUM(B95:S95) | U95: =SUM('ABA P&L'!$R32:$T32) | V95: =SUM('BK P&L'!$R32:$T32) | W95: =SUM('BW P&L'!$R32:$T32) | X95: =SUM('CED P&L'!$R32:$T32) | Y95: =SUM('HB P&L'!$R32:$T32) | Z95: =SUM('KIN P&L'!$R32:$T32) | AA95: =SUM('MER P&L'!$R32:$T32) | AB95: =SUM('SST P&L'!$R32:$T32) | AC95: =SUM('HDN P&L'!$R32:$T32) | AD95: =SUM('NDN P&L'!$R32:$T32) | AE95: =SUM('SDN P&L'!$R32:$T32) | AF95: =SUM('LE P&L'!$R32:$T32) | AG95: =SUM('WH P&L'!$R32:$T32) | AH95: =SUM('HS P&L'!$R32:$T32) | AI95: =SUM('FH P&L'!$R32:$T32) | AJ95: =SUM('HAB P&L'!$R32:$T32) | AK95: =SUM('SALT P&L'!$R32:$T32) | AL95: =SUM('KNL HO P&L'!$R32:$T32)+SUM('CCL HO P&L'!$R32:$T32)+SUM('YBHN HO P&L'!$R32:$T32)+SUM('YBN HO P&L'!$R32:$T32)+SUM('Moe2 P&L'!$R32:$T32) | AM95: =SUM(U95:AL95) | AN95: =SUM('ABA P&L'!$U32:$W32) | AO95: =SUM('BK P&L'!$U32:$W32) | AP95: =SUM('BW P&L'!$U32:$W32) | AQ95: =SUM('CED P&L'!$U32:$W32) | AR95: =SUM('HB P&L'!$U32:$W32) | AS95: =SUM('KIN P&L'!$U32:$W32) | AT95: =SUM('MER P&L'!$U32:$W32) | AU95: =SUM('SST P&L'!$U32:$W32) | AV95: =SUM('HDN P&L'!$U32:$W32) | AW95: =SUM('NDN P&L'!$U32:$W32) | AX95: =SUM('SDN P&L'!$U32:$W32) | AY95: =SUM('LE P&L'!$U32:$W32) | AZ95: =SUM('WH P&L'!$U32:$W32) | BA95: =SUM('HS P&L'!$U32:$W32) | BB95: =SUM('FH P&L'!$U32:$W32) | BC95: =SUM('HAB P&L'!$U32:$W32) | BD95: =SUM('SALT P&L'!$U32:$W32) | BE95: =SUM('KNL HO P&L'!$U32:$W32)+SUM('CCL HO P&L'!$U32:$W32)+SUM('YBHN HO P&L'!$U32:$W32)+SUM('YBN HO P&L'!$U32:$W32)+SUM('Moe2 P&L'!$U32:$W32) | BF95: =SUM(AN95:BE95) | BG95: =SUM('ABA P&L'!$X32:$Z32) | BH95: =SUM('BK P&L'!$X32:$Z32) | BI95: =SUM('BW P&L'!$X32:$Z32) | BJ95: =SUM('CED P&L'!$X32:$Z32) | BK95: =SUM('HB P&L'!$X32:$Z32) | BL95: =SUM('KIN P&L'!$X32:$Z32) | BM95: =SUM('MER P&L'!$X32:$Z32) | BN95: =SUM('SST P&L'!$X32:$Z32) | BO95: =SUM('HDN P&L'!$X32:$Z32) | BP95: =SUM('NDN P&L'!$X32:$Z32) | BQ95: =SUM('SDN P&L'!$X32:$Z32) | BR95: =SUM('LE P&L'!$X32:$Z32) | BS95: =SUM('WH P&L'!$X32:$Z32) | BT95: =SUM('HS P&L'!$X32:$Z32) | BU95: =SUM('FH P&L'!$X32:$Z32) | BV95: =SUM('HAB P&L'!$X32:$Z32) | BW95: =SUM('SALT P&L'!$X32:$Z32) | BX95: =SUM('KNL HO P&L'!$X32:$Z32)+SUM('CCL HO P&L'!$X32:$Z32)+SUM('YBHN HO P&L'!$X32:$Z32)+SUM('YBN HO P&L'!$X32:$Z32)+SUM('Moe2 P&L'!$X32:$Z32) | BY95: =SUM(BG95:BX95) | BZ95: =BY95+BF95+AM95+T95 | CA95: ='GROUP TOTALS MONTHLY P&L'!AB32 | CB95: =BZ95-CA95
A96: Miscellaneous Child Care | B96: =SUM('ABA P&L'!$O33:$Q33) | C96: =SUM('BK P&L'!$O33:$Q33) | D96: =SUM('BW P&L'!$O33:$Q33) | E96: =SUM('CED P&L'!$O33:$Q33) | F96: =SUM('HB P&L'!$O33:$Q33) | G96: =SUM('KIN P&L'!$O33:$Q33) | H96: =SUM('MER P&L'!$O33:$Q33) | I96: =SUM('SST P&L'!$O33:$Q33) | J96: =SUM('HDN P&L'!$O33:$Q33) | K96: =SUM('NDN P&L'!$O33:$Q33) | L96: =SUM('SDN P&L'!$O33:$Q33) | M96: =SUM('LE P&L'!$O33:$Q33) | N96: =SUM('WH P&L'!$O33:$Q33) | O96: =SUM('HS P&L'!$O33:$Q33) | P96: =SUM('FH P&L'!$O33:$Q33) | Q96: =SUM('HAB P&L'!$O33:$Q33) | R96: =SUM('SALT P&L'!$O33:$Q33) | S96: =SUM('KNL HO P&L'!$O33:$Q33)+SUM('CCL HO P&L'!$O33:$Q33)+SUM('YBHN HO P&L'!$O33:$Q33)+SUM('YBN HO P&L'!$O33:$Q33)+SUM('Moe2 P&L'!$O33:$Q33) | T96: =SUM(B96:S96) | U96: =SUM('ABA P&L'!$R33:$T33) | V96: =SUM('BK P&L'!$R33:$T33) | W96: =SUM('BW P&L'!$R33:$T33) | X96: =SUM('CED P&L'!$R33:$T33) | Y96: =SUM('HB P&L'!$R33:$T33) | Z96: =SUM('KIN P&L'!$R33:$T33) | AA96: =SUM('MER P&L'!$R33:$T33) | AB96: =SUM('SST P&L'!$R33:$T33) | AC96: =SUM('HDN P&L'!$R33:$T33) | AD96: =SUM('NDN P&L'!$R33:$T33) | AE96: =SUM('SDN P&L'!$R33:$T33) | AF96: =SUM('LE P&L'!$R33:$T33) | AG96: =SUM('WH P&L'!$R33:$T33) | AH96: =SUM('HS P&L'!$R33:$T33) | AI96: =SUM('FH P&L'!$R33:$T33) | AJ96: =SUM('HAB P&L'!$R33:$T33) | AK96: =SUM('SALT P&L'!$R33:$T33) | AL96: =SUM('KNL HO P&L'!$R33:$T33)+SUM('CCL HO P&L'!$R33:$T33)+SUM('YBHN HO P&L'!$R33:$T33)+SUM('YBN HO P&L'!$R33:$T33)+SUM('Moe2 P&L'!$R33:$T33) | AM96: =SUM(U96:AL96) | AN96: =SUM('ABA P&L'!$U33:$W33) | AO96: =SUM('BK P&L'!$U33:$W33) | AP96: =SUM('BW P&L'!$U33:$W33) | AQ96: =SUM('CED P&L'!$U33:$W33) | AR96: =SUM('HB P&L'!$U33:$W33) | AS96: =SUM('KIN P&L'!$U33:$W33) | AT96: =SUM('MER P&L'!$U33:$W33) | AU96: =SUM('SST P&L'!$U33:$W33) | AV96: =SUM('HDN P&L'!$U33:$W33) | AW96: =SUM('NDN P&L'!$U33:$W33) | AX96: =SUM('SDN P&L'!$U33:$W33) | AY96: =SUM('LE P&L'!$U33:$W33) | AZ96: =SUM('WH P&L'!$U33:$W33) | BA96: =SUM('HS P&L'!$U33:$W33) | BB96: =SUM('FH P&L'!$U33:$W33) | BC96: =SUM('HAB P&L'!$U33:$W33) | BD96: =SUM('SALT P&L'!$U33:$W33) | BE96: =SUM('KNL HO P&L'!$U33:$W33)+SUM('CCL HO P&L'!$U33:$W33)+SUM('YBHN HO P&L'!$U33:$W33)+SUM('YBN HO P&L'!$U33:$W33)+SUM('Moe2 P&L'!$U33:$W33) | BF96: =SUM(AN96:BE96) | BG96: =SUM('ABA P&L'!$X33:$Z33) | BH96: =SUM('BK P&L'!$X33:$Z33) | BI96: =SUM('BW P&L'!$X33:$Z33) | BJ96: =SUM('CED P&L'!$X33:$Z33) | BK96: =SUM('HB P&L'!$X33:$Z33) | BL96: =SUM('KIN P&L'!$X33:$Z33) | BM96: =SUM('MER P&L'!$X33:$Z33) | BN96: =SUM('SST P&L'!$X33:$Z33) | BO96: =SUM('HDN P&L'!$X33:$Z33) | BP96: =SUM('NDN P&L'!$X33:$Z33) | BQ96: =SUM('SDN P&L'!$X33:$Z33) | BR96: =SUM('LE P&L'!$X33:$Z33) | BS96: =SUM('WH P&L'!$X33:$Z33) | BT96: =SUM('HS P&L'!$X33:$Z33) | BU96: =SUM('FH P&L'!$X33:$Z33) | BV96: =SUM('HAB P&L'!$X33:$Z33) | BW96: =SUM('SALT P&L'!$X33:$Z33) | BX96: =SUM('KNL HO P&L'!$X33:$Z33)+SUM('CCL HO P&L'!$X33:$Z33)+SUM('YBHN HO P&L'!$X33:$Z33)+SUM('YBN HO P&L'!$X33:$Z33)+SUM('Moe2 P&L'!$X33:$Z33) | BY96: =SUM(BG96:BX96) | BZ96: =BY96+BF96+AM96+T96 | CA96: ='GROUP TOTALS MONTHLY P&L'!AB33 | CB96: =BZ96-CA96
A97: Total Childcare Costs | B97: =SUM('ABA P&L'!$O34:$Q34) | C97: =SUM('BK P&L'!$O34:$Q34) | D97: =SUM('BW P&L'!$O34:$Q34) | E97: =SUM('CED P&L'!$O34:$Q34) | F97: =SUM('HB P&L'!$O34:$Q34) | G97: =SUM('KIN P&L'!$O34:$Q34) | H97: =SUM('MER P&L'!$O34:$Q34) | I97: =SUM('SST P&L'!$O34:$Q34) | J97: =SUM('HDN P&L'!$O34:$Q34) | K97: =SUM('NDN P&L'!$O34:$Q34) | L97: =SUM('SDN P&L'!$O34:$Q34) | M97: =SUM('LE P&L'!$O34:$Q34) | N97: =SUM('WH P&L'!$O34:$Q34) | O97: =SUM('HS P&L'!$O34:$Q34) | P97: =SUM('FH P&L'!$O34:$Q34) | Q97: =SUM('HAB P&L'!$O34:$Q34) | R97: =SUM('SALT P&L'!$O34:$Q34) | S97: =SUM('KNL HO P&L'!$O34:$Q34)+SUM('CCL HO P&L'!$O34:$Q34)+SUM('YBHN HO P&L'!$O34:$Q34)+SUM('YBN HO P&L'!$O34:$Q34)+SUM('Moe2 P&L'!$O34:$Q34) | T97: =SUM(B97:S97) | U97: =SUM('ABA P&L'!$R34:$T34) | V97: =SUM('BK P&L'!$R34:$T34) | W97: =SUM('BW P&L'!$R34:$T34) | X97: =SUM('CED P&L'!$R34:$T34) | Y97: =SUM('HB P&L'!$R34:$T34) | Z97: =SUM('KIN P&L'!$R34:$T34) | AA97: =SUM('MER P&L'!$R34:$T34) | AB97: =SUM('SST P&L'!$R34:$T34) | AC97: =SUM('HDN P&L'!$R34:$T34) | AD97: =SUM('NDN P&L'!$R34:$T34) | AE97: =SUM('SDN P&L'!$R34:$T34) | AF97: =SUM('LE P&L'!$R34:$T34) | AG97: =SUM('WH P&L'!$R34:$T34) | AH97: =SUM('HS P&L'!$R34:$T34) | AI97: =SUM('FH P&L'!$R34:$T34) | AJ97: =SUM('HAB P&L'!$R34:$T34) | AK97: =SUM('SALT P&L'!$R34:$T34) | AL97: =SUM('KNL HO P&L'!$R34:$T34)+SUM('CCL HO P&L'!$R34:$T34)+SUM('YBHN HO P&L'!$R34:$T34)+SUM('YBN HO P&L'!$R34:$T34)+SUM('Moe2 P&L'!$R34:$T34) | AM97: =SUM(U97:AL97) | AN97: =SUM('ABA P&L'!$U34:$W34) | AO97: =SUM('BK P&L'!$U34:$W34) | AP97: =SUM('BW P&L'!$U34:$W34) | AQ97: =SUM('CED P&L'!$U34:$W34) | AR97: =SUM('HB P&L'!$U34:$W34) | AS97: =SUM('KIN P&L'!$U34:$W34) | AT97: =SUM('MER P&L'!$U34:$W34) | AU97: =SUM('SST P&L'!$U34:$W34) | AV97: =SUM('HDN P&L'!$U34:$W34) | AW97: =SUM('NDN P&L'!$U34:$W34) | AX97: =SUM('SDN P&L'!$U34:$W34) | AY97: =SUM('LE P&L'!$U34:$W34) | AZ97: =SUM('WH P&L'!$U34:$W34) | BA97: =SUM('HS P&L'!$U34:$W34) | BB97: =SUM('FH P&L'!$U34:$W34) | BC97: =SUM('HAB P&L'!$U34:$W34) | BD97: =SUM('SALT P&L'!$U34:$W34) | BE97: =SUM('KNL HO P&L'!$U34:$W34)+SUM('CCL HO P&L'!$U34:$W34)+SUM('YBHN HO P&L'!$U34:$W34)+SUM('YBN HO P&L'!$U34:$W34)+SUM('Moe2 P&L'!$U34:$W34) | BF97: =SUM(AN97:BE97) | BG97: =SUM('ABA P&L'!$X34:$Z34) | BH97: =SUM('BK P&L'!$X34:$Z34) | BI97: =SUM('BW P&L'!$X34:$Z34) | BJ97: =SUM('CED P&L'!$X34:$Z34) | BK97: =SUM('HB P&L'!$X34:$Z34) | BL97: =SUM('KIN P&L'!$X34:$Z34) | BM97: =SUM('MER P&L'!$X34:$Z34) | BN97: =SUM('SST P&L'!$X34:$Z34) | BO97: =SUM('HDN P&L'!$X34:$Z34) | BP97: =SUM('NDN P&L'!$X34:$Z34) | BQ97: =SUM('SDN P&L'!$X34:$Z34) | BR97: =SUM('LE P&L'!$X34:$Z34) | BS97: =SUM('WH P&L'!$X34:$Z34) | BT97: =SUM('HS P&L'!$X34:$Z34) | BU97: =SUM('FH P&L'!$X34:$Z34) | BV97: =SUM('HAB P&L'!$X34:$Z34) | BW97: =SUM('SALT P&L'!$X34:$Z34) | BX97: =SUM('KNL HO P&L'!$X34:$Z34)+SUM('CCL HO P&L'!$X34:$Z34)+SUM('YBHN HO P&L'!$X34:$Z34)+SUM('YBN HO P&L'!$X34:$Z34)+SUM('Moe2 P&L'!$X34:$Z34) | BY97: =SUM(BG97:BX97) | BZ97: =BY97+BF97+AM97+T97 | CA97: ='GROUP TOTALS MONTHLY P&L'!AB34 | CB97: =BZ97-CA97 | CC97: Incorrect Setting codes
